Workbook
Name Slicer_PlayerCompleted: #REF!
Name Slicer_TargetType: #REF!
Name craftifactNames: #REF!
Name Slicer_ChainAwareStatus: #REF!
Name Slicer_TargetType1: #REF!
Name AllDependencies: Dependencies!$D$1:$E$1000
Name Slicer_PlayerPaid: #REF!
Name Slicer_TargetCompleted: #REF!
Name Slicer_TargetFunded: #REF!
Name NormalizePrereqs: LAMBDA(_xlpm.txt, LET(_xlpm.t,_xlpm.txt,TRIM(SUBSTITUTE(SUBSTITUTE(SUBSTITUTE(SUBSTITUTE(SUBSTITUTE(_xlpm.t,CHAR(10),"|"),"<br/>","|"),"<br>","|"),"/","|"),"\","|"))))
Name SlicerCache_Table_1_Col_4: #N/A
Name SlicerCache_Table_1_Col_5: #N/A
Name SlicerCache_Table_1_Col_7: #N/A
Name SlicerCache_Table_1_Col_8: #N/A
Name SlicerCache_Table_3_Col_4: #N/A
Name SlicerCache_Table_3_Col_9: #N/A
Name SlicerCache_Table_3_Col_10: #N/A

Sheet README

Sheet Player
A1: Setting | B1: Value | C1: PlayerStateID | D1: Description | E1: Note | G1: Player Type | H1: Active | K1: Active
A2: Character Level | B2: 1 | C2: state.character_level | D2: Current player level | E2: Only needs to be tracked until level 80 | K2: Passive
A3: Cartographer | B3: 0 | C3: state.character_cartographer | D3: Current cartographer level | E3: Only needs to be tracked until level 4
A4: Cooking | B4: 0 | C4: state.character_cooking | D4: Current Cooking level | E4: Only needs to be tracked until level 13

Sheet Dashboard
A1: Current Cost | I1: One Away | O1: Open Quests | S1: Pending actions | V1: Funded not Complete | Y1: Select Resource | Z1: ruby | AA1: =IFERROR(__xludf.DUMMYFUNCTION("IFERROR( FILTER( { 'cost checklist'!C2:C1000, 'cost checklist'!G2:G1000, 'cost checklist'!D2:D1000 }, ('cost checklist'!E2:E1000=$Z$1)* ('cost checklist'!J2:J1000=FALSE)* ('cost checklist'!I2:I1000=""READY"") ), ""No ready unpaid tar"&"gets require this resource"" )"),"Guild Lv 2") -> Guild Lv 2 | AB1: =IFERROR(__xludf.DUMMYFUNCTION("""COMPUTED_VALUE"""),1.0) -> 1 | AC1: =IFERROR(__xludf.DUMMYFUNCTION("""COMPUTED_VALUE"""),"BUILDING") -> BUILDING
A2: Target | B2: Type | C2: Sort | D2: Funded | E2: Remaining | F2: Cost Details | I2: Target | J2: Type | K2: Missing | L2: Cost Details | O2: Active Quest | P2: Outstanding Objective | S2: Action | T2: Unlocks | V2: =IFERROR(__xludf.DUMMYFUNCTION("IFERROR( FILTER( { TargetStatus!B2:B1000, TargetStatus!E2:E1000 }, (TargetStatus!C2:C1000=""READY"")* (TargetStatus!X2:X1000=TRUE) ), ""No funded targets waiting for completion"" )"),"No funded targets waiting for completion") -> No funded targets waiting for completion
A3: =IFERROR(__xludf.DUMMYFUNCTION("IFERROR( LET( data, FILTER( { TargetStatus!B2:B1000, TargetStatus!E2:E1000, TargetStatus!R2:R1000, TargetStatus!V2:V1000, TargetStatus!W2:W1000, TargetStatus!Y2:Y1000 }, (TargetStatus!C2:C1000=""READY"")* "&" (TargetStatus!D2:D1000=FALSE)* (TargetStatus!U2:U1000=TRUE)* (TargetStatus!X2:X1000=FALSE) ), sorted, SORT( HSTACK( data, IF(CHOOSECOLS(data,3)="""",1,0) ), 7,TRUE, 3,TRUE ), CHOOSECOLS(sorted,1,2,3,4,5,6) "&" ), ""Nothing currently waiting for payment"" )"),"Guild Lv 2") -> Guild Lv 2 | B3: =IFERROR(__xludf.DUMMYFUNCTION("""COMPUTED_VALUE"""),"BUILDING") -> BUILDING | C3: =IFERROR(__xludf.DUMMYFUNCTION("""COMPUTED_VALUE"""),1.0) -> 1 | D3: =IFERROR(__xludf.DUMMYFUNCTION("""COMPUTED_VALUE"""),0.0) -> 0 | E3: =IFERROR(__xludf.DUMMYFUNCTION("""COMPUTED_VALUE"""),4.0) -> 4 | F3: =IFERROR(__xludf.DUMMYFUNCTION("""COMPUTED_VALUE"""),"coin: 50, ruby: 1, stone: 50, wood: 50") -> coin: 50, ruby: 1, stone: 50, wood: 50 | I3: =IFERROR(__xludf.DUMMYFUNCTION("IFERROR( FILTER( { TargetStatus!B2:B1000, TargetStatus!E2:E1000, TargetStatus!N2:N1000, TargetStatus!O2:O1000 }, (TargetStatus!Q2:Q1000=""ONE AWAY"")* (TargetStatus!D2:D1000=FALSE)* (TargetStatus!T2:T1000=""PLAYER"") ), ""Nothing "&"one step away"" )"),"Alchemist's Hut Lv 1") -> Alchemist's Hut Lv 1 | J3: =IFERROR(__xludf.DUMMYFUNCTION("""COMPUTED_VALUE"""),"BUILDING") -> BUILDING | K3: =IFERROR(__xludf.DUMMYFUNCTION("""COMPUTED_VALUE"""),"Character Level@6") -> Character Level@6 | L3: =IFERROR(__xludf.DUMMYFUNCTION("""COMPUTED_VALUE"""),"1 ruby,140 coin,70 wood,70 stone") -> 1 ruby,140 coin,70 wood,70 stone | O3: =IFERROR(__xludf.DUMMYFUNCTION("IFERROR( FILTER( { QuestObjectives!H2:H1000, QuestObjectives!C2:C1000 }, (QuestObjectives!F2:F1000=TRUE)* (QuestObjectives!G2:G1000=TRUE) ), ""No active quests"" )"),"No active quests") -> No active quests | S3: =IFERROR(__xludf.DUMMYFUNCTION("IFERROR( FILTER( { TargetStatus!B2:B1000, TargetStatus!AA2:AA1000 }, (TargetStatus!C2:C1000=""READY"")* (TargetStatus!E2:E1000=""STATE"")* (TargetStatus!D2:D1000=FALSE)* (TargetStatus!AA2:AA1000<>"""") ), ""No pending quest acceptance"&" actions"" )"),"No pending quest acceptance actions") -> No pending quest acceptance actions
I4: =IFERROR(__xludf.DUMMYFUNCTION("""COMPUTED_VALUE"""),"Bonsai Lv 1") -> Bonsai Lv 1 | J4: =IFERROR(__xludf.DUMMYFUNCTION("""COMPUTED_VALUE"""),"BUILDING") -> BUILDING | K4: =IFERROR(__xludf.DUMMYFUNCTION("""COMPUTED_VALUE"""),"Character Level@21") -> Character Level@21 | L4: =IFERROR(__xludf.DUMMYFUNCTION("""COMPUTED_VALUE"""),"3 ruby,500 coin,500 plank,120 beans") -> 3 ruby,500 coin,500 plank,120 beans
I5: =IFERROR(__xludf.DUMMYFUNCTION("""COMPUTED_VALUE"""),"Bridge Lv 1") -> Bridge Lv 1 | J5: =IFERROR(__xludf.DUMMYFUNCTION("""COMPUTED_VALUE"""),"BUILDING") -> BUILDING | K5: =IFERROR(__xludf.DUMMYFUNCTION("""COMPUTED_VALUE"""),"Character Level@30") -> Character Level@30 | L5: =IFERROR(__xludf.DUMMYFUNCTION("""COMPUTED_VALUE"""),"4 ruby,1000 coin,400 beam,1000 plank,400 stone,100 steel") -> 4 ruby,1000 coin,400 beam,1000 plank,400 stone,100 steel
I6: =IFERROR(__xludf.DUMMYFUNCTION("""COMPUTED_VALUE"""),"Chicken Lv 1") -> Chicken Lv 1 | J6: =IFERROR(__xludf.DUMMYFUNCTION("""COMPUTED_VALUE"""),"BUILDING") -> BUILDING | K6: =IFERROR(__xludf.DUMMYFUNCTION("""COMPUTED_VALUE"""),"Character Level@15") -> Character Level@15 | L6: =IFERROR(__xludf.DUMMYFUNCTION("""COMPUTED_VALUE"""),"2 ruby,400 coin,400 beam,200 stone,20 wheat,10 thread,1 egg") -> 2 ruby,400 coin,400 beam,200 stone,20 wheat,10 thread,1 egg
I7: =IFERROR(__xludf.DUMMYFUNCTION("""COMPUTED_VALUE"""),"Dungeon Lv 1") -> Dungeon Lv 1 | J7: =IFERROR(__xludf.DUMMYFUNCTION("""COMPUTED_VALUE"""),"BUILDING") -> BUILDING | K7: =IFERROR(__xludf.DUMMYFUNCTION("""COMPUTED_VALUE"""),"Character Level@10") -> Character Level@10 | L7: =IFERROR(__xludf.DUMMYFUNCTION("""COMPUTED_VALUE"""),"1 ruby,300 coin,200 wood,50 stone,100 steel,30 fan") -> 1 ruby,300 coin,200 wood,50 stone,100 steel,30 fan
I8: =IFERROR(__xludf.DUMMYFUNCTION("""COMPUTED_VALUE"""),"Field Lv 1") -> Field Lv 1 | J8: =IFERROR(__xludf.DUMMYFUNCTION("""COMPUTED_VALUE"""),"BUILDING") -> BUILDING | K8: =IFERROR(__xludf.DUMMYFUNCTION("""COMPUTED_VALUE"""),"Character Level@7") -> Character Level@7 | L8: =IFERROR(__xludf.DUMMYFUNCTION("""COMPUTED_VALUE"""),"1 ruby,200 coin,100 wood,20 chemicals") -> 1 ruby,200 coin,100 wood,20 chemicals
I9: =IFERROR(__xludf.DUMMYFUNCTION("""COMPUTED_VALUE"""),"Food Stall Lv 1") -> Food Stall Lv 1 | J9: =IFERROR(__xludf.DUMMYFUNCTION("""COMPUTED_VALUE"""),"BUILDING") -> BUILDING | K9: =IFERROR(__xludf.DUMMYFUNCTION("""COMPUTED_VALUE"""),"Character Level@8") -> Character Level@8 | L9: =IFERROR(__xludf.DUMMYFUNCTION("""COMPUTED_VALUE"""),"1 ruby,300 coin,150 wood,150 stone,20 rice") -> 1 ruby,300 coin,150 wood,150 stone,20 rice
I10: =IFERROR(__xludf.DUMMYFUNCTION("""COMPUTED_VALUE"""),"Furnace Lv 1") -> Furnace Lv 1 | J10: =IFERROR(__xludf.DUMMYFUNCTION("""COMPUTED_VALUE"""),"BUILDING") -> BUILDING | K10: =IFERROR(__xludf.DUMMYFUNCTION("""COMPUTED_VALUE"""),"Character Level@8") -> Character Level@8 | L10: =IFERROR(__xludf.DUMMYFUNCTION("""COMPUTED_VALUE"""),"1 ruby,200 coin,100 wood,100 stone") -> 1 ruby,200 coin,100 wood,100 stone
I11: =IFERROR(__xludf.DUMMYFUNCTION("""COMPUTED_VALUE"""),"Garden Lv 1") -> Garden Lv 1 | J11: =IFERROR(__xludf.DUMMYFUNCTION("""COMPUTED_VALUE"""),"BUILDING") -> BUILDING | K11: =IFERROR(__xludf.DUMMYFUNCTION("""COMPUTED_VALUE"""),"Character Level@12") -> Character Level@12 | L11: =IFERROR(__xludf.DUMMYFUNCTION("""COMPUTED_VALUE"""),"1 ruby,400 coin,200 wood,100 stone") -> 1 ruby,400 coin,200 wood,100 stone
I12: =IFERROR(__xludf.DUMMYFUNCTION("""COMPUTED_VALUE"""),"Gong Lv 1") -> Gong Lv 1 | J12: =IFERROR(__xludf.DUMMYFUNCTION("""COMPUTED_VALUE"""),"BUILDING") -> BUILDING | K12: =IFERROR(__xludf.DUMMYFUNCTION("""COMPUTED_VALUE"""),"Character Level@10") -> Character Level@10 | L12: =IFERROR(__xludf.DUMMYFUNCTION("""COMPUTED_VALUE"""),"3 ruby,200 coin,100 wood,50 stone,50 steel") -> 3 ruby,200 coin,100 wood,50 stone,50 steel
I13: =IFERROR(__xludf.DUMMYFUNCTION("""COMPUTED_VALUE"""),"Guild Lv 3") -> Guild Lv 3 | J13: =IFERROR(__xludf.DUMMYFUNCTION("""COMPUTED_VALUE"""),"BUILDING") -> BUILDING | K13: =IFERROR(__xludf.DUMMYFUNCTION("""COMPUTED_VALUE"""),"Guild Lv 2") -> Guild Lv 2 | L13: =IFERROR(__xludf.DUMMYFUNCTION("""COMPUTED_VALUE"""),"2 ruby,150 coin,300 beam,150 stone") -> 2 ruby,150 coin,300 beam,150 stone
I14: =IFERROR(__xludf.DUMMYFUNCTION("""COMPUTED_VALUE"""),"Lumber Lv 1") -> Lumber Lv 1 | J14: =IFERROR(__xludf.DUMMYFUNCTION("""COMPUTED_VALUE"""),"BUILDING") -> BUILDING | K14: =IFERROR(__xludf.DUMMYFUNCTION("""COMPUTED_VALUE"""),"Character Level@11") -> Character Level@11 | L14: =IFERROR(__xludf.DUMMYFUNCTION("""COMPUTED_VALUE"""),"1 ruby,300 coin,150 wood,150 stone") -> 1 ruby,300 coin,150 wood,150 stone
I15: =IFERROR(__xludf.DUMMYFUNCTION("""COMPUTED_VALUE"""),"Onsen Lv 1") -> Onsen Lv 1 | J15: =IFERROR(__xludf.DUMMYFUNCTION("""COMPUTED_VALUE"""),"BUILDING") -> BUILDING | K15: =IFERROR(__xludf.DUMMYFUNCTION("""COMPUTED_VALUE"""),"Character Level@20") -> Character Level@20 | L15: =IFERROR(__xludf.DUMMYFUNCTION("""COMPUTED_VALUE"""),"3 ruby,500 coin,500 plank,400 stone") -> 3 ruby,500 coin,500 plank,400 stone
I16: =IFERROR(__xludf.DUMMYFUNCTION("""COMPUTED_VALUE"""),"Pagoda Lv 1") -> Pagoda Lv 1 | J16: =IFERROR(__xludf.DUMMYFUNCTION("""COMPUTED_VALUE"""),"BUILDING") -> BUILDING | K16: =IFERROR(__xludf.DUMMYFUNCTION("""COMPUTED_VALUE"""),"Character Level@4") -> Character Level@4 | L16: =IFERROR(__xludf.DUMMYFUNCTION("""COMPUTED_VALUE"""),"1 ruby,50 coin,50 wood,50 stone,5 petard") -> 1 ruby,50 coin,50 wood,50 stone,5 petard
I17: =IFERROR(__xludf.DUMMYFUNCTION("""COMPUTED_VALUE"""),"Rock Garden Lv 1") -> Rock Garden Lv 1 | J17: =IFERROR(__xludf.DUMMYFUNCTION("""COMPUTED_VALUE"""),"BUILDING") -> BUILDING | K17: =IFERROR(__xludf.DUMMYFUNCTION("""COMPUTED_VALUE"""),"Character Level@13") -> Character Level@13 | L17: =IFERROR(__xludf.DUMMYFUNCTION("""COMPUTED_VALUE"""),"1 ruby,400 coin,100 wood,200 stone") -> 1 ruby,400 coin,100 wood,200 stone
I18: =IFERROR(__xludf.DUMMYFUNCTION("""COMPUTED_VALUE"""),"Shop Lv 1") -> Shop Lv 1 | J18: =IFERROR(__xludf.DUMMYFUNCTION("""COMPUTED_VALUE"""),"BUILDING") -> BUILDING | K18: =IFERROR(__xludf.DUMMYFUNCTION("""COMPUTED_VALUE"""),"Character Level@3") -> Character Level@3 | L18: =IFERROR(__xludf.DUMMYFUNCTION("""COMPUTED_VALUE"""),"1 ruby,100 coin,20 wood,20 stone") -> 1 ruby,100 coin,20 wood,20 stone
I19: =IFERROR(__xludf.DUMMYFUNCTION("""COMPUTED_VALUE"""),"Smithy Lv 1") -> Smithy Lv 1 | J19: =IFERROR(__xludf.DUMMYFUNCTION("""COMPUTED_VALUE"""),"BUILDING") -> BUILDING | K19: =IFERROR(__xludf.DUMMYFUNCTION("""COMPUTED_VALUE"""),"Character Level@9") -> Character Level@9 | L19: =IFERROR(__xludf.DUMMYFUNCTION("""COMPUTED_VALUE"""),"1 ruby,240 coin,120 wood,120 stone,20 steel") -> 1 ruby,240 coin,120 wood,120 stone,20 steel
I20: =IFERROR(__xludf.DUMMYFUNCTION("""COMPUTED_VALUE"""),"Warehouse Lv 1") -> Warehouse Lv 1 | J20: =IFERROR(__xludf.DUMMYFUNCTION("""COMPUTED_VALUE"""),"BUILDING") -> BUILDING | K20: =IFERROR(__xludf.DUMMYFUNCTION("""COMPUTED_VALUE"""),"Character Level@5") -> Character Level@5 | L20: =IFERROR(__xludf.DUMMYFUNCTION("""COMPUTED_VALUE"""),"1 ruby,100 coin,60 wood,60 stone") -> 1 ruby,100 coin,60 wood,60 stone
I21: =IFERROR(__xludf.DUMMYFUNCTION("""COMPUTED_VALUE"""),"Windmill Lv 1") -> Windmill Lv 1 | J21: =IFERROR(__xludf.DUMMYFUNCTION("""COMPUTED_VALUE"""),"BUILDING") -> BUILDING | K21: =IFERROR(__xludf.DUMMYFUNCTION("""COMPUTED_VALUE"""),"Character Level@9") -> Character Level@9 | L21: =IFERROR(__xludf.DUMMYFUNCTION("""COMPUTED_VALUE"""),"1 ruby,300 coin,150 wood,150 stone,40 steel") -> 1 ruby,300 coin,150 wood,150 stone,40 steel
I22: =IFERROR(__xludf.DUMMYFUNCTION("""COMPUTED_VALUE"""),"Workshop Lv 1") -> Workshop Lv 1 | J22: =IFERROR(__xludf.DUMMYFUNCTION("""COMPUTED_VALUE"""),"BUILDING") -> BUILDING | K22: =IFERROR(__xludf.DUMMYFUNCTION("""COMPUTED_VALUE"""),"Character Level@2") -> Character Level@2 | L22: =IFERROR(__xludf.DUMMYFUNCTION("""COMPUTED_VALUE"""),"1 ruby,20 coin,10 wood,10 stone") -> 1 ruby,20 coin,10 wood,10 stone

Sheet Checklist
A1: TargetID | B1: DisplayName | C1: Successors | D1: TargetType | E1: ChainAwareStatus | F1: PlayerSort | G1: PlayerCompleted | H1: TargetFunded | I1: Recommended
A2: building.airship@1 | B2: {=_xlfn.XLOOKUP(Checklist!$A2,tblTargets[TargetID],tblTargets[DisplayName])} -> Airship Lv 1 | C2: {=_xlfn.XLOOKUP( A2, tblTargetStatus[TargetID], tblTargetStatus[successors], "" )} -> Airship Lv 2, Astrolabe, Cinema Projector, Dagger, Helmet, Safe, Telescope, Tetrachloroaurate, Festival Returns Accepted, Quest for Knowledge Chapter 5 Accepted | D2: {=_xlfn.XLOOKUP( A2, tblTargets[TargetID], tblTargets[TargetType], "" )} -> BUILDING | E2: {=_xlfn.XLOOKUP( A2, tblTargetStatus[TargetID], tblTargetStatus[ChainAwareStatus], "" )} -> BLOCKED | F2: 44 | G2: FALSE | H2: {=_xlfn.XLOOKUP( A2, tblTargetStatus[TargetID], tblTargetStatus[TargetFunded], "" )} -> FALSE | I2: {=IF( D2<>"BUILDING", "", IF( Player!$H$1="Active", _xlfn.XLOOKUP( A2, tblrecommended[ActiveTargetID], tblrecommended[Order], "" ), _xlfn.XLOOKUP( A2, tblrecommended[PassiveTargetID], tblrecommended[Order], "" ) ) )} -> 44
A3: building.airship@2 | B3: {=_xlfn.XLOOKUP(Checklist!$A3,tblTargets[TargetID],tblTargets[DisplayName])} -> Airship Lv 2 | C3: {=_xlfn.XLOOKUP( A3, tblTargetStatus[TargetID], tblTargetStatus[successors], "" )} -> Airship maxed | D3: {=_xlfn.XLOOKUP( A3, tblTargets[TargetID], tblTargets[TargetType], "" )} -> BUILDING | E3: {=_xlfn.XLOOKUP( A3, tblTargetStatus[TargetID], tblTargetStatus[ChainAwareStatus], "" )} -> BLOCKED | F3: 45 | G3: FALSE | H3: {=_xlfn.XLOOKUP( A3, tblTargetStatus[TargetID], tblTargetStatus[TargetFunded], "" )} -> FALSE | I3: {=IF( D3<>"BUILDING", "", IF( Player!$H$1="Active", _xlfn.XLOOKUP( A3, tblrecommended[ActiveTargetID], tblrecommended[Order], "" ), _xlfn.XLOOKUP( A3, tblrecommended[PassiveTargetID], tblrecommended[Order], "" ) ) )} -> 45
A4: building.alchemists_hut@1 | B4: {=_xlfn.XLOOKUP(Checklist!$A4,tblTargets[TargetID],tblTargets[DisplayName])} -> Alchemist's Hut Lv 1 | C4: {=_xlfn.XLOOKUP( A4, tblTargetStatus[TargetID], tblTargetStatus[successors], "" )} -> Alchemist's Hut Lv 2 | D4: {=_xlfn.XLOOKUP( A4, tblTargets[TargetID], tblTargets[TargetType], "" )} -> BUILDING | E4: {=_xlfn.XLOOKUP( A4, tblTargetStatus[TargetID], tblTargetStatus[ChainAwareStatus], "" )} -> ONE AWAY | F4: 4 | G4: FALSE | H4: {=_xlfn.XLOOKUP( A4, tblTargetStatus[TargetID], tblTargetStatus[TargetFunded], "" )} -> FALSE | I4: {=IF( D4<>"BUILDING", "", IF( Player!$H$1="Active", _xlfn.XLOOKUP( A4, tblrecommended[ActiveTargetID], tblrecommended[Order], "" ), _xlfn.XLOOKUP( A4, tblrecommended[PassiveTargetID], tblrecommended[Order], "" ) ) )} -> 4
A5: building.alchemists_hut@2 | B5: {=_xlfn.XLOOKUP(Checklist!$A5,tblTargets[TargetID],tblTargets[DisplayName])} -> Alchemist's Hut Lv 2 | C5: {=_xlfn.XLOOKUP( A5, tblTargetStatus[TargetID], tblTargetStatus[successors], "" )} -> Alchemist's Hut Lv 3 | D5: {=_xlfn.XLOOKUP( A5, tblTargets[TargetID], tblTargets[TargetType], "" )} -> BUILDING | E5: {=_xlfn.XLOOKUP( A5, tblTargetStatus[TargetID], tblTargetStatus[ChainAwareStatus], "" )} -> BLOCKED | F5: 5 | G5: FALSE | H5: {=_xlfn.XLOOKUP( A5, tblTargetStatus[TargetID], tblTargetStatus[TargetFunded], "" )} -> FALSE | I5: {=IF( D5<>"BUILDING", "", IF( Player!$H$1="Active", _xlfn.XLOOKUP( A5, tblrecommended[ActiveTargetID], tblrecommended[Order], "" ), _xlfn.XLOOKUP( A5, tblrecommended[PassiveTargetID], tblrecommended[Order], "" ) ) )} -> 5
A6: building.alchemists_hut@3 | B6: {=_xlfn.XLOOKUP(Checklist!$A6,tblTargets[TargetID],tblTargets[DisplayName])} -> Alchemist's Hut Lv 3 | C6: {=_xlfn.XLOOKUP( A6, tblTargetStatus[TargetID], tblTargetStatus[successors], "" )} -> Alchemist's Hut Lv 4 | D6: {=_xlfn.XLOOKUP( A6, tblTargets[TargetID], tblTargets[TargetType], "" )} -> BUILDING | E6: {=_xlfn.XLOOKUP( A6, tblTargetStatus[TargetID], tblTargetStatus[ChainAwareStatus], "" )} -> BLOCKED | F6: 51 | G6: FALSE | H6: {=_xlfn.XLOOKUP( A6, tblTargetStatus[TargetID], tblTargetStatus[TargetFunded], "" )} -> FALSE | I6: {=IF( D6<>"BUILDING", "", IF( Player!$H$1="Active", _xlfn.XLOOKUP( A6, tblrecommended[ActiveTargetID], tblrecommended[Order], "" ), _xlfn.XLOOKUP( A6, tblrecommended[PassiveTargetID], tblrecommended[Order], "" ) ) )} -> 51
A7: building.alchemists_hut@4 | B7: {=_xlfn.XLOOKUP(Checklist!$A7,tblTargets[TargetID],tblTargets[DisplayName])} -> Alchemist's Hut Lv 4 | C7: {=_xlfn.XLOOKUP( A7, tblTargetStatus[TargetID], tblTargetStatus[successors], "" )} -> Alchemist's Hut Lv 5 | D7: {=_xlfn.XLOOKUP( A7, tblTargets[TargetID], tblTargets[TargetType], "" )} -> BUILDING | E7: {=_xlfn.XLOOKUP( A7, tblTargetStatus[TargetID], tblTargetStatus[ChainAwareStatus], "" )} -> BLOCKED | F7: 52 | G7: FALSE | H7: {=_xlfn.XLOOKUP( A7, tblTargetStatus[TargetID], tblTargetStatus[TargetFunded], "" )} -> FALSE | I7: {=IF( D7<>"BUILDING", "", IF( Player!$H$1="Active", _xlfn.XLOOKUP( A7, tblrecommended[ActiveTargetID], tblrecommended[Order], "" ), _xlfn.XLOOKUP( A7, tblrecommended[PassiveTargetID], tblrecommended[Order], "" ) ) )} -> 52
A8: building.alchemists_hut@5 | B8: {=_xlfn.XLOOKUP(Checklist!$A8,tblTargets[TargetID],tblTargets[DisplayName])} -> Alchemist's Hut Lv 5 | C8: {=_xlfn.XLOOKUP( A8, tblTargetStatus[TargetID], tblTargetStatus[successors], "" )} -> Alchemist's Hut Lv 6 | D8: {=_xlfn.XLOOKUP( A8, tblTargets[TargetID], tblTargets[TargetType], "" )} -> BUILDING | E8: {=_xlfn.XLOOKUP( A8, tblTargetStatus[TargetID], tblTargetStatus[ChainAwareStatus], "" )} -> BLOCKED | F8: 53 | G8: FALSE | H8: {=_xlfn.XLOOKUP( A8, tblTargetStatus[TargetID], tblTargetStatus[TargetFunded], "" )} -> FALSE | I8: {=IF( D8<>"BUILDING", "", IF( Player!$H$1="Active", _xlfn.XLOOKUP( A8, tblrecommended[ActiveTargetID], tblrecommended[Order], "" ), _xlfn.XLOOKUP( A8, tblrecommended[PassiveTargetID], tblrecommended[Order], "" ) ) )} -> 53
A9: building.alchemists_hut@6 | B9: {=_xlfn.XLOOKUP(Checklist!$A9,tblTargets[TargetID],tblTargets[DisplayName])} -> Alchemist's Hut Lv 6 | C9: {=_xlfn.XLOOKUP( A9, tblTargetStatus[TargetID], tblTargetStatus[successors], "" )} -> Alchemists Hut maxed, Flamethrower, Tetrachloroaurate | D9: {=_xlfn.XLOOKUP( A9, tblTargets[TargetID], tblTargets[TargetType], "" )} -> BUILDING | E9: {=_xlfn.XLOOKUP( A9, tblTargetStatus[TargetID], tblTargetStatus[ChainAwareStatus], "" )} -> BLOCKED | F9: 54 | G9: FALSE | H9: {=_xlfn.XLOOKUP( A9, tblTargetStatus[TargetID], tblTargetStatus[TargetFunded], "" )} -> FALSE | I9: {=IF( D9<>"BUILDING", "", IF( Player!$H$1="Active", _xlfn.XLOOKUP( A9, tblrecommended[ActiveTargetID], tblrecommended[Order], "" ), _xlfn.XLOOKUP( A9, tblrecommended[PassiveTargetID], tblrecommended[Order], "" ) ) )} -> 54
A10: building.bonsai@1 | B10: {=_xlfn.XLOOKUP(Checklist!$A10,tblTargets[TargetID],tblTargets[DisplayName])} -> Bonsai Lv 1 | C10: {=_xlfn.XLOOKUP( A10, tblTargetStatus[TargetID], tblTargetStatus[successors], "" )} -> Bonsai Lv 2 | D10: {=_xlfn.XLOOKUP( A10, tblTargets[TargetID], tblTargets[TargetType], "" )} -> BUILDING | E10: {=_xlfn.XLOOKUP( A10, tblTargetStatus[TargetID], tblTargetStatus[ChainAwareStatus], "" )} -> ONE AWAY | F10: 89 | G10: FALSE | H10: {=_xlfn.XLOOKUP( A10, tblTargetStatus[TargetID], tblTargetStatus[TargetFunded], "" )} -> FALSE | I10: {=IF( D10<>"BUILDING", "", IF( Player!$H$1="Active", _xlfn.XLOOKUP( A10, tblrecommended[ActiveTargetID], tblrecommended[Order], "" ), _xlfn.XLOOKUP( A10, tblrecommended[PassiveTargetID], tblrecommended[Order], "" ) ) )} -> 89
A11: building.bonsai@2 | B11: {=_xlfn.XLOOKUP(Checklist!$A11,tblTargets[TargetID],tblTargets[DisplayName])} -> Bonsai Lv 2 | C11: {=_xlfn.XLOOKUP( A11, tblTargetStatus[TargetID], tblTargetStatus[successors], "" )} | D11: {=_xlfn.XLOOKUP( A11, tblTargets[TargetID], tblTargets[TargetType], "" )} -> BUILDING | E11: {=_xlfn.XLOOKUP( A11, tblTargetStatus[TargetID], tblTargetStatus[ChainAwareStatus], "" )} -> BLOCKED | F11: 90 | G11: FALSE | H11: {=_xlfn.XLOOKUP( A11, tblTargetStatus[TargetID], tblTargetStatus[TargetFunded], "" )} -> FALSE | I11: {=IF( D11<>"BUILDING", "", IF( Player!$H$1="Active", _xlfn.XLOOKUP( A11, tblrecommended[ActiveTargetID], tblrecommended[Order], "" ), _xlfn.XLOOKUP( A11, tblrecommended[PassiveTargetID], tblrecommended[Order], "" ) ) )} -> 90
A12: building.bridge@1 | B12: {=_xlfn.XLOOKUP(Checklist!$A12,tblTargets[TargetID],tblTargets[DisplayName])} -> Bridge Lv 1 | C12: {=_xlfn.XLOOKUP( A12, tblTargetStatus[TargetID], tblTargetStatus[successors], "" )} -> Airship Lv 1, Bridge maxed, Caravan Lv 1, Outpost Lv 1, Station Lv 1, Tailor Lv 1, Guild Banner, Guild Codex, Guild Supplies, Festival Accepted, Honor, Glory, Sushi Accepted, Silk Road Accepted | D12: {=_xlfn.XLOOKUP( A12, tblTargets[TargetID], tblTargets[TargetType], "" )} -> BUILDING | E12: {=_xlfn.XLOOKUP( A12, tblTargetStatus[TargetID], tblTargetStatus[ChainAwareStatus], "" )} -> ONE AWAY | F12: 27 | G12: FALSE | H12: {=_xlfn.XLOOKUP( A12, tblTargetStatus[TargetID], tblTargetStatus[TargetFunded], "" )} -> FALSE | I12: {=IF( D12<>"BUILDING", "", IF( Player!$H$1="Active", _xlfn.XLOOKUP( A12, tblrecommended[ActiveTargetID], tblrecommended[Order], "" ), _xlfn.XLOOKUP( A12, tblrecommended[PassiveTargetID], tblrecommended[Order], "" ) ) )} -> 27
A13: building.caravan@1 | B13: {=_xlfn.XLOOKUP(Checklist!$A13,tblTargets[TargetID],tblTargets[DisplayName])} -> Caravan Lv 1 | C13: {=_xlfn.XLOOKUP( A13, tblTargetStatus[TargetID], tblTargetStatus[successors], "" )} -> Caravan Lv 2 | D13: {=_xlfn.XLOOKUP( A13, tblTargets[TargetID], tblTargets[TargetType], "" )} -> BUILDING | E13: {=_xlfn.XLOOKUP( A13, tblTargetStatus[TargetID], tblTargetStatus[ChainAwareStatus], "" )} -> BLOCKED | F13: 36 | G13: FALSE | H13: {=_xlfn.XLOOKUP( A13, tblTargetStatus[TargetID], tblTargetStatus[TargetFunded], "" )} -> FALSE | I13: {=IF( D13<>"BUILDING", "", IF( Player!$H$1="Active", _xlfn.XLOOKUP( A13, tblrecommended[ActiveTargetID], tblrecommended[Order], "" ), _xlfn.XLOOKUP( A13, tblrecommended[PassiveTargetID], tblrecommended[Order], "" ) ) )} -> 36
... A25: building.dungeon@5 | B25: {=_xlfn.XLOOKUP(Checklist!$A25,tblTargets[TargetID],tblTargets[DisplayName])} -> Dungeon Lv 5 | C25: {=_xlfn.XLOOKUP( A25, tblTargetStatus[TargetID], tblTargetStatus[successors], "" )} -> dungeon maxed, Dungeon Lv 6, Attic, Courtyard, Lair lvl. 1, Tavern, Metal Detector, Magic Beans Accepted, Tame A Critter, Complete Dungeon 5C | D25: {=_xlfn.XLOOKUP( A25, tblTargets[TargetID], tblTargets[TargetType], "" )} -> BUILDING | E25: {=_xlfn.XLOOKUP( A25, tblTargetStatus[TargetID], tblTargetStatus[ChainAwareStatus], "" )} -> BLOCKED | F25: 65 | G25: FALSE | H25: {=_xlfn.XLOOKUP( A25, tblTargetStatus[TargetID], tblTargetStatus[TargetFunded], "" )} -> FALSE | I25: {=IF( D25<>"BUILDING", "", IF( Player!$H$1="Active", _xlfn.XLOOKUP( A25, tblrecommended[ActiveTargetID], tblrecommended[Order], "" ), _xlfn.XLOOKUP( A25, tblrecommended[PassiveTargetID], tblrecommended[Order], "" ) ) )} -> 65
A26: building.dungeon@6 | B26: {=_xlfn.XLOOKUP(Checklist!$A26,tblTargets[TargetID],tblTargets[DisplayName])} -> Dungeon Lv 6 | C26: {=_xlfn.XLOOKUP( A26, tblTargetStatus[TargetID], tblTargetStatus[successors], "" )} -> Complete Dungeon 6C | D26: {=_xlfn.XLOOKUP( A26, tblTargets[TargetID], tblTargets[TargetType], "" )} -> BUILDING | E26: {=_xlfn.XLOOKUP( A26, tblTargetStatus[TargetID], tblTargetStatus[ChainAwareStatus], "" )} -> BLOCKED | G26: FALSE | H26: {=_xlfn.XLOOKUP( A26, tblTargetStatus[TargetID], tblTargetStatus[TargetFunded], "" )} -> N/A | I26: {=IF( D26<>"BUILDING", "", IF( Player!$H$1="Active", _xlfn.XLOOKUP( A26, tblrecommended[ActiveTargetID], tblrecommended[Order], "" ), _xlfn.XLOOKUP( A26, tblrecommended[PassiveTargetID], tblrecommended[Order], "" ) ) )}
A27: building.fermentory@1 | B27: {=_xlfn.XLOOKUP(Checklist!$A27,tblTargets[TargetID],tblTargets[DisplayName])} -> Fermentory Lv 1 | C27: {=_xlfn.XLOOKUP( A27, tblTargetStatus[TargetID], tblTargetStatus[successors], "" )} -> Fermentory Lv 2 | D27: {=_xlfn.XLOOKUP( A27, tblTargets[TargetID], tblTargets[TargetType], "" )} -> BUILDING | E27: {=_xlfn.XLOOKUP( A27, tblTargetStatus[TargetID], tblTargetStatus[ChainAwareStatus], "" )} -> BLOCKED | F27: 72 | G27: FALSE | H27: {=_xlfn.XLOOKUP( A27, tblTargetStatus[TargetID], tblTargetStatus[TargetFunded], "" )} -> FALSE | I27: {=IF( D27<>"BUILDING", "", IF( Player!$H$1="Active", _xlfn.XLOOKUP( A27, tblrecommended[ActiveTargetID], tblrecommended[Order], "" ), _xlfn.XLOOKUP( A27, tblrecommended[PassiveTargetID], tblrecommended[Order], "" ) ) )} -> 72
A28: building.fermentory@2 | B28: {=_xlfn.XLOOKUP(Checklist!$A28,tblTargets[TargetID],tblTargets[DisplayName])} -> Fermentory Lv 2 | C28: {=_xlfn.XLOOKUP( A28, tblTargetStatus[TargetID], tblTargetStatus[successors], "" )} -> Fermentory Lv 3 | D28: {=_xlfn.XLOOKUP( A28, tblTargets[TargetID], tblTargets[TargetType], "" )} -> BUILDING | E28: {=_xlfn.XLOOKUP( A28, tblTargetStatus[TargetID], tblTargetStatus[ChainAwareStatus], "" )} -> BLOCKED | F28: 73 | G28: FALSE | H28: {=_xlfn.XLOOKUP( A28, tblTargetStatus[TargetID], tblTargetStatus[TargetFunded], "" )} -> FALSE | I28: {=IF( D28<>"BUILDING", "", IF( Player!$H$1="Active", _xlfn.XLOOKUP( A28, tblrecommended[ActiveTargetID], tblrecommended[Order], "" ), _xlfn.XLOOKUP( A28, tblrecommended[PassiveTargetID], tblrecommended[Order], "" ) ) )} -> 73
A29: building.fermentory@3 | B29: {=_xlfn.XLOOKUP(Checklist!$A29,tblTargets[TargetID],tblTargets[DisplayName])} -> Fermentory Lv 3 | C29: {=_xlfn.XLOOKUP( A29, tblTargetStatus[TargetID], tblTargetStatus[successors], "" )} -> Fermentory Lv 4 | D29: {=_xlfn.XLOOKUP( A29, tblTargets[TargetID], tblTargets[TargetType], "" )} -> BUILDING | E29: {=_xlfn.XLOOKUP( A29, tblTargetStatus[TargetID], tblTargetStatus[ChainAwareStatus], "" )} -> BLOCKED | F29: 74 | G29: FALSE | H29: {=_xlfn.XLOOKUP( A29, tblTargetStatus[TargetID], tblTargetStatus[TargetFunded], "" )} -> FALSE | I29: {=IF( D29<>"BUILDING", "", IF( Player!$H$1="Active", _xlfn.XLOOKUP( A29, tblrecommended[ActiveTargetID], tblrecommended[Order], "" ), _xlfn.XLOOKUP( A29, tblrecommended[PassiveTargetID], tblrecommended[Order], "" ) ) )} -> 74
A30: building.fermentory@4 | B30: {=_xlfn.XLOOKUP(Checklist!$A30,tblTargets[TargetID],tblTargets[DisplayName])} -> Fermentory Lv 4 | C30: {=_xlfn.XLOOKUP( A30, tblTargetStatus[TargetID], tblTargetStatus[successors], "" )} -> Fermentory Lv 5 | D30: {=_xlfn.XLOOKUP( A30, tblTargets[TargetID], tblTargets[TargetType], "" )} -> BUILDING | E30: {=_xlfn.XLOOKUP( A30, tblTargetStatus[TargetID], tblTargetStatus[ChainAwareStatus], "" )} -> BLOCKED | F30: 79 | G30: FALSE | H30: {=_xlfn.XLOOKUP( A30, tblTargetStatus[TargetID], tblTargetStatus[TargetFunded], "" )} -> FALSE | I30: {=IF( D30<>"BUILDING", "", IF( Player!$H$1="Active", _xlfn.XLOOKUP( A30, tblrecommended[ActiveTargetID], tblrecommended[Order], "" ), _xlfn.XLOOKUP( A30, tblrecommended[PassiveTargetID], tblrecommended[Order], "" ) ) )} -> 79
A31: building.fermentory@5 | B31: {=_xlfn.XLOOKUP(Checklist!$A31,tblTargets[TargetID],tblTargets[DisplayName])} -> Fermentory Lv 5 | C31: {=_xlfn.XLOOKUP( A31, tblTargetStatus[TargetID], tblTargetStatus[successors], "" )} -> Fermentory Lv 6 | D31: {=_xlfn.XLOOKUP( A31, tblTargets[TargetID], tblTargets[TargetType], "" )} -> BUILDING | E31: {=_xlfn.XLOOKUP( A31, tblTargetStatus[TargetID], tblTargetStatus[ChainAwareStatus], "" )} -> BLOCKED | F31: 80 | G31: FALSE | H31: {=_xlfn.XLOOKUP( A31, tblTargetStatus[TargetID], tblTargetStatus[TargetFunded], "" )} -> FALSE | I31: {=IF( D31<>"BUILDING", "", IF( Player!$H$1="Active", _xlfn.XLOOKUP( A31, tblrecommended[ActiveTargetID], tblrecommended[Order], "" ), _xlfn.XLOOKUP( A31, tblrecommended[PassiveTargetID], tblrecommended[Order], "" ) ) )} -> 80
A32: building.fermentory@6 | B32: {=_xlfn.XLOOKUP(Checklist!$A32,tblTargets[TargetID],tblTargets[DisplayName])} -> Fermentory Lv 6 | C32: {=_xlfn.XLOOKUP( A32, tblTargetStatus[TargetID], tblTargetStatus[successors], "" )} -> Fermentory maxed, Festival of Beans Accepted | D32: {=_xlfn.XLOOKUP( A32, tblTargets[TargetID], tblTargets[TargetType], "" )} -> BUILDING | E32: {=_xlfn.XLOOKUP( A32, tblTargetStatus[TargetID], tblTargetStatus[ChainAwareStatus], "" )} -> BLOCKED | F32: 81 | G32: FALSE | H32: {=_xlfn.XLOOKUP( A32, tblTargetStatus[TargetID], tblTargetStatus[TargetFunded], "" )} -> FALSE | I32: {=IF( D32<>"BUILDING", "", IF( Player!$H$1="Active", _xlfn.XLOOKUP( A32, tblrecommended[ActiveTargetID], tblrecommended[Order], "" ), _xlfn.XLOOKUP( A32, tblrecommended[PassiveTargetID], tblrecommended[Order], "" ) ) )} -> 81
A33: building.field@1 | B33: {=_xlfn.XLOOKUP(Checklist!$A33,tblTargets[TargetID],tblTargets[DisplayName])} -> Field Lv 1 | C33: {=_xlfn.XLOOKUP( A33, tblTargetStatus[TargetID], tblTargetStatus[successors], "" )} -> Field Lv 2, Quest for Knowledge Chapter 1 Finished | D33: {=_xlfn.XLOOKUP( A33, tblTargets[TargetID], tblTargets[TargetType], "" )} -> BUILDING | E33: {=_xlfn.XLOOKUP( A33, tblTargetStatus[TargetID], tblTargetStatus[ChainAwareStatus], "" )} -> ONE AWAY | F33: 6 | G33: FALSE | H33: {=_xlfn.XLOOKUP( A33, tblTargetStatus[TargetID], tblTargetStatus[TargetFunded], "" )} -> FALSE | I33: {=IF( D33<>"BUILDING", "", IF( Player!$H$1="Active", _xlfn.XLOOKUP( A33, tblrecommended[ActiveTargetID], tblrecommended[Order], "" ), _xlfn.XLOOKUP( A33, tblrecommended[PassiveTargetID], tblrecommended[Order], "" ) ) )} -> 6
A34: building.field@2 | B34: {=_xlfn.XLOOKUP(Checklist!$A34,tblTargets[TargetID],tblTargets[DisplayName])} -> Field Lv 2 | C34: {=_xlfn.XLOOKUP( A34, tblTargetStatus[TargetID], tblTargetStatus[successors], "" )} -> Field maxed | D34: {=_xlfn.XLOOKUP( A34, tblTargets[TargetID], tblTargets[TargetType], "" )} -> BUILDING | E34: {=_xlfn.XLOOKUP( A34, tblTargetStatus[TargetID], tblTargetStatus[ChainAwareStatus], "" )} -> BLOCKED | F34: 8 | G34: FALSE | H34: {=_xlfn.XLOOKUP( A34, tblTargetStatus[TargetID], tblTargetStatus[TargetFunded], "" )} -> FALSE | I34: {=IF( D34<>"BUILDING", "", IF( Player!$H$1="Active", _xlfn.XLOOKUP( A34, tblrecommended[ActiveTargetID], tblrecommended[Order], "" ), _xlfn.XLOOKUP( A34, tblrecommended[PassiveTargetID], tblrecommended[Order], "" ) ) )} -> 8
A35: building.food_stall@1 | B35: {=_xlfn.XLOOKUP(Checklist!$A35,tblTargets[TargetID],tblTargets[DisplayName])} -> Food Stall Lv 1 | C35: {=_xlfn.XLOOKUP( A35, tblTargetStatus[TargetID], tblTargetStatus[successors], "" )} -> Food Stall Lv 2, Quest for Knowledge Chapter 1 Finished | D35: {=_xlfn.XLOOKUP( A35, tblTargets[TargetID], tblTargets[TargetType], "" )} -> BUILDING | E35: {=_xlfn.XLOOKUP( A35, tblTargetStatus[TargetID], tblTargetStatus[ChainAwareStatus], "" )} -> ONE AWAY | F35: 7 | G35: FALSE | H35: {=_xlfn.XLOOKUP( A35, tblTargetStatus[TargetID], tblTargetStatus[TargetFunded], "" )} -> FALSE | I35: {=IF( D35<>"BUILDING", "", IF( Player!$H$1="Active", _xlfn.XLOOKUP( A35, tblrecommended[ActiveTargetID], tblrecommended[Order], "" ), _xlfn.XLOOKUP( A35, tblrecommended[PassiveTargetID], tblrecommended[Order], "" ) ) )} -> 7
A36: building.food_stall@2 | B36: {=_xlfn.XLOOKUP(Checklist!$A36,tblTargets[TargetID],tblTargets[DisplayName])} -> Food Stall Lv 2 | C36: {=_xlfn.XLOOKUP( A36, tblTargetStatus[TargetID], tblTargetStatus[successors], "" )} -> Food Stall Lv 3, Shogun's Katana Chapter 3 Finished | D36: {=_xlfn.XLOOKUP( A36, tblTargets[TargetID], tblTargets[TargetType], "" )} -> BUILDING | E36: {=_xlfn.XLOOKUP( A36, tblTargetStatus[TargetID], tblTargetStatus[ChainAwareStatus], "" )} -> BLOCKED | F36: 25 | G36: FALSE | H36: {=_xlfn.XLOOKUP( A36, tblTargetStatus[TargetID], tblTargetStatus[TargetFunded], "" )} -> FALSE | I36: {=IF( D36<>"BUILDING", "", IF( Player!$H$1="Active", _xlfn.XLOOKUP( A36, tblrecommended[ActiveTargetID], tblrecommended[Order], "" ), _xlfn.XLOOKUP( A36, tblrecommended[PassiveTargetID], tblrecommended[Order], "" ) ) )} -> 25
A37: building.food_stall@3 | B37: {=_xlfn.XLOOKUP(Checklist!$A37,tblTargets[TargetID],tblTargets[DisplayName])} -> Food Stall Lv 3 | C37: {=_xlfn.XLOOKUP( A37, tblTargetStatus[TargetID], tblTargetStatus[successors], "" )} -> Food stall maxed, Guild Supplies, Shogun's Katana Chapter 6 Finished | D37: {=_xlfn.XLOOKUP( A37, tblTargets[TargetID], tblTargets[TargetType], "" )} -> BUILDING | E37: {=_xlfn.XLOOKUP( A37, tblTargetStatus[TargetID], tblTargetStatus[ChainAwareStatus], "" )} -> BLOCKED | F37: 26 | G37: FALSE | H37: {=_xlfn.XLOOKUP( A37, tblTargetStatus[TargetID], tblTargetStatus[TargetFunded], "" )} -> FALSE | I37: {=IF( D37<>"BUILDING", "", IF( Player!$H$1="Active", _xlfn.XLOOKUP( A37, tblrecommended[ActiveTargetID], tblrecommended[Order], "" ), _xlfn.XLOOKUP( A37, tblrecommended[PassiveTargetID], tblrecommended[Order], "" ) ) )} -> 26
A38: building.furnace@1 | B38: {=_xlfn.XLOOKUP(Checklist!$A38,tblTargets[TargetID],tblTargets[DisplayName])} -> Furnace Lv 1 | C38: {=_xlfn.XLOOKUP( A38, tblTargetStatus[TargetID], tblTargetStatus[successors], "" )} -> Furnace Lv 2, Shogun's Katana Chapter 1 Finished | D38: {=_xlfn.XLOOKUP( A38, tblTargets[TargetID], tblTargets[TargetType], "" )} -> BUILDING | E38: {=_xlfn.XLOOKUP( A38, tblTargetStatus[TargetID], tblTargetStatus[ChainAwareStatus], "" )} -> ONE AWAY | F38: 10 | G38: FALSE | H38: {=_xlfn.XLOOKUP( A38, tblTargetStatus[TargetID], tblTargetStatus[TargetFunded], "" )} -> FALSE | I38: {=IF( D38<>"BUILDING", "", IF( Player!$H$1="Active", _xlfn.XLOOKUP( A38, tblrecommended[ActiveTargetID], tblrecommended[Order], "" ), _xlfn.XLOOKUP( A38, tblrecommended[PassiveTargetID], tblrecommended[Order], "" ) ) )} -> 10
... A44: building.gong@1 | B44: {=_xlfn.XLOOKUP(Checklist!$A44,tblTargets[TargetID],tblTargets[DisplayName])} -> Gong Lv 1 | C44: {=_xlfn.XLOOKUP( A44, tblTargetStatus[TargetID], tblTargetStatus[successors], "" )} | D44: {=_xlfn.XLOOKUP( A44, tblTargets[TargetID], tblTargets[TargetType], "" )} -> BUILDING | E44: {=_xlfn.XLOOKUP( A44, tblTargetStatus[TargetID], tblTargetStatus[ChainAwareStatus], "" )} -> ONE AWAY | F44: 102 | G44: FALSE | H44: {=_xlfn.XLOOKUP( A44, tblTargetStatus[TargetID], tblTargetStatus[TargetFunded], "" )} -> FALSE | I44: {=IF( D44<>"BUILDING", "", IF( Player!$H$1="Active", _xlfn.XLOOKUP( A44, tblrecommended[ActiveTargetID], tblrecommended[Order], "" ), _xlfn.XLOOKUP( A44, tblrecommended[PassiveTargetID], tblrecommended[Order], "" ) ) )} -> 102
A45: building.guild@1 | B45: {=_xlfn.XLOOKUP(Checklist!$A45,tblTargets[TargetID],tblTargets[DisplayName])} -> Guild Lv 1 | C45: {=_xlfn.XLOOKUP( A45, tblTargetStatus[TargetID], tblTargetStatus[successors], "" )} -> Guild Lv 2 | D45: {=_xlfn.XLOOKUP( A45, tblTargets[TargetID], tblTargets[TargetType], "" )} -> BUILDING | E45: {=_xlfn.XLOOKUP( A45, tblTargetStatus[TargetID], tblTargetStatus[ChainAwareStatus], "" )} -> COMPLETED | G45: TRUE | H45: {=_xlfn.XLOOKUP( A45, tblTargetStatus[TargetID], tblTargetStatus[TargetFunded], "" )} -> N/A | I45: {=IF( D45<>"BUILDING", "", IF( Player!$H$1="Active", _xlfn.XLOOKUP( A45, tblrecommended[ActiveTargetID], tblrecommended[Order], "" ), _xlfn.XLOOKUP( A45, tblrecommended[PassiveTargetID], tblrecommended[Order], "" ) ) )}
A46: building.guild@2 | B46: {=_xlfn.XLOOKUP(Checklist!$A46,tblTargets[TargetID],tblTargets[DisplayName])} -> Guild Lv 2 | C46: {=_xlfn.XLOOKUP( A46, tblTargetStatus[TargetID], tblTargetStatus[successors], "" )} -> Alchemist's Hut Lv 2, Food Stall Lv 2, Guild Lv 3, Warehouse Lv 2 | D46: {=_xlfn.XLOOKUP( A46, tblTargets[TargetID], tblTargets[TargetType], "" )} -> BUILDING | E46: {=_xlfn.XLOOKUP( A46, tblTargetStatus[TargetID], tblTargetStatus[ChainAwareStatus], "" )} -> READY | F46: 1 | G46: FALSE | H46: {=_xlfn.XLOOKUP( A46, tblTargetStatus[TargetID], tblTargetStatus[TargetFunded], "" )} -> FALSE | I46: {=IF( D46<>"BUILDING", "", IF( Player!$H$1="Active", _xlfn.XLOOKUP( A46, tblrecommended[ActiveTargetID], tblrecommended[Order], "" ), _xlfn.XLOOKUP( A46, tblrecommended[PassiveTargetID], tblrecommended[Order], "" ) ) )} -> 1
A47: building.guild@3 | B47: {=_xlfn.XLOOKUP(Checklist!$A47,tblTargets[TargetID],tblTargets[DisplayName])} -> Guild Lv 3 | C47: {=_xlfn.XLOOKUP( A47, tblTargetStatus[TargetID], tblTargetStatus[successors], "" )} -> Alchemist's Hut Lv 3, Alchemist's Hut Lv 4, Guild Lv 4, Warehouse Lv 3 | D47: {=_xlfn.XLOOKUP( A47, tblTargets[TargetID], tblTargets[TargetType], "" )} -> BUILDING | E47: {=_xlfn.XLOOKUP( A47, tblTargetStatus[TargetID], tblTargetStatus[ChainAwareStatus], "" )} -> ONE AWAY | F47: 17 | G47: FALSE | H47: {=_xlfn.XLOOKUP( A47, tblTargetStatus[TargetID], tblTargetStatus[TargetFunded], "" )} -> FALSE | I47: {=IF( D47<>"BUILDING", "", IF( Player!$H$1="Active", _xlfn.XLOOKUP( A47, tblrecommended[ActiveTargetID], tblrecommended[Order], "" ), _xlfn.XLOOKUP( A47, tblrecommended[PassiveTargetID], tblrecommended[Order], "" ) ) )} -> 17
A48: building.guild@4 | B48: {=_xlfn.XLOOKUP(Checklist!$A48,tblTargets[TargetID],tblTargets[DisplayName])} -> Guild Lv 4 | C48: {=_xlfn.XLOOKUP( A48, tblTargetStatus[TargetID], tblTargetStatus[successors], "" )} -> Alchemist's Hut Lv 4, Guild Lv 5, Warehouse Lv 4 | D48: {=_xlfn.XLOOKUP( A48, tblTargets[TargetID], tblTargets[TargetType], "" )} -> BUILDING | E48: {=_xlfn.XLOOKUP( A48, tblTargetStatus[TargetID], tblTargetStatus[ChainAwareStatus], "" )} -> BLOCKED | F48: 23 | G48: FALSE | H48: {=_xlfn.XLOOKUP( A48, tblTargetStatus[TargetID], tblTargetStatus[TargetFunded], "" )} -> FALSE | I48: {=IF( D48<>"BUILDING", "", IF( Player!$H$1="Active", _xlfn.XLOOKUP( A48, tblrecommended[ActiveTargetID], tblrecommended[Order], "" ), _xlfn.XLOOKUP( A48, tblrecommended[PassiveTargetID], tblrecommended[Order], "" ) ) )} -> 23
A49: building.guild@5 | B49: {=_xlfn.XLOOKUP(Checklist!$A49,tblTargets[TargetID],tblTargets[DisplayName])} -> Guild Lv 5 | C49: {=_xlfn.XLOOKUP( A49, tblTargetStatus[TargetID], tblTargetStatus[successors], "" )} -> Alchemist's Hut Lv 5, Warehouse Lv 5, Emerald Tablet, Guild Codex, Historical Library, Trigonometry, Build the Guild Finished | D49: {=_xlfn.XLOOKUP( A49, tblTargets[TargetID], tblTargets[TargetType], "" )} -> BUILDING | E49: {=_xlfn.XLOOKUP( A49, tblTargetStatus[TargetID], tblTargetStatus[ChainAwareStatus], "" )} -> BLOCKED | F49: 29 | G49: FALSE | H49: {=_xlfn.XLOOKUP( A49, tblTargetStatus[TargetID], tblTargetStatus[TargetFunded], "" )} -> FALSE | I49: {=IF( D49<>"BUILDING", "", IF( Player!$H$1="Active", _xlfn.XLOOKUP( A49, tblrecommended[ActiveTargetID], tblrecommended[Order], "" ), _xlfn.XLOOKUP( A49, tblrecommended[PassiveTargetID], tblrecommended[Order], "" ) ) )} -> 29
A50: building.guild_video_game_arcade@1 | B50: {=_xlfn.XLOOKUP(Checklist!$A50,tblTargets[TargetID],tblTargets[DisplayName])} -> Guild: Video Game Arcade Lv 1 | C50: {=_xlfn.XLOOKUP( A50, tblTargetStatus[TargetID], tblTargetStatus[successors], "" )} | D50: {=_xlfn.XLOOKUP( A50, tblTargets[TargetID], tblTargets[TargetType], "" )} -> BUILDING | E50: {=_xlfn.XLOOKUP( A50, tblTargetStatus[TargetID], tblTargetStatus[ChainAwareStatus], "" )} -> BLOCKED | G50: FALSE | H50: {=_xlfn.XLOOKUP( A50, tblTargetStatus[TargetID], tblTargetStatus[TargetFunded], "" )} -> FALSE | I50: {=IF( D50<>"BUILDING", "", IF( Player!$H$1="Active", _xlfn.XLOOKUP( A50, tblrecommended[ActiveTargetID], tblrecommended[Order], "" ), _xlfn.XLOOKUP( A50, tblrecommended[PassiveTargetID], tblrecommended[Order], "" ) ) )}
A51: building.laboratory@1 | B51: {=_xlfn.XLOOKUP(Checklist!$A51,tblTargets[TargetID],tblTargets[DisplayName])} -> Laboratory Lv 1 | C51: {=_xlfn.XLOOKUP( A51, tblTargetStatus[TargetID], tblTargetStatus[successors], "" )} -> Laboratory Lv 2 | D51: {=_xlfn.XLOOKUP( A51, tblTargets[TargetID], tblTargets[TargetType], "" )} -> BUILDING | E51: {=_xlfn.XLOOKUP( A51, tblTargetStatus[TargetID], tblTargetStatus[ChainAwareStatus], "" )} -> BLOCKED | F51: 66 | G51: FALSE | H51: {=_xlfn.XLOOKUP( A51, tblTargetStatus[TargetID], tblTargetStatus[TargetFunded], "" )} -> FALSE | I51: {=IF( D51<>"BUILDING", "", IF( Player!$H$1="Active", _xlfn.XLOOKUP( A51, tblrecommended[ActiveTargetID], tblrecommended[Order], "" ), _xlfn.XLOOKUP( A51, tblrecommended[PassiveTargetID], tblrecommended[Order], "" ) ) )} -> 66
A52: building.laboratory@2 | B52: {=_xlfn.XLOOKUP(Checklist!$A52,tblTargets[TargetID],tblTargets[DisplayName])} -> Laboratory Lv 2 | C52: {=_xlfn.XLOOKUP( A52, tblTargetStatus[TargetID], tblTargetStatus[successors], "" )} -> Laboratory Lv 3 | D52: {=_xlfn.XLOOKUP( A52, tblTargets[TargetID], tblTargets[TargetType], "" )} -> BUILDING | E52: {=_xlfn.XLOOKUP( A52, tblTargetStatus[TargetID], tblTargetStatus[ChainAwareStatus], "" )} -> BLOCKED | F52: 67 | G52: FALSE | H52: {=_xlfn.XLOOKUP( A52, tblTargetStatus[TargetID], tblTargetStatus[TargetFunded], "" )} -> FALSE | I52: {=IF( D52<>"BUILDING", "", IF( Player!$H$1="Active", _xlfn.XLOOKUP( A52, tblrecommended[ActiveTargetID], tblrecommended[Order], "" ), _xlfn.XLOOKUP( A52, tblrecommended[PassiveTargetID], tblrecommended[Order], "" ) ) )} -> 67
A53: building.laboratory@3 | B53: {=_xlfn.XLOOKUP(Checklist!$A53,tblTargets[TargetID],tblTargets[DisplayName])} -> Laboratory Lv 3 | C53: {=_xlfn.XLOOKUP( A53, tblTargetStatus[TargetID], tblTargetStatus[successors], "" )} -> Laboratory Lv 4 | D53: {=_xlfn.XLOOKUP( A53, tblTargets[TargetID], tblTargets[TargetType], "" )} -> BUILDING | E53: {=_xlfn.XLOOKUP( A53, tblTargetStatus[TargetID], tblTargetStatus[ChainAwareStatus], "" )} -> BLOCKED | F53: 68 | G53: FALSE | H53: {=_xlfn.XLOOKUP( A53, tblTargetStatus[TargetID], tblTargetStatus[TargetFunded], "" )} -> FALSE | I53: {=IF( D53<>"BUILDING", "", IF( Player!$H$1="Active", _xlfn.XLOOKUP( A53, tblrecommended[ActiveTargetID], tblrecommended[Order], "" ), _xlfn.XLOOKUP( A53, tblrecommended[PassiveTargetID], tblrecommended[Order], "" ) ) )} -> 68
A54: building.laboratory@4 | B54: {=_xlfn.XLOOKUP(Checklist!$A54,tblTargets[TargetID],tblTargets[DisplayName])} -> Laboratory Lv 4 | C54: {=_xlfn.XLOOKUP( A54, tblTargetStatus[TargetID], tblTargetStatus[successors], "" )} -> Laboratory Lv 5 | D54: {=_xlfn.XLOOKUP( A54, tblTargets[TargetID], tblTargets[TargetType], "" )} -> BUILDING | E54: {=_xlfn.XLOOKUP( A54, tblTargetStatus[TargetID], tblTargetStatus[ChainAwareStatus], "" )} -> BLOCKED | F54: 75 | G54: FALSE | H54: {=_xlfn.XLOOKUP( A54, tblTargetStatus[TargetID], tblTargetStatus[TargetFunded], "" )} -> FALSE | I54: {=IF( D54<>"BUILDING", "", IF( Player!$H$1="Active", _xlfn.XLOOKUP( A54, tblrecommended[ActiveTargetID], tblrecommended[Order], "" ), _xlfn.XLOOKUP( A54, tblrecommended[PassiveTargetID], tblrecommended[Order], "" ) ) )} -> 75
A55: building.laboratory@5 | B55: {=_xlfn.XLOOKUP(Checklist!$A55,tblTargets[TargetID],tblTargets[DisplayName])} -> Laboratory Lv 5 | C55: {=_xlfn.XLOOKUP( A55, tblTargetStatus[TargetID], tblTargetStatus[successors], "" )} -> Laboratory maxed, Ahead of Time Chapter 1 Finished | D55: {=_xlfn.XLOOKUP( A55, tblTargets[TargetID], tblTargets[TargetType], "" )} -> BUILDING | E55: {=_xlfn.XLOOKUP( A55, tblTargetStatus[TargetID], tblTargetStatus[ChainAwareStatus], "" )} -> BLOCKED | F55: 76 | G55: FALSE | H55: {=_xlfn.XLOOKUP( A55, tblTargetStatus[TargetID], tblTargetStatus[TargetFunded], "" )} -> FALSE | I55: {=IF( D55<>"BUILDING", "", IF( Player!$H$1="Active", _xlfn.XLOOKUP( A55, tblrecommended[ActiveTargetID], tblrecommended[Order], "" ), _xlfn.XLOOKUP( A55, tblrecommended[PassiveTargetID], tblrecommended[Order], "" ) ) )} -> 76
A56: building.laboratory_data_center@1 | B56: {=_xlfn.XLOOKUP(Checklist!$A56,tblTargets[TargetID],tblTargets[DisplayName])} -> Laboratory: Data Center Lv 1 | C56: {=_xlfn.XLOOKUP( A56, tblTargetStatus[TargetID], tblTargetStatus[successors], "" )} -> Laboratory: Data Center maxed, Ahead of Time Chapter 5 Finished | D56: {=_xlfn.XLOOKUP( A56, tblTargets[TargetID], tblTargets[TargetType], "" )} -> BUILDING | E56: {=_xlfn.XLOOKUP( A56, tblTargetStatus[TargetID], tblTargetStatus[ChainAwareStatus], "" )} -> BLOCKED | G56: FALSE | H56: {=_xlfn.XLOOKUP( A56, tblTargetStatus[TargetID], tblTargetStatus[TargetFunded], "" )} -> FALSE | I56: {=IF( D56<>"BUILDING", "", IF( Player!$H$1="Active", _xlfn.XLOOKUP( A56, tblrecommended[ActiveTargetID], tblrecommended[Order], "" ), _xlfn.XLOOKUP( A56, tblrecommended[PassiveTargetID], tblrecommended[Order], "" ) ) )}
A57: building.lumber@1 | B57: {=_xlfn.XLOOKUP(Checklist!$A57,tblTargets[TargetID],tblTargets[DisplayName])} -> Lumber Lv 1 | C57: {=_xlfn.XLOOKUP( A57, tblTargetStatus[TargetID], tblTargetStatus[successors], "" )} -> Lumber Lv 2 | D57: {=_xlfn.XLOOKUP( A57, tblTargets[TargetID], tblTargets[TargetType], "" )} -> BUILDING | E57: {=_xlfn.XLOOKUP( A57, tblTargetStatus[TargetID], tblTargetStatus[ChainAwareStatus], "" )} -> ONE AWAY | F57: 13 | G57: FALSE | H57: {=_xlfn.XLOOKUP( A57, tblTargetStatus[TargetID], tblTargetStatus[TargetFunded], "" )} -> FALSE | I57: {=IF( D57<>"BUILDING", "", IF( Player!$H$1="Active", _xlfn.XLOOKUP( A57, tblrecommended[ActiveTargetID], tblrecommended[Order], "" ), _xlfn.XLOOKUP( A57, tblrecommended[PassiveTargetID], tblrecommended[Order], "" ) ) )} -> 13
A58: building.lumber@2 | B58: {=_xlfn.XLOOKUP(Checklist!$A58,tblTargets[TargetID],tblTargets[DisplayName])} -> Lumber Lv 2 | C58: {=_xlfn.XLOOKUP( A58, tblTargetStatus[TargetID], tblTargetStatus[successors], "" )} -> Lumber Lv 3 | D58: {=_xlfn.XLOOKUP( A58, tblTargets[TargetID], tblTargets[TargetType], "" )} -> BUILDING | E58: {=_xlfn.XLOOKUP( A58, tblTargetStatus[TargetID], tblTargetStatus[ChainAwareStatus], "" )} -> BLOCKED | F58: 14 | G58: FALSE | H58: {=_xlfn.XLOOKUP( A58, tblTargetStatus[TargetID], tblTargetStatus[TargetFunded], "" )} -> FALSE | I58: {=IF( D58<>"BUILDING", "", IF( Player!$H$1="Active", _xlfn.XLOOKUP( A58, tblrecommended[ActiveTargetID], tblrecommended[Order], "" ), _xlfn.XLOOKUP( A58, tblrecommended[PassiveTargetID], tblrecommended[Order], "" ) ) )} -> 14
A59: building.lumber@3 | B59: {=_xlfn.XLOOKUP(Checklist!$A59,tblTargets[TargetID],tblTargets[DisplayName])} -> Lumber Lv 3 | C59: {=_xlfn.XLOOKUP( A59, tblTargetStatus[TargetID], tblTargetStatus[successors], "" )} -> Shogun's Katana Chapter 2 Finished | D59: {=_xlfn.XLOOKUP( A59, tblTargets[TargetID], tblTargets[TargetType], "" )} -> BUILDING | E59: {=_xlfn.XLOOKUP( A59, tblTargetStatus[TargetID], tblTargetStatus[ChainAwareStatus], "" )} -> BLOCKED | F59: 18 | G59: FALSE | H59: {=_xlfn.XLOOKUP( A59, tblTargetStatus[TargetID], tblTargetStatus[TargetFunded], "" )} -> FALSE | I59: {=IF( D59<>"BUILDING", "", IF( Player!$H$1="Active", _xlfn.XLOOKUP( A59, tblrecommended[ActiveTargetID], tblrecommended[Order], "" ), _xlfn.XLOOKUP( A59, tblrecommended[PassiveTargetID], tblrecommended[Order], "" ) ) )} -> 18
A60: building.onsen@1 | B60: {=_xlfn.XLOOKUP(Checklist!$A60,tblTargets[TargetID],tblTargets[DisplayName])} -> Onsen Lv 1 | C60: {=_xlfn.XLOOKUP( A60, tblTargetStatus[TargetID], tblTargetStatus[successors], "" )} -> Onsen Lv 2 | D60: {=_xlfn.XLOOKUP( A60, tblTargets[TargetID], tblTargets[TargetType], "" )} -> BUILDING | E60: {=_xlfn.XLOOKUP( A60, tblTargetStatus[TargetID], tblTargetStatus[ChainAwareStatus], "" )} -> ONE AWAY | F60: 91 | G60: FALSE | H60: {=_xlfn.XLOOKUP( A60, tblTargetStatus[TargetID], tblTargetStatus[TargetFunded], "" )} -> FALSE | I60: {=IF( D60<>"BUILDING", "", IF( Player!$H$1="Active", _xlfn.XLOOKUP( A60, tblrecommended[ActiveTargetID], tblrecommended[Order], "" ), _xlfn.XLOOKUP( A60, tblrecommended[PassiveTargetID], tblrecommended[Order], "" ) ) )} -> 91
A61: building.onsen@2 | B61: {=_xlfn.XLOOKUP(Checklist!$A61,tblTargets[TargetID],tblTargets[DisplayName])} -> Onsen Lv 2 | C61: {=_xlfn.XLOOKUP( A61, tblTargetStatus[TargetID], tblTargetStatus[successors], "" )} | D61: {=_xlfn.XLOOKUP( A61, tblTargets[TargetID], tblTargets[TargetType], "" )} -> BUILDING | E61: {=_xlfn.XLOOKUP( A61, tblTargetStatus[TargetID], tblTargetStatus[ChainAwareStatus], "" )} -> BLOCKED | F61: 92 | G61: FALSE | H61: {=_xlfn.XLOOKUP( A61, tblTargetStatus[TargetID], tblTargetStatus[TargetFunded], "" )} -> FALSE | I61: {=IF( D61<>"BUILDING", "", IF( Player!$H$1="Active", _xlfn.XLOOKUP( A61, tblrecommended[ActiveTargetID], tblrecommended[Order], "" ), _xlfn.XLOOKUP( A61, tblrecommended[PassiveTargetID], tblrecommended[Order], "" ) ) )} -> 92
A62: building.outpost@1 | B62: {=_xlfn.XLOOKUP(Checklist!$A62,tblTargets[TargetID],tblTargets[DisplayName])} -> Outpost Lv 1 | C62: {=_xlfn.XLOOKUP( A62, tblTargetStatus[TargetID], tblTargetStatus[successors], "" )} -> Outpost Lv 2 | D62: {=_xlfn.XLOOKUP( A62, tblTargets[TargetID], tblTargets[TargetType], "" )} -> BUILDING | E62: {=_xlfn.XLOOKUP( A62, tblTargetStatus[TargetID], tblTargetStatus[ChainAwareStatus], "" )} -> BLOCKED | F62: 28 | G62: FALSE | H62: {=_xlfn.XLOOKUP( A62, tblTargetStatus[TargetID], tblTargetStatus[TargetFunded], "" )} -> FALSE | I62: {=IF( D62<>"BUILDING", "", IF( Player!$H$1="Active", _xlfn.XLOOKUP( A62, tblrecommended[ActiveTargetID], tblrecommended[Order], "" ), _xlfn.XLOOKUP( A62, tblrecommended[PassiveTargetID], tblrecommended[Order], "" ) ) )} -> 28
A63: building.outpost@2 | B63: {=_xlfn.XLOOKUP(Checklist!$A63,tblTargets[TargetID],tblTargets[DisplayName])} -> Outpost Lv 2 | C63: {=_xlfn.XLOOKUP( A63, tblTargetStatus[TargetID], tblTargetStatus[successors], "" )} -> Outpost Lv 3 | D63: {=_xlfn.XLOOKUP( A63, tblTargets[TargetID], tblTargets[TargetType], "" )} -> BUILDING | E63: {=_xlfn.XLOOKUP( A63, tblTargetStatus[TargetID], tblTargetStatus[ChainAwareStatus], "" )} -> BLOCKED | F63: 35 | G63: FALSE | H63: {=_xlfn.XLOOKUP( A63, tblTargetStatus[TargetID], tblTargetStatus[TargetFunded], "" )} -> FALSE | I63: {=IF( D63<>"BUILDING", "", IF( Player!$H$1="Active", _xlfn.XLOOKUP( A63, tblrecommended[ActiveTargetID], tblrecommended[Order], "" ), _xlfn.XLOOKUP( A63, tblrecommended[PassiveTargetID], tblrecommended[Order], "" ) ) )} -> 35
A64: building.outpost@3 | B64: {=_xlfn.XLOOKUP(Checklist!$A64,tblTargets[TargetID],tblTargets[DisplayName])} -> Outpost Lv 3 | C64: {=_xlfn.XLOOKUP( A64, tblTargetStatus[TargetID], tblTargetStatus[successors], "" )} -> Outpost maxed, Honor, Glory, Sushi Finished | D64: {=_xlfn.XLOOKUP( A64, tblTargets[TargetID], tblTargets[TargetType], "" )} -> BUILDING | E64: {=_xlfn.XLOOKUP( A64, tblTargetStatus[TargetID], tblTargetStatus[ChainAwareStatus], "" )} -> BLOCKED | F64: 50 | G64: FALSE | H64: {=_xlfn.XLOOKUP( A64, tblTargetStatus[TargetID], tblTargetStatus[TargetFunded], "" )} -> FALSE | I64: {=IF( D64<>"BUILDING", "", IF( Player!$H$1="Active", _xlfn.XLOOKUP( A64, tblrecommended[ActiveTargetID], tblrecommended[Order], "" ), _xlfn.XLOOKUP( A64, tblrecommended[PassiveTargetID], tblrecommended[Order], "" ) ) )} -> 50
A65: building.pagoda@1 | B65: {=_xlfn.XLOOKUP(Checklist!$A65,tblTargets[TargetID],tblTargets[DisplayName])} -> Pagoda Lv 1 | C65: {=_xlfn.XLOOKUP( A65, tblTargetStatus[TargetID], tblTargetStatus[successors], "" )} -> Pagoda Lv 2 | D65: {=_xlfn.XLOOKUP( A65, tblTargets[TargetID], tblTargets[TargetType], "" )} -> BUILDING | E65: {=_xlfn.XLOOKUP( A65, tblTargetStatus[TargetID], tblTargetStatus[ChainAwareStatus], "" )} -> ONE AWAY | F65: 57 | G65: FALSE | H65: {=_xlfn.XLOOKUP( A65, tblTargetStatus[TargetID], tblTargetStatus[TargetFunded], "" )} -> FALSE | I65: {=IF( D65<>"BUILDING", "", IF( Player!$H$1="Active", _xlfn.XLOOKUP( A65, tblrecommended[ActiveTargetID], tblrecommended[Order], "" ), _xlfn.XLOOKUP( A65, tblrecommended[PassiveTargetID], tblrecommended[Order], "" ) ) )} -> 57
A66: building.pagoda@2 | B66: {=_xlfn.XLOOKUP(Checklist!$A66,tblTargets[TargetID],tblTargets[DisplayName])} -> Pagoda Lv 2 | C66: {=_xlfn.XLOOKUP( A66, tblTargetStatus[TargetID], tblTargetStatus[successors], "" )} -> Pagoda Lv 3 | D66: {=_xlfn.XLOOKUP( A66, tblTargets[TargetID], tblTargets[TargetType], "" )} -> BUILDING | E66: {=_xlfn.XLOOKUP( A66, tblTargetStatus[TargetID], tblTargetStatus[ChainAwareStatus], "" )} -> BLOCKED | F66: 58 | G66: FALSE | H66: {=_xlfn.XLOOKUP( A66, tblTargetStatus[TargetID], tblTargetStatus[TargetFunded], "" )} -> FALSE | I66: {=IF( D66<>"BUILDING", "", IF( Player!$H$1="Active", _xlfn.XLOOKUP( A66, tblrecommended[ActiveTargetID], tblrecommended[Order], "" ), _xlfn.XLOOKUP( A66, tblrecommended[PassiveTargetID], tblrecommended[Order], "" ) ) )} -> 58
A67: building.pagoda@3 | B67: {=_xlfn.XLOOKUP(Checklist!$A67,tblTargets[TargetID],tblTargets[DisplayName])} -> Pagoda Lv 3 | C67: {=_xlfn.XLOOKUP( A67, tblTargetStatus[TargetID], tblTargetStatus[successors], "" )} -> Pagoda Lv 4 | D67: {=_xlfn.XLOOKUP( A67, tblTargets[TargetID], tblTargets[TargetType], "" )} -> BUILDING | E67: {=_xlfn.XLOOKUP( A67, tblTargetStatus[TargetID], tblTargetStatus[ChainAwareStatus], "" )} -> BLOCKED | F67: 59 | G67: FALSE | H67: {=_xlfn.XLOOKUP( A67, tblTargetStatus[TargetID], tblTargetStatus[TargetFunded], "" )} -> FALSE | I67: {=IF( D67<>"BUILDING", "", IF( Player!$H$1="Active", _xlfn.XLOOKUP( A67, tblrecommended[ActiveTargetID], tblrecommended[Order], "" ), _xlfn.XLOOKUP( A67, tblrecommended[PassiveTargetID], tblrecommended[Order], "" ) ) )} -> 59
A68: building.pagoda@4 | B68: {=_xlfn.XLOOKUP(Checklist!$A68,tblTargets[TargetID],tblTargets[DisplayName])} -> Pagoda Lv 4 | C68: {=_xlfn.XLOOKUP( A68, tblTargetStatus[TargetID], tblTargetStatus[successors], "" )} -> Pagoda Lv 5 | D68: {=_xlfn.XLOOKUP( A68, tblTargets[TargetID], tblTargets[TargetType], "" )} -> BUILDING | E68: {=_xlfn.XLOOKUP( A68, tblTargetStatus[TargetID], tblTargetStatus[ChainAwareStatus], "" )} -> BLOCKED | F68: 60 | G68: FALSE | H68: {=_xlfn.XLOOKUP( A68, tblTargetStatus[TargetID], tblTargetStatus[TargetFunded], "" )} -> FALSE | I68: {=IF( D68<>"BUILDING", "", IF( Player!$H$1="Active", _xlfn.XLOOKUP( A68, tblrecommended[ActiveTargetID], tblrecommended[Order], "" ), _xlfn.XLOOKUP( A68, tblrecommended[PassiveTargetID], tblrecommended[Order], "" ) ) )} -> 60
... A91: building.train@2 | B91: {=_xlfn.XLOOKUP(Checklist!$A91,tblTargets[TargetID],tblTargets[DisplayName])} -> Train Lv 2 | C91: {=_xlfn.XLOOKUP( A91, tblTargetStatus[TargetID], tblTargetStatus[successors], "" )} -> train maxed, Visit Aomori, Visit Fukushima, Visit Tokyo, Journey Through Japan By Train Finished | D91: {=_xlfn.XLOOKUP( A91, tblTargets[TargetID], tblTargets[TargetType], "" )} -> BUILDING | E91: {=_xlfn.XLOOKUP( A91, tblTargetStatus[TargetID], tblTargetStatus[ChainAwareStatus], "" )} -> BLOCKED | F91: 71 | G91: FALSE | H91: {=_xlfn.XLOOKUP( A91, tblTargetStatus[TargetID], tblTargetStatus[TargetFunded], "" )} -> FALSE | I91: {=IF( D91<>"BUILDING", "", IF( Player!$H$1="Active", _xlfn.XLOOKUP( A91, tblrecommended[ActiveTargetID], tblrecommended[Order], "" ), _xlfn.XLOOKUP( A91, tblrecommended[PassiveTargetID], tblrecommended[Order], "" ) ) )} -> 71
A92: building.train_freight_carriage@1 | B92: {=_xlfn.XLOOKUP(Checklist!$A92,tblTargets[TargetID],tblTargets[DisplayName])} -> Train: Freight Carriage Lv 1 | C92: {=_xlfn.XLOOKUP( A92, tblTargetStatus[TargetID], tblTargetStatus[successors], "" )} -> Train: Freight Carriage Lv 2 | D92: {=_xlfn.XLOOKUP( A92, tblTargets[TargetID], tblTargets[TargetType], "" )} -> BUILDING | E92: {=_xlfn.XLOOKUP( A92, tblTargetStatus[TargetID], tblTargetStatus[ChainAwareStatus], "" )} -> BLOCKED | G92: FALSE | H92: {=_xlfn.XLOOKUP( A92, tblTargetStatus[TargetID], tblTargetStatus[TargetFunded], "" )} -> FALSE | I92: {=IF( D92<>"BUILDING", "", IF( Player!$H$1="Active", _xlfn.XLOOKUP( A92, tblrecommended[ActiveTargetID], tblrecommended[Order], "" ), _xlfn.XLOOKUP( A92, tblrecommended[PassiveTargetID], tblrecommended[Order], "" ) ) )}
A93: building.train_freight_carriage@2 | B93: {=_xlfn.XLOOKUP(Checklist!$A93,tblTargets[TargetID],tblTargets[DisplayName])} -> Train: Freight Carriage Lv 2 | C93: {=_xlfn.XLOOKUP( A93, tblTargetStatus[TargetID], tblTargetStatus[successors], "" )} | D93: {=_xlfn.XLOOKUP( A93, tblTargets[TargetID], tblTargets[TargetType], "" )} -> BUILDING | E93: {=_xlfn.XLOOKUP( A93, tblTargetStatus[TargetID], tblTargetStatus[ChainAwareStatus], "" )} -> BLOCKED | G93: FALSE | H93: {=_xlfn.XLOOKUP( A93, tblTargetStatus[TargetID], tblTargetStatus[TargetFunded], "" )} -> FALSE | I93: {=IF( D93<>"BUILDING", "", IF( Player!$H$1="Active", _xlfn.XLOOKUP( A93, tblrecommended[ActiveTargetID], tblrecommended[Order], "" ), _xlfn.XLOOKUP( A93, tblrecommended[PassiveTargetID], tblrecommended[Order], "" ) ) )}
A94: building.train_passenger_carriage@1 | B94: {=_xlfn.XLOOKUP(Checklist!$A94,tblTargets[TargetID],tblTargets[DisplayName])} -> Train: Passenger Carriage Lv 1 | C94: {=_xlfn.XLOOKUP( A94, tblTargetStatus[TargetID], tblTargetStatus[successors], "" )} -> Train: Passenger Carriage Lv 2, Journey Through Japan By Train Finished | D94: {=_xlfn.XLOOKUP( A94, tblTargets[TargetID], tblTargets[TargetType], "" )} -> BUILDING | E94: {=_xlfn.XLOOKUP( A94, tblTargetStatus[TargetID], tblTargetStatus[ChainAwareStatus], "" )} -> BLOCKED | G94: FALSE | H94: {=_xlfn.XLOOKUP( A94, tblTargetStatus[TargetID], tblTargetStatus[TargetFunded], "" )} -> FALSE | I94: {=IF( D94<>"BUILDING", "", IF( Player!$H$1="Active", _xlfn.XLOOKUP( A94, tblrecommended[ActiveTargetID], tblrecommended[Order], "" ), _xlfn.XLOOKUP( A94, tblrecommended[PassiveTargetID], tblrecommended[Order], "" ) ) )}
A95: building.train_passenger_carriage@2 | B95: {=_xlfn.XLOOKUP(Checklist!$A95,tblTargets[TargetID],tblTargets[DisplayName])} -> Train: Passenger Carriage Lv 2 | C95: {=_xlfn.XLOOKUP( A95, tblTargetStatus[TargetID], tblTargetStatus[successors], "" )} | D95: {=_xlfn.XLOOKUP( A95, tblTargets[TargetID], tblTargets[TargetType], "" )} -> BUILDING | E95: {=_xlfn.XLOOKUP( A95, tblTargetStatus[TargetID], tblTargetStatus[ChainAwareStatus], "" )} -> BLOCKED | G95: FALSE | H95: {=_xlfn.XLOOKUP( A95, tblTargetStatus[TargetID], tblTargetStatus[TargetFunded], "" )} -> FALSE | I95: {=IF( D95<>"BUILDING", "", IF( Player!$H$1="Active", _xlfn.XLOOKUP( A95, tblrecommended[ActiveTargetID], tblrecommended[Order], "" ), _xlfn.XLOOKUP( A95, tblrecommended[PassiveTargetID], tblrecommended[Order], "" ) ) )}
A96: building.warehouse@1 | B96: {=_xlfn.XLOOKUP(Checklist!$A96,tblTargets[TargetID],tblTargets[DisplayName])} -> Warehouse Lv 1 | C96: {=_xlfn.XLOOKUP( A96, tblTargetStatus[TargetID], tblTargetStatus[successors], "" )} -> Pier Lv 1, Warehouse Lv 2, Shogun's Katana Chapter 2 Finished | D96: {=_xlfn.XLOOKUP( A96, tblTargets[TargetID], tblTargets[TargetType], "" )} -> BUILDING | E96: {=_xlfn.XLOOKUP( A96, tblTargetStatus[TargetID], tblTargetStatus[ChainAwareStatus], "" )} -> ONE AWAY | F96: 2 | G96: FALSE | H96: {=_xlfn.XLOOKUP( A96, tblTargetStatus[TargetID], tblTargetStatus[TargetFunded], "" )} -> FALSE | I96: {=IF( D96<>"BUILDING", "", IF( Player!$H$1="Active", _xlfn.XLOOKUP( A96, tblrecommended[ActiveTargetID], tblrecommended[Order], "" ), _xlfn.XLOOKUP( A96, tblrecommended[PassiveTargetID], tblrecommended[Order], "" ) ) )} -> 2
A97: building.warehouse@2 | B97: {=_xlfn.XLOOKUP(Checklist!$A97,tblTargets[TargetID],tblTargets[DisplayName])} -> Warehouse Lv 2 | C97: {=_xlfn.XLOOKUP( A97, tblTargetStatus[TargetID], tblTargetStatus[successors], "" )} -> Warehouse Lv 3 | D97: {=_xlfn.XLOOKUP( A97, tblTargets[TargetID], tblTargets[TargetType], "" )} -> BUILDING | E97: {=_xlfn.XLOOKUP( A97, tblTargetStatus[TargetID], tblTargetStatus[ChainAwareStatus], "" )} -> BLOCKED | F97: 94 | G97: FALSE | H97: {=_xlfn.XLOOKUP( A97, tblTargetStatus[TargetID], tblTargetStatus[TargetFunded], "" )} -> FALSE | I97: {=IF( D97<>"BUILDING", "", IF( Player!$H$1="Active", _xlfn.XLOOKUP( A97, tblrecommended[ActiveTargetID], tblrecommended[Order], "" ), _xlfn.XLOOKUP( A97, tblrecommended[PassiveTargetID], tblrecommended[Order], "" ) ) )} -> 94
A98: building.warehouse@3 | B98: {=_xlfn.XLOOKUP(Checklist!$A98,tblTargets[TargetID],tblTargets[DisplayName])} -> Warehouse Lv 3 | C98: {=_xlfn.XLOOKUP( A98, tblTargetStatus[TargetID], tblTargetStatus[successors], "" )} -> Warehouse Lv 4 | D98: {=_xlfn.XLOOKUP( A98, tblTargets[TargetID], tblTargets[TargetType], "" )} -> BUILDING | E98: {=_xlfn.XLOOKUP( A98, tblTargetStatus[TargetID], tblTargetStatus[ChainAwareStatus], "" )} -> BLOCKED | F98: 95 | G98: FALSE | H98: {=_xlfn.XLOOKUP( A98, tblTargetStatus[TargetID], tblTargetStatus[TargetFunded], "" )} -> FALSE | I98: {=IF( D98<>"BUILDING", "", IF( Player!$H$1="Active", _xlfn.XLOOKUP( A98, tblrecommended[ActiveTargetID], tblrecommended[Order], "" ), _xlfn.XLOOKUP( A98, tblrecommended[PassiveTargetID], tblrecommended[Order], "" ) ) )} -> 95
A99: building.warehouse@4 | B99: {=_xlfn.XLOOKUP(Checklist!$A99,tblTargets[TargetID],tblTargets[DisplayName])} -> Warehouse Lv 4 | C99: {=_xlfn.XLOOKUP( A99, tblTargetStatus[TargetID], tblTargetStatus[successors], "" )} -> Warehouse Lv 5 | D99: {=_xlfn.XLOOKUP( A99, tblTargets[TargetID], tblTargets[TargetType], "" )} -> BUILDING | E99: {=_xlfn.XLOOKUP( A99, tblTargetStatus[TargetID], tblTargetStatus[ChainAwareStatus], "" )} -> BLOCKED | F99: 96 | G99: FALSE | H99: {=_xlfn.XLOOKUP( A99, tblTargetStatus[TargetID], tblTargetStatus[TargetFunded], "" )} -> FALSE | I99: {=IF( D99<>"BUILDING", "", IF( Player!$H$1="Active", _xlfn.XLOOKUP( A99, tblrecommended[ActiveTargetID], tblrecommended[Order], "" ), _xlfn.XLOOKUP( A99, tblrecommended[PassiveTargetID], tblrecommended[Order], "" ) ) )} -> 96
A100: building.warehouse@5 | B100: {=_xlfn.XLOOKUP(Checklist!$A100,tblTargets[TargetID],tblTargets[DisplayName])} -> Warehouse Lv 5 | C100: {=_xlfn.XLOOKUP( A100, tblTargetStatus[TargetID], tblTargetStatus[successors], "" )} -> Warehouse Lv 6 | D100: {=_xlfn.XLOOKUP( A100, tblTargets[TargetID], tblTargets[TargetType], "" )} -> BUILDING | E100: {=_xlfn.XLOOKUP( A100, tblTargetStatus[TargetID], tblTargetStatus[ChainAwareStatus], "" )} -> BLOCKED | F100: 97 | G100: FALSE | H100: {=_xlfn.XLOOKUP( A100, tblTargetStatus[TargetID], tblTargetStatus[TargetFunded], "" )} -> FALSE | I100: {=IF( D100<>"BUILDING", "", IF( Player!$H$1="Active", _xlfn.XLOOKUP( A100, tblrecommended[ActiveTargetID], tblrecommended[Order], "" ), _xlfn.XLOOKUP( A100, tblrecommended[PassiveTargetID], tblrecommended[Order], "" ) ) )} -> 97
A101: building.warehouse@6 | B101: {=_xlfn.XLOOKUP(Checklist!$A101,tblTargets[TargetID],tblTargets[DisplayName])} -> Warehouse Lv 6 | C101: {=_xlfn.XLOOKUP( A101, tblTargetStatus[TargetID], tblTargetStatus[successors], "" )} -> Warehouse Lv 7 | D101: {=_xlfn.XLOOKUP( A101, tblTargets[TargetID], tblTargets[TargetType], "" )} -> BUILDING | E101: {=_xlfn.XLOOKUP( A101, tblTargetStatus[TargetID], tblTargetStatus[ChainAwareStatus], "" )} -> BLOCKED | F101: 98 | G101: FALSE | H101: {=_xlfn.XLOOKUP( A101, tblTargetStatus[TargetID], tblTargetStatus[TargetFunded], "" )} -> FALSE | I101: {=IF( D101<>"BUILDING", "", IF( Player!$H$1="Active", _xlfn.XLOOKUP( A101, tblrecommended[ActiveTargetID], tblrecommended[Order], "" ), _xlfn.XLOOKUP( A101, tblrecommended[PassiveTargetID], tblrecommended[Order], "" ) ) )} -> 98
A102: building.warehouse@7 | B102: {=_xlfn.XLOOKUP(Checklist!$A102,tblTargets[TargetID],tblTargets[DisplayName])} -> Warehouse Lv 7 | C102: {=_xlfn.XLOOKUP( A102, tblTargetStatus[TargetID], tblTargetStatus[successors], "" )} -> warehouse maxed | D102: {=_xlfn.XLOOKUP( A102, tblTargets[TargetID], tblTargets[TargetType], "" )} -> BUILDING | E102: {=_xlfn.XLOOKUP( A102, tblTargetStatus[TargetID], tblTargetStatus[ChainAwareStatus], "" )} -> BLOCKED | F102: 99 | G102: FALSE | H102: {=_xlfn.XLOOKUP( A102, tblTargetStatus[TargetID], tblTargetStatus[TargetFunded], "" )} -> FALSE | I102: {=IF( D102<>"BUILDING", "", IF( Player!$H$1="Active", _xlfn.XLOOKUP( A102, tblrecommended[ActiveTargetID], tblrecommended[Order], "" ), _xlfn.XLOOKUP( A102, tblrecommended[PassiveTargetID], tblrecommended[Order], "" ) ) )} -> 99
A103: building.windmill@1 | B103: {=_xlfn.XLOOKUP(Checklist!$A103,tblTargets[TargetID],tblTargets[DisplayName])} -> Windmill Lv 1 | C103: {=_xlfn.XLOOKUP( A103, tblTargetStatus[TargetID], tblTargetStatus[successors], "" )} -> Windmill Lv 2 | D103: {=_xlfn.XLOOKUP( A103, tblTargets[TargetID], tblTargets[TargetType], "" )} -> BUILDING | E103: {=_xlfn.XLOOKUP( A103, tblTargetStatus[TargetID], tblTargetStatus[ChainAwareStatus], "" )} -> ONE AWAY | F103: 9 | G103: FALSE | H103: {=_xlfn.XLOOKUP( A103, tblTargetStatus[TargetID], tblTargetStatus[TargetFunded], "" )} -> FALSE | I103: {=IF( D103<>"BUILDING", "", IF( Player!$H$1="Active", _xlfn.XLOOKUP( A103, tblrecommended[ActiveTargetID], tblrecommended[Order], "" ), _xlfn.XLOOKUP( A103, tblrecommended[PassiveTargetID], tblrecommended[Order], "" ) ) )} -> 9
A104: building.windmill@2 | B104: {=_xlfn.XLOOKUP(Checklist!$A104,tblTargets[TargetID],tblTargets[DisplayName])} -> Windmill Lv 2 | C104: {=_xlfn.XLOOKUP( A104, tblTargetStatus[TargetID], tblTargetStatus[successors], "" )} -> windmill maxed | D104: {=_xlfn.XLOOKUP( A104, tblTargets[TargetID], tblTargets[TargetType], "" )} -> BUILDING | E104: {=_xlfn.XLOOKUP( A104, tblTargetStatus[TargetID], tblTargetStatus[ChainAwareStatus], "" )} -> BLOCKED | F104: 15 | G104: FALSE | H104: {=_xlfn.XLOOKUP( A104, tblTargetStatus[TargetID], tblTargetStatus[TargetFunded], "" )} -> FALSE | I104: {=IF( D104<>"BUILDING", "", IF( Player!$H$1="Active", _xlfn.XLOOKUP( A104, tblrecommended[ActiveTargetID], tblrecommended[Order], "" ), _xlfn.XLOOKUP( A104, tblrecommended[PassiveTargetID], tblrecommended[Order], "" ) ) )} -> 15
A105: building.workshop@1 | B105: {=_xlfn.XLOOKUP(Checklist!$A105,tblTargets[TargetID],tblTargets[DisplayName])} -> Workshop Lv 1 | C105: {=_xlfn.XLOOKUP( A105, tblTargetStatus[TargetID], tblTargetStatus[successors], "" )} -> Workshop Lv 2 | D105: {=_xlfn.XLOOKUP( A105, tblTargets[TargetID], tblTargets[TargetType], "" )} -> BUILDING | E105: {=_xlfn.XLOOKUP( A105, tblTargetStatus[TargetID], tblTargetStatus[ChainAwareStatus], "" )} -> ONE AWAY | F105: 30 | G105: FALSE | H105: {=_xlfn.XLOOKUP( A105, tblTargetStatus[TargetID], tblTargetStatus[TargetFunded], "" )} -> FALSE | I105: {=IF( D105<>"BUILDING", "", IF( Player!$H$1="Active", _xlfn.XLOOKUP( A105, tblrecommended[ActiveTargetID], tblrecommended[Order], "" ), _xlfn.XLOOKUP( A105, tblrecommended[PassiveTargetID], tblrecommended[Order], "" ) ) )} -> 30
A106: building.workshop@2 | B106: {=_xlfn.XLOOKUP(Checklist!$A106,tblTargets[TargetID],tblTargets[DisplayName])} -> Workshop Lv 2 | C106: {=_xlfn.XLOOKUP( A106, tblTargetStatus[TargetID], tblTargetStatus[successors], "" )} -> Workshop Lv 3 | D106: {=_xlfn.XLOOKUP( A106, tblTargets[TargetID], tblTargets[TargetType], "" )} -> BUILDING | E106: {=_xlfn.XLOOKUP( A106, tblTargetStatus[TargetID], tblTargetStatus[ChainAwareStatus], "" )} -> BLOCKED | F106: 31 | G106: FALSE | H106: {=_xlfn.XLOOKUP( A106, tblTargetStatus[TargetID], tblTargetStatus[TargetFunded], "" )} -> FALSE | I106: {=IF( D106<>"BUILDING", "", IF( Player!$H$1="Active", _xlfn.XLOOKUP( A106, tblrecommended[ActiveTargetID], tblrecommended[Order], "" ), _xlfn.XLOOKUP( A106, tblrecommended[PassiveTargetID], tblrecommended[Order], "" ) ) )} -> 31
A107: building.workshop@3 | B107: {=_xlfn.XLOOKUP(Checklist!$A107,tblTargets[TargetID],tblTargets[DisplayName])} -> Workshop Lv 3 | C107: {=_xlfn.XLOOKUP( A107, tblTargetStatus[TargetID], tblTargetStatus[successors], "" )} -> Workshop Lv 4 | D107: {=_xlfn.XLOOKUP( A107, tblTargets[TargetID], tblTargets[TargetType], "" )} -> BUILDING | E107: {=_xlfn.XLOOKUP( A107, tblTargetStatus[TargetID], tblTargetStatus[ChainAwareStatus], "" )} -> BLOCKED | F107: 32 | G107: FALSE | H107: {=_xlfn.XLOOKUP( A107, tblTargetStatus[TargetID], tblTargetStatus[TargetFunded], "" )} -> FALSE | I107: {=IF( D107<>"BUILDING", "", IF( Player!$H$1="Active", _xlfn.XLOOKUP( A107, tblrecommended[ActiveTargetID], tblrecommended[Order], "" ), _xlfn.XLOOKUP( A107, tblrecommended[PassiveTargetID], tblrecommended[Order], "" ) ) )} -> 32
... A109: building.workshop@5 | B109: {=_xlfn.XLOOKUP(Checklist!$A109,tblTargets[TargetID],tblTargets[DisplayName])} -> Workshop Lv 5 | C109: {=_xlfn.XLOOKUP( A109, tblTargetStatus[TargetID], tblTargetStatus[successors], "" )} -> workshop maxed, Barometer, Cinema Projector, Necklace For Haruka, Safe, Solver 1 Prototype, Telescope | D109: {=_xlfn.XLOOKUP( A109, tblTargets[TargetID], tblTargets[TargetType], "" )} -> BUILDING | E109: {=_xlfn.XLOOKUP( A109, tblTargetStatus[TargetID], tblTargetStatus[ChainAwareStatus], "" )} -> BLOCKED | F109: 34 | G109: FALSE | H109: {=_xlfn.XLOOKUP( A109, tblTargetStatus[TargetID], tblTargetStatus[TargetFunded], "" )} -> FALSE | I109: {=IF( D109<>"BUILDING", "", IF( Player!$H$1="Active", _xlfn.XLOOKUP( A109, tblrecommended[ActiveTargetID], tblrecommended[Order], "" ), _xlfn.XLOOKUP( A109, tblrecommended[PassiveTargetID], tblrecommended[Order], "" ) ) )} -> 34
A110: citadel.armory | B110: {=_xlfn.XLOOKUP(Checklist!$A110,tblTargets[TargetID],tblTargets[DisplayName])} -> Armory | C110: {=_xlfn.XLOOKUP( A110, tblTargetStatus[TargetID], tblTargetStatus[successors], "" )} -> Armory 1 Lv 1 | D110: {=_xlfn.XLOOKUP( A110, tblTargets[TargetID], tblTargets[TargetType], "" )} -> CITADEL | E110: {=_xlfn.XLOOKUP( A110, tblTargetStatus[TargetID], tblTargetStatus[ChainAwareStatus], "" )} -> BLOCKED | G110: FALSE | H110: {=_xlfn.XLOOKUP( A110, tblTargetStatus[TargetID], tblTargetStatus[TargetFunded], "" )} -> FALSE | I110: {=IF( D110<>"BUILDING", "", IF( Player!$H$1="Active", _xlfn.XLOOKUP( A110, tblrecommended[ActiveTargetID], tblrecommended[Order], "" ), _xlfn.XLOOKUP( A110, tblrecommended[PassiveTargetID], tblrecommended[Order], "" ) ) )}
A111: citadel.attic | B111: {=_xlfn.XLOOKUP(Checklist!$A111,tblTargets[TargetID],tblTargets[DisplayName])} -> Attic | C111: {=_xlfn.XLOOKUP( A111, tblTargetStatus[TargetID], tblTargetStatus[successors], "" )} -> Attic Lv 1 | D111: {=_xlfn.XLOOKUP( A111, tblTargets[TargetID], tblTargets[TargetType], "" )} -> CITADEL | E111: {=_xlfn.XLOOKUP( A111, tblTargetStatus[TargetID], tblTargetStatus[ChainAwareStatus], "" )} -> BLOCKED | G111: FALSE | H111: {=_xlfn.XLOOKUP( A111, tblTargetStatus[TargetID], tblTargetStatus[TargetFunded], "" )} -> FALSE | I111: {=IF( D111<>"BUILDING", "", IF( Player!$H$1="Active", _xlfn.XLOOKUP( A111, tblrecommended[ActiveTargetID], tblrecommended[Order], "" ), _xlfn.XLOOKUP( A111, tblrecommended[PassiveTargetID], tblrecommended[Order], "" ) ) )}
A112: citadel.cheese_cave | B112: {=_xlfn.XLOOKUP(Checklist!$A112,tblTargets[TargetID],tblTargets[DisplayName])} -> Cheese Cave | C112: {=_xlfn.XLOOKUP( A112, tblTargetStatus[TargetID], tblTargetStatus[successors], "" )} | D112: {=_xlfn.XLOOKUP( A112, tblTargets[TargetID], tblTargets[TargetType], "" )} -> CITADEL | E112: {=_xlfn.XLOOKUP( A112, tblTargetStatus[TargetID], tblTargetStatus[ChainAwareStatus], "" )} -> BLOCKED | G112: FALSE | H112: {=_xlfn.XLOOKUP( A112, tblTargetStatus[TargetID], tblTargetStatus[TargetFunded], "" )} -> FALSE | I112: {=IF( D112<>"BUILDING", "", IF( Player!$H$1="Active", _xlfn.XLOOKUP( A112, tblrecommended[ActiveTargetID], tblrecommended[Order], "" ), _xlfn.XLOOKUP( A112, tblrecommended[PassiveTargetID], tblrecommended[Order], "" ) ) )}
A113: citadel.courtyard | B113: {=_xlfn.XLOOKUP(Checklist!$A113,tblTargets[TargetID],tblTargets[DisplayName])} -> Courtyard | C113: {=_xlfn.XLOOKUP( A113, tblTargetStatus[TargetID], tblTargetStatus[successors], "" )} -> Courtyard 1 Lv 1, Courtyard 2 Lv 1 | D113: {=_xlfn.XLOOKUP( A113, tblTargets[TargetID], tblTargets[TargetType], "" )} -> CITADEL | E113: {=_xlfn.XLOOKUP( A113, tblTargetStatus[TargetID], tblTargetStatus[ChainAwareStatus], "" )} -> BLOCKED | G113: FALSE | H113: {=_xlfn.XLOOKUP( A113, tblTargetStatus[TargetID], tblTargetStatus[TargetFunded], "" )} -> FALSE | I113: {=IF( D113<>"BUILDING", "", IF( Player!$H$1="Active", _xlfn.XLOOKUP( A113, tblrecommended[ActiveTargetID], tblrecommended[Order], "" ), _xlfn.XLOOKUP( A113, tblrecommended[PassiveTargetID], tblrecommended[Order], "" ) ) )}
A114: citadel.gallery | B114: {=_xlfn.XLOOKUP(Checklist!$A114,tblTargets[TargetID],tblTargets[DisplayName])} -> Gallery | C114: {=_xlfn.XLOOKUP( A114, tblTargetStatus[TargetID], tblTargetStatus[successors], "" )} -> Gallery 1 Lv 1, Gallery 2 Lv 1, Gallery 3 Lv 1 | D114: {=_xlfn.XLOOKUP( A114, tblTargets[TargetID], tblTargets[TargetType], "" )} -> CITADEL | E114: {=_xlfn.XLOOKUP( A114, tblTargetStatus[TargetID], tblTargetStatus[ChainAwareStatus], "" )} -> BLOCKED | G114: FALSE | H114: {=_xlfn.XLOOKUP( A114, tblTargetStatus[TargetID], tblTargetStatus[TargetFunded], "" )} -> FALSE | I114: {=IF( D114<>"BUILDING", "", IF( Player!$H$1="Active", _xlfn.XLOOKUP( A114, tblrecommended[ActiveTargetID], tblrecommended[Order], "" ), _xlfn.XLOOKUP( A114, tblrecommended[PassiveTargetID], tblrecommended[Order], "" ) ) )}
A115: citadel.great_hall | B115: {=_xlfn.XLOOKUP(Checklist!$A115,tblTargets[TargetID],tblTargets[DisplayName])} -> Great Hall | C115: {=_xlfn.XLOOKUP( A115, tblTargetStatus[TargetID], tblTargetStatus[successors], "" )} -> Cheese Cave, Courtyard, Historical Library 1 Lv 1, Historical Library 2 Lv 1, Horse Lv 1, Statue Lv 1, Tame A Critter | D115: {=_xlfn.XLOOKUP( A115, tblTargets[TargetID], tblTargets[TargetType], "" )} -> CITADEL | E115: {=_xlfn.XLOOKUP( A115, tblTargetStatus[TargetID], tblTargetStatus[ChainAwareStatus], "" )} -> BLOCKED | G115: FALSE | H115: {=_xlfn.XLOOKUP( A115, tblTargetStatus[TargetID], tblTargetStatus[TargetFunded], "" )} -> FALSE | I115: {=IF( D115<>"BUILDING", "", IF( Player!$H$1="Active", _xlfn.XLOOKUP( A115, tblrecommended[ActiveTargetID], tblrecommended[Order], "" ), _xlfn.XLOOKUP( A115, tblrecommended[PassiveTargetID], tblrecommended[Order], "" ) ) )}
A116: citadel.kitchen_and_buttery | B116: {=_xlfn.XLOOKUP(Checklist!$A116,tblTargets[TargetID],tblTargets[DisplayName])} -> Kitchen and Buttery | C116: {=_xlfn.XLOOKUP( A116, tblTargetStatus[TargetID], tblTargetStatus[successors], "" )} -> Kitchen And Buttery 1 Lv 1, Kitchen And Buttery 2 Lv 1 | D116: {=_xlfn.XLOOKUP( A116, tblTargets[TargetID], tblTargets[TargetType], "" )} -> CITADEL | E116: {=_xlfn.XLOOKUP( A116, tblTargetStatus[TargetID], tblTargetStatus[ChainAwareStatus], "" )} -> BLOCKED | G116: FALSE | H116: {=_xlfn.XLOOKUP( A116, tblTargetStatus[TargetID], tblTargetStatus[TargetFunded], "" )} -> FALSE | I116: {=IF( D116<>"BUILDING", "", IF( Player!$H$1="Active", _xlfn.XLOOKUP( A116, tblrecommended[ActiveTargetID], tblrecommended[Order], "" ), _xlfn.XLOOKUP( A116, tblrecommended[PassiveTargetID], tblrecommended[Order], "" ) ) )}
A117: citadel.lair_lvl_1 | B117: {=_xlfn.XLOOKUP(Checklist!$A117,tblTargets[TargetID],tblTargets[DisplayName])} -> Lair lvl. 1 | C117: {=_xlfn.XLOOKUP( A117, tblTargetStatus[TargetID], tblTargetStatus[successors], "" )} -> Lair lvl. 2 | D117: {=_xlfn.XLOOKUP( A117, tblTargets[TargetID], tblTargets[TargetType], "" )} -> CITADEL | E117: {=_xlfn.XLOOKUP( A117, tblTargetStatus[TargetID], tblTargetStatus[ChainAwareStatus], "" )} -> BLOCKED | F117: 50 | G117: FALSE | H117: {=_xlfn.XLOOKUP( A117, tblTargetStatus[TargetID], tblTargetStatus[TargetFunded], "" )} -> FALSE | I117: {=IF( D117<>"BUILDING", "", IF( Player!$H$1="Active", _xlfn.XLOOKUP( A117, tblrecommended[ActiveTargetID], tblrecommended[Order], "" ), _xlfn.XLOOKUP( A117, tblrecommended[PassiveTargetID], tblrecommended[Order], "" ) ) )}
A118: citadel.lair_lvl_2 | B118: {=_xlfn.XLOOKUP(Checklist!$A118,tblTargets[TargetID],tblTargets[DisplayName])} -> Lair lvl. 2 | C118: {=_xlfn.XLOOKUP( A118, tblTargetStatus[TargetID], tblTargetStatus[successors], "" )} | D118: {=_xlfn.XLOOKUP( A118, tblTargets[TargetID], tblTargets[TargetType], "" )} -> CITADEL | E118: {=_xlfn.XLOOKUP( A118, tblTargetStatus[TargetID], tblTargetStatus[ChainAwareStatus], "" )} -> BLOCKED | G118: FALSE | H118: {=_xlfn.XLOOKUP( A118, tblTargetStatus[TargetID], tblTargetStatus[TargetFunded], "" )} -> FALSE | I118: {=IF( D118<>"BUILDING", "", IF( Player!$H$1="Active", _xlfn.XLOOKUP( A118, tblrecommended[ActiveTargetID], tblrecommended[Order], "" ), _xlfn.XLOOKUP( A118, tblrecommended[PassiveTargetID], tblrecommended[Order], "" ) ) )}
A119: citadel.mushroom_farm | B119: {=_xlfn.XLOOKUP(Checklist!$A119,tblTargets[TargetID],tblTargets[DisplayName])} -> Mushroom Farm | C119: {=_xlfn.XLOOKUP( A119, tblTargetStatus[TargetID], tblTargetStatus[successors], "" )} -> Mushroom Farm Lv 1 | D119: {=_xlfn.XLOOKUP( A119, tblTargets[TargetID], tblTargets[TargetType], "" )} -> CITADEL | E119: {=_xlfn.XLOOKUP( A119, tblTargetStatus[TargetID], tblTargetStatus[ChainAwareStatus], "" )} -> BLOCKED | G119: FALSE | H119: {=_xlfn.XLOOKUP( A119, tblTargetStatus[TargetID], tblTargetStatus[TargetFunded], "" )} -> FALSE | I119: {=IF( D119<>"BUILDING", "", IF( Player!$H$1="Active", _xlfn.XLOOKUP( A119, tblrecommended[ActiveTargetID], tblrecommended[Order], "" ), _xlfn.XLOOKUP( A119, tblrecommended[PassiveTargetID], tblrecommended[Order], "" ) ) )}
A120: citadel.orangery | B120: {=_xlfn.XLOOKUP(Checklist!$A120,tblTargets[TargetID],tblTargets[DisplayName])} -> Orangery | C120: {=_xlfn.XLOOKUP( A120, tblTargetStatus[TargetID], tblTargetStatus[successors], "" )} -> Orangery Lv 1 | D120: {=_xlfn.XLOOKUP( A120, tblTargets[TargetID], tblTargets[TargetType], "" )} -> CITADEL | E120: {=_xlfn.XLOOKUP( A120, tblTargetStatus[TargetID], tblTargetStatus[ChainAwareStatus], "" )} -> BLOCKED | G120: FALSE | H120: {=_xlfn.XLOOKUP( A120, tblTargetStatus[TargetID], tblTargetStatus[TargetFunded], "" )} -> FALSE | I120: {=IF( D120<>"BUILDING", "", IF( Player!$H$1="Active", _xlfn.XLOOKUP( A120, tblrecommended[ActiveTargetID], tblrecommended[Order], "" ), _xlfn.XLOOKUP( A120, tblrecommended[PassiveTargetID], tblrecommended[Order], "" ) ) )}
A121: citadel.pantry | B121: {=_xlfn.XLOOKUP(Checklist!$A121,tblTargets[TargetID],tblTargets[DisplayName])} -> Pantry | C121: {=_xlfn.XLOOKUP( A121, tblTargetStatus[TargetID], tblTargetStatus[successors], "" )} -> Pantry 1 Lv 1, Pantry 2 Lv 1, Pantry 3 Lv 1, Pantry 4 Lv 1 | D121: {=_xlfn.XLOOKUP( A121, tblTargets[TargetID], tblTargets[TargetType], "" )} -> CITADEL | E121: {=_xlfn.XLOOKUP( A121, tblTargetStatus[TargetID], tblTargetStatus[ChainAwareStatus], "" )} -> BLOCKED | G121: FALSE | H121: {=_xlfn.XLOOKUP( A121, tblTargetStatus[TargetID], tblTargetStatus[TargetFunded], "" )} -> FALSE | I121: {=IF( D121<>"BUILDING", "", IF( Player!$H$1="Active", _xlfn.XLOOKUP( A121, tblrecommended[ActiveTargetID], tblrecommended[Order], "" ), _xlfn.XLOOKUP( A121, tblrecommended[PassiveTargetID], tblrecommended[Order], "" ) ) )}
A122: citadel.tavern | B122: {=_xlfn.XLOOKUP(Checklist!$A122,tblTargets[TargetID],tblTargets[DisplayName])} -> Tavern | C122: {=_xlfn.XLOOKUP( A122, tblTargetStatus[TargetID], tblTargetStatus[successors], "" )} -> Tavern Lv 1 | D122: {=_xlfn.XLOOKUP( A122, tblTargets[TargetID], tblTargets[TargetType], "" )} -> CITADEL | E122: {=_xlfn.XLOOKUP( A122, tblTargetStatus[TargetID], tblTargetStatus[ChainAwareStatus], "" )} -> BLOCKED | G122: FALSE | H122: {=_xlfn.XLOOKUP( A122, tblTargetStatus[TargetID], tblTargetStatus[TargetFunded], "" )} -> FALSE | I122: {=IF( D122<>"BUILDING", "", IF( Player!$H$1="Active", _xlfn.XLOOKUP( A122, tblrecommended[ActiveTargetID], tblrecommended[Order], "" ), _xlfn.XLOOKUP( A122, tblrecommended[PassiveTargetID], tblrecommended[Order], "" ) ) )}
A123: citadel.treasury | B123: {=_xlfn.XLOOKUP(Checklist!$A123,tblTargets[TargetID],tblTargets[DisplayName])} -> Treasury | C123: {=_xlfn.XLOOKUP( A123, tblTargetStatus[TargetID], tblTargetStatus[successors], "" )} -> Treasury 1 Lv 1, Treasury 2 Lv 1, Treasury 3 Lv 1 | D123: {=_xlfn.XLOOKUP( A123, tblTargets[TargetID], tblTargets[TargetType], "" )} -> CITADEL | E123: {=_xlfn.XLOOKUP( A123, tblTargetStatus[TargetID], tblTargetStatus[ChainAwareStatus], "" )} -> BLOCKED | G123: FALSE | H123: {=_xlfn.XLOOKUP( A123, tblTargetStatus[TargetID], tblTargetStatus[TargetFunded], "" )} -> FALSE | I123: {=IF( D123<>"BUILDING", "", IF( Player!$H$1="Active", _xlfn.XLOOKUP( A123, tblrecommended[ActiveTargetID], tblrecommended[Order], "" ), _xlfn.XLOOKUP( A123, tblrecommended[PassiveTargetID], tblrecommended[Order], "" ) ) )}
A124: citadel.tunnel | B124: {=_xlfn.XLOOKUP(Checklist!$A124,tblTargets[TargetID],tblTargets[DisplayName])} -> Tunnel | C124: {=_xlfn.XLOOKUP( A124, tblTargetStatus[TargetID], tblTargetStatus[successors], "" )} -> Send Train to Sapporo, Ahead of Time Chapter 2 Finished | D124: {=_xlfn.XLOOKUP( A124, tblTargets[TargetID], tblTargets[TargetType], "" )} -> CITADEL | E124: {=_xlfn.XLOOKUP( A124, tblTargetStatus[TargetID], tblTargetStatus[ChainAwareStatus], "" )} -> BLOCKED | G124: FALSE | H124: {=_xlfn.XLOOKUP( A124, tblTargetStatus[TargetID], tblTargetStatus[TargetFunded], "" )} -> FALSE | I124: {=IF( D124<>"BUILDING", "", IF( Player!$H$1="Active", _xlfn.XLOOKUP( A124, tblrecommended[ActiveTargetID], tblrecommended[Order], "" ), _xlfn.XLOOKUP( A124, tblrecommended[PassiveTargetID], tblrecommended[Order], "" ) ) )}
A125: collection.alchemist_hall_1@1 | B125: {=_xlfn.XLOOKUP(Checklist!$A125,tblTargets[TargetID],tblTargets[DisplayName])} -> Alchemist Hall Lv 1 | C125: {=_xlfn.XLOOKUP( A125, tblTargetStatus[TargetID], tblTargetStatus[successors], "" )} -> Alchemist Hall Lv 2, Letter from the Dark Lady Finished | D125: {=_xlfn.XLOOKUP( A125, tblTargets[TargetID], tblTargets[TargetType], "" )} -> COLLECTION | E125: {=_xlfn.XLOOKUP( A125, tblTargetStatus[TargetID], tblTargetStatus[ChainAwareStatus], "" )} -> BLOCKED | G125: FALSE | H125: {=_xlfn.XLOOKUP( A125, tblTargetStatus[TargetID], tblTargetStatus[TargetFunded], "" )} -> FALSE | I125: {=IF( D125<>"BUILDING", "", IF( Player!$H$1="Active", _xlfn.XLOOKUP( A125, tblrecommended[ActiveTargetID], tblrecommended[Order], "" ), _xlfn.XLOOKUP( A125, tblrecommended[PassiveTargetID], tblrecommended[Order], "" ) ) )}
A126: collection.alchemist_hall_1@2 | B126: {=_xlfn.XLOOKUP(Checklist!$A126,tblTargets[TargetID],tblTargets[DisplayName])} -> Alchemist Hall Lv 2 | C126: {=_xlfn.XLOOKUP( A126, tblTargetStatus[TargetID], tblTargetStatus[successors], "" )} | D126: {=_xlfn.XLOOKUP( A126, tblTargets[TargetID], tblTargets[TargetType], "" )} -> COLLECTION | E126: {=_xlfn.XLOOKUP( A126, tblTargetStatus[TargetID], tblTargetStatus[ChainAwareStatus], "" )} -> BLOCKED | G126: FALSE | H126: {=_xlfn.XLOOKUP( A126, tblTargetStatus[TargetID], tblTargetStatus[TargetFunded], "" )} -> FALSE | I126: {=IF( D126<>"BUILDING", "", IF( Player!$H$1="Active", _xlfn.XLOOKUP( A126, tblrecommended[ActiveTargetID], tblrecommended[Order], "" ), _xlfn.XLOOKUP( A126, tblrecommended[PassiveTargetID], tblrecommended[Order], "" ) ) )}
A127: collection.alchemist_hall_2@1 | B127: {=_xlfn.XLOOKUP(Checklist!$A127,tblTargets[TargetID],tblTargets[DisplayName])} -> Alchemist Hall Lv 1 | C127: {=_xlfn.XLOOKUP( A127, tblTargetStatus[TargetID], tblTargetStatus[successors], "" )} -> Alchemist Hall Lv 2, Letter from the Dark Lady Finished | D127: {=_xlfn.XLOOKUP( A127, tblTargets[TargetID], tblTargets[TargetType], "" )} -> COLLECTION | E127: {=_xlfn.XLOOKUP( A127, tblTargetStatus[TargetID], tblTargetStatus[ChainAwareStatus], "" )} -> BLOCKED | G127: FALSE | H127: {=_xlfn.XLOOKUP( A127, tblTargetStatus[TargetID], tblTargetStatus[TargetFunded], "" )} -> FALSE | I127: {=IF( D127<>"BUILDING", "", IF( Player!$H$1="Active", _xlfn.XLOOKUP( A127, tblrecommended[ActiveTargetID], tblrecommended[Order], "" ), _xlfn.XLOOKUP( A127, tblrecommended[PassiveTargetID], tblrecommended[Order], "" ) ) )}
A128: collection.alchemist_hall_2@2 | B128: {=_xlfn.XLOOKUP(Checklist!$A128,tblTargets[TargetID],tblTargets[DisplayName])} -> Alchemist Hall Lv 2 | C128: {=_xlfn.XLOOKUP( A128, tblTargetStatus[TargetID], tblTargetStatus[successors], "" )} | D128: {=_xlfn.XLOOKUP( A128, tblTargets[TargetID], tblTargets[TargetType], "" )} -> COLLECTION | E128: {=_xlfn.XLOOKUP( A128, tblTargetStatus[TargetID], tblTargetStatus[ChainAwareStatus], "" )} -> BLOCKED | G128: FALSE | H128: {=_xlfn.XLOOKUP( A128, tblTargetStatus[TargetID], tblTargetStatus[TargetFunded], "" )} -> FALSE | I128: {=IF( D128<>"BUILDING", "", IF( Player!$H$1="Active", _xlfn.XLOOKUP( A128, tblrecommended[ActiveTargetID], tblrecommended[Order], "" ), _xlfn.XLOOKUP( A128, tblrecommended[PassiveTargetID], tblrecommended[Order], "" ) ) )}
A129: collection.alchemist_hall_3@1 | B129: {=_xlfn.XLOOKUP(Checklist!$A129,tblTargets[TargetID],tblTargets[DisplayName])} -> Alchemist Hall Lv 1 | C129: {=_xlfn.XLOOKUP( A129, tblTargetStatus[TargetID], tblTargetStatus[successors], "" )} -> Alchemist Hall Lv 2, Letter from the Dark Lady Finished | D129: {=_xlfn.XLOOKUP( A129, tblTargets[TargetID], tblTargets[TargetType], "" )} -> COLLECTION | E129: {=_xlfn.XLOOKUP( A129, tblTargetStatus[TargetID], tblTargetStatus[ChainAwareStatus], "" )} -> BLOCKED | G129: FALSE | H129: {=_xlfn.XLOOKUP( A129, tblTargetStatus[TargetID], tblTargetStatus[TargetFunded], "" )} -> FALSE | I129: {=IF( D129<>"BUILDING", "", IF( Player!$H$1="Active", _xlfn.XLOOKUP( A129, tblrecommended[ActiveTargetID], tblrecommended[Order], "" ), _xlfn.XLOOKUP( A129, tblrecommended[PassiveTargetID], tblrecommended[Order], "" ) ) )}
... A166: collection.historical_library_1@1 | B166: {=_xlfn.XLOOKUP(Checklist!$A166,tblTargets[TargetID],tblTargets[DisplayName])} -> Historical Library 1 Lv 1 | C166: {=_xlfn.XLOOKUP( A166, tblTargetStatus[TargetID], tblTargetStatus[successors], "" )} -> Historical Library 1 Lv 2 | D166: {=_xlfn.XLOOKUP( A166, tblTargets[TargetID], tblTargets[TargetType], "" )} -> COLLECTION | E166: {=_xlfn.XLOOKUP( A166, tblTargetStatus[TargetID], tblTargetStatus[ChainAwareStatus], "" )} -> BLOCKED | G166: FALSE | H166: {=_xlfn.XLOOKUP( A166, tblTargetStatus[TargetID], tblTargetStatus[TargetFunded], "" )} -> FALSE | I166: {=IF( D166<>"BUILDING", "", IF( Player!$H$1="Active", _xlfn.XLOOKUP( A166, tblrecommended[ActiveTargetID], tblrecommended[Order], "" ), _xlfn.XLOOKUP( A166, tblrecommended[PassiveTargetID], tblrecommended[Order], "" ) ) )}
A167: collection.historical_library_1@2 | B167: {=_xlfn.XLOOKUP(Checklist!$A167,tblTargets[TargetID],tblTargets[DisplayName])} -> Historical Library 1 Lv 2 | C167: {=_xlfn.XLOOKUP( A167, tblTargetStatus[TargetID], tblTargetStatus[successors], "" )} -> Historical Library 1 Lv 3 | D167: {=_xlfn.XLOOKUP( A167, tblTargets[TargetID], tblTargets[TargetType], "" )} -> COLLECTION | E167: {=_xlfn.XLOOKUP( A167, tblTargetStatus[TargetID], tblTargetStatus[ChainAwareStatus], "" )} -> BLOCKED | F167: 20 | G167: FALSE | H167: {=_xlfn.XLOOKUP( A167, tblTargetStatus[TargetID], tblTargetStatus[TargetFunded], "" )} -> FALSE | I167: {=IF( D167<>"BUILDING", "", IF( Player!$H$1="Active", _xlfn.XLOOKUP( A167, tblrecommended[ActiveTargetID], tblrecommended[Order], "" ), _xlfn.XLOOKUP( A167, tblrecommended[PassiveTargetID], tblrecommended[Order], "" ) ) )}
A168: collection.historical_library_1@3 | B168: {=_xlfn.XLOOKUP(Checklist!$A168,tblTargets[TargetID],tblTargets[DisplayName])} -> Historical Library 1 Lv 3 | C168: {=_xlfn.XLOOKUP( A168, tblTargetStatus[TargetID], tblTargetStatus[successors], "" )} | D168: {=_xlfn.XLOOKUP( A168, tblTargets[TargetID], tblTargets[TargetType], "" )} -> COLLECTION | E168: {=_xlfn.XLOOKUP( A168, tblTargetStatus[TargetID], tblTargetStatus[ChainAwareStatus], "" )} -> BLOCKED | G168: FALSE | H168: {=_xlfn.XLOOKUP( A168, tblTargetStatus[TargetID], tblTargetStatus[TargetFunded], "" )} -> FALSE | I168: {=IF( D168<>"BUILDING", "", IF( Player!$H$1="Active", _xlfn.XLOOKUP( A168, tblrecommended[ActiveTargetID], tblrecommended[Order], "" ), _xlfn.XLOOKUP( A168, tblrecommended[PassiveTargetID], tblrecommended[Order], "" ) ) )}
A169: collection.historical_library_2@1 | B169: {=_xlfn.XLOOKUP(Checklist!$A169,tblTargets[TargetID],tblTargets[DisplayName])} -> Historical Library 2 Lv 1 | C169: {=_xlfn.XLOOKUP( A169, tblTargetStatus[TargetID], tblTargetStatus[successors], "" )} -> Historical Library 2 Lv 2 | D169: {=_xlfn.XLOOKUP( A169, tblTargets[TargetID], tblTargets[TargetType], "" )} -> COLLECTION | E169: {=_xlfn.XLOOKUP( A169, tblTargetStatus[TargetID], tblTargetStatus[ChainAwareStatus], "" )} -> BLOCKED | G169: FALSE | H169: {=_xlfn.XLOOKUP( A169, tblTargetStatus[TargetID], tblTargetStatus[TargetFunded], "" )} -> FALSE | I169: {=IF( D169<>"BUILDING", "", IF( Player!$H$1="Active", _xlfn.XLOOKUP( A169, tblrecommended[ActiveTargetID], tblrecommended[Order], "" ), _xlfn.XLOOKUP( A169, tblrecommended[PassiveTargetID], tblrecommended[Order], "" ) ) )}
A170: collection.historical_library_2@2 | B170: {=_xlfn.XLOOKUP(Checklist!$A170,tblTargets[TargetID],tblTargets[DisplayName])} -> Historical Library 2 Lv 2 | C170: {=_xlfn.XLOOKUP( A170, tblTargetStatus[TargetID], tblTargetStatus[successors], "" )} -> Historical Library 2 Lv 3 | D170: {=_xlfn.XLOOKUP( A170, tblTargets[TargetID], tblTargets[TargetType], "" )} -> COLLECTION | E170: {=_xlfn.XLOOKUP( A170, tblTargetStatus[TargetID], tblTargetStatus[ChainAwareStatus], "" )} -> BLOCKED | G170: FALSE | H170: {=_xlfn.XLOOKUP( A170, tblTargetStatus[TargetID], tblTargetStatus[TargetFunded], "" )} -> FALSE | I170: {=IF( D170<>"BUILDING", "", IF( Player!$H$1="Active", _xlfn.XLOOKUP( A170, tblrecommended[ActiveTargetID], tblrecommended[Order], "" ), _xlfn.XLOOKUP( A170, tblrecommended[PassiveTargetID], tblrecommended[Order], "" ) ) )}
A171: collection.historical_library_2@3 | B171: {=_xlfn.XLOOKUP(Checklist!$A171,tblTargets[TargetID],tblTargets[DisplayName])} -> Historical Library 2 Lv 3 | C171: {=_xlfn.XLOOKUP( A171, tblTargetStatus[TargetID], tblTargetStatus[successors], "" )} | D171: {=_xlfn.XLOOKUP( A171, tblTargets[TargetID], tblTargets[TargetType], "" )} -> COLLECTION | E171: {=_xlfn.XLOOKUP( A171, tblTargetStatus[TargetID], tblTargetStatus[ChainAwareStatus], "" )} -> BLOCKED | F171: 21 | G171: FALSE | H171: {=_xlfn.XLOOKUP( A171, tblTargetStatus[TargetID], tblTargetStatus[TargetFunded], "" )} -> FALSE | I171: {=IF( D171<>"BUILDING", "", IF( Player!$H$1="Active", _xlfn.XLOOKUP( A171, tblrecommended[ActiveTargetID], tblrecommended[Order], "" ), _xlfn.XLOOKUP( A171, tblrecommended[PassiveTargetID], tblrecommended[Order], "" ) ) )}
A172: collection.horse@1 | B172: {=_xlfn.XLOOKUP(Checklist!$A172,tblTargets[TargetID],tblTargets[DisplayName])} -> Horse Lv 1 | C172: {=_xlfn.XLOOKUP( A172, tblTargetStatus[TargetID], tblTargetStatus[successors], "" )} | D172: {=_xlfn.XLOOKUP( A172, tblTargets[TargetID], tblTargets[TargetType], "" )} -> COLLECTION | E172: {=_xlfn.XLOOKUP( A172, tblTargetStatus[TargetID], tblTargetStatus[ChainAwareStatus], "" )} -> BLOCKED | F172: 800 | G172: FALSE | H172: {=_xlfn.XLOOKUP( A172, tblTargetStatus[TargetID], tblTargetStatus[TargetFunded], "" )} -> FALSE | I172: {=IF( D172<>"BUILDING", "", IF( Player!$H$1="Active", _xlfn.XLOOKUP( A172, tblrecommended[ActiveTargetID], tblrecommended[Order], "" ), _xlfn.XLOOKUP( A172, tblrecommended[PassiveTargetID], tblrecommended[Order], "" ) ) )}
A173: collection.kitchen_and_buttery_1@1 | B173: {=_xlfn.XLOOKUP(Checklist!$A173,tblTargets[TargetID],tblTargets[DisplayName])} -> Kitchen And Buttery 1 Lv 1 | C173: {=_xlfn.XLOOKUP( A173, tblTargetStatus[TargetID], tblTargetStatus[successors], "" )} -> Kitchen And Buttery 1 Lv 2 | D173: {=_xlfn.XLOOKUP( A173, tblTargets[TargetID], tblTargets[TargetType], "" )} -> COLLECTION | E173: {=_xlfn.XLOOKUP( A173, tblTargetStatus[TargetID], tblTargetStatus[ChainAwareStatus], "" )} -> BLOCKED | G173: FALSE | H173: {=_xlfn.XLOOKUP( A173, tblTargetStatus[TargetID], tblTargetStatus[TargetFunded], "" )} -> FALSE | I173: {=IF( D173<>"BUILDING", "", IF( Player!$H$1="Active", _xlfn.XLOOKUP( A173, tblrecommended[ActiveTargetID], tblrecommended[Order], "" ), _xlfn.XLOOKUP( A173, tblrecommended[PassiveTargetID], tblrecommended[Order], "" ) ) )}
A174: collection.kitchen_and_buttery_1@2 | B174: {=_xlfn.XLOOKUP(Checklist!$A174,tblTargets[TargetID],tblTargets[DisplayName])} -> Kitchen And Buttery 1 Lv 2 | C174: {=_xlfn.XLOOKUP( A174, tblTargetStatus[TargetID], tblTargetStatus[successors], "" )} -> Kitchen And Buttery 1 Lv 3 | D174: {=_xlfn.XLOOKUP( A174, tblTargets[TargetID], tblTargets[TargetType], "" )} -> COLLECTION | E174: {=_xlfn.XLOOKUP( A174, tblTargetStatus[TargetID], tblTargetStatus[ChainAwareStatus], "" )} -> BLOCKED | G174: FALSE | H174: {=_xlfn.XLOOKUP( A174, tblTargetStatus[TargetID], tblTargetStatus[TargetFunded], "" )} -> FALSE | I174: {=IF( D174<>"BUILDING", "", IF( Player!$H$1="Active", _xlfn.XLOOKUP( A174, tblrecommended[ActiveTargetID], tblrecommended[Order], "" ), _xlfn.XLOOKUP( A174, tblrecommended[PassiveTargetID], tblrecommended[Order], "" ) ) )}
A175: collection.kitchen_and_buttery_1@3 | B175: {=_xlfn.XLOOKUP(Checklist!$A175,tblTargets[TargetID],tblTargets[DisplayName])} -> Kitchen And Buttery 1 Lv 3 | C175: {=_xlfn.XLOOKUP( A175, tblTargetStatus[TargetID], tblTargetStatus[successors], "" )} -> Kitchen And Buttery 1 Lv 4 | D175: {=_xlfn.XLOOKUP( A175, tblTargets[TargetID], tblTargets[TargetType], "" )} -> COLLECTION | E175: {=_xlfn.XLOOKUP( A175, tblTargetStatus[TargetID], tblTargetStatus[ChainAwareStatus], "" )} -> BLOCKED | G175: FALSE | H175: {=_xlfn.XLOOKUP( A175, tblTargetStatus[TargetID], tblTargetStatus[TargetFunded], "" )} -> FALSE | I175: {=IF( D175<>"BUILDING", "", IF( Player!$H$1="Active", _xlfn.XLOOKUP( A175, tblrecommended[ActiveTargetID], tblrecommended[Order], "" ), _xlfn.XLOOKUP( A175, tblrecommended[PassiveTargetID], tblrecommended[Order], "" ) ) )}
...

Sheet cost checklist
A1: RequirementID | B1: TargetID | C1: DisplayName | D1: TargetType | E1: ResourceID | F1: PaymentSlot | G1: QuantityRequired | H1: Sort | I1: TargetCompleted | J1: PlayerPaid | R1: =IFERROR(__xludf.DUMMYFUNCTION("SORT( UNIQUE( FILTER( E2:E2011, (J2:J2011=FALSE)* (I2:I2011=""READY"") ) ) )"),"coin") -> coin
A2: cost.building.airship@1.chemicals.1 | B2: =IFERROR(__xludf.DUMMYFUNCTION("REGEXREPLACE( REGEXREPLACE(A2,""^cost\."",""""), ""\.[^.]+\.[^.]+$"", """" )"),"building.airship@1") -> building.airship@1 | C2: {=_xlfn.XLOOKUP( B2, tblTargets[TargetID], tblTargets[DisplayName], "" )} -> Airship Lv 1 | D2: {=_xlfn.XLOOKUP( B2, tblTargets[TargetID], tblTargets[TargetType], "" )} -> BUILDING | E2: chemicals | F2: 1 | G2: {=_xlfn.XLOOKUP( A2, tblCost[RequirementID], tblCost[QuantityRequired], "" )} -> 200 | H2: {=IF( OR( LEFT(B2,15)="state.character", RIGHT(B2,6)=".maxed" ), 0, LET( sort, _xlfn.XLOOKUP( B2, tblChecklist[TargetID], tblChecklist[PlayerSort], 0 ), IF(sort=0,500,sort) ) )} -> 44 | I2: {=_xlfn.XLOOKUP( B2, tblTargetStatus[TargetID], tblTargetStatus[Status], "" )} -> BLOCKED | J2: FALSE | R2: =IFERROR(__xludf.DUMMYFUNCTION("""COMPUTED_VALUE"""),"ruby") -> ruby
A3: cost.building.airship@1.coin.1 | B3: =IFERROR(__xludf.DUMMYFUNCTION("REGEXREPLACE( REGEXREPLACE(A3,""^cost\."",""""), ""\.[^.]+\.[^.]+$"", """" )"),"building.airship@1") -> building.airship@1 | C3: {=_xlfn.XLOOKUP( B3, tblTargets[TargetID], tblTargets[DisplayName], "" )} -> Airship Lv 1 | D3: {=_xlfn.XLOOKUP( B3, tblTargets[TargetID], tblTargets[TargetType], "" )} -> BUILDING | E3: coin | F3: 1 | G3: {=_xlfn.XLOOKUP( A3, tblCost[RequirementID], tblCost[QuantityRequired], "" )} -> 2000 | H3: {=IF( OR( LEFT(B3,15)="state.character", RIGHT(B3,6)=".maxed" ), 0, LET( sort, _xlfn.XLOOKUP( B3, tblChecklist[TargetID], tblChecklist[PlayerSort], 0 ), IF(sort=0,500,sort) ) )} -> 44 | I3: {=_xlfn.XLOOKUP( B3, tblTargetStatus[TargetID], tblTargetStatus[Status], "" )} -> BLOCKED | J3: FALSE | R3: =IFERROR(__xludf.DUMMYFUNCTION("""COMPUTED_VALUE"""),"stone") -> stone
A4: cost.building.airship@1.miron.1 | B4: =IFERROR(__xludf.DUMMYFUNCTION("REGEXREPLACE( REGEXREPLACE(A4,""^cost\."",""""), ""\.[^.]+\.[^.]+$"", """" )"),"building.airship@1") -> building.airship@1 | C4: {=_xlfn.XLOOKUP( B4, tblTargets[TargetID], tblTargets[DisplayName], "" )} -> Airship Lv 1 | D4: {=_xlfn.XLOOKUP( B4, tblTargets[TargetID], tblTargets[TargetType], "" )} -> BUILDING | E4: miron | F4: 1 | G4: {=_xlfn.XLOOKUP( A4, tblCost[RequirementID], tblCost[QuantityRequired], "" )} -> 50 | H4: {=IF( OR( LEFT(B4,15)="state.character", RIGHT(B4,6)=".maxed" ), 0, LET( sort, _xlfn.XLOOKUP( B4, tblChecklist[TargetID], tblChecklist[PlayerSort], 0 ), IF(sort=0,500,sort) ) )} -> 44 | I4: {=_xlfn.XLOOKUP( B4, tblTargetStatus[TargetID], tblTargetStatus[Status], "" )} -> BLOCKED | J4: FALSE | R4: =IFERROR(__xludf.DUMMYFUNCTION("""COMPUTED_VALUE"""),"wood") -> wood
A5: cost.building.airship@1.page.1 | B5: =IFERROR(__xludf.DUMMYFUNCTION("REGEXREPLACE( REGEXREPLACE(A5,""^cost\."",""""), ""\.[^.]+\.[^.]+$"", """" )"),"building.airship@1") -> building.airship@1 | C5: {=_xlfn.XLOOKUP( B5, tblTargets[TargetID], tblTargets[DisplayName], "" )} -> Airship Lv 1 | D5: {=_xlfn.XLOOKUP( B5, tblTargets[TargetID], tblTargets[TargetType], "" )} -> BUILDING | E5: page | F5: 1 | G5: {=_xlfn.XLOOKUP( A5, tblCost[RequirementID], tblCost[QuantityRequired], "" )} -> 40 | H5: {=IF( OR( LEFT(B5,15)="state.character", RIGHT(B5,6)=".maxed" ), 0, LET( sort, _xlfn.XLOOKUP( B5, tblChecklist[TargetID], tblChecklist[PlayerSort], 0 ), IF(sort=0,500,sort) ) )} -> 44 | I5: {=_xlfn.XLOOKUP( B5, tblTargetStatus[TargetID], tblTargetStatus[Status], "" )} -> BLOCKED | J5: FALSE
A6: cost.building.airship@1.reagent.1 | B6: =IFERROR(__xludf.DUMMYFUNCTION("REGEXREPLACE( REGEXREPLACE(A6,""^cost\."",""""), ""\.[^.]+\.[^.]+$"", """" )"),"building.airship@1") -> building.airship@1 | C6: {=_xlfn.XLOOKUP( B6, tblTargets[TargetID], tblTargets[DisplayName], "" )} -> Airship Lv 1 | D6: {=_xlfn.XLOOKUP( B6, tblTargets[TargetID], tblTargets[TargetType], "" )} -> BUILDING | E6: reagent | F6: 1 | G6: {=_xlfn.XLOOKUP( A6, tblCost[RequirementID], tblCost[QuantityRequired], "" )} -> 20 | H6: {=IF( OR( LEFT(B6,15)="state.character", RIGHT(B6,6)=".maxed" ), 0, LET( sort, _xlfn.XLOOKUP( B6, tblChecklist[TargetID], tblChecklist[PlayerSort], 0 ), IF(sort=0,500,sort) ) )} -> 44 | I6: {=_xlfn.XLOOKUP( B6, tblTargetStatus[TargetID], tblTargetStatus[Status], "" )} -> BLOCKED | J6: FALSE
A7: cost.building.airship@1.ruby.1 | B7: =IFERROR(__xludf.DUMMYFUNCTION("REGEXREPLACE( REGEXREPLACE(A7,""^cost\."",""""), ""\.[^.]+\.[^.]+$"", """" )"),"building.airship@1") -> building.airship@1 | C7: {=_xlfn.XLOOKUP( B7, tblTargets[TargetID], tblTargets[DisplayName], "" )} -> Airship Lv 1 | D7: {=_xlfn.XLOOKUP( B7, tblTargets[TargetID], tblTargets[TargetType], "" )} -> BUILDING | E7: ruby | F7: 1 | G7: {=_xlfn.XLOOKUP( A7, tblCost[RequirementID], tblCost[QuantityRequired], "" )} -> 10 | H7: {=IF( OR( LEFT(B7,15)="state.character", RIGHT(B7,6)=".maxed" ), 0, LET( sort, _xlfn.XLOOKUP( B7, tblChecklist[TargetID], tblChecklist[PlayerSort], 0 ), IF(sort=0,500,sort) ) )} -> 44 | I7: {=_xlfn.XLOOKUP( B7, tblTargetStatus[TargetID], tblTargetStatus[Status], "" )} -> BLOCKED | J7: FALSE
A8: cost.building.airship@1.silk.1 | B8: =IFERROR(__xludf.DUMMYFUNCTION("REGEXREPLACE( REGEXREPLACE(A8,""^cost\."",""""), ""\.[^.]+\.[^.]+$"", """" )"),"building.airship@1") -> building.airship@1 | C8: {=_xlfn.XLOOKUP( B8, tblTargets[TargetID], tblTargets[DisplayName], "" )} -> Airship Lv 1 | D8: {=_xlfn.XLOOKUP( B8, tblTargets[TargetID], tblTargets[TargetType], "" )} -> BUILDING | E8: silk | F8: 1 | G8: {=_xlfn.XLOOKUP( A8, tblCost[RequirementID], tblCost[QuantityRequired], "" )} -> 120 | H8: {=IF( OR( LEFT(B8,15)="state.character", RIGHT(B8,6)=".maxed" ), 0, LET( sort, _xlfn.XLOOKUP( B8, tblChecklist[TargetID], tblChecklist[PlayerSort], 0 ), IF(sort=0,500,sort) ) )} -> 44 | I8: {=_xlfn.XLOOKUP( B8, tblTargetStatus[TargetID], tblTargetStatus[Status], "" )} -> BLOCKED | J8: FALSE
A9: cost.building.airship@1.thread.1 | B9: =IFERROR(__xludf.DUMMYFUNCTION("REGEXREPLACE( REGEXREPLACE(A9,""^cost\."",""""), ""\.[^.]+\.[^.]+$"", """" )"),"building.airship@1") -> building.airship@1 | C9: {=_xlfn.XLOOKUP( B9, tblTargets[TargetID], tblTargets[DisplayName], "" )} -> Airship Lv 1 | D9: {=_xlfn.XLOOKUP( B9, tblTargets[TargetID], tblTargets[TargetType], "" )} -> BUILDING | E9: thread | F9: 1 | G9: {=_xlfn.XLOOKUP( A9, tblCost[RequirementID], tblCost[QuantityRequired], "" )} -> 20 | H9: {=IF( OR( LEFT(B9,15)="state.character", RIGHT(B9,6)=".maxed" ), 0, LET( sort, _xlfn.XLOOKUP( B9, tblChecklist[TargetID], tblChecklist[PlayerSort], 0 ), IF(sort=0,500,sort) ) )} -> 44 | I9: {=_xlfn.XLOOKUP( B9, tblTargetStatus[TargetID], tblTargetStatus[Status], "" )} -> BLOCKED | J9: FALSE
A10: cost.building.airship@2.coin.1 | B10: =IFERROR(__xludf.DUMMYFUNCTION("REGEXREPLACE( REGEXREPLACE(A10,""^cost\."",""""), ""\.[^.]+\.[^.]+$"", """" )"),"building.airship@2") -> building.airship@2 | C10: {=_xlfn.XLOOKUP( B10, tblTargets[TargetID], tblTargets[DisplayName], "" )} -> Airship Lv 2 | D10: {=_xlfn.XLOOKUP( B10, tblTargets[TargetID], tblTargets[TargetType], "" )} -> BUILDING | E10: coin | F10: 1 | G10: {=_xlfn.XLOOKUP( A10, tblCost[RequirementID], tblCost[QuantityRequired], "" )} -> 3000 | H10: {=IF( OR( LEFT(B10,15)="state.character", RIGHT(B10,6)=".maxed" ), 0, LET( sort, _xlfn.XLOOKUP( B10, tblChecklist[TargetID], tblChecklist[PlayerSort], 0 ), IF(sort=0,500,sort) ) )} -> 45 | I10: {=_xlfn.XLOOKUP( B10, tblTargetStatus[TargetID], tblTargetStatus[Status], "" )} -> BLOCKED | J10: FALSE
A11: cost.building.airship@2.fan.1 | B11: =IFERROR(__xludf.DUMMYFUNCTION("REGEXREPLACE( REGEXREPLACE(A11,""^cost\."",""""), ""\.[^.]+\.[^.]+$"", """" )"),"building.airship@2") -> building.airship@2 | C11: {=_xlfn.XLOOKUP( B11, tblTargets[TargetID], tblTargets[DisplayName], "" )} -> Airship Lv 2 | D11: {=_xlfn.XLOOKUP( B11, tblTargets[TargetID], tblTargets[TargetType], "" )} -> BUILDING | E11: fan | F11: 1 | G11: {=_xlfn.XLOOKUP( A11, tblCost[RequirementID], tblCost[QuantityRequired], "" )} -> 50 | H11: {=IF( OR( LEFT(B11,15)="state.character", RIGHT(B11,6)=".maxed" ), 0, LET( sort, _xlfn.XLOOKUP( B11, tblChecklist[TargetID], tblChecklist[PlayerSort], 0 ), IF(sort=0,500,sort) ) )} -> 45 | I11: {=_xlfn.XLOOKUP( B11, tblTargetStatus[TargetID], tblTargetStatus[Status], "" )} -> BLOCKED | J11: FALSE
A12: cost.building.airship@2.gears.1 | B12: =IFERROR(__xludf.DUMMYFUNCTION("REGEXREPLACE( REGEXREPLACE(A12,""^cost\."",""""), ""\.[^.]+\.[^.]+$"", """" )"),"building.airship@2") -> building.airship@2 | C12: {=_xlfn.XLOOKUP( B12, tblTargets[TargetID], tblTargets[DisplayName], "" )} -> Airship Lv 2 | D12: {=_xlfn.XLOOKUP( B12, tblTargets[TargetID], tblTargets[TargetType], "" )} -> BUILDING | E12: gears | F12: 1 | G12: {=_xlfn.XLOOKUP( A12, tblCost[RequirementID], tblCost[QuantityRequired], "" )} -> 20 | H12: {=IF( OR( LEFT(B12,15)="state.character", RIGHT(B12,6)=".maxed" ), 0, LET( sort, _xlfn.XLOOKUP( B12, tblChecklist[TargetID], tblChecklist[PlayerSort], 0 ), IF(sort=0,500,sort) ) )} -> 45 | I12: {=_xlfn.XLOOKUP( B12, tblTargetStatus[TargetID], tblTargetStatus[Status], "" )} -> BLOCKED | J12: FALSE
A13: cost.building.airship@2.plank.1 | B13: =IFERROR(__xludf.DUMMYFUNCTION("REGEXREPLACE( REGEXREPLACE(A13,""^cost\."",""""), ""\.[^.]+\.[^.]+$"", """" )"),"building.airship@2") -> building.airship@2 | C13: {=_xlfn.XLOOKUP( B13, tblTargets[TargetID], tblTargets[DisplayName], "" )} -> Airship Lv 2 | D13: {=_xlfn.XLOOKUP( B13, tblTargets[TargetID], tblTargets[TargetType], "" )} -> BUILDING | E13: plank | F13: 1 | G13: {=_xlfn.XLOOKUP( A13, tblCost[RequirementID], tblCost[QuantityRequired], "" )} -> 60 | H13: {=IF( OR( LEFT(B13,15)="state.character", RIGHT(B13,6)=".maxed" ), 0, LET( sort, _xlfn.XLOOKUP( B13, tblChecklist[TargetID], tblChecklist[PlayerSort], 0 ), IF(sort=0,500,sort) ) )} -> 45 | I13: {=_xlfn.XLOOKUP( B13, tblTargetStatus[TargetID], tblTargetStatus[Status], "" )} -> BLOCKED | J13: FALSE
A14: cost.building.airship@2.ruby.1 | B14: =IFERROR(__xludf.DUMMYFUNCTION("REGEXREPLACE( REGEXREPLACE(A14,""^cost\."",""""), ""\.[^.]+\.[^.]+$"", """" )"),"building.airship@2") -> building.airship@2 | C14: {=_xlfn.XLOOKUP( B14, tblTargets[TargetID], tblTargets[DisplayName], "" )} -> Airship Lv 2 | D14: {=_xlfn.XLOOKUP( B14, tblTargets[TargetID], tblTargets[TargetType], "" )} -> BUILDING | E14: ruby | F14: 1 | G14: {=_xlfn.XLOOKUP( A14, tblCost[RequirementID], tblCost[QuantityRequired], "" )} -> 12 | H14: {=IF( OR( LEFT(B14,15)="state.character", RIGHT(B14,6)=".maxed" ), 0, LET( sort, _xlfn.XLOOKUP( B14, tblChecklist[TargetID], tblChecklist[PlayerSort], 0 ), IF(sort=0,500,sort) ) )} -> 45 | I14: {=_xlfn.XLOOKUP( B14, tblTargetStatus[TargetID], tblTargetStatus[Status], "" )} -> BLOCKED | J14: FALSE
A15: cost.building.airship@2.silk.1 | B15: =IFERROR(__xludf.DUMMYFUNCTION("REGEXREPLACE( REGEXREPLACE(A15,""^cost\."",""""), ""\.[^.]+\.[^.]+$"", """" )"),"building.airship@2") -> building.airship@2 | C15: {=_xlfn.XLOOKUP( B15, tblTargets[TargetID], tblTargets[DisplayName], "" )} -> Airship Lv 2 | D15: {=_xlfn.XLOOKUP( B15, tblTargets[TargetID], tblTargets[TargetType], "" )} -> BUILDING | E15: silk | F15: 1 | G15: {=_xlfn.XLOOKUP( A15, tblCost[RequirementID], tblCost[QuantityRequired], "" )} -> 100 | H15: {=IF( OR( LEFT(B15,15)="state.character", RIGHT(B15,6)=".maxed" ), 0, LET( sort, _xlfn.XLOOKUP( B15, tblChecklist[TargetID], tblChecklist[PlayerSort], 0 ), IF(sort=0,500,sort) ) )} -> 45 | I15: {=_xlfn.XLOOKUP( B15, tblTargetStatus[TargetID], tblTargetStatus[Status], "" )} -> BLOCKED | J15: FALSE
A16: cost.building.airship@2.thread.1 | B16: =IFERROR(__xludf.DUMMYFUNCTION("REGEXREPLACE( REGEXREPLACE(A16,""^cost\."",""""), ""\.[^.]+\.[^.]+$"", """" )"),"building.airship@2") -> building.airship@2 | C16: {=_xlfn.XLOOKUP( B16, tblTargets[TargetID], tblTargets[DisplayName], "" )} -> Airship Lv 2 | D16: {=_xlfn.XLOOKUP( B16, tblTargets[TargetID], tblTargets[TargetType], "" )} -> BUILDING | E16: thread | F16: 1 | G16: {=_xlfn.XLOOKUP( A16, tblCost[RequirementID], tblCost[QuantityRequired], "" )} -> 10 | H16: {=IF( OR( LEFT(B16,15)="state.character", RIGHT(B16,6)=".maxed" ), 0, LET( sort, _xlfn.XLOOKUP( B16, tblChecklist[TargetID], tblChecklist[PlayerSort], 0 ), IF(sort=0,500,sort) ) )} -> 45 | I16: {=_xlfn.XLOOKUP( B16, tblTargetStatus[TargetID], tblTargetStatus[Status], "" )} -> BLOCKED | J16: FALSE
A17: cost.building.alchemists_hut@1.coin.1 | B17: =IFERROR(__xludf.DUMMYFUNCTION("REGEXREPLACE( REGEXREPLACE(A17,""^cost\."",""""), ""\.[^.]+\.[^.]+$"", """" )"),"building.alchemists_hut@1") -> building.alchemists_hut@1 | C17: {=_xlfn.XLOOKUP( B17, tblTargets[TargetID], tblTargets[DisplayName], "" )} -> Alchemist's Hut Lv 1 | D17: {=_xlfn.XLOOKUP( B17, tblTargets[TargetID], tblTargets[TargetType], "" )} -> BUILDING | E17: coin | F17: 1 | G17: {=_xlfn.XLOOKUP( A17, tblCost[RequirementID], tblCost[QuantityRequired], "" )} -> 140 | H17: {=IF( OR( LEFT(B17,15)="state.character", RIGHT(B17,6)=".maxed" ), 0, LET( sort, _xlfn.XLOOKUP( B17, tblChecklist[TargetID], tblChecklist[PlayerSort], 0 ), IF(sort=0,500,sort) ) )} -> 4 | I17: {=_xlfn.XLOOKUP( B17, tblTargetStatus[TargetID], tblTargetStatus[Status], "" )} -> BLOCKED | J17: FALSE
A18: cost.building.alchemists_hut@1.ruby.1 | B18: =IFERROR(__xludf.DUMMYFUNCTION("REGEXREPLACE( REGEXREPLACE(A18,""^cost\."",""""), ""\.[^.]+\.[^.]+$"", """" )"),"building.alchemists_hut@1") -> building.alchemists_hut@1 | C18: {=_xlfn.XLOOKUP( B18, tblTargets[TargetID], tblTargets[DisplayName], "" )} -> Alchemist's Hut Lv 1 | D18: {=_xlfn.XLOOKUP( B18, tblTargets[TargetID], tblTargets[TargetType], "" )} -> BUILDING | E18: ruby | F18: 1 | G18: {=_xlfn.XLOOKUP( A18, tblCost[RequirementID], tblCost[QuantityRequired], "" )} -> 1 | H18: {=IF( OR( LEFT(B18,15)="state.character", RIGHT(B18,6)=".maxed" ), 0, LET( sort, _xlfn.XLOOKUP( B18, tblChecklist[TargetID], tblChecklist[PlayerSort], 0 ), IF(sort=0,500,sort) ) )} -> 4 | I18: {=_xlfn.XLOOKUP( B18, tblTargetStatus[TargetID], tblTargetStatus[Status], "" )} -> BLOCKED | J18: FALSE
A19: cost.building.alchemists_hut@1.stone.1 | B19: =IFERROR(__xludf.DUMMYFUNCTION("REGEXREPLACE( REGEXREPLACE(A19,""^cost\."",""""), ""\.[^.]+\.[^.]+$"", """" )"),"building.alchemists_hut@1") -> building.alchemists_hut@1 | C19: {=_xlfn.XLOOKUP( B19, tblTargets[TargetID], tblTargets[DisplayName], "" )} -> Alchemist's Hut Lv 1 | D19: {=_xlfn.XLOOKUP( B19, tblTargets[TargetID], tblTargets[TargetType], "" )} -> BUILDING | E19: stone | F19: 1 | G19: {=_xlfn.XLOOKUP( A19, tblCost[RequirementID], tblCost[QuantityRequired], "" )} -> 70 | H19: {=IF( OR( LEFT(B19,15)="state.character", RIGHT(B19,6)=".maxed" ), 0, LET( sort, _xlfn.XLOOKUP( B19, tblChecklist[TargetID], tblChecklist[PlayerSort], 0 ), IF(sort=0,500,sort) ) )} -> 4 | I19: {=_xlfn.XLOOKUP( B19, tblTargetStatus[TargetID], tblTargetStatus[Status], "" )} -> BLOCKED | J19: FALSE
A20: cost.building.alchemists_hut@1.wood.1 | B20: =IFERROR(__xludf.DUMMYFUNCTION("REGEXREPLACE( REGEXREPLACE(A20,""^cost\."",""""), ""\.[^.]+\.[^.]+$"", """" )"),"building.alchemists_hut@1") -> building.alchemists_hut@1 | C20: {=_xlfn.XLOOKUP( B20, tblTargets[TargetID], tblTargets[DisplayName], "" )} -> Alchemist's Hut Lv 1 | D20: {=_xlfn.XLOOKUP( B20, tblTargets[TargetID], tblTargets[TargetType], "" )} -> BUILDING | E20: wood | F20: 1 | G20: {=_xlfn.XLOOKUP( A20, tblCost[RequirementID], tblCost[QuantityRequired], "" )} -> 70 | H20: {=IF( OR( LEFT(B20,15)="state.character", RIGHT(B20,6)=".maxed" ), 0, LET( sort, _xlfn.XLOOKUP( B20, tblChecklist[TargetID], tblChecklist[PlayerSort], 0 ), IF(sort=0,500,sort) ) )} -> 4 | I20: {=_xlfn.XLOOKUP( B20, tblTargetStatus[TargetID], tblTargetStatus[Status], "" )} -> BLOCKED | J20: FALSE
A21: cost.building.alchemists_hut@2.chemicals.1 | B21: =IFERROR(__xludf.DUMMYFUNCTION("REGEXREPLACE( REGEXREPLACE(A21,""^cost\."",""""), ""\.[^.]+\.[^.]+$"", """" )"),"building.alchemists_hut@2") -> building.alchemists_hut@2 | C21: {=_xlfn.XLOOKUP( B21, tblTargets[TargetID], tblTargets[DisplayName], "" )} -> Alchemist's Hut Lv 2 | D21: {=_xlfn.XLOOKUP( B21, tblTargets[TargetID], tblTargets[TargetType], "" )} -> BUILDING | E21: chemicals | F21: 1 | G21: {=_xlfn.XLOOKUP( A21, tblCost[RequirementID], tblCost[QuantityRequired], "" )} -> 20 | H21: {=IF( OR( LEFT(B21,15)="state.character", RIGHT(B21,6)=".maxed" ), 0, LET( sort, _xlfn.XLOOKUP( B21, tblChecklist[TargetID], tblChecklist[PlayerSort], 0 ), IF(sort=0,500,sort) ) )} -> 5 | I21: {=_xlfn.XLOOKUP( B21, tblTargetStatus[TargetID], tblTargetStatus[Status], "" )} -> BLOCKED | J21: FALSE
A22: cost.building.alchemists_hut@2.coin.1 | B22: =IFERROR(__xludf.DUMMYFUNCTION("REGEXREPLACE( REGEXREPLACE(A22,""^cost\."",""""), ""\.[^.]+\.[^.]+$"", """" )"),"building.alchemists_hut@2") -> building.alchemists_hut@2 | C22: {=_xlfn.XLOOKUP( B22, tblTargets[TargetID], tblTargets[DisplayName], "" )} -> Alchemist's Hut Lv 2 | D22: {=_xlfn.XLOOKUP( B22, tblTargets[TargetID], tblTargets[TargetType], "" )} -> BUILDING | E22: coin | F22: 1 | G22: {=_xlfn.XLOOKUP( A22, tblCost[RequirementID], tblCost[QuantityRequired], "" )} -> 200 | H22: {=IF( OR( LEFT(B22,15)="state.character", RIGHT(B22,6)=".maxed" ), 0, LET( sort, _xlfn.XLOOKUP( B22, tblChecklist[TargetID], tblChecklist[PlayerSort], 0 ), IF(sort=0,500,sort) ) )} -> 5 | I22: {=_xlfn.XLOOKUP( B22, tblTargetStatus[TargetID], tblTargetStatus[Status], "" )} -> BLOCKED | J22: FALSE
A23: cost.building.alchemists_hut@2.ruby.1 | B23: =IFERROR(__xludf.DUMMYFUNCTION("REGEXREPLACE( REGEXREPLACE(A23,""^cost\."",""""), ""\.[^.]+\.[^.]+$"", """" )"),"building.alchemists_hut@2") -> building.alchemists_hut@2 | C23: {=_xlfn.XLOOKUP( B23, tblTargets[TargetID], tblTargets[DisplayName], "" )} -> Alchemist's Hut Lv 2 | D23: {=_xlfn.XLOOKUP( B23, tblTargets[TargetID], tblTargets[TargetType], "" )} -> BUILDING | E23: ruby | F23: 1 | G23: {=_xlfn.XLOOKUP( A23, tblCost[RequirementID], tblCost[QuantityRequired], "" )} -> 2 | H23: {=IF( OR( LEFT(B23,15)="state.character", RIGHT(B23,6)=".maxed" ), 0, LET( sort, _xlfn.XLOOKUP( B23, tblChecklist[TargetID], tblChecklist[PlayerSort], 0 ), IF(sort=0,500,sort) ) )} -> 5 | I23: {=_xlfn.XLOOKUP( B23, tblTargetStatus[TargetID], tblTargetStatus[Status], "" )} -> BLOCKED | J23: FALSE
A24: cost.building.alchemists_hut@2.stone.1 | B24: =IFERROR(__xludf.DUMMYFUNCTION("REGEXREPLACE( REGEXREPLACE(A24,""^cost\."",""""), ""\.[^.]+\.[^.]+$"", """" )"),"building.alchemists_hut@2") -> building.alchemists_hut@2 | C24: {=_xlfn.XLOOKUP( B24, tblTargets[TargetID], tblTargets[DisplayName], "" )} -> Alchemist's Hut Lv 2 | D24: {=_xlfn.XLOOKUP( B24, tblTargets[TargetID], tblTargets[TargetType], "" )} -> BUILDING | E24: stone | F24: 1 | G24: {=_xlfn.XLOOKUP( A24, tblCost[RequirementID], tblCost[QuantityRequired], "" )} -> 100 | H24: {=IF( OR( LEFT(B24,15)="state.character", RIGHT(B24,6)=".maxed" ), 0, LET( sort, _xlfn.XLOOKUP( B24, tblChecklist[TargetID], tblChecklist[PlayerSort], 0 ), IF(sort=0,500,sort) ) )} -> 5 | I24: {=_xlfn.XLOOKUP( B24, tblTargetStatus[TargetID], tblTargetStatus[Status], "" )} -> BLOCKED | J24: FALSE
A25: cost.building.alchemists_hut@2.wood.1 | B25: =IFERROR(__xludf.DUMMYFUNCTION("REGEXREPLACE( REGEXREPLACE(A25,""^cost\."",""""), ""\.[^.]+\.[^.]+$"", """" )"),"building.alchemists_hut@2") -> building.alchemists_hut@2 | C25: {=_xlfn.XLOOKUP( B25, tblTargets[TargetID], tblTargets[DisplayName], "" )} -> Alchemist's Hut Lv 2 | D25: {=_xlfn.XLOOKUP( B25, tblTargets[TargetID], tblTargets[TargetType], "" )} -> BUILDING | E25: wood | F25: 1 | G25: {=_xlfn.XLOOKUP( A25, tblCost[RequirementID], tblCost[QuantityRequired], "" )} -> 100 | H25: {=IF( OR( LEFT(B25,15)="state.character", RIGHT(B25,6)=".maxed" ), 0, LET( sort, _xlfn.XLOOKUP( B25, tblChecklist[TargetID], tblChecklist[PlayerSort], 0 ), IF(sort=0,500,sort) ) )} -> 5 | I25: {=_xlfn.XLOOKUP( B25, tblTargetStatus[TargetID], tblTargetStatus[Status], "" )} -> BLOCKED | J25: FALSE
A26: cost.building.alchemists_hut@3.beam.1 | B26: =IFERROR(__xludf.DUMMYFUNCTION("REGEXREPLACE( REGEXREPLACE(A26,""^cost\."",""""), ""\.[^.]+\.[^.]+$"", """" )"),"building.alchemists_hut@3") -> building.alchemists_hut@3 | C26: {=_xlfn.XLOOKUP( B26, tblTargets[TargetID], tblTargets[DisplayName], "" )} -> Alchemist's Hut Lv 3 | D26: {=_xlfn.XLOOKUP( B26, tblTargets[TargetID], tblTargets[TargetType], "" )} -> BUILDING | E26: beam | F26: 1 | G26: {=_xlfn.XLOOKUP( A26, tblCost[RequirementID], tblCost[QuantityRequired], "" )} -> 300 | H26: {=IF( OR( LEFT(B26,15)="state.character", RIGHT(B26,6)=".maxed" ), 0, LET( sort, _xlfn.XLOOKUP( B26, tblChecklist[TargetID], tblChecklist[PlayerSort], 0 ), IF(sort=0,500,sort) ) )} -> 51 | I26: {=_xlfn.XLOOKUP( B26, tblTargetStatus[TargetID], tblTargetStatus[Status], "" )} -> BLOCKED | J26: FALSE
A27: cost.building.alchemists_hut@3.charcoal.1 | B27: =IFERROR(__xludf.DUMMYFUNCTION("REGEXREPLACE( REGEXREPLACE(A27,""^cost\."",""""), ""\.[^.]+\.[^.]+$"", """" )"),"building.alchemists_hut@3") -> building.alchemists_hut@3 | C27: {=_xlfn.XLOOKUP( B27, tblTargets[TargetID], tblTargets[DisplayName], "" )} -> Alchemist's Hut Lv 3 | D27: {=_xlfn.XLOOKUP( B27, tblTargets[TargetID], tblTargets[TargetType], "" )} -> BUILDING | E27: charcoal | F27: 1 | G27: {=_xlfn.XLOOKUP( A27, tblCost[RequirementID], tblCost[QuantityRequired], "" )} -> 40 | H27: {=IF( OR( LEFT(B27,15)="state.character", RIGHT(B27,6)=".maxed" ), 0, LET( sort, _xlfn.XLOOKUP( B27, tblChecklist[TargetID], tblChecklist[PlayerSort], 0 ), IF(sort=0,500,sort) ) )} -> 51 | I27: {=_xlfn.XLOOKUP( B27, tblTargetStatus[TargetID], tblTargetStatus[Status], "" )} -> BLOCKED | J27: FALSE
A28: cost.building.alchemists_hut@3.chemicals.1 | B28: =IFERROR(__xludf.DUMMYFUNCTION("REGEXREPLACE( REGEXREPLACE(A28,""^cost\."",""""), ""\.[^.]+\.[^.]+$"", """" )"),"building.alchemists_hut@3") -> building.alchemists_hut@3 | C28: {=_xlfn.XLOOKUP( B28, tblTargets[TargetID], tblTargets[DisplayName], "" )} -> Alchemist's Hut Lv 3 | D28: {=_xlfn.XLOOKUP( B28, tblTargets[TargetID], tblTargets[TargetType], "" )} -> BUILDING | E28: chemicals | F28: 1 | G28: {=_xlfn.XLOOKUP( A28, tblCost[RequirementID], tblCost[QuantityRequired], "" )} -> 40 | H28: {=IF( OR( LEFT(B28,15)="state.character", RIGHT(B28,6)=".maxed" ), 0, LET( sort, _xlfn.XLOOKUP( B28, tblChecklist[TargetID], tblChecklist[PlayerSort], 0 ), IF(sort=0,500,sort) ) )} -> 51 | I28: {=_xlfn.XLOOKUP( B28, tblTargetStatus[TargetID], tblTargetStatus[Status], "" )} -> BLOCKED | J28: FALSE
A29: cost.building.alchemists_hut@3.coin.1 | B29: =IFERROR(__xludf.DUMMYFUNCTION("REGEXREPLACE( REGEXREPLACE(A29,""^cost\."",""""), ""\.[^.]+\.[^.]+$"", """" )"),"building.alchemists_hut@3") -> building.alchemists_hut@3 | C29: {=_xlfn.XLOOKUP( B29, tblTargets[TargetID], tblTargets[DisplayName], "" )} -> Alchemist's Hut Lv 3 | D29: {=_xlfn.XLOOKUP( B29, tblTargets[TargetID], tblTargets[TargetType], "" )} -> BUILDING | E29: coin | F29: 1 | G29: {=_xlfn.XLOOKUP( A29, tblCost[RequirementID], tblCost[QuantityRequired], "" )} -> 300 | H29: {=IF( OR( LEFT(B29,15)="state.character", RIGHT(B29,6)=".maxed" ), 0, LET( sort, _xlfn.XLOOKUP( B29, tblChecklist[TargetID], tblChecklist[PlayerSort], 0 ), IF(sort=0,500,sort) ) )} -> 51 | I29: {=_xlfn.XLOOKUP( B29, tblTargetStatus[TargetID], tblTargetStatus[Status], "" )} -> BLOCKED | J29: FALSE
A30: cost.building.alchemists_hut@3.ruby.1 | B30: =IFERROR(__xludf.DUMMYFUNCTION("REGEXREPLACE( REGEXREPLACE(A30,""^cost\."",""""), ""\.[^.]+\.[^.]+$"", """" )"),"building.alchemists_hut@3") -> building.alchemists_hut@3 | C30: {=_xlfn.XLOOKUP( B30, tblTargets[TargetID], tblTargets[DisplayName], "" )} -> Alchemist's Hut Lv 3 | D30: {=_xlfn.XLOOKUP( B30, tblTargets[TargetID], tblTargets[TargetType], "" )} -> BUILDING | E30: ruby | F30: 1 | G30: {=_xlfn.XLOOKUP( A30, tblCost[RequirementID], tblCost[QuantityRequired], "" )} -> 3 | H30: {=IF( OR( LEFT(B30,15)="state.character", RIGHT(B30,6)=".maxed" ), 0, LET( sort, _xlfn.XLOOKUP( B30, tblChecklist[TargetID], tblChecklist[PlayerSort], 0 ), IF(sort=0,500,sort) ) )} -> 51 | I30: {=_xlfn.XLOOKUP( B30, tblTargetStatus[TargetID], tblTargetStatus[Status], "" )} -> BLOCKED | J30: FALSE
A31: cost.building.alchemists_hut@3.stone.1 | B31: =IFERROR(__xludf.DUMMYFUNCTION("REGEXREPLACE( REGEXREPLACE(A31,""^cost\."",""""), ""\.[^.]+\.[^.]+$"", """" )"),"building.alchemists_hut@3") -> building.alchemists_hut@3 | C31: {=_xlfn.XLOOKUP( B31, tblTargets[TargetID], tblTargets[DisplayName], "" )} -> Alchemist's Hut Lv 3 | D31: {=_xlfn.XLOOKUP( B31, tblTargets[TargetID], tblTargets[TargetType], "" )} -> BUILDING | E31: stone | F31: 1 | G31: {=_xlfn.XLOOKUP( A31, tblCost[RequirementID], tblCost[QuantityRequired], "" )} -> 150 | H31: {=IF( OR( LEFT(B31,15)="state.character", RIGHT(B31,6)=".maxed" ), 0, LET( sort, _xlfn.XLOOKUP( B31, tblChecklist[TargetID], tblChecklist[PlayerSort], 0 ), IF(sort=0,500,sort) ) )} -> 51 | I31: {=_xlfn.XLOOKUP( B31, tblTargetStatus[TargetID], tblTargetStatus[Status], "" )} -> BLOCKED | J31: FALSE
A32: cost.building.alchemists_hut@4.beam.1 | B32: =IFERROR(__xludf.DUMMYFUNCTION("REGEXREPLACE( REGEXREPLACE(A32,""^cost\."",""""), ""\.[^.]+\.[^.]+$"", """" )"),"building.alchemists_hut@4") -> building.alchemists_hut@4 | C32: {=_xlfn.XLOOKUP( B32, tblTargets[TargetID], tblTargets[DisplayName], "" )} -> Alchemist's Hut Lv 4 | D32: {=_xlfn.XLOOKUP( B32, tblTargets[TargetID], tblTargets[TargetType], "" )} -> BUILDING | E32: beam | F32: 1 | G32: {=_xlfn.XLOOKUP( A32, tblCost[RequirementID], tblCost[QuantityRequired], "" )} -> 400 | H32: {=IF( OR( LEFT(B32,15)="state.character", RIGHT(B32,6)=".maxed" ), 0, LET( sort, _xlfn.XLOOKUP( B32, tblChecklist[TargetID], tblChecklist[PlayerSort], 0 ), IF(sort=0,500,sort) ) )} -> 52 | I32: {=_xlfn.XLOOKUP( B32, tblTargetStatus[TargetID], tblTargetStatus[Status], "" )} -> BLOCKED | J32: FALSE
A33: cost.building.alchemists_hut@4.coin.1 | B33: =IFERROR(__xludf.DUMMYFUNCTION("REGEXREPLACE( REGEXREPLACE(A33,""^cost\."",""""), ""\.[^.]+\.[^.]+$"", """" )"),"building.alchemists_hut@4") -> building.alchemists_hut@4 | C33: {=_xlfn.XLOOKUP( B33, tblTargets[TargetID], tblTargets[DisplayName], "" )} -> Alchemist's Hut Lv 4 | D33: {=_xlfn.XLOOKUP( B33, tblTargets[TargetID], tblTargets[TargetType], "" )} -> BUILDING | E33: coin | F33: 1 | G33: {=_xlfn.XLOOKUP( A33, tblCost[RequirementID], tblCost[QuantityRequired], "" )} -> 400 | H33: {=IF( OR( LEFT(B33,15)="state.character", RIGHT(B33,6)=".maxed" ), 0, LET( sort, _xlfn.XLOOKUP( B33, tblChecklist[TargetID], tblChecklist[PlayerSort], 0 ), IF(sort=0,500,sort) ) )} -> 52 | I33: {=_xlfn.XLOOKUP( B33, tblTargetStatus[TargetID], tblTargetStatus[Status], "" )} -> BLOCKED | J33: FALSE
A34: cost.building.alchemists_hut@4.gunpowder.1 | B34: =IFERROR(__xludf.DUMMYFUNCTION("REGEXREPLACE( REGEXREPLACE(A34,""^cost\."",""""), ""\.[^.]+\.[^.]+$"", """" )"),"building.alchemists_hut@4") -> building.alchemists_hut@4 | C34: {=_xlfn.XLOOKUP( B34, tblTargets[TargetID], tblTargets[DisplayName], "" )} -> Alchemist's Hut Lv 4 | D34: {=_xlfn.XLOOKUP( B34, tblTargets[TargetID], tblTargets[TargetType], "" )} -> BUILDING | E34: gunpowder | F34: 1 | G34: {=_xlfn.XLOOKUP( A34, tblCost[RequirementID], tblCost[QuantityRequired], "" )} -> 40 | H34: {=IF( OR( LEFT(B34,15)="state.character", RIGHT(B34,6)=".maxed" ), 0, LET( sort, _xlfn.XLOOKUP( B34, tblChecklist[TargetID], tblChecklist[PlayerSort], 0 ), IF(sort=0,500,sort) ) )} -> 52 | I34: {=_xlfn.XLOOKUP( B34, tblTargetStatus[TargetID], tblTargetStatus[Status], "" )} -> BLOCKED | J34: FALSE
A35: cost.building.alchemists_hut@4.ruby.1 | B35: =IFERROR(__xludf.DUMMYFUNCTION("REGEXREPLACE( REGEXREPLACE(A35,""^cost\."",""""), ""\.[^.]+\.[^.]+$"", """" )"),"building.alchemists_hut@4") -> building.alchemists_hut@4 | C35: {=_xlfn.XLOOKUP( B35, tblTargets[TargetID], tblTargets[DisplayName], "" )} -> Alchemist's Hut Lv 4 | D35: {=_xlfn.XLOOKUP( B35, tblTargets[TargetID], tblTargets[TargetType], "" )} -> BUILDING | E35: ruby | F35: 1 | G35: {=_xlfn.XLOOKUP( A35, tblCost[RequirementID], tblCost[QuantityRequired], "" )} -> 4 | H35: {=IF( OR( LEFT(B35,15)="state.character", RIGHT(B35,6)=".maxed" ), 0, LET( sort, _xlfn.XLOOKUP( B35, tblChecklist[TargetID], tblChecklist[PlayerSort], 0 ), IF(sort=0,500,sort) ) )} -> 52 | I35: {=_xlfn.XLOOKUP( B35, tblTargetStatus[TargetID], tblTargetStatus[Status], "" )} -> BLOCKED | J35: FALSE
A36: cost.building.alchemists_hut@4.stone.1 | B36: =IFERROR(__xludf.DUMMYFUNCTION("REGEXREPLACE( REGEXREPLACE(A36,""^cost\."",""""), ""\.[^.]+\.[^.]+$"", """" )"),"building.alchemists_hut@4") -> building.alchemists_hut@4 | C36: {=_xlfn.XLOOKUP( B36, tblTargets[TargetID], tblTargets[DisplayName], "" )} -> Alchemist's Hut Lv 4 | D36: {=_xlfn.XLOOKUP( B36, tblTargets[TargetID], tblTargets[TargetType], "" )} -> BUILDING | E36: stone | F36: 1 | G36: {=_xlfn.XLOOKUP( A36, tblCost[RequirementID], tblCost[QuantityRequired], "" )} -> 200 | H36: {=IF( OR( LEFT(B36,15)="state.character", RIGHT(B36,6)=".maxed" ), 0, LET( sort, _xlfn.XLOOKUP( B36, tblChecklist[TargetID], tblChecklist[PlayerSort], 0 ), IF(sort=0,500,sort) ) )} -> 52 | I36: {=_xlfn.XLOOKUP( B36, tblTargetStatus[TargetID], tblTargetStatus[Status], "" )} -> BLOCKED | J36: FALSE
A37: cost.building.alchemists_hut@5.beam.1 | B37: =IFERROR(__xludf.DUMMYFUNCTION("REGEXREPLACE( REGEXREPLACE(A37,""^cost\."",""""), ""\.[^.]+\.[^.]+$"", """" )"),"building.alchemists_hut@5") -> building.alchemists_hut@5 | C37: {=_xlfn.XLOOKUP( B37, tblTargets[TargetID], tblTargets[DisplayName], "" )} -> Alchemist's Hut Lv 5 | D37: {=_xlfn.XLOOKUP( B37, tblTargets[TargetID], tblTargets[TargetType], "" )} -> BUILDING | E37: beam | F37: 1 | G37: {=_xlfn.XLOOKUP( A37, tblCost[RequirementID], tblCost[QuantityRequired], "" )} -> 440 | H37: {=IF( OR( LEFT(B37,15)="state.character", RIGHT(B37,6)=".maxed" ), 0, LET( sort, _xlfn.XLOOKUP( B37, tblChecklist[TargetID], tblChecklist[PlayerSort], 0 ), IF(sort=0,500,sort) ) )} -> 53 | I37: {=_xlfn.XLOOKUP( B37, tblTargetStatus[TargetID], tblTargetStatus[Status], "" )} -> BLOCKED | J37: FALSE
A38: cost.building.alchemists_hut@5.coin.1 | B38: =IFERROR(__xludf.DUMMYFUNCTION("REGEXREPLACE( REGEXREPLACE(A38,""^cost\."",""""), ""\.[^.]+\.[^.]+$"", """" )"),"building.alchemists_hut@5") -> building.alchemists_hut@5 | C38: {=_xlfn.XLOOKUP( B38, tblTargets[TargetID], tblTargets[DisplayName], "" )} -> Alchemist's Hut Lv 5 | D38: {=_xlfn.XLOOKUP( B38, tblTargets[TargetID], tblTargets[TargetType], "" )} -> BUILDING | E38: coin | F38: 1 | G38: {=_xlfn.XLOOKUP( A38, tblCost[RequirementID], tblCost[QuantityRequired], "" )} -> 500 | H38: {=IF( OR( LEFT(B38,15)="state.character", RIGHT(B38,6)=".maxed" ), 0, LET( sort, _xlfn.XLOOKUP( B38, tblChecklist[TargetID], tblChecklist[PlayerSort], 0 ), IF(sort=0,500,sort) ) )} -> 53 | I38: {=_xlfn.XLOOKUP( B38, tblTargetStatus[TargetID], tblTargetStatus[Status], "" )} -> BLOCKED | J38: FALSE
A39: cost.building.alchemists_hut@5.gunpowder.1 | B39: =IFERROR(__xludf.DUMMYFUNCTION("REGEXREPLACE( REGEXREPLACE(A39,""^cost\."",""""), ""\.[^.]+\.[^.]+$"", """" )"),"building.alchemists_hut@5") -> building.alchemists_hut@5 | C39: {=_xlfn.XLOOKUP( B39, tblTargets[TargetID], tblTargets[DisplayName], "" )} -> Alchemist's Hut Lv 5 | D39: {=_xlfn.XLOOKUP( B39, tblTargets[TargetID], tblTargets[TargetType], "" )} -> BUILDING | E39: gunpowder | F39: 1 | G39: {=_xlfn.XLOOKUP( A39, tblCost[RequirementID], tblCost[QuantityRequired], "" )} -> 80 | H39: {=IF( OR( LEFT(B39,15)="state.character", RIGHT(B39,6)=".maxed" ), 0, LET( sort, _xlfn.XLOOKUP( B39, tblChecklist[TargetID], tblChecklist[PlayerSort], 0 ), IF(sort=0,500,sort) ) )} -> 53 | I39: {=_xlfn.XLOOKUP( B39, tblTargetStatus[TargetID], tblTargetStatus[Status], "" )} -> BLOCKED | J39: FALSE
A40: cost.building.alchemists_hut@5.ruby.1 | B40: =IFERROR(__xludf.DUMMYFUNCTION("REGEXREPLACE( REGEXREPLACE(A40,""^cost\."",""""), ""\.[^.]+\.[^.]+$"", """" )"),"building.alchemists_hut@5") -> building.alchemists_hut@5 | C40: {=_xlfn.XLOOKUP( B40, tblTargets[TargetID], tblTargets[DisplayName], "" )} -> Alchemist's Hut Lv 5 | D40: {=_xlfn.XLOOKUP( B40, tblTargets[TargetID], tblTargets[TargetType], "" )} -> BUILDING | E40: ruby | F40: 1 | G40: {=_xlfn.XLOOKUP( A40, tblCost[RequirementID], tblCost[QuantityRequired], "" )} -> 5 | H40: {=IF( OR( LEFT(B40,15)="state.character", RIGHT(B40,6)=".maxed" ), 0, LET( sort, _xlfn.XLOOKUP( B40, tblChecklist[TargetID], tblChecklist[PlayerSort], 0 ), IF(sort=0,500,sort) ) )} -> 53 | I40: {=_xlfn.XLOOKUP( B40, tblTargetStatus[TargetID], tblTargetStatus[Status], "" )} -> BLOCKED | J40: FALSE
A41: cost.building.alchemists_hut@5.stone.1 | B41: =IFERROR(__xludf.DUMMYFUNCTION("REGEXREPLACE( REGEXREPLACE(A41,""^cost\."",""""), ""\.[^.]+\.[^.]+$"", """" )"),"building.alchemists_hut@5") -> building.alchemists_hut@5 | C41: {=_xlfn.XLOOKUP( B41, tblTargets[TargetID], tblTargets[DisplayName], "" )} -> Alchemist's Hut Lv 5 | D41: {=_xlfn.XLOOKUP( B41, tblTargets[TargetID], tblTargets[TargetType], "" )} -> BUILDING | E41: stone | F41: 1 | G41: {=_xlfn.XLOOKUP( A41, tblCost[RequirementID], tblCost[QuantityRequired], "" )} -> 220 | H41: {=IF( OR( LEFT(B41,15)="state.character", RIGHT(B41,6)=".maxed" ), 0, LET( sort, _xlfn.XLOOKUP( B41, tblChecklist[TargetID], tblChecklist[PlayerSort], 0 ), IF(sort=0,500,sort) ) )} -> 53 | I41: {=_xlfn.XLOOKUP( B41, tblTargetStatus[TargetID], tblTargetStatus[Status], "" )} -> BLOCKED | J41: FALSE
A42: cost.building.alchemists_hut@6.beam.1 | B42: =IFERROR(__xludf.DUMMYFUNCTION("REGEXREPLACE( REGEXREPLACE(A42,""^cost\."",""""), ""\.[^.]+\.[^.]+$"", """" )"),"building.alchemists_hut@6") -> building.alchemists_hut@6 | C42: {=_xlfn.XLOOKUP( B42, tblTargets[TargetID], tblTargets[DisplayName], "" )} -> Alchemist's Hut Lv 6 | D42: {=_xlfn.XLOOKUP( B42, tblTargets[TargetID], tblTargets[TargetType], "" )} -> BUILDING | E42: beam | F42: 1 | G42: {=_xlfn.XLOOKUP( A42, tblCost[RequirementID], tblCost[QuantityRequired], "" )} -> 800 | H42: {=IF( OR( LEFT(B42,15)="state.character", RIGHT(B42,6)=".maxed" ), 0, LET( sort, _xlfn.XLOOKUP( B42, tblChecklist[TargetID], tblChecklist[PlayerSort], 0 ), IF(sort=0,500,sort) ) )} -> 54 | I42: {=_xlfn.XLOOKUP( B42, tblTargetStatus[TargetID], tblTargetStatus[Status], "" )} -> BLOCKED | J42: FALSE
A43: cost.building.alchemists_hut@6.chemicals.1 | B43: =IFERROR(__xludf.DUMMYFUNCTION("REGEXREPLACE( REGEXREPLACE(A43,""^cost\."",""""), ""\.[^.]+\.[^.]+$"", """" )"),"building.alchemists_hut@6") -> building.alchemists_hut@6 | C43: {=_xlfn.XLOOKUP( B43, tblTargets[TargetID], tblTargets[DisplayName], "" )} -> Alchemist's Hut Lv 6 | D43: {=_xlfn.XLOOKUP( B43, tblTargets[TargetID], tblTargets[TargetType], "" )} -> BUILDING | E43: chemicals | F43: 1 | G43: {=_xlfn.XLOOKUP( A43, tblCost[RequirementID], tblCost[QuantityRequired], "" )} -> 200 | H43: {=IF( OR( LEFT(B43,15)="state.character", RIGHT(B43,6)=".maxed" ), 0, LET( sort, _xlfn.XLOOKUP( B43, tblChecklist[TargetID], tblChecklist[PlayerSort], 0 ), IF(sort=0,500,sort) ) )} -> 54 | I43: {=_xlfn.XLOOKUP( B43, tblTargetStatus[TargetID], tblTargetStatus[Status], "" )} -> BLOCKED | J43: FALSE
A44: cost.building.alchemists_hut@6.coin.1 | B44: =IFERROR(__xludf.DUMMYFUNCTION("REGEXREPLACE( REGEXREPLACE(A44,""^cost\."",""""), ""\.[^.]+\.[^.]+$"", """" )"),"building.alchemists_hut@6") -> building.alchemists_hut@6 | C44: {=_xlfn.XLOOKUP( B44, tblTargets[TargetID], tblTargets[DisplayName], "" )} -> Alchemist's Hut Lv 6 | D44: {=_xlfn.XLOOKUP( B44, tblTargets[TargetID], tblTargets[TargetType], "" )} -> BUILDING | E44: coin | F44: 1 | G44: {=_xlfn.XLOOKUP( A44, tblCost[RequirementID], tblCost[QuantityRequired], "" )} -> 1000 | H44: {=IF( OR( LEFT(B44,15)="state.character", RIGHT(B44,6)=".maxed" ), 0, LET( sort, _xlfn.XLOOKUP( B44, tblChecklist[TargetID], tblChecklist[PlayerSort], 0 ), IF(sort=0,500,sort) ) )} -> 54 | I44: {=_xlfn.XLOOKUP( B44, tblTargetStatus[TargetID], tblTargetStatus[Status], "" )} -> BLOCKED | J44: FALSE
A45: cost.building.alchemists_hut@6.glass.1 | B45: =IFERROR(__xludf.DUMMYFUNCTION("REGEXREPLACE( REGEXREPLACE(A45,""^cost\."",""""), ""\.[^.]+\.[^.]+$"", """" )"),"building.alchemists_hut@6") -> building.alchemists_hut@6 | C45: {=_xlfn.XLOOKUP( B45, tblTargets[TargetID], tblTargets[DisplayName], "" )} -> Alchemist's Hut Lv 6 | D45: {=_xlfn.XLOOKUP( B45, tblTargets[TargetID], tblTargets[TargetType], "" )} -> BUILDING | E45: glass | F45: 1 | G45: {=_xlfn.XLOOKUP( A45, tblCost[RequirementID], tblCost[QuantityRequired], "" )} -> 50 | H45: {=IF( OR( LEFT(B45,15)="state.character", RIGHT(B45,6)=".maxed" ), 0, LET( sort, _xlfn.XLOOKUP( B45, tblChecklist[TargetID], tblChecklist[PlayerSort], 0 ), IF(sort=0,500,sort) ) )} -> 54 | I45: {=_xlfn.XLOOKUP( B45, tblTargetStatus[TargetID], tblTargetStatus[Status], "" )} -> BLOCKED | J45: FALSE
A46: cost.building.alchemists_hut@6.ruby.1 | B46: =IFERROR(__xludf.DUMMYFUNCTION("REGEXREPLACE( REGEXREPLACE(A46,""^cost\."",""""), ""\.[^.]+\.[^.]+$"", """" )"),"building.alchemists_hut@6") -> building.alchemists_hut@6 | C46: {=_xlfn.XLOOKUP( B46, tblTargets[TargetID], tblTargets[DisplayName], "" )} -> Alchemist's Hut Lv 6 | D46: {=_xlfn.XLOOKUP( B46, tblTargets[TargetID], tblTargets[TargetType], "" )} -> BUILDING | E46: ruby | F46: 1 | G46: {=_xlfn.XLOOKUP( A46, tblCost[RequirementID], tblCost[QuantityRequired], "" )} -> 6 | H46: {=IF( OR( LEFT(B46,15)="state.character", RIGHT(B46,6)=".maxed" ), 0, LET( sort, _xlfn.XLOOKUP( B46, tblChecklist[TargetID], tblChecklist[PlayerSort], 0 ), IF(sort=0,500,sort) ) )} -> 54 | I46: {=_xlfn.XLOOKUP( B46, tblTargetStatus[TargetID], tblTargetStatus[Status], "" )} -> BLOCKED | J46: FALSE
A47: cost.building.alchemists_hut@6.stone.1 | B47: =IFERROR(__xludf.DUMMYFUNCTION("REGEXREPLACE( REGEXREPLACE(A47,""^cost\."",""""), ""\.[^.]+\.[^.]+$"", """" )"),"building.alchemists_hut@6") -> building.alchemists_hut@6 | C47: {=_xlfn.XLOOKUP( B47, tblTargets[TargetID], tblTargets[DisplayName], "" )} -> Alchemist's Hut Lv 6 | D47: {=_xlfn.XLOOKUP( B47, tblTargets[TargetID], tblTargets[TargetType], "" )} -> BUILDING | E47: stone | F47: 1 | G47: {=_xlfn.XLOOKUP( A47, tblCost[RequirementID], tblCost[QuantityRequired], "" )} -> 400 | H47: {=IF( OR( LEFT(B47,15)="state.character", RIGHT(B47,6)=".maxed" ), 0, LET( sort, _xlfn.XLOOKUP( B47, tblChecklist[TargetID], tblChecklist[PlayerSort], 0 ), IF(sort=0,500,sort) ) )} -> 54 | I47: {=_xlfn.XLOOKUP( B47, tblTargetStatus[TargetID], tblTargetStatus[Status], "" )} -> BLOCKED | J47: FALSE
A48: cost.building.bonsai@1.beans.1 | B48: =IFERROR(__xludf.DUMMYFUNCTION("REGEXREPLACE( REGEXREPLACE(A48,""^cost\."",""""), ""\.[^.]+\.[^.]+$"", """" )"),"building.bonsai@1") -> building.bonsai@1 | C48: {=_xlfn.XLOOKUP( B48, tblTargets[TargetID], tblTargets[DisplayName], "" )} -> Bonsai Lv 1 | D48: {=_xlfn.XLOOKUP( B48, tblTargets[TargetID], tblTargets[TargetType], "" )} -> BUILDING | E48: beans | F48: 1 | G48: {=_xlfn.XLOOKUP( A48, tblCost[RequirementID], tblCost[QuantityRequired], "" )} -> 120 | H48: {=IF( OR( LEFT(B48,15)="state.character", RIGHT(B48,6)=".maxed" ), 0, LET( sort, _xlfn.XLOOKUP( B48, tblChecklist[TargetID], tblChecklist[PlayerSort], 0 ), IF(sort=0,500,sort) ) )} -> 89 | I48: {=_xlfn.XLOOKUP( B48, tblTargetStatus[TargetID], tblTargetStatus[Status], "" )} -> BLOCKED | J48: FALSE
A49: cost.building.bonsai@1.coin.1 | B49: =IFERROR(__xludf.DUMMYFUNCTION("REGEXREPLACE( REGEXREPLACE(A49,""^cost\."",""""), ""\.[^.]+\.[^.]+$"", """" )"),"building.bonsai@1") -> building.bonsai@1 | C49: {=_xlfn.XLOOKUP( B49, tblTargets[TargetID], tblTargets[DisplayName], "" )} -> Bonsai Lv 1 | D49: {=_xlfn.XLOOKUP( B49, tblTargets[TargetID], tblTargets[TargetType], "" )} -> BUILDING | E49: coin | F49: 1 | G49: {=_xlfn.XLOOKUP( A49, tblCost[RequirementID], tblCost[QuantityRequired], "" )} -> 500 | H49: {=IF( OR( LEFT(B49,15)="state.character", RIGHT(B49,6)=".maxed" ), 0, LET( sort, _xlfn.XLOOKUP( B49, tblChecklist[TargetID], tblChecklist[PlayerSort], 0 ), IF(sort=0,500,sort) ) )} -> 89 | I49: {=_xlfn.XLOOKUP( B49, tblTargetStatus[TargetID], tblTargetStatus[Status], "" )} -> BLOCKED | J49: FALSE
A50: cost.building.bonsai@1.plank.1 | B50: =IFERROR(__xludf.DUMMYFUNCTION("REGEXREPLACE( REGEXREPLACE(A50,""^cost\."",""""), ""\.[^.]+\.[^.]+$"", """" )"),"building.bonsai@1") -> building.bonsai@1 | C50: {=_xlfn.XLOOKUP( B50, tblTargets[TargetID], tblTargets[DisplayName], "" )} -> Bonsai Lv 1 | D50: {=_xlfn.XLOOKUP( B50, tblTargets[TargetID], tblTargets[TargetType], "" )} -> BUILDING | E50: plank | F50: 1 | G50: {=_xlfn.XLOOKUP( A50, tblCost[RequirementID], tblCost[QuantityRequired], "" )} -> 500 | H50: {=IF( OR( LEFT(B50,15)="state.character", RIGHT(B50,6)=".maxed" ), 0, LET( sort, _xlfn.XLOOKUP( B50, tblChecklist[TargetID], tblChecklist[PlayerSort], 0 ), IF(sort=0,500,sort) ) )} -> 89 | I50: {=_xlfn.XLOOKUP( B50, tblTargetStatus[TargetID], tblTargetStatus[Status], "" )} -> BLOCKED | J50: FALSE
A51: cost.building.bonsai@1.ruby.1 | B51: =IFERROR(__xludf.DUMMYFUNCTION("REGEXREPLACE( REGEXREPLACE(A51,""^cost\."",""""), ""\.[^.]+\.[^.]+$"", """" )"),"building.bonsai@1") -> building.bonsai@1 | C51: {=_xlfn.XLOOKUP( B51, tblTargets[TargetID], tblTargets[DisplayName], "" )} -> Bonsai Lv 1 | D51: {=_xlfn.XLOOKUP( B51, tblTargets[TargetID], tblTargets[TargetType], "" )} -> BUILDING | E51: ruby | F51: 1 | G51: {=_xlfn.XLOOKUP( A51, tblCost[RequirementID], tblCost[QuantityRequired], "" )} -> 3 | H51: {=IF( OR( LEFT(B51,15)="state.character", RIGHT(B51,6)=".maxed" ), 0, LET( sort, _xlfn.XLOOKUP( B51, tblChecklist[TargetID], tblChecklist[PlayerSort], 0 ), IF(sort=0,500,sort) ) )} -> 89 | I51: {=_xlfn.XLOOKUP( B51, tblTargetStatus[TargetID], tblTargetStatus[Status], "" )} -> BLOCKED | J51: FALSE
A52: cost.building.bonsai@2.beans.1 | B52: =IFERROR(__xludf.DUMMYFUNCTION("REGEXREPLACE( REGEXREPLACE(A52,""^cost\."",""""), ""\.[^.]+\.[^.]+$"", """" )"),"building.bonsai@2") -> building.bonsai@2 | C52: {=_xlfn.XLOOKUP( B52, tblTargets[TargetID], tblTargets[DisplayName], "" )} -> Bonsai Lv 2 | D52: {=_xlfn.XLOOKUP( B52, tblTargets[TargetID], tblTargets[TargetType], "" )} -> BUILDING | E52: beans | F52: 1 | G52: {=_xlfn.XLOOKUP( A52, tblCost[RequirementID], tblCost[QuantityRequired], "" )} -> 240 | H52: {=IF( OR( LEFT(B52,15)="state.character", RIGHT(B52,6)=".maxed" ), 0, LET( sort, _xlfn.XLOOKUP( B52, tblChecklist[TargetID], tblChecklist[PlayerSort], 0 ), IF(sort=0,500,sort) ) )} -> 90 | I52: {=_xlfn.XLOOKUP( B52, tblTargetStatus[TargetID], tblTargetStatus[Status], "" )} -> BLOCKED | J52: FALSE
A53: cost.building.bonsai@2.chemicals.1 | B53: =IFERROR(__xludf.DUMMYFUNCTION("REGEXREPLACE( REGEXREPLACE(A53,""^cost\."",""""), ""\.[^.]+\.[^.]+$"", """" )"),"building.bonsai@2") -> building.bonsai@2 | C53: {=_xlfn.XLOOKUP( B53, tblTargets[TargetID], tblTargets[DisplayName], "" )} -> Bonsai Lv 2 | D53: {=_xlfn.XLOOKUP( B53, tblTargets[TargetID], tblTargets[TargetType], "" )} -> BUILDING | E53: chemicals | F53: 1 | G53: {=_xlfn.XLOOKUP( A53, tblCost[RequirementID], tblCost[QuantityRequired], "" )} -> 150 | H53: {=IF( OR( LEFT(B53,15)="state.character", RIGHT(B53,6)=".maxed" ), 0, LET( sort, _xlfn.XLOOKUP( B53, tblChecklist[TargetID], tblChecklist[PlayerSort], 0 ), IF(sort=0,500,sort) ) )} -> 90 | I53: {=_xlfn.XLOOKUP( B53, tblTargetStatus[TargetID], tblTargetStatus[Status], "" )} -> BLOCKED | J53: FALSE
A54: cost.building.bonsai@2.coin.1 | B54: =IFERROR(__xludf.DUMMYFUNCTION("REGEXREPLACE( REGEXREPLACE(A54,""^cost\."",""""), ""\.[^.]+\.[^.]+$"", """" )"),"building.bonsai@2") -> building.bonsai@2 | C54: {=_xlfn.XLOOKUP( B54, tblTargets[TargetID], tblTargets[DisplayName], "" )} -> Bonsai Lv 2 | D54: {=_xlfn.XLOOKUP( B54, tblTargets[TargetID], tblTargets[TargetType], "" )} -> BUILDING | E54: coin | F54: 1 | G54: {=_xlfn.XLOOKUP( A54, tblCost[RequirementID], tblCost[QuantityRequired], "" )} -> 800 | H54: {=IF( OR( LEFT(B54,15)="state.character", RIGHT(B54,6)=".maxed" ), 0, LET( sort, _xlfn.XLOOKUP( B54, tblChecklist[TargetID], tblChecklist[PlayerSort], 0 ), IF(sort=0,500,sort) ) )} -> 90 | I54: {=_xlfn.XLOOKUP( B54, tblTargetStatus[TargetID], tblTargetStatus[Status], "" )} -> BLOCKED | J54: FALSE
A55: cost.building.bonsai@2.plank.1 | B55: =IFERROR(__xludf.DUMMYFUNCTION("REGEXREPLACE( REGEXREPLACE(A55,""^cost\."",""""), ""\.[^.]+\.[^.]+$"", """" )"),"building.bonsai@2") -> building.bonsai@2 | C55: {=_xlfn.XLOOKUP( B55, tblTargets[TargetID], tblTargets[DisplayName], "" )} -> Bonsai Lv 2 | D55: {=_xlfn.XLOOKUP( B55, tblTargets[TargetID], tblTargets[TargetType], "" )} -> BUILDING | E55: plank | F55: 1 | G55: {=_xlfn.XLOOKUP( A55, tblCost[RequirementID], tblCost[QuantityRequired], "" )} -> 600 | H55: {=IF( OR( LEFT(B55,15)="state.character", RIGHT(B55,6)=".maxed" ), 0, LET( sort, _xlfn.XLOOKUP( B55, tblChecklist[TargetID], tblChecklist[PlayerSort], 0 ), IF(sort=0,500,sort) ) )} -> 90 | I55: {=_xlfn.XLOOKUP( B55, tblTargetStatus[TargetID], tblTargetStatus[Status], "" )} -> BLOCKED | J55: FALSE
A56: cost.building.bonsai@2.ruby.1 | B56: =IFERROR(__xludf.DUMMYFUNCTION("REGEXREPLACE( REGEXREPLACE(A56,""^cost\."",""""), ""\.[^.]+\.[^.]+$"", """" )"),"building.bonsai@2") -> building.bonsai@2 | C56: {=_xlfn.XLOOKUP( B56, tblTargets[TargetID], tblTargets[DisplayName], "" )} -> Bonsai Lv 2 | D56: {=_xlfn.XLOOKUP( B56, tblTargets[TargetID], tblTargets[TargetType], "" )} -> BUILDING | E56: ruby | F56: 1 | G56: {=_xlfn.XLOOKUP( A56, tblCost[RequirementID], tblCost[QuantityRequired], "" )} -> 5 | H56: {=IF( OR( LEFT(B56,15)="state.character", RIGHT(B56,6)=".maxed" ), 0, LET( sort, _xlfn.XLOOKUP( B56, tblChecklist[TargetID], tblChecklist[PlayerSort], 0 ), IF(sort=0,500,sort) ) )} -> 90 | I56: {=_xlfn.XLOOKUP( B56, tblTargetStatus[TargetID], tblTargetStatus[Status], "" )} -> BLOCKED | J56: FALSE
A57: cost.building.bridge@1.beam.1 | B57: =IFERROR(__xludf.DUMMYFUNCTION("REGEXREPLACE( REGEXREPLACE(A57,""^cost\."",""""), ""\.[^.]+\.[^.]+$"", """" )"),"building.bridge@1") -> building.bridge@1 | C57: {=_xlfn.XLOOKUP( B57, tblTargets[TargetID], tblTargets[DisplayName], "" )} -> Bridge Lv 1 | D57: {=_xlfn.XLOOKUP( B57, tblTargets[TargetID], tblTargets[TargetType], "" )} -> BUILDING | E57: beam | F57: 1 | G57: {=_xlfn.XLOOKUP( A57, tblCost[RequirementID], tblCost[QuantityRequired], "" )} -> 400 | H57: {=IF( OR( LEFT(B57,15)="state.character", RIGHT(B57,6)=".maxed" ), 0, LET( sort, _xlfn.XLOOKUP( B57, tblChecklist[TargetID], tblChecklist[PlayerSort], 0 ), IF(sort=0,500,sort) ) )} -> 27 | I57: {=_xlfn.XLOOKUP( B57, tblTargetStatus[TargetID], tblTargetStatus[Status], "" )} -> BLOCKED | J57: FALSE
A58: cost.building.bridge@1.coin.1 | B58: =IFERROR(__xludf.DUMMYFUNCTION("REGEXREPLACE( REGEXREPLACE(A58,""^cost\."",""""), ""\.[^.]+\.[^.]+$"", """" )"),"building.bridge@1") -> building.bridge@1 | C58: {=_xlfn.XLOOKUP( B58, tblTargets[TargetID], tblTargets[DisplayName], "" )} -> Bridge Lv 1 | D58: {=_xlfn.XLOOKUP( B58, tblTargets[TargetID], tblTargets[TargetType], "" )} -> BUILDING | E58: coin | F58: 1 | G58: {=_xlfn.XLOOKUP( A58, tblCost[RequirementID], tblCost[QuantityRequired], "" )} -> 1000 | H58: {=IF( OR( LEFT(B58,15)="state.character", RIGHT(B58,6)=".maxed" ), 0, LET( sort, _xlfn.XLOOKUP( B58, tblChecklist[TargetID], tblChecklist[PlayerSort], 0 ), IF(sort=0,500,sort) ) )} -> 27 | I58: {=_xlfn.XLOOKUP( B58, tblTargetStatus[TargetID], tblTargetStatus[Status], "" )} -> BLOCKED | J58: FALSE
A59: cost.building.bridge@1.plank.1 | B59: =IFERROR(__xludf.DUMMYFUNCTION("REGEXREPLACE( REGEXREPLACE(A59,""^cost\."",""""), ""\.[^.]+\.[^.]+$"", """" )"),"building.bridge@1") -> building.bridge@1 | C59: {=_xlfn.XLOOKUP( B59, tblTargets[TargetID], tblTargets[DisplayName], "" )} -> Bridge Lv 1 | D59: {=_xlfn.XLOOKUP( B59, tblTargets[TargetID], tblTargets[TargetType], "" )} -> BUILDING | E59: plank | F59: 1 | G59: {=_xlfn.XLOOKUP( A59, tblCost[RequirementID], tblCost[QuantityRequired], "" )} -> 1000 | H59: {=IF( OR( LEFT(B59,15)="state.character", RIGHT(B59,6)=".maxed" ), 0, LET( sort, _xlfn.XLOOKUP( B59, tblChecklist[TargetID], tblChecklist[PlayerSort], 0 ), IF(sort=0,500,sort) ) )} -> 27 | I59: {=_xlfn.XLOOKUP( B59, tblTargetStatus[TargetID], tblTargetStatus[Status], "" )} -> BLOCKED | J59: FALSE
A60: cost.building.bridge@1.ruby.1 | B60: =IFERROR(__xludf.DUMMYFUNCTION("REGEXREPLACE( REGEXREPLACE(A60,""^cost\."",""""), ""\.[^.]+\.[^.]+$"", """" )"),"building.bridge@1") -> building.bridge@1 | C60: {=_xlfn.XLOOKUP( B60, tblTargets[TargetID], tblTargets[DisplayName], "" )} -> Bridge Lv 1 | D60: {=_xlfn.XLOOKUP( B60, tblTargets[TargetID], tblTargets[TargetType], "" )} -> BUILDING | E60: ruby | F60: 1 | G60: {=_xlfn.XLOOKUP( A60, tblCost[RequirementID], tblCost[QuantityRequired], "" )} -> 4 | H60: {=IF( OR( LEFT(B60,15)="state.character", RIGHT(B60,6)=".maxed" ), 0, LET( sort, _xlfn.XLOOKUP( B60, tblChecklist[TargetID], tblChecklist[PlayerSort], 0 ), IF(sort=0,500,sort) ) )} -> 27 | I60: {=_xlfn.XLOOKUP( B60, tblTargetStatus[TargetID], tblTargetStatus[Status], "" )} -> BLOCKED | J60: FALSE
A61: cost.building.bridge@1.steel.1 | B61: =IFERROR(__xludf.DUMMYFUNCTION("REGEXREPLACE( REGEXREPLACE(A61,""^cost\."",""""), ""\.[^.]+\.[^.]+$"", """" )"),"building.bridge@1") -> building.bridge@1 | C61: {=_xlfn.XLOOKUP( B61, tblTargets[TargetID], tblTargets[DisplayName], "" )} -> Bridge Lv 1 | D61: {=_xlfn.XLOOKUP( B61, tblTargets[TargetID], tblTargets[TargetType], "" )} -> BUILDING | E61: steel | F61: 1 | G61: {=_xlfn.XLOOKUP( A61, tblCost[RequirementID], tblCost[QuantityRequired], "" )} -> 100 | H61: {=IF( OR( LEFT(B61,15)="state.character", RIGHT(B61,6)=".maxed" ), 0, LET( sort, _xlfn.XLOOKUP( B61, tblChecklist[TargetID], tblChecklist[PlayerSort], 0 ), IF(sort=0,500,sort) ) )} -> 27 | I61: {=_xlfn.XLOOKUP( B61, tblTargetStatus[TargetID], tblTargetStatus[Status], "" )} -> BLOCKED | J61: FALSE
A62: cost.building.bridge@1.stone.1 | B62: =IFERROR(__xludf.DUMMYFUNCTION("REGEXREPLACE( REGEXREPLACE(A62,""^cost\."",""""), ""\.[^.]+\.[^.]+$"", """" )"),"building.bridge@1") -> building.bridge@1 | C62: {=_xlfn.XLOOKUP( B62, tblTargets[TargetID], tblTargets[DisplayName], "" )} -> Bridge Lv 1 | D62: {=_xlfn.XLOOKUP( B62, tblTargets[TargetID], tblTargets[TargetType], "" )} -> BUILDING | E62: stone | F62: 1 | G62: {=_xlfn.XLOOKUP( A62, tblCost[RequirementID], tblCost[QuantityRequired], "" )} -> 400 | H62: {=IF( OR( LEFT(B62,15)="state.character", RIGHT(B62,6)=".maxed" ), 0, LET( sort, _xlfn.XLOOKUP( B62, tblChecklist[TargetID], tblChecklist[PlayerSort], 0 ), IF(sort=0,500,sort) ) )} -> 27 | I62: {=_xlfn.XLOOKUP( B62, tblTargetStatus[TargetID], tblTargetStatus[Status], "" )} -> BLOCKED | J62: FALSE
A63: cost.building.caravan@1.beans.1 | B63: =IFERROR(__xludf.DUMMYFUNCTION("REGEXREPLACE( REGEXREPLACE(A63,""^cost\."",""""), ""\.[^.]+\.[^.]+$"", """" )"),"building.caravan@1") -> building.caravan@1 | C63: {=_xlfn.XLOOKUP( B63, tblTargets[TargetID], tblTargets[DisplayName], "" )} -> Caravan Lv 1 | D63: {=_xlfn.XLOOKUP( B63, tblTargets[TargetID], tblTargets[TargetType], "" )} -> BUILDING | E63: beans | F63: 1 | G63: {=_xlfn.XLOOKUP( A63, tblCost[RequirementID], tblCost[QuantityRequired], "" )} -> 50 | H63: {=IF( OR( LEFT(B63,15)="state.character", RIGHT(B63,6)=".maxed" ), 0, LET( sort, _xlfn.XLOOKUP( B63, tblChecklist[TargetID], tblChecklist[PlayerSort], 0 ), IF(sort=0,500,sort) ) )} -> 36 | I63: {=_xlfn.XLOOKUP( B63, tblTargetStatus[TargetID], tblTargetStatus[Status], "" )} -> BLOCKED | J63: FALSE
A64: cost.building.caravan@1.coin.1 | B64: =IFERROR(__xludf.DUMMYFUNCTION("REGEXREPLACE( REGEXREPLACE(A64,""^cost\."",""""), ""\.[^.]+\.[^.]+$"", """" )"),"building.caravan@1") -> building.caravan@1 | C64: {=_xlfn.XLOOKUP( B64, tblTargets[TargetID], tblTargets[DisplayName], "" )} -> Caravan Lv 1 | D64: {=_xlfn.XLOOKUP( B64, tblTargets[TargetID], tblTargets[TargetType], "" )} -> BUILDING | E64: coin | F64: 1 | G64: {=_xlfn.XLOOKUP( A64, tblCost[RequirementID], tblCost[QuantityRequired], "" )} -> 1000 | H64: {=IF( OR( LEFT(B64,15)="state.character", RIGHT(B64,6)=".maxed" ), 0, LET( sort, _xlfn.XLOOKUP( B64, tblChecklist[TargetID], tblChecklist[PlayerSort], 0 ), IF(sort=0,500,sort) ) )} -> 36 | I64: {=_xlfn.XLOOKUP( B64, tblTargetStatus[TargetID], tblTargetStatus[Status], "" )} -> BLOCKED | J64: FALSE
A65: cost.building.caravan@1.plank.1 | B65: =IFERROR(__xludf.DUMMYFUNCTION("REGEXREPLACE( REGEXREPLACE(A65,""^cost\."",""""), ""\.[^.]+\.[^.]+$"", """" )"),"building.caravan@1") -> building.caravan@1 | C65: {=_xlfn.XLOOKUP( B65, tblTargets[TargetID], tblTargets[DisplayName], "" )} -> Caravan Lv 1 | D65: {=_xlfn.XLOOKUP( B65, tblTargets[TargetID], tblTargets[TargetType], "" )} -> BUILDING | E65: plank | F65: 1 | G65: {=_xlfn.XLOOKUP( A65, tblCost[RequirementID], tblCost[QuantityRequired], "" )} -> 400 | H65: {=IF( OR( LEFT(B65,15)="state.character", RIGHT(B65,6)=".maxed" ), 0, LET( sort, _xlfn.XLOOKUP( B65, tblChecklist[TargetID], tblChecklist[PlayerSort], 0 ), IF(sort=0,500,sort) ) )} -> 36 | I65: {=_xlfn.XLOOKUP( B65, tblTargetStatus[TargetID], tblTargetStatus[Status], "" )} -> BLOCKED | J65: FALSE
A66: cost.building.caravan@1.ruby.1 | B66: =IFERROR(__xludf.DUMMYFUNCTION("REGEXREPLACE( REGEXREPLACE(A66,""^cost\."",""""), ""\.[^.]+\.[^.]+$"", """" )"),"building.caravan@1") -> building.caravan@1 | C66: {=_xlfn.XLOOKUP( B66, tblTargets[TargetID], tblTargets[DisplayName], "" )} -> Caravan Lv 1 | D66: {=_xlfn.XLOOKUP( B66, tblTargets[TargetID], tblTargets[TargetType], "" )} -> BUILDING | E66: ruby | F66: 1 | G66: {=_xlfn.XLOOKUP( A66, tblCost[RequirementID], tblCost[QuantityRequired], "" )} -> 5 | H66: {=IF( OR( LEFT(B66,15)="state.character", RIGHT(B66,6)=".maxed" ), 0, LET( sort, _xlfn.XLOOKUP( B66, tblChecklist[TargetID], tblChecklist[PlayerSort], 0 ), IF(sort=0,500,sort) ) )} -> 36 | I66: {=_xlfn.XLOOKUP( B66, tblTargetStatus[TargetID], tblTargetStatus[Status], "" )} -> BLOCKED | J66: FALSE
A67: cost.building.caravan@1.stone.1 | B67: =IFERROR(__xludf.DUMMYFUNCTION("REGEXREPLACE( REGEXREPLACE(A67,""^cost\."",""""), ""\.[^.]+\.[^.]+$"", """" )"),"building.caravan@1") -> building.caravan@1 | C67: {=_xlfn.XLOOKUP( B67, tblTargets[TargetID], tblTargets[DisplayName], "" )} -> Caravan Lv 1 | D67: {=_xlfn.XLOOKUP( B67, tblTargets[TargetID], tblTargets[TargetType], "" )} -> BUILDING | E67: stone | F67: 1 | G67: {=_xlfn.XLOOKUP( A67, tblCost[RequirementID], tblCost[QuantityRequired], "" )} -> 200 | H67: {=IF( OR( LEFT(B67,15)="state.character", RIGHT(B67,6)=".maxed" ), 0, LET( sort, _xlfn.XLOOKUP( B67, tblChecklist[TargetID], tblChecklist[PlayerSort], 0 ), IF(sort=0,500,sort) ) )} -> 36 | I67: {=_xlfn.XLOOKUP( B67, tblTargetStatus[TargetID], tblTargetStatus[Status], "" )} -> BLOCKED | J67: FALSE
A68: cost.building.caravan@1.sushi.1 | B68: =IFERROR(__xludf.DUMMYFUNCTION("REGEXREPLACE( REGEXREPLACE(A68,""^cost\."",""""), ""\.[^.]+\.[^.]+$"", """" )"),"building.caravan@1") -> building.caravan@1 | C68: {=_xlfn.XLOOKUP( B68, tblTargets[TargetID], tblTargets[DisplayName], "" )} -> Caravan Lv 1 | D68: {=_xlfn.XLOOKUP( B68, tblTargets[TargetID], tblTargets[TargetType], "" )} -> BUILDING | E68: sushi | F68: 1 | G68: {=_xlfn.XLOOKUP( A68, tblCost[RequirementID], tblCost[QuantityRequired], "" )} -> 10 | H68: {=IF( OR( LEFT(B68,15)="state.character", RIGHT(B68,6)=".maxed" ), 0, LET( sort, _xlfn.XLOOKUP( B68, tblChecklist[TargetID], tblChecklist[PlayerSort], 0 ), IF(sort=0,500,sort) ) )} -> 36 | I68: {=_xlfn.XLOOKUP( B68, tblTargetStatus[TargetID], tblTargetStatus[Status], "" )} -> BLOCKED | J68: FALSE
A69: cost.building.caravan@2.coin.1 | B69: =IFERROR(__xludf.DUMMYFUNCTION("REGEXREPLACE( REGEXREPLACE(A69,""^cost\."",""""), ""\.[^.]+\.[^.]+$"", """" )"),"building.caravan@2") -> building.caravan@2 | C69: {=_xlfn.XLOOKUP( B69, tblTargets[TargetID], tblTargets[DisplayName], "" )} -> Caravan Lv 2 | D69: {=_xlfn.XLOOKUP( B69, tblTargets[TargetID], tblTargets[TargetType], "" )} -> BUILDING | E69: coin | F69: 1 | G69: {=_xlfn.XLOOKUP( A69, tblCost[RequirementID], tblCost[QuantityRequired], "" )} -> 1200 | H69: {=IF( OR( LEFT(B69,15)="state.character", RIGHT(B69,6)=".maxed" ), 0, LET( sort, _xlfn.XLOOKUP( B69, tblChecklist[TargetID], tblChecklist[PlayerSort], 0 ), IF(sort=0,500,sort) ) )} -> 37 | I69: {=_xlfn.XLOOKUP( B69, tblTargetStatus[TargetID], tblTargetStatus[Status], "" )} -> BLOCKED | J69: FALSE
A70: cost.building.caravan@2.fan.1 | B70: =IFERROR(__xludf.DUMMYFUNCTION("REGEXREPLACE( REGEXREPLACE(A70,""^cost\."",""""), ""\.[^.]+\.[^.]+$"", """" )"),"building.caravan@2") -> building.caravan@2 | C70: {=_xlfn.XLOOKUP( B70, tblTargets[TargetID], tblTargets[DisplayName], "" )} -> Caravan Lv 2 | D70: {=_xlfn.XLOOKUP( B70, tblTargets[TargetID], tblTargets[TargetType], "" )} -> BUILDING | E70: fan | F70: 1 | G70: {=_xlfn.XLOOKUP( A70, tblCost[RequirementID], tblCost[QuantityRequired], "" )} -> 50 | H70: {=IF( OR( LEFT(B70,15)="state.character", RIGHT(B70,6)=".maxed" ), 0, LET( sort, _xlfn.XLOOKUP( B70, tblChecklist[TargetID], tblChecklist[PlayerSort], 0 ), IF(sort=0,500,sort) ) )} -> 37 | I70: {=_xlfn.XLOOKUP( B70, tblTargetStatus[TargetID], tblTargetStatus[Status], "" )} -> BLOCKED | J70: FALSE
A71: cost.building.caravan@2.ingot.1 | B71: =IFERROR(__xludf.DUMMYFUNCTION("REGEXREPLACE( REGEXREPLACE(A71,""^cost\."",""""), ""\.[^.]+\.[^.]+$"", """" )"),"building.caravan@2") -> building.caravan@2 | C71: {=_xlfn.XLOOKUP( B71, tblTargets[TargetID], tblTargets[DisplayName], "" )} -> Caravan Lv 2 | D71: {=_xlfn.XLOOKUP( B71, tblTargets[TargetID], tblTargets[TargetType], "" )} -> BUILDING | E71: ingot | F71: 1 | G71: {=_xlfn.XLOOKUP( A71, tblCost[RequirementID], tblCost[QuantityRequired], "" )} -> 50 | H71: {=IF( OR( LEFT(B71,15)="state.character", RIGHT(B71,6)=".maxed" ), 0, LET( sort, _xlfn.XLOOKUP( B71, tblChecklist[TargetID], tblChecklist[PlayerSort], 0 ), IF(sort=0,500,sort) ) )} -> 37 | I71: {=_xlfn.XLOOKUP( B71, tblTargetStatus[TargetID], tblTargetStatus[Status], "" )} -> BLOCKED | J71: FALSE
A72: cost.building.caravan@2.plank.1 | B72: =IFERROR(__xludf.DUMMYFUNCTION("REGEXREPLACE( REGEXREPLACE(A72,""^cost\."",""""), ""\.[^.]+\.[^.]+$"", """" )"),"building.caravan@2") -> building.caravan@2 | C72: {=_xlfn.XLOOKUP( B72, tblTargets[TargetID], tblTargets[DisplayName], "" )} -> Caravan Lv 2 | D72: {=_xlfn.XLOOKUP( B72, tblTargets[TargetID], tblTargets[TargetType], "" )} -> BUILDING | E72: plank | F72: 1 | G72: {=_xlfn.XLOOKUP( A72, tblCost[RequirementID], tblCost[QuantityRequired], "" )} -> 600 | H72: {=IF( OR( LEFT(B72,15)="state.character", RIGHT(B72,6)=".maxed" ), 0, LET( sort, _xlfn.XLOOKUP( B72, tblChecklist[TargetID], tblChecklist[PlayerSort], 0 ), IF(sort=0,500,sort) ) )} -> 37 | I72: {=_xlfn.XLOOKUP( B72, tblTargetStatus[TargetID], tblTargetStatus[Status], "" )} -> BLOCKED | J72: FALSE
A73: cost.building.caravan@2.ruby.1 | B73: =IFERROR(__xludf.DUMMYFUNCTION("REGEXREPLACE( REGEXREPLACE(A73,""^cost\."",""""), ""\.[^.]+\.[^.]+$"", """" )"),"building.caravan@2") -> building.caravan@2 | C73: {=_xlfn.XLOOKUP( B73, tblTargets[TargetID], tblTargets[DisplayName], "" )} -> Caravan Lv 2 | D73: {=_xlfn.XLOOKUP( B73, tblTargets[TargetID], tblTargets[TargetType], "" )} -> BUILDING | E73: ruby | F73: 1 | G73: {=_xlfn.XLOOKUP( A73, tblCost[RequirementID], tblCost[QuantityRequired], "" )} -> 7 | H73: {=IF( OR( LEFT(B73,15)="state.character", RIGHT(B73,6)=".maxed" ), 0, LET( sort, _xlfn.XLOOKUP( B73, tblChecklist[TargetID], tblChecklist[PlayerSort], 0 ), IF(sort=0,500,sort) ) )} -> 37 | I73: {=_xlfn.XLOOKUP( B73, tblTargetStatus[TargetID], tblTargetStatus[Status], "" )} -> BLOCKED | J73: FALSE
A74: cost.building.caravan@2.stone.1 | B74: =IFERROR(__xludf.DUMMYFUNCTION("REGEXREPLACE( REGEXREPLACE(A74,""^cost\."",""""), ""\.[^.]+\.[^.]+$"", """" )"),"building.caravan@2") -> building.caravan@2 | C74: {=_xlfn.XLOOKUP( B74, tblTargets[TargetID], tblTargets[DisplayName], "" )} -> Caravan Lv 2 | D74: {=_xlfn.XLOOKUP( B74, tblTargets[TargetID], tblTargets[TargetType], "" )} -> BUILDING | E74: stone | F74: 1 | G74: {=_xlfn.XLOOKUP( A74, tblCost[RequirementID], tblCost[QuantityRequired], "" )} -> 300 | H74: {=IF( OR( LEFT(B74,15)="state.character", RIGHT(B74,6)=".maxed" ), 0, LET( sort, _xlfn.XLOOKUP( B74, tblChecklist[TargetID], tblChecklist[PlayerSort], 0 ), IF(sort=0,500,sort) ) )} -> 37 | I74: {=_xlfn.XLOOKUP( B74, tblTargetStatus[TargetID], tblTargetStatus[Status], "" )} -> BLOCKED | J74: FALSE
A75: cost.building.caravan@3.coin.1 | B75: =IFERROR(__xludf.DUMMYFUNCTION("REGEXREPLACE( REGEXREPLACE(A75,""^cost\."",""""), ""\.[^.]+\.[^.]+$"", """" )"),"building.caravan@3") -> building.caravan@3 | C75: {=_xlfn.XLOOKUP( B75, tblTargets[TargetID], tblTargets[DisplayName], "" )} -> Caravan Lv 3 | D75: {=_xlfn.XLOOKUP( B75, tblTargets[TargetID], tblTargets[TargetType], "" )} -> BUILDING | E75: coin | F75: 1 | G75: {=_xlfn.XLOOKUP( A75, tblCost[RequirementID], tblCost[QuantityRequired], "" )} -> 1500 | H75: {=IF( OR( LEFT(B75,15)="state.character", RIGHT(B75,6)=".maxed" ), 0, LET( sort, _xlfn.XLOOKUP( B75, tblChecklist[TargetID], tblChecklist[PlayerSort], 0 ), IF(sort=0,500,sort) ) )} -> 38 | I75: {=_xlfn.XLOOKUP( B75, tblTargetStatus[TargetID], tblTargetStatus[Status], "" )} -> BLOCKED | J75: FALSE
A76: cost.building.caravan@3.paper.1 | B76: =IFERROR(__xludf.DUMMYFUNCTION("REGEXREPLACE( REGEXREPLACE(A76,""^cost\."",""""), ""\.[^.]+\.[^.]+$"", """" )"),"building.caravan@3") -> building.caravan@3 | C76: {=_xlfn.XLOOKUP( B76, tblTargets[TargetID], tblTargets[DisplayName], "" )} -> Caravan Lv 3 | D76: {=_xlfn.XLOOKUP( B76, tblTargets[TargetID], tblTargets[TargetType], "" )} -> BUILDING | E76: paper | F76: 1 | G76: {=_xlfn.XLOOKUP( A76, tblCost[RequirementID], tblCost[QuantityRequired], "" )} -> 20 | H76: {=IF( OR( LEFT(B76,15)="state.character", RIGHT(B76,6)=".maxed" ), 0, LET( sort, _xlfn.XLOOKUP( B76, tblChecklist[TargetID], tblChecklist[PlayerSort], 0 ), IF(sort=0,500,sort) ) )} -> 38 | I76: {=_xlfn.XLOOKUP( B76, tblTargetStatus[TargetID], tblTargetStatus[Status], "" )} -> BLOCKED | J76: FALSE
A77: cost.building.caravan@3.pearl.1 | B77: =IFERROR(__xludf.DUMMYFUNCTION("REGEXREPLACE( REGEXREPLACE(A77,""^cost\."",""""), ""\.[^.]+\.[^.]+$"", """" )"),"building.caravan@3") -> building.caravan@3 | C77: {=_xlfn.XLOOKUP( B77, tblTargets[TargetID], tblTargets[DisplayName], "" )} -> Caravan Lv 3 | D77: {=_xlfn.XLOOKUP( B77, tblTargets[TargetID], tblTargets[TargetType], "" )} -> BUILDING | E77: pearl | F77: 1 | G77: {=_xlfn.XLOOKUP( A77, tblCost[RequirementID], tblCost[QuantityRequired], "" )} -> 10 | H77: {=IF( OR( LEFT(B77,15)="state.character", RIGHT(B77,6)=".maxed" ), 0, LET( sort, _xlfn.XLOOKUP( B77, tblChecklist[TargetID], tblChecklist[PlayerSort], 0 ), IF(sort=0,500,sort) ) )} -> 38 | I77: {=_xlfn.XLOOKUP( B77, tblTargetStatus[TargetID], tblTargetStatus[Status], "" )} -> BLOCKED | J77: FALSE
A78: cost.building.caravan@3.plank.1 | B78: =IFERROR(__xludf.DUMMYFUNCTION("REGEXREPLACE( REGEXREPLACE(A78,""^cost\."",""""), ""\.[^.]+\.[^.]+$"", """" )"),"building.caravan@3") -> building.caravan@3 | C78: {=_xlfn.XLOOKUP( B78, tblTargets[TargetID], tblTargets[DisplayName], "" )} -> Caravan Lv 3 | D78: {=_xlfn.XLOOKUP( B78, tblTargets[TargetID], tblTargets[TargetType], "" )} -> BUILDING | E78: plank | F78: 1 | G78: {=_xlfn.XLOOKUP( A78, tblCost[RequirementID], tblCost[QuantityRequired], "" )} -> 800 | H78: {=IF( OR( LEFT(B78,15)="state.character", RIGHT(B78,6)=".maxed" ), 0, LET( sort, _xlfn.XLOOKUP( B78, tblChecklist[TargetID], tblChecklist[PlayerSort], 0 ), IF(sort=0,500,sort) ) )} -> 38 | I78: {=_xlfn.XLOOKUP( B78, tblTargetStatus[TargetID], tblTargetStatus[Status], "" )} -> BLOCKED | J78: FALSE
A79: cost.building.caravan@3.ruby.1 | B79: =IFERROR(__xludf.DUMMYFUNCTION("REGEXREPLACE( REGEXREPLACE(A79,""^cost\."",""""), ""\.[^.]+\.[^.]+$"", """" )"),"building.caravan@3") -> building.caravan@3 | C79: {=_xlfn.XLOOKUP( B79, tblTargets[TargetID], tblTargets[DisplayName], "" )} -> Caravan Lv 3 | D79: {=_xlfn.XLOOKUP( B79, tblTargets[TargetID], tblTargets[TargetType], "" )} -> BUILDING | E79: ruby | F79: 1 | G79: {=_xlfn.XLOOKUP( A79, tblCost[RequirementID], tblCost[QuantityRequired], "" )} -> 9 | H79: {=IF( OR( LEFT(B79,15)="state.character", RIGHT(B79,6)=".maxed" ), 0, LET( sort, _xlfn.XLOOKUP( B79, tblChecklist[TargetID], tblChecklist[PlayerSort], 0 ), IF(sort=0,500,sort) ) )} -> 38 | I79: {=_xlfn.XLOOKUP( B79, tblTargetStatus[TargetID], tblTargetStatus[Status], "" )} -> BLOCKED | J79: FALSE
A80: cost.building.caravan@3.stone.1 | B80: =IFERROR(__xludf.DUMMYFUNCTION("REGEXREPLACE( REGEXREPLACE(A80,""^cost\."",""""), ""\.[^.]+\.[^.]+$"", """" )"),"building.caravan@3") -> building.caravan@3 | C80: {=_xlfn.XLOOKUP( B80, tblTargets[TargetID], tblTargets[DisplayName], "" )} -> Caravan Lv 3 | D80: {=_xlfn.XLOOKUP( B80, tblTargets[TargetID], tblTargets[TargetType], "" )} -> BUILDING | E80: stone | F80: 1 | G80: {=_xlfn.XLOOKUP( A80, tblCost[RequirementID], tblCost[QuantityRequired], "" )} -> 400 | H80: {=IF( OR( LEFT(B80,15)="state.character", RIGHT(B80,6)=".maxed" ), 0, LET( sort, _xlfn.XLOOKUP( B80, tblChecklist[TargetID], tblChecklist[PlayerSort], 0 ), IF(sort=0,500,sort) ) )} -> 38 | I80: {=_xlfn.XLOOKUP( B80, tblTargetStatus[TargetID], tblTargetStatus[Status], "" )} -> BLOCKED | J80: FALSE
A81: cost.building.caravan@4.coin.1 | B81: =IFERROR(__xludf.DUMMYFUNCTION("REGEXREPLACE( REGEXREPLACE(A81,""^cost\."",""""), ""\.[^.]+\.[^.]+$"", """" )"),"building.caravan@4") -> building.caravan@4 | C81: {=_xlfn.XLOOKUP( B81, tblTargets[TargetID], tblTargets[DisplayName], "" )} -> Caravan Lv 4 | D81: {=_xlfn.XLOOKUP( B81, tblTargets[TargetID], tblTargets[TargetType], "" )} -> BUILDING | E81: coin | F81: 1 | G81: {=_xlfn.XLOOKUP( A81, tblCost[RequirementID], tblCost[QuantityRequired], "" )} -> 2000 | H81: {=IF( OR( LEFT(B81,15)="state.character", RIGHT(B81,6)=".maxed" ), 0, LET( sort, _xlfn.XLOOKUP( B81, tblChecklist[TargetID], tblChecklist[PlayerSort], 0 ), IF(sort=0,500,sort) ) )} -> 39 | I81: {=_xlfn.XLOOKUP( B81, tblTargetStatus[TargetID], tblTargetStatus[Status], "" )} -> BLOCKED | J81: FALSE
A82: cost.building.caravan@4.plank.1 | B82: =IFERROR(__xludf.DUMMYFUNCTION("REGEXREPLACE( REGEXREPLACE(A82,""^cost\."",""""), ""\.[^.]+\.[^.]+$"", """" )"),"building.caravan@4") -> building.caravan@4 | C82: {=_xlfn.XLOOKUP( B82, tblTargets[TargetID], tblTargets[DisplayName], "" )} -> Caravan Lv 4 | D82: {=_xlfn.XLOOKUP( B82, tblTargets[TargetID], tblTargets[TargetType], "" )} -> BUILDING | E82: plank | F82: 1 | G82: {=_xlfn.XLOOKUP( A82, tblCost[RequirementID], tblCost[QuantityRequired], "" )} -> 1000 | H82: {=IF( OR( LEFT(B82,15)="state.character", RIGHT(B82,6)=".maxed" ), 0, LET( sort, _xlfn.XLOOKUP( B82, tblChecklist[TargetID], tblChecklist[PlayerSort], 0 ), IF(sort=0,500,sort) ) )} -> 39 | I82: {=_xlfn.XLOOKUP( B82, tblTargetStatus[TargetID], tblTargetStatus[Status], "" )} -> BLOCKED | J82: FALSE
A83: cost.building.caravan@4.ruby.1 | B83: =IFERROR(__xludf.DUMMYFUNCTION("REGEXREPLACE( REGEXREPLACE(A83,""^cost\."",""""), ""\.[^.]+\.[^.]+$"", """" )"),"building.caravan@4") -> building.caravan@4 | C83: {=_xlfn.XLOOKUP( B83, tblTargets[TargetID], tblTargets[DisplayName], "" )} -> Caravan Lv 4 | D83: {=_xlfn.XLOOKUP( B83, tblTargets[TargetID], tblTargets[TargetType], "" )} -> BUILDING | E83: ruby | F83: 1 | G83: {=_xlfn.XLOOKUP( A83, tblCost[RequirementID], tblCost[QuantityRequired], "" )} -> 12 | H83: {=IF( OR( LEFT(B83,15)="state.character", RIGHT(B83,6)=".maxed" ), 0, LET( sort, _xlfn.XLOOKUP( B83, tblChecklist[TargetID], tblChecklist[PlayerSort], 0 ), IF(sort=0,500,sort) ) )} -> 39 | I83: {=_xlfn.XLOOKUP( B83, tblTargetStatus[TargetID], tblTargetStatus[Status], "" )} -> BLOCKED | J83: FALSE
A84: cost.building.caravan@4.silk.1 | B84: =IFERROR(__xludf.DUMMYFUNCTION("REGEXREPLACE( REGEXREPLACE(A84,""^cost\."",""""), ""\.[^.]+\.[^.]+$"", """" )"),"building.caravan@4") -> building.caravan@4 | C84: {=_xlfn.XLOOKUP( B84, tblTargets[TargetID], tblTargets[DisplayName], "" )} -> Caravan Lv 4 | D84: {=_xlfn.XLOOKUP( B84, tblTargets[TargetID], tblTargets[TargetType], "" )} -> BUILDING | E84: silk | F84: 1 | G84: {=_xlfn.XLOOKUP( A84, tblCost[RequirementID], tblCost[QuantityRequired], "" )} -> 30 | H84: {=IF( OR( LEFT(B84,15)="state.character", RIGHT(B84,6)=".maxed" ), 0, LET( sort, _xlfn.XLOOKUP( B84, tblChecklist[TargetID], tblChecklist[PlayerSort], 0 ), IF(sort=0,500,sort) ) )} -> 39 | I84: {=_xlfn.XLOOKUP( B84, tblTargetStatus[TargetID], tblTargetStatus[Status], "" )} -> BLOCKED | J84: FALSE
A85: cost.building.caravan@4.spices.1 | B85: =IFERROR(__xludf.DUMMYFUNCTION("REGEXREPLACE( REGEXREPLACE(A85,""^cost\."",""""), ""\.[^.]+\.[^.]+$"", """" )"),"building.caravan@4") -> building.caravan@4 | C85: {=_xlfn.XLOOKUP( B85, tblTargets[TargetID], tblTargets[DisplayName], "" )} -> Caravan Lv 4 | D85: {=_xlfn.XLOOKUP( B85, tblTargets[TargetID], tblTargets[TargetType], "" )} -> BUILDING | E85: spices | F85: 1 | G85: {=_xlfn.XLOOKUP( A85, tblCost[RequirementID], tblCost[QuantityRequired], "" )} -> 5 | H85: {=IF( OR( LEFT(B85,15)="state.character", RIGHT(B85,6)=".maxed" ), 0, LET( sort, _xlfn.XLOOKUP( B85, tblChecklist[TargetID], tblChecklist[PlayerSort], 0 ), IF(sort=0,500,sort) ) )} -> 39 | I85: {=_xlfn.XLOOKUP( B85, tblTargetStatus[TargetID], tblTargetStatus[Status], "" )} -> BLOCKED | J85: FALSE
A86: cost.building.caravan@4.stone.1 | B86: =IFERROR(__xludf.DUMMYFUNCTION("REGEXREPLACE( REGEXREPLACE(A86,""^cost\."",""""), ""\.[^.]+\.[^.]+$"", """" )"),"building.caravan@4") -> building.caravan@4 | C86: {=_xlfn.XLOOKUP( B86, tblTargets[TargetID], tblTargets[DisplayName], "" )} -> Caravan Lv 4 | D86: {=_xlfn.XLOOKUP( B86, tblTargets[TargetID], tblTargets[TargetType], "" )} -> BUILDING | E86: stone | F86: 1 | G86: {=_xlfn.XLOOKUP( A86, tblCost[RequirementID], tblCost[QuantityRequired], "" )} -> 500 | H86: {=IF( OR( LEFT(B86,15)="state.character", RIGHT(B86,6)=".maxed" ), 0, LET( sort, _xlfn.XLOOKUP( B86, tblChecklist[TargetID], tblChecklist[PlayerSort], 0 ), IF(sort=0,500,sort) ) )} -> 39 | I86: {=_xlfn.XLOOKUP( B86, tblTargetStatus[TargetID], tblTargetStatus[Status], "" )} -> BLOCKED | J86: FALSE
A87: cost.building.chicken@1.beam.1 | B87: =IFERROR(__xludf.DUMMYFUNCTION("REGEXREPLACE( REGEXREPLACE(A87,""^cost\."",""""), ""\.[^.]+\.[^.]+$"", """" )"),"building.chicken@1") -> building.chicken@1 | C87: {=_xlfn.XLOOKUP( B87, tblTargets[TargetID], tblTargets[DisplayName], "" )} -> Chicken Lv 1 | D87: {=_xlfn.XLOOKUP( B87, tblTargets[TargetID], tblTargets[TargetType], "" )} -> BUILDING | E87: beam | F87: 1 | G87: {=_xlfn.XLOOKUP( A87, tblCost[RequirementID], tblCost[QuantityRequired], "" )} -> 400 | H87: {=IF( OR( LEFT(B87,15)="state.character", RIGHT(B87,6)=".maxed" ), 0, LET( sort, _xlfn.XLOOKUP( B87, tblChecklist[TargetID], tblChecklist[PlayerSort], 0 ), IF(sort=0,500,sort) ) )} -> 55 | I87: {=_xlfn.XLOOKUP( B87, tblTargetStatus[TargetID], tblTargetStatus[Status], "" )} -> BLOCKED | J87: FALSE
A88: cost.building.chicken@1.coin.1 | B88: =IFERROR(__xludf.DUMMYFUNCTION("REGEXREPLACE( REGEXREPLACE(A88,""^cost\."",""""), ""\.[^.]+\.[^.]+$"", """" )"),"building.chicken@1") -> building.chicken@1 | C88: {=_xlfn.XLOOKUP( B88, tblTargets[TargetID], tblTargets[DisplayName], "" )} -> Chicken Lv 1 | D88: {=_xlfn.XLOOKUP( B88, tblTargets[TargetID], tblTargets[TargetType], "" )} -> BUILDING | E88: coin | F88: 1 | G88: {=_xlfn.XLOOKUP( A88, tblCost[RequirementID], tblCost[QuantityRequired], "" )} -> 400 | H88: {=IF( OR( LEFT(B88,15)="state.character", RIGHT(B88,6)=".maxed" ), 0, LET( sort, _xlfn.XLOOKUP( B88, tblChecklist[TargetID], tblChecklist[PlayerSort], 0 ), IF(sort=0,500,sort) ) )} -> 55 | I88: {=_xlfn.XLOOKUP( B88, tblTargetStatus[TargetID], tblTargetStatus[Status], "" )} -> BLOCKED | J88: FALSE
A89: cost.building.chicken@1.egg.1 | B89: =IFERROR(__xludf.DUMMYFUNCTION("REGEXREPLACE( REGEXREPLACE(A89,""^cost\."",""""), ""\.[^.]+\.[^.]+$"", """" )"),"building.chicken@1") -> building.chicken@1 | C89: {=_xlfn.XLOOKUP( B89, tblTargets[TargetID], tblTargets[DisplayName], "" )} -> Chicken Lv 1 | D89: {=_xlfn.XLOOKUP( B89, tblTargets[TargetID], tblTargets[TargetType], "" )} -> BUILDING | E89: egg | F89: 1 | G89: {=_xlfn.XLOOKUP( A89, tblCost[RequirementID], tblCost[QuantityRequired], "" )} -> 1 | H89: {=IF( OR( LEFT(B89,15)="state.character", RIGHT(B89,6)=".maxed" ), 0, LET( sort, _xlfn.XLOOKUP( B89, tblChecklist[TargetID], tblChecklist[PlayerSort], 0 ), IF(sort=0,500,sort) ) )} -> 55 | I89: {=_xlfn.XLOOKUP( B89, tblTargetStatus[TargetID], tblTargetStatus[Status], "" )} -> BLOCKED | J89: FALSE
A90: cost.building.chicken@1.ruby.1 | B90: =IFERROR(__xludf.DUMMYFUNCTION("REGEXREPLACE( REGEXREPLACE(A90,""^cost\."",""""), ""\.[^.]+\.[^.]+$"", """" )"),"building.chicken@1") -> building.chicken@1 | C90: {=_xlfn.XLOOKUP( B90, tblTargets[TargetID], tblTargets[DisplayName], "" )} -> Chicken Lv 1 | D90: {=_xlfn.XLOOKUP( B90, tblTargets[TargetID], tblTargets[TargetType], "" )} -> BUILDING | E90: ruby | F90: 1 | G90: {=_xlfn.XLOOKUP( A90, tblCost[RequirementID], tblCost[QuantityRequired], "" )} -> 2 | H90: {=IF( OR( LEFT(B90,15)="state.character", RIGHT(B90,6)=".maxed" ), 0, LET( sort, _xlfn.XLOOKUP( B90, tblChecklist[TargetID], tblChecklist[PlayerSort], 0 ), IF(sort=0,500,sort) ) )} -> 55 | I90: {=_xlfn.XLOOKUP( B90, tblTargetStatus[TargetID], tblTargetStatus[Status], "" )} -> BLOCKED | J90: FALSE
A91: cost.building.chicken@1.stone.1 | B91: =IFERROR(__xludf.DUMMYFUNCTION("REGEXREPLACE( REGEXREPLACE(A91,""^cost\."",""""), ""\.[^.]+\.[^.]+$"", """" )"),"building.chicken@1") -> building.chicken@1 | C91: {=_xlfn.XLOOKUP( B91, tblTargets[TargetID], tblTargets[DisplayName], "" )} -> Chicken Lv 1 | D91: {=_xlfn.XLOOKUP( B91, tblTargets[TargetID], tblTargets[TargetType], "" )} -> BUILDING | E91: stone | F91: 1 | G91: {=_xlfn.XLOOKUP( A91, tblCost[RequirementID], tblCost[QuantityRequired], "" )} -> 200 | H91: {=IF( OR( LEFT(B91,15)="state.character", RIGHT(B91,6)=".maxed" ), 0, LET( sort, _xlfn.XLOOKUP( B91, tblChecklist[TargetID], tblChecklist[PlayerSort], 0 ), IF(sort=0,500,sort) ) )} -> 55 | I91: {=_xlfn.XLOOKUP( B91, tblTargetStatus[TargetID], tblTargetStatus[Status], "" )} -> BLOCKED | J91: FALSE
A92: cost.building.chicken@1.thread.1 | B92: =IFERROR(__xludf.DUMMYFUNCTION("REGEXREPLACE( REGEXREPLACE(A92,""^cost\."",""""), ""\.[^.]+\.[^.]+$"", """" )"),"building.chicken@1") -> building.chicken@1 | C92: {=_xlfn.XLOOKUP( B92, tblTargets[TargetID], tblTargets[DisplayName], "" )} -> Chicken Lv 1 | D92: {=_xlfn.XLOOKUP( B92, tblTargets[TargetID], tblTargets[TargetType], "" )} -> BUILDING | E92: thread | F92: 1 | G92: {=_xlfn.XLOOKUP( A92, tblCost[RequirementID], tblCost[QuantityRequired], "" )} -> 10 | H92: {=IF( OR( LEFT(B92,15)="state.character", RIGHT(B92,6)=".maxed" ), 0, LET( sort, _xlfn.XLOOKUP( B92, tblChecklist[TargetID], tblChecklist[PlayerSort], 0 ), IF(sort=0,500,sort) ) )} -> 55 | I92: {=_xlfn.XLOOKUP( B92, tblTargetStatus[TargetID], tblTargetStatus[Status], "" )} -> BLOCKED | J92: FALSE
A93: cost.building.chicken@1.wheat.1 | B93: =IFERROR(__xludf.DUMMYFUNCTION("REGEXREPLACE( REGEXREPLACE(A93,""^cost\."",""""), ""\.[^.]+\.[^.]+$"", """" )"),"building.chicken@1") -> building.chicken@1 | C93: {=_xlfn.XLOOKUP( B93, tblTargets[TargetID], tblTargets[DisplayName], "" )} -> Chicken Lv 1 | D93: {=_xlfn.XLOOKUP( B93, tblTargets[TargetID], tblTargets[TargetType], "" )} -> BUILDING | E93: wheat | F93: 1 | G93: {=_xlfn.XLOOKUP( A93, tblCost[RequirementID], tblCost[QuantityRequired], "" )} -> 20 | H93: {=IF( OR( LEFT(B93,15)="state.character", RIGHT(B93,6)=".maxed" ), 0, LET( sort, _xlfn.XLOOKUP( B93, tblChecklist[TargetID], tblChecklist[PlayerSort], 0 ), IF(sort=0,500,sort) ) )} -> 55 | I93: {=_xlfn.XLOOKUP( B93, tblTargetStatus[TargetID], tblTargetStatus[Status], "" )} -> BLOCKED | J93: FALSE
A94: cost.building.chicken@2.beam.1 | B94: =IFERROR(__xludf.DUMMYFUNCTION("REGEXREPLACE( REGEXREPLACE(A94,""^cost\."",""""), ""\.[^.]+\.[^.]+$"", """" )"),"building.chicken@2") -> building.chicken@2 | C94: {=_xlfn.XLOOKUP( B94, tblTargets[TargetID], tblTargets[DisplayName], "" )} -> Chicken Lv 2 | D94: {=_xlfn.XLOOKUP( B94, tblTargets[TargetID], tblTargets[TargetType], "" )} -> BUILDING | E94: beam | F94: 1 | G94: {=_xlfn.XLOOKUP( A94, tblCost[RequirementID], tblCost[QuantityRequired], "" )} -> 600 | H94: {=IF( OR( LEFT(B94,15)="state.character", RIGHT(B94,6)=".maxed" ), 0, LET( sort, _xlfn.XLOOKUP( B94, tblChecklist[TargetID], tblChecklist[PlayerSort], 0 ), IF(sort=0,500,sort) ) )} -> 56 | I94: {=_xlfn.XLOOKUP( B94, tblTargetStatus[TargetID], tblTargetStatus[Status], "" )} -> BLOCKED | J94: FALSE
A95: cost.building.chicken@2.coin.1 | B95: =IFERROR(__xludf.DUMMYFUNCTION("REGEXREPLACE( REGEXREPLACE(A95,""^cost\."",""""), ""\.[^.]+\.[^.]+$"", """" )"),"building.chicken@2") -> building.chicken@2 | C95: {=_xlfn.XLOOKUP( B95, tblTargets[TargetID], tblTargets[DisplayName], "" )} -> Chicken Lv 2 | D95: {=_xlfn.XLOOKUP( B95, tblTargets[TargetID], tblTargets[TargetType], "" )} -> BUILDING | E95: coin | F95: 1 | G95: {=_xlfn.XLOOKUP( A95, tblCost[RequirementID], tblCost[QuantityRequired], "" )} -> 600 | H95: {=IF( OR( LEFT(B95,15)="state.character", RIGHT(B95,6)=".maxed" ), 0, LET( sort, _xlfn.XLOOKUP( B95, tblChecklist[TargetID], tblChecklist[PlayerSort], 0 ), IF(sort=0,500,sort) ) )} -> 56 | I95: {=_xlfn.XLOOKUP( B95, tblTargetStatus[TargetID], tblTargetStatus[Status], "" )} -> BLOCKED | J95: FALSE
A96: cost.building.chicken@2.egg.1 | B96: =IFERROR(__xludf.DUMMYFUNCTION("REGEXREPLACE( REGEXREPLACE(A96,""^cost\."",""""), ""\.[^.]+\.[^.]+$"", """" )"),"building.chicken@2") -> building.chicken@2 | C96: {=_xlfn.XLOOKUP( B96, tblTargets[TargetID], tblTargets[DisplayName], "" )} -> Chicken Lv 2 | D96: {=_xlfn.XLOOKUP( B96, tblTargets[TargetID], tblTargets[TargetType], "" )} -> BUILDING | E96: egg | F96: 1 | G96: {=_xlfn.XLOOKUP( A96, tblCost[RequirementID], tblCost[QuantityRequired], "" )} -> 1 | H96: {=IF( OR( LEFT(B96,15)="state.character", RIGHT(B96,6)=".maxed" ), 0, LET( sort, _xlfn.XLOOKUP( B96, tblChecklist[TargetID], tblChecklist[PlayerSort], 0 ), IF(sort=0,500,sort) ) )} -> 56 | I96: {=_xlfn.XLOOKUP( B96, tblTargetStatus[TargetID], tblTargetStatus[Status], "" )} -> BLOCKED | J96: FALSE
A97: cost.building.chicken@2.ruby.1 | B97: =IFERROR(__xludf.DUMMYFUNCTION("REGEXREPLACE( REGEXREPLACE(A97,""^cost\."",""""), ""\.[^.]+\.[^.]+$"", """" )"),"building.chicken@2") -> building.chicken@2 | C97: {=_xlfn.XLOOKUP( B97, tblTargets[TargetID], tblTargets[DisplayName], "" )} -> Chicken Lv 2 | D97: {=_xlfn.XLOOKUP( B97, tblTargets[TargetID], tblTargets[TargetType], "" )} -> BUILDING | E97: ruby | F97: 1 | G97: {=_xlfn.XLOOKUP( A97, tblCost[RequirementID], tblCost[QuantityRequired], "" )} -> 3 | H97: {=IF( OR( LEFT(B97,15)="state.character", RIGHT(B97,6)=".maxed" ), 0, LET( sort, _xlfn.XLOOKUP( B97, tblChecklist[TargetID], tblChecklist[PlayerSort], 0 ), IF(sort=0,500,sort) ) )} -> 56 | I97: {=_xlfn.XLOOKUP( B97, tblTargetStatus[TargetID], tblTargetStatus[Status], "" )} -> BLOCKED | J97: FALSE
A98: cost.building.chicken@2.stone.1 | B98: =IFERROR(__xludf.DUMMYFUNCTION("REGEXREPLACE( REGEXREPLACE(A98,""^cost\."",""""), ""\.[^.]+\.[^.]+$"", """" )"),"building.chicken@2") -> building.chicken@2 | C98: {=_xlfn.XLOOKUP( B98, tblTargets[TargetID], tblTargets[DisplayName], "" )} -> Chicken Lv 2 | D98: {=_xlfn.XLOOKUP( B98, tblTargets[TargetID], tblTargets[TargetType], "" )} -> BUILDING | E98: stone | F98: 1 | G98: {=_xlfn.XLOOKUP( A98, tblCost[RequirementID], tblCost[QuantityRequired], "" )} -> 300 | H98: {=IF( OR( LEFT(B98,15)="state.character", RIGHT(B98,6)=".maxed" ), 0, LET( sort, _xlfn.XLOOKUP( B98, tblChecklist[TargetID], tblChecklist[PlayerSort], 0 ), IF(sort=0,500,sort) ) )} -> 56 | I98: {=_xlfn.XLOOKUP( B98, tblTargetStatus[TargetID], tblTargetStatus[Status], "" )} -> BLOCKED | J98: FALSE
A99: cost.building.chicken@2.thread.1 | B99: =IFERROR(__xludf.DUMMYFUNCTION("REGEXREPLACE( REGEXREPLACE(A99,""^cost\."",""""), ""\.[^.]+\.[^.]+$"", """" )"),"building.chicken@2") -> building.chicken@2 | C99: {=_xlfn.XLOOKUP( B99, tblTargets[TargetID], tblTargets[DisplayName], "" )} -> Chicken Lv 2 | D99: {=_xlfn.XLOOKUP( B99, tblTargets[TargetID], tblTargets[TargetType], "" )} -> BUILDING | E99: thread | F99: 1 | G99: {=_xlfn.XLOOKUP( A99, tblCost[RequirementID], tblCost[QuantityRequired], "" )} -> 10 | H99: {=IF( OR( LEFT(B99,15)="state.character", RIGHT(B99,6)=".maxed" ), 0, LET( sort, _xlfn.XLOOKUP( B99, tblChecklist[TargetID], tblChecklist[PlayerSort], 0 ), IF(sort=0,500,sort) ) )} -> 56 | I99: {=_xlfn.XLOOKUP( B99, tblTargetStatus[TargetID], tblTargetStatus[Status], "" )} -> BLOCKED | J99: FALSE
A100: cost.building.chicken@2.wheat.1 | B100: =IFERROR(__xludf.DUMMYFUNCTION("REGEXREPLACE( REGEXREPLACE(A100,""^cost\."",""""), ""\.[^.]+\.[^.]+$"", """" )"),"building.chicken@2") -> building.chicken@2 | C100: {=_xlfn.XLOOKUP( B100, tblTargets[TargetID], tblTargets[DisplayName], "" )} -> Chicken Lv 2 | D100: {=_xlfn.XLOOKUP( B100, tblTargets[TargetID], tblTargets[TargetType], "" )} -> BUILDING | E100: wheat | F100: 1 | G100: {=_xlfn.XLOOKUP( A100, tblCost[RequirementID], tblCost[QuantityRequired], "" )} -> 20 | H100: {=IF( OR( LEFT(B100,15)="state.character", RIGHT(B100,6)=".maxed" ), 0, LET( sort, _xlfn.XLOOKUP( B100, tblChecklist[TargetID], tblChecklist[PlayerSort], 0 ), IF(sort=0,500,sort) ) )} -> 56 | I100: {=_xlfn.XLOOKUP( B100, tblTargetStatus[TargetID], tblTargetStatus[Status], "" )} -> BLOCKED | J100: FALSE
...

Sheet Recommended
B1: Building order list
A2: Order | B2: PassiveTargetID | C2: ActiveTargetID | F2: Order | G2: Passive Buildings | H2: Passive ID | I2: Active ID | J2: Active Buildings | K2: Notes
A3: 1 | B3: {=_xlfn.XLOOKUP( A3, tblwikirecommended[Order], tblwikirecommended[Passive ID], "" )} -> building.guild@2 | C3: {=_xlfn.XLOOKUP( A3, tblwikirecommended[Order], tblwikirecommended[Active ID], "" )} -> building.guild@2 | F3: 1 | G3: Guild lvl. 2 | H3: =IFERROR(__xludf.DUMMYFUNCTION("LET( txt,TRIM(SUBSTITUTE(G3,CHAR(160),"" "")), buildingName,LOWER(TRIM(REGEXEXTRACT(txt,""(?i)^(.*?)\s*lvl\.""))), level,VALUE(REGEXEXTRACT(txt,""(?i)lvl\.\s*(\d+)"")), normalized, SUBSTITUTE( SUBSTITUTE( SUBSTITUTE(buildingName,""'"",""""), "&" ""’"","""" ), "" "",""_"" ), buildingKey, SWITCH( normalized, ""chicken_coop"",""chicken"", ""food_stall"",""food_stall"", ""dairy_farm"",""dairy"", ""lumber_mill"",""lumber"", ""train_station"",""station"", ""coffee_bo"&"nsai"",""bonsai"", normalized ), ""building.""&buildingKey&""@""&level )"),"building.guild@2") -> building.guild@2 | I3: =IFERROR(__xludf.DUMMYFUNCTION("LET( txt,TRIM(SUBSTITUTE(J3,CHAR(160),"" "")), buildingName,LOWER(TRIM(REGEXEXTRACT(txt,""(?i)^(.*?)\s*lvl\.""))), level,VALUE(REGEXEXTRACT(txt,""(?i)lvl\.\s*(\d+)"")), normalized, SUBSTITUTE( SUBSTITUTE( SUBSTITUTE(buildingName,""'"",""""), "&" ""’"","""" ), "" "",""_"" ), buildingKey, SWITCH( normalized, ""chicken_coop"",""chicken"", ""food_stall"",""food_stall"", ""dairy_farm"",""dairy"", ""lumber_mill"",""lumber"", ""train_station"",""station"", ""coffee_bo"&"nsai"",""bonsai"", normalized ), ""building.""&buildingKey&""@""&level )"),"building.guild@2") -> building.guild@2 | J3: Guild lvl. 2 | K3: Increases daily rewards and enables building lvl. 2 buildings.
A4: 2 | B4: {=_xlfn.XLOOKUP( A4, tblwikirecommended[Order], tblwikirecommended[Passive ID], "" )} -> building.warehouse@1 | C4: {=_xlfn.XLOOKUP( A4, tblwikirecommended[Order], tblwikirecommended[Active ID], "" )} -> building.warehouse@1 | F4: =1+F3 -> 2 | G4: Warehouse lvl. 1 | H4: =IFERROR(__xludf.DUMMYFUNCTION("LET( txt,TRIM(SUBSTITUTE(G4,CHAR(160),"" "")), buildingName,LOWER(TRIM(REGEXEXTRACT(txt,""(?i)^(.*?)\s*lvl\.""))), level,VALUE(REGEXEXTRACT(txt,""(?i)lvl\.\s*(\d+)"")), normalized, SUBSTITUTE( SUBSTITUTE( SUBSTITUTE(buildingName,""'"",""""), "&" ""’"","""" ), "" "",""_"" ), buildingKey, SWITCH( normalized, ""chicken_coop"",""chicken"", ""food_stall"",""food_stall"", ""dairy_farm"",""dairy"", ""lumber_mill"",""lumber"", ""train_station"",""station"", ""coffee_bo"&"nsai"",""bonsai"", normalized ), ""building.""&buildingKey&""@""&level )"),"building.warehouse@1") -> building.warehouse@1 | I4: =IFERROR(__xludf.DUMMYFUNCTION("LET( txt,TRIM(SUBSTITUTE(J4,CHAR(160),"" "")), buildingName,LOWER(TRIM(REGEXEXTRACT(txt,""(?i)^(.*?)\s*lvl\.""))), level,VALUE(REGEXEXTRACT(txt,""(?i)lvl\.\s*(\d+)"")), normalized, SUBSTITUTE( SUBSTITUTE( SUBSTITUTE(buildingName,""'"",""""), "&" ""’"","""" ), "" "",""_"" ), buildingKey, SWITCH( normalized, ""chicken_coop"",""chicken"", ""food_stall"",""food_stall"", ""dairy_farm"",""dairy"", ""lumber_mill"",""lumber"", ""train_station"",""station"", ""coffee_bo"&"nsai"",""bonsai"", normalized ), ""building.""&buildingKey&""@""&level )"),"building.warehouse@1") -> building.warehouse@1 | J4: Warehouse lvl. 1 | K4: Unlocks Bourse - watching ads for Treasure map fragments, Katanas and Coffee beans.
A5: 3 | B5: {=_xlfn.XLOOKUP( A5, tblwikirecommended[Order], tblwikirecommended[Passive ID], "" )} -> building.shop@1 | C5: {=_xlfn.XLOOKUP( A5, tblwikirecommended[Order], tblwikirecommended[Active ID], "" )} -> building.shop@1 | F5: =1+F4 -> 3 | G5: Shop lvl. 1 | H5: =IFERROR(__xludf.DUMMYFUNCTION("LET( txt,TRIM(SUBSTITUTE(G5,CHAR(160),"" "")), buildingName,LOWER(TRIM(REGEXEXTRACT(txt,""(?i)^(.*?)\s*lvl\.""))), level,VALUE(REGEXEXTRACT(txt,""(?i)lvl\.\s*(\d+)"")), normalized, SUBSTITUTE( SUBSTITUTE( SUBSTITUTE(buildingName,""'"",""""), "&" ""’"","""" ), "" "",""_"" ), buildingKey, SWITCH( normalized, ""chicken_coop"",""chicken"", ""food_stall"",""food_stall"", ""dairy_farm"",""dairy"", ""lumber_mill"",""lumber"", ""train_station"",""station"", ""coffee_bo"&"nsai"",""bonsai"", normalized ), ""building.""&buildingKey&""@""&level )"),"building.shop@1") -> building.shop@1 | I5: =IFERROR(__xludf.DUMMYFUNCTION("LET( txt,TRIM(SUBSTITUTE(J5,CHAR(160),"" "")), buildingName,LOWER(TRIM(REGEXEXTRACT(txt,""(?i)^(.*?)\s*lvl\.""))), level,VALUE(REGEXEXTRACT(txt,""(?i)lvl\.\s*(\d+)"")), normalized, SUBSTITUTE( SUBSTITUTE( SUBSTITUTE(buildingName,""'"",""""), "&" ""’"","""" ), "" "",""_"" ), buildingKey, SWITCH( normalized, ""chicken_coop"",""chicken"", ""food_stall"",""food_stall"", ""dairy_farm"",""dairy"", ""lumber_mill"",""lumber"", ""train_station"",""station"", ""coffee_bo"&"nsai"",""bonsai"", normalized ), ""building.""&buildingKey&""@""&level )"),"building.shop@1") -> building.shop@1 | J5: Shop lvl. 1 | K5: Enables buying Chemicals, which are required for Alchemist's Hut lvl. 2.
A6: 4 | B6: {=_xlfn.XLOOKUP( A6, tblwikirecommended[Order], tblwikirecommended[Passive ID], "" )} -> building.alchemists_hut@1 | C6: {=_xlfn.XLOOKUP( A6, tblwikirecommended[Order], tblwikirecommended[Active ID], "" )} -> building.alchemists_hut@1 | F6: =1+F5 -> 4 | G6: Alchemist's Hut lvl. 1 | H6: =IFERROR(__xludf.DUMMYFUNCTION("LET( txt,TRIM(SUBSTITUTE(G6,CHAR(160),"" "")), buildingName,LOWER(TRIM(REGEXEXTRACT(txt,""(?i)^(.*?)\s*lvl\.""))), level,VALUE(REGEXEXTRACT(txt,""(?i)lvl\.\s*(\d+)"")), normalized, SUBSTITUTE( SUBSTITUTE( SUBSTITUTE(buildingName,""'"",""""), "&" ""’"","""" ), "" "",""_"" ), buildingKey, SWITCH( normalized, ""chicken_coop"",""chicken"", ""food_stall"",""food_stall"", ""dairy_farm"",""dairy"", ""lumber_mill"",""lumber"", ""train_station"",""station"", ""coffee_bo"&"nsai"",""bonsai"", normalized ), ""building.""&buildingKey&""@""&level )"),"building.alchemists_hut@1") -> building.alchemists_hut@1 | I6: =IFERROR(__xludf.DUMMYFUNCTION("LET( txt,TRIM(SUBSTITUTE(J6,CHAR(160),"" "")), buildingName,LOWER(TRIM(REGEXEXTRACT(txt,""(?i)^(.*?)\s*lvl\.""))), level,VALUE(REGEXEXTRACT(txt,""(?i)lvl\.\s*(\d+)"")), normalized, SUBSTITUTE( SUBSTITUTE( SUBSTITUTE(buildingName,""'"",""""), "&" ""’"","""" ), "" "",""_"" ), buildingKey, SWITCH( normalized, ""chicken_coop"",""chicken"", ""food_stall"",""food_stall"", ""dairy_farm"",""dairy"", ""lumber_mill"",""lumber"", ""train_station"",""station"", ""coffee_bo"&"nsai"",""bonsai"", normalized ), ""building.""&buildingKey&""@""&level )"),"building.alchemists_hut@1") -> building.alchemists_hut@1 | J6: Alchemist's Hut lvl. 1 | K6: Enables building Alchemist's Hut lvl. 2.
A7: 5 | B7: {=_xlfn.XLOOKUP( A7, tblwikirecommended[Order], tblwikirecommended[Passive ID], "" )} -> building.alchemists_hut@2 | C7: {=_xlfn.XLOOKUP( A7, tblwikirecommended[Order], tblwikirecommended[Active ID], "" )} -> building.alchemists_hut@2 | F7: =1+F6 -> 5 | G7: Alchemist's Hut lvl. 2 | H7: =IFERROR(__xludf.DUMMYFUNCTION("LET( txt,TRIM(SUBSTITUTE(G7,CHAR(160),"" "")), buildingName,LOWER(TRIM(REGEXEXTRACT(txt,""(?i)^(.*?)\s*lvl\.""))), level,VALUE(REGEXEXTRACT(txt,""(?i)lvl\.\s*(\d+)"")), normalized, SUBSTITUTE( SUBSTITUTE( SUBSTITUTE(buildingName,""'"",""""), "&" ""’"","""" ), "" "",""_"" ), buildingKey, SWITCH( normalized, ""chicken_coop"",""chicken"", ""food_stall"",""food_stall"", ""dairy_farm"",""dairy"", ""lumber_mill"",""lumber"", ""train_station"",""station"", ""coffee_bo"&"nsai"",""bonsai"", normalized ), ""building.""&buildingKey&""@""&level )"),"building.alchemists_hut@2") -> building.alchemists_hut@2 | I7: =IFERROR(__xludf.DUMMYFUNCTION("LET( txt,TRIM(SUBSTITUTE(J7,CHAR(160),"" "")), buildingName,LOWER(TRIM(REGEXEXTRACT(txt,""(?i)^(.*?)\s*lvl\.""))), level,VALUE(REGEXEXTRACT(txt,""(?i)lvl\.\s*(\d+)"")), normalized, SUBSTITUTE( SUBSTITUTE( SUBSTITUTE(buildingName,""'"",""""), "&" ""’"","""" ), "" "",""_"" ), buildingKey, SWITCH( normalized, ""chicken_coop"",""chicken"", ""food_stall"",""food_stall"", ""dairy_farm"",""dairy"", ""lumber_mill"",""lumber"", ""train_station"",""station"", ""coffee_bo"&"nsai"",""bonsai"", normalized ), ""building.""&buildingKey&""@""&level )"),"building.alchemists_hut@2") -> building.alchemists_hut@2 | J7: Alchemist's Hut lvl. 2 | K7: Unlocks Cauldron.
A8: 6 | B8: {=_xlfn.XLOOKUP( A8, tblwikirecommended[Order], tblwikirecommended[Passive ID], "" )} -> building.field@1 | C8: {=_xlfn.XLOOKUP( A8, tblwikirecommended[Order], tblwikirecommended[Active ID], "" )} -> building.field@1 | F8: =1+F7 -> 6 | G8: Field lvl. 1 | H8: =IFERROR(__xludf.DUMMYFUNCTION("LET( txt,TRIM(SUBSTITUTE(G8,CHAR(160),"" "")), buildingName,LOWER(TRIM(REGEXEXTRACT(txt,""(?i)^(.*?)\s*lvl\.""))), level,VALUE(REGEXEXTRACT(txt,""(?i)lvl\.\s*(\d+)"")), normalized, SUBSTITUTE( SUBSTITUTE( SUBSTITUTE(buildingName,""'"",""""), "&" ""’"","""" ), "" "",""_"" ), buildingKey, SWITCH( normalized, ""chicken_coop"",""chicken"", ""food_stall"",""food_stall"", ""dairy_farm"",""dairy"", ""lumber_mill"",""lumber"", ""train_station"",""station"", ""coffee_bo"&"nsai"",""bonsai"", normalized ), ""building.""&buildingKey&""@""&level )"),"building.field@1") -> building.field@1 | I8: =IFERROR(__xludf.DUMMYFUNCTION("LET( txt,TRIM(SUBSTITUTE(J8,CHAR(160),"" "")), buildingName,LOWER(TRIM(REGEXEXTRACT(txt,""(?i)^(.*?)\s*lvl\.""))), level,VALUE(REGEXEXTRACT(txt,""(?i)lvl\.\s*(\d+)"")), normalized, SUBSTITUTE( SUBSTITUTE( SUBSTITUTE(buildingName,""'"",""""), "&" ""’"","""" ), "" "",""_"" ), buildingKey, SWITCH( normalized, ""chicken_coop"",""chicken"", ""food_stall"",""food_stall"", ""dairy_farm"",""dairy"", ""lumber_mill"",""lumber"", ""train_station"",""station"", ""coffee_bo"&"nsai"",""bonsai"", normalized ), ""building.""&buildingKey&""@""&level )"),"building.field@1") -> building.field@1 | J8: Field lvl. 1 | K8: Passive income of Rice (used in dungeon).
A9: 7 | B9: {=_xlfn.XLOOKUP( A9, tblwikirecommended[Order], tblwikirecommended[Passive ID], "" )} -> building.rock_garden@1 | C9: {=_xlfn.XLOOKUP( A9, tblwikirecommended[Order], tblwikirecommended[Active ID], "" )} -> building.food_stall@1 | F9: =1+F8 -> 7 | G9: Rock Garden lvl. 1 | H9: =IFERROR(__xludf.DUMMYFUNCTION("LET( txt,TRIM(SUBSTITUTE(G9,CHAR(160),"" "")), buildingName,LOWER(TRIM(REGEXEXTRACT(txt,""(?i)^(.*?)\s*lvl\.""))), level,VALUE(REGEXEXTRACT(txt,""(?i)lvl\.\s*(\d+)"")), normalized, SUBSTITUTE( SUBSTITUTE( SUBSTITUTE(buildingName,""'"",""""), "&" ""’"","""" ), "" "",""_"" ), buildingKey, SWITCH( normalized, ""chicken_coop"",""chicken"", ""food_stall"",""food_stall"", ""dairy_farm"",""dairy"", ""lumber_mill"",""lumber"", ""train_station"",""station"", ""coffee_bo"&"nsai"",""bonsai"", normalized ), ""building.""&buildingKey&""@""&level )"),"building.rock_garden@1") -> building.rock_garden@1 | I9: =IFERROR(__xludf.DUMMYFUNCTION("LET( txt,TRIM(SUBSTITUTE(J9,CHAR(160),"" "")), buildingName,LOWER(TRIM(REGEXEXTRACT(txt,""(?i)^(.*?)\s*lvl\.""))), level,VALUE(REGEXEXTRACT(txt,""(?i)lvl\.\s*(\d+)"")), normalized, SUBSTITUTE( SUBSTITUTE( SUBSTITUTE(buildingName,""'"",""""), "&" ""’"","""" ), "" "",""_"" ), buildingKey, SWITCH( normalized, ""chicken_coop"",""chicken"", ""food_stall"",""food_stall"", ""dairy_farm"",""dairy"", ""lumber_mill"",""lumber"", ""train_station"",""station"", ""coffee_bo"&"nsai"",""bonsai"", normalized ), ""building.""&buildingKey&""@""&level )"),"building.food_stall@1") -> building.food_stall@1 | J9: Food Stall lvl. 1 | K9: Enables crafting dungeon related items.
A10: 8 | B10: {=_xlfn.XLOOKUP( A10, tblwikirecommended[Order], tblwikirecommended[Passive ID], "" )} -> building.rock_garden@2 | C10: {=_xlfn.XLOOKUP( A10, tblwikirecommended[Order], tblwikirecommended[Active ID], "" )} -> building.field@2 | F10: =1+F9 -> 8 | G10: Rock Garden lvl. 2 | H10: =IFERROR(__xludf.DUMMYFUNCTION("LET( txt,TRIM(SUBSTITUTE(G10,CHAR(160),"" "")), buildingName,LOWER(TRIM(REGEXEXTRACT(txt,""(?i)^(.*?)\s*lvl\.""))), level,VALUE(REGEXEXTRACT(txt,""(?i)lvl\.\s*(\d+)"")), normalized, SUBSTITUTE( SUBSTITUTE( SUBSTITUTE(buildingName,""'"",""""),"&" ""’"","""" ), "" "",""_"" ), buildingKey, SWITCH( normalized, ""chicken_coop"",""chicken"", ""food_stall"",""food_stall"", ""dairy_farm"",""dairy"", ""lumber_mill"",""lumber"", ""train_station"",""station"", ""coffee_b"&"onsai"",""bonsai"", normalized ), ""building.""&buildingKey&""@""&level )"),"building.rock_garden@2") -> building.rock_garden@2 | I10: =IFERROR(__xludf.DUMMYFUNCTION("LET( txt,TRIM(SUBSTITUTE(J10,CHAR(160),"" "")), buildingName,LOWER(TRIM(REGEXEXTRACT(txt,""(?i)^(.*?)\s*lvl\.""))), level,VALUE(REGEXEXTRACT(txt,""(?i)lvl\.\s*(\d+)"")), normalized, SUBSTITUTE( SUBSTITUTE( SUBSTITUTE(buildingName,""'"",""""),"&" ""’"","""" ), "" "",""_"" ), buildingKey, SWITCH( normalized, ""chicken_coop"",""chicken"", ""food_stall"",""food_stall"", ""dairy_farm"",""dairy"", ""lumber_mill"",""lumber"", ""train_station"",""station"", ""coffee_b"&"onsai"",""bonsai"", normalized ), ""building.""&buildingKey&""@""&level )"),"building.field@2") -> building.field@2 | J10: Field lvl. 2 | K10: Passive income of Wheat (also used in dungeon).
A11: 9 | B11: {=_xlfn.XLOOKUP( A11, tblwikirecommended[Order], tblwikirecommended[Passive ID], "" )} -> building.garden@1 | C11: {=_xlfn.XLOOKUP( A11, tblwikirecommended[Order], tblwikirecommended[Active ID], "" )} -> building.windmill@1 | F11: =1+F10 -> 9 | G11: Garden lvl. 1 | H11: =IFERROR(__xludf.DUMMYFUNCTION("LET( txt,TRIM(SUBSTITUTE(G11,CHAR(160),"" "")), buildingName,LOWER(TRIM(REGEXEXTRACT(txt,""(?i)^(.*?)\s*lvl\.""))), level,VALUE(REGEXEXTRACT(txt,""(?i)lvl\.\s*(\d+)"")), normalized, SUBSTITUTE( SUBSTITUTE( SUBSTITUTE(buildingName,""'"",""""),"&" ""’"","""" ), "" "",""_"" ), buildingKey, SWITCH( normalized, ""chicken_coop"",""chicken"", ""food_stall"",""food_stall"", ""dairy_farm"",""dairy"", ""lumber_mill"",""lumber"", ""train_station"",""station"", ""coffee_b"&"onsai"",""bonsai"", normalized ), ""building.""&buildingKey&""@""&level )"),"building.garden@1") -> building.garden@1 | I11: =IFERROR(__xludf.DUMMYFUNCTION("LET( txt,TRIM(SUBSTITUTE(J11,CHAR(160),"" "")), buildingName,LOWER(TRIM(REGEXEXTRACT(txt,""(?i)^(.*?)\s*lvl\.""))), level,VALUE(REGEXEXTRACT(txt,""(?i)lvl\.\s*(\d+)"")), normalized, SUBSTITUTE( SUBSTITUTE( SUBSTITUTE(buildingName,""'"",""""),"&" ""’"","""" ), "" "",""_"" ), buildingKey, SWITCH( normalized, ""chicken_coop"",""chicken"", ""food_stall"",""food_stall"", ""dairy_farm"",""dairy"", ""lumber_mill"",""lumber"", ""train_station"",""station"", ""coffee_b"&"onsai"",""bonsai"", normalized ), ""building.""&buildingKey&""@""&level )"),"building.windmill@1") -> building.windmill@1 | J11: Windmill lvl. 1 | K11: Enables crafting Flour from Wheat.
A12: 10 | B12: {=_xlfn.XLOOKUP( A12, tblwikirecommended[Order], tblwikirecommended[Passive ID], "" )} -> building.garden@2 | C12: {=_xlfn.XLOOKUP( A12, tblwikirecommended[Order], tblwikirecommended[Active ID], "" )} -> building.furnace@1 | F12: =1+F11 -> 10 | G12: Garden lvl. 2 | H12: =IFERROR(__xludf.DUMMYFUNCTION("LET( txt,TRIM(SUBSTITUTE(G12,CHAR(160),"" "")), buildingName,LOWER(TRIM(REGEXEXTRACT(txt,""(?i)^(.*?)\s*lvl\.""))), level,VALUE(REGEXEXTRACT(txt,""(?i)lvl\.\s*(\d+)"")), normalized, SUBSTITUTE( SUBSTITUTE( SUBSTITUTE(buildingName,""'"",""""),"&" ""’"","""" ), "" "",""_"" ), buildingKey, SWITCH( normalized, ""chicken_coop"",""chicken"", ""food_stall"",""food_stall"", ""dairy_farm"",""dairy"", ""lumber_mill"",""lumber"", ""train_station"",""station"", ""coffee_b"&"onsai"",""bonsai"", normalized ), ""building.""&buildingKey&""@""&level )"),"building.garden@2") -> building.garden@2 | I12: =IFERROR(__xludf.DUMMYFUNCTION("LET( txt,TRIM(SUBSTITUTE(J12,CHAR(160),"" "")), buildingName,LOWER(TRIM(REGEXEXTRACT(txt,""(?i)^(.*?)\s*lvl\.""))), level,VALUE(REGEXEXTRACT(txt,""(?i)lvl\.\s*(\d+)"")), normalized, SUBSTITUTE( SUBSTITUTE( SUBSTITUTE(buildingName,""'"",""""),"&" ""’"","""" ), "" "",""_"" ), buildingKey, SWITCH( normalized, ""chicken_coop"",""chicken"", ""food_stall"",""food_stall"", ""dairy_farm"",""dairy"", ""lumber_mill"",""lumber"", ""train_station"",""station"", ""coffee_b"&"onsai"",""bonsai"", normalized ), ""building.""&buildingKey&""@""&level )"),"building.furnace@1") -> building.furnace@1 | J12: Furnace lvl. 1 | K12: Enables crafting Steel (required for Dungeon and later other buildings).
A13: 11 | B13: {=_xlfn.XLOOKUP( A13, tblwikirecommended[Order], tblwikirecommended[Passive ID], "" )} -> building.lumber@1 | C13: {=_xlfn.XLOOKUP( A13, tblwikirecommended[Order], tblwikirecommended[Active ID], "" )} -> building.furnace@2 | F13: =1+F12 -> 11 | G13: Lumber Mill lvl. 1 | H13: =IFERROR(__xludf.DUMMYFUNCTION("LET( txt,TRIM(SUBSTITUTE(G13,CHAR(160),"" "")), buildingName,LOWER(TRIM(REGEXEXTRACT(txt,""(?i)^(.*?)\s*lvl\.""))), level,VALUE(REGEXEXTRACT(txt,""(?i)lvl\.\s*(\d+)"")), normalized, SUBSTITUTE( SUBSTITUTE( SUBSTITUTE(buildingName,""'"",""""),"&" ""’"","""" ), "" "",""_"" ), buildingKey, SWITCH( normalized, ""chicken_coop"",""chicken"", ""food_stall"",""food_stall"", ""dairy_farm"",""dairy"", ""lumber_mill"",""lumber"", ""train_station"",""station"", ""coffee_b"&"onsai"",""bonsai"", normalized ), ""building.""&buildingKey&""@""&level )"),"building.lumber@1") -> building.lumber@1 | I13: =IFERROR(__xludf.DUMMYFUNCTION("LET( txt,TRIM(SUBSTITUTE(J13,CHAR(160),"" "")), buildingName,LOWER(TRIM(REGEXEXTRACT(txt,""(?i)^(.*?)\s*lvl\.""))), level,VALUE(REGEXEXTRACT(txt,""(?i)lvl\.\s*(\d+)"")), normalized, SUBSTITUTE( SUBSTITUTE( SUBSTITUTE(buildingName,""'"",""""),"&" ""’"","""" ), "" "",""_"" ), buildingKey, SWITCH( normalized, ""chicken_coop"",""chicken"", ""food_stall"",""food_stall"", ""dairy_farm"",""dairy"", ""lumber_mill"",""lumber"", ""train_station"",""station"", ""coffee_b"&"onsai"",""bonsai"", normalized ), ""building.""&buildingKey&""@""&level )"),"building.furnace@2") -> building.furnace@2 | J13: Furnace lvl. 2 | K13: Increases Steel production by 25%. Preferably only craft Steel when you have Furnace lvl. 2.
A14: 12 | B14: {=_xlfn.XLOOKUP( A14, tblwikirecommended[Order], tblwikirecommended[Passive ID], "" )} -> building.lumber@2 | C14: {=_xlfn.XLOOKUP( A14, tblwikirecommended[Order], tblwikirecommended[Active ID], "" )} -> building.dungeon@1 | F14: =1+F13 -> 12 | G14: Lumber Mill lvl. 2 | H14: =IFERROR(__xludf.DUMMYFUNCTION("LET( txt,TRIM(SUBSTITUTE(G14,CHAR(160),"" "")), buildingName,LOWER(TRIM(REGEXEXTRACT(txt,""(?i)^(.*?)\s*lvl\.""))), level,VALUE(REGEXEXTRACT(txt,""(?i)lvl\.\s*(\d+)"")), normalized, SUBSTITUTE( SUBSTITUTE( SUBSTITUTE(buildingName,""'"",""""),"&" ""’"","""" ), "" "",""_"" ), buildingKey, SWITCH( normalized, ""chicken_coop"",""chicken"", ""food_stall"",""food_stall"", ""dairy_farm"",""dairy"", ""lumber_mill"",""lumber"", ""train_station"",""station"", ""coffee_b"&"onsai"",""bonsai"", normalized ), ""building.""&buildingKey&""@""&level )"),"building.lumber@2") -> building.lumber@2 | I14: =IFERROR(__xludf.DUMMYFUNCTION("LET( txt,TRIM(SUBSTITUTE(J14,CHAR(160),"" "")), buildingName,LOWER(TRIM(REGEXEXTRACT(txt,""(?i)^(.*?)\s*lvl\.""))), level,VALUE(REGEXEXTRACT(txt,""(?i)lvl\.\s*(\d+)"")), normalized, SUBSTITUTE( SUBSTITUTE( SUBSTITUTE(buildingName,""'"",""""),"&" ""’"","""" ), "" "",""_"" ), buildingKey, SWITCH( normalized, ""chicken_coop"",""chicken"", ""food_stall"",""food_stall"", ""dairy_farm"",""dairy"", ""lumber_mill"",""lumber"", ""train_station"",""station"", ""coffee_b"&"onsai"",""bonsai"", normalized ), ""building.""&buildingKey&""@""&level )"),"building.dungeon@1") -> building.dungeon@1 | J14: Dungeon lvl. 1 | K14: Enables acquiring dungeon related items. Allows to convert nonogram loot -> MP -> dungeon loot.
A15: 13 | B15: {=_xlfn.XLOOKUP( A15, tblwikirecommended[Order], tblwikirecommended[Passive ID], "" )} -> building.guild@3 | C15: {=_xlfn.XLOOKUP( A15, tblwikirecommended[Order], tblwikirecommended[Active ID], "" )} -> building.lumber@1 | F15: =1+F14 -> 13 | G15: Guild lvl. 3 | H15: =IFERROR(__xludf.DUMMYFUNCTION("LET( txt,TRIM(SUBSTITUTE(G15,CHAR(160),"" "")), buildingName,LOWER(TRIM(REGEXEXTRACT(txt,""(?i)^(.*?)\s*lvl\.""))), level,VALUE(REGEXEXTRACT(txt,""(?i)lvl\.\s*(\d+)"")), normalized, SUBSTITUTE( SUBSTITUTE( SUBSTITUTE(buildingName,""'"",""""),"&" ""’"","""" ), "" "",""_"" ), buildingKey, SWITCH( normalized, ""chicken_coop"",""chicken"", ""food_stall"",""food_stall"", ""dairy_farm"",""dairy"", ""lumber_mill"",""lumber"", ""train_station"",""station"", ""coffee_b"&"onsai"",""bonsai"", normalized ), ""building.""&buildingKey&""@""&level )"),"building.guild@3") -> building.guild@3 | I15: =IFERROR(__xludf.DUMMYFUNCTION("LET( txt,TRIM(SUBSTITUTE(J15,CHAR(160),"" "")), buildingName,LOWER(TRIM(REGEXEXTRACT(txt,""(?i)^(.*?)\s*lvl\.""))), level,VALUE(REGEXEXTRACT(txt,""(?i)lvl\.\s*(\d+)"")), normalized, SUBSTITUTE( SUBSTITUTE( SUBSTITUTE(buildingName,""'"",""""),"&" ""’"","""" ), "" "",""_"" ), buildingKey, SWITCH( normalized, ""chicken_coop"",""chicken"", ""food_stall"",""food_stall"", ""dairy_farm"",""dairy"", ""lumber_mill"",""lumber"", ""train_station"",""station"", ""coffee_b"&"onsai"",""bonsai"", normalized ), ""building.""&buildingKey&""@""&level )"),"building.lumber@1") -> building.lumber@1 | J15: Lumber Mill lvl. 1 | K15: Enables crafting Wooden beams, which is needed for a lot of buildings.
A16: 14 | B16: {=_xlfn.XLOOKUP( A16, tblwikirecommended[Order], tblwikirecommended[Passive ID], "" )} -> building.rock_garden@3 | C16: {=_xlfn.XLOOKUP( A16, tblwikirecommended[Order], tblwikirecommended[Active ID], "" )} -> building.lumber@2 | F16: =1+F15 -> 14 | G16: Rock Garden lvl. 3 | H16: =IFERROR(__xludf.DUMMYFUNCTION("LET( txt,TRIM(SUBSTITUTE(G16,CHAR(160),"" "")), buildingName,LOWER(TRIM(REGEXEXTRACT(txt,""(?i)^(.*?)\s*lvl\.""))), level,VALUE(REGEXEXTRACT(txt,""(?i)lvl\.\s*(\d+)"")), normalized, SUBSTITUTE( SUBSTITUTE( SUBSTITUTE(buildingName,""'"",""""),"&" ""’"","""" ), "" "",""_"" ), buildingKey, SWITCH( normalized, ""chicken_coop"",""chicken"", ""food_stall"",""food_stall"", ""dairy_farm"",""dairy"", ""lumber_mill"",""lumber"", ""train_station"",""station"", ""coffee_b"&"onsai"",""bonsai"", normalized ), ""building.""&buildingKey&""@""&level )"),"building.rock_garden@3") -> building.rock_garden@3 | I16: =IFERROR(__xludf.DUMMYFUNCTION("LET( txt,TRIM(SUBSTITUTE(J16,CHAR(160),"" "")), buildingName,LOWER(TRIM(REGEXEXTRACT(txt,""(?i)^(.*?)\s*lvl\.""))), level,VALUE(REGEXEXTRACT(txt,""(?i)lvl\.\s*(\d+)"")), normalized, SUBSTITUTE( SUBSTITUTE( SUBSTITUTE(buildingName,""'"",""""),"&" ""’"","""" ), "" "",""_"" ), buildingKey, SWITCH( normalized, ""chicken_coop"",""chicken"", ""food_stall"",""food_stall"", ""dairy_farm"",""dairy"", ""lumber_mill"",""lumber"", ""train_station"",""station"", ""coffee_b"&"onsai"",""bonsai"", normalized ), ""building.""&buildingKey&""@""&level )"),"building.lumber@2") -> building.lumber@2 | J16: Lumber Mill lvl. 2 | K16: Increases production of Wooden beams.
A17: 15 | B17: {=_xlfn.XLOOKUP( A17, tblwikirecommended[Order], tblwikirecommended[Passive ID], "" )} -> building.garden@3 | C17: {=_xlfn.XLOOKUP( A17, tblwikirecommended[Order], tblwikirecommended[Active ID], "" )} -> building.windmill@2 | F17: =1+F16 -> 15 | G17: Garden lvl. 3 | H17: =IFERROR(__xludf.DUMMYFUNCTION("LET( txt,TRIM(SUBSTITUTE(G17,CHAR(160),"" "")), buildingName,LOWER(TRIM(REGEXEXTRACT(txt,""(?i)^(.*?)\s*lvl\.""))), level,VALUE(REGEXEXTRACT(txt,""(?i)lvl\.\s*(\d+)"")), normalized, SUBSTITUTE( SUBSTITUTE( SUBSTITUTE(buildingName,""'"",""""),"&" ""’"","""" ), "" "",""_"" ), buildingKey, SWITCH( normalized, ""chicken_coop"",""chicken"", ""food_stall"",""food_stall"", ""dairy_farm"",""dairy"", ""lumber_mill"",""lumber"", ""train_station"",""station"", ""coffee_b"&"onsai"",""bonsai"", normalized ), ""building.""&buildingKey&""@""&level )"),"building.garden@3") -> building.garden@3 | I17: =IFERROR(__xludf.DUMMYFUNCTION("LET( txt,TRIM(SUBSTITUTE(J17,CHAR(160),"" "")), buildingName,LOWER(TRIM(REGEXEXTRACT(txt,""(?i)^(.*?)\s*lvl\.""))), level,VALUE(REGEXEXTRACT(txt,""(?i)lvl\.\s*(\d+)"")), normalized, SUBSTITUTE( SUBSTITUTE( SUBSTITUTE(buildingName,""'"",""""),"&" ""’"","""" ), "" "",""_"" ), buildingKey, SWITCH( normalized, ""chicken_coop"",""chicken"", ""food_stall"",""food_stall"", ""dairy_farm"",""dairy"", ""lumber_mill"",""lumber"", ""train_station"",""station"", ""coffee_b"&"onsai"",""bonsai"", normalized ), ""building.""&buildingKey&""@""&level )"),"building.windmill@2") -> building.windmill@2 | J17: Windmill lvl. 2 | K17: More efficient Flour crafting.
