Workbook
Name AllDependencies: _xlfn.VSTACK( _xlfn.HSTACK(tblDependencies[TargetID],tblDependencies[DependencyID]), _xlfn.HSTACK(tblQuestObjectives[QuestTargetID],tblQuestObjectives[ObjectiveID]) )
Name craftifactNames: #REF!
Name NormalizePrereqs: _xlfn.LAMBDA(_xlpm.txt,_xlfn.LET(_xlpm.t,_xlpm.txt,TRIM(SUBSTITUTE(SUBSTITUTE(SUBSTITUTE(SUBSTITUTE(SUBSTITUTE(_xlpm.t,CHAR(10),"|"),"<br/>","|"),"<br>","|"),"/","|"),"\","|"))))
Name Slicer_ChainAwareStatus: #N/A
Name Slicer_PlayerCompleted: #N/A
Name Slicer_PlayerPaid: #N/A
Name Slicer_TargetCompleted: #N/A
Name Slicer_TargetFunded: #N/A
Name Slicer_TargetType: #N/A
Name Slicer_TargetType1: #N/A

Sheet README

Sheet Player
A1: Setting | B1: Value | C1: PlayerStateID | D1: Description | E1: Note | G1: Player Type | H1: Active | K1: Active
A2: Character Level | B2: 1 | C2: state.character_level | D2: Current player level | E2: Only needs to be tracked until level 80 | K2: Passive
A3: Cartographer | B3: 0 | C3: state.character_cartographer | D3: Current cartographer level | E3: Only needs to be tracked until level 4
A4: Cooking | B4: 0 | C4: state.character_cooking | D4: Current Cooking level | E4: Only needs to be tracked until level 13

Sheet Dashboard
A1: Current Cost | I1: One Away | O1: Open Quests | S1: Pending actions | V1: Funded not Complete | Y1: Select Resource | Z1: ruby | AA1: {=_xlfn._xlws.FILTER( _xlfn.HSTACK( tblCostChecklist[DisplayName], tblCostChecklist[QuantityRequired], tblCostChecklist[TargetType] ), (tblCostChecklist[ResourceID]=$Z$1)* (tblCostChecklist[PlayerPaid]=FALSE)* (tblCostChecklist[TargetCompleted]="READY"), "No ready unpaid targets require this resource" )} -> Guild Lv 2 | AB1: 1 | AC1: BUILDING
A2: Target | B2: Type | C2: Sort | D2: Funded | E2: Remaining | F2: Cost Details | I2: Target | J2: Type | K2: Missing | L2: Cost Details | O2: Active Quest | P2: Outstanding Objective | S2: Action | T2: Unlocks | V2: {=_xlfn._xlws.FILTER( _xlfn.HSTACK( tblTargetStatus[DisplayName], tblTargetStatus[TargetType] ), (tblTargetStatus[Status]="READY")* (tblTargetStatus[TargetFunded]=TRUE), "No funded targets waiting for completion" )} -> No funded targets waiting for completion
A3: {=_xlfn.LET( _xlpm.data, _xlfn._xlws.FILTER( _xlfn.HSTACK( tblTargetStatus[DisplayName], tblTargetStatus[TargetType], tblTargetStatus[PlayerSort], tblTargetStatus[FundingPercent], tblTargetStatus[RemainingRequirements], tblTargetStatus[OutstandingResources] ), (tblTargetStatus[Status]="READY")* (tblTargetStatus[PlayerCompleted]=FALSE)* (tblTargetStatus[HasCost]=TRUE)* (tblTargetStatus[TargetFunded]=FALSE), "" ), IF( AND(ROWS(_xlpm.data)=1,INDEX(_xlpm.data,1,1)=""), "Nothing currently waiting for payment", _xlfn.SORTBY( _xlpm.data, _xlfn.CHOOSECOLS(_xlpm.data,3)="",1, _xlfn.CHOOSECOLS(_xlpm.data,3),1 ) ) )} -> Guild Lv 2 | B3: BUILDING | C3: 1 | D3: 0 | E3: 4 | F3: ruby: 1, coin: 50, wood: 50, stone: 50 | I3: {=_xlfn._xlws.FILTER( _xlfn.HSTACK( tblTargetStatus[DisplayName], tblTargetStatus[TargetType], tblTargetStatus[FirstMissingDependency], IFERROR(tblTargetStatus[Cost],"") ), (tblTargetStatus[ChainAwareStatus]="ONE AWAY")* (tblTargetStatus[PlayerCompleted]=FALSE)* (tblTargetStatus[completionmethod]="PLAYER"), "Nothing one step away" )} -> Alchemist's Hut Lv 1 | J3: BUILDING | K3: Character Level@6 | L3: 1 ruby,140 coin,70 wood,70 stone | O3: {=_xlfn._xlws.FILTER( _xlfn.HSTACK( tblQuestObjectives[QuestDisplayName], tblQuestObjectives[ObjectiveDisplayName] ), (tblQuestObjectives[Outstanding])* (tblQuestObjectives[activequest]), "No active quests" )} -> No active quests | S3: {=_xlfn._xlws.FILTER( _xlfn.HSTACK( tblTargetStatus[DisplayName], tblTargetStatus[PendingQuestAcceptances] ), (tblTargetStatus[Status]="READY")* (tblTargetStatus[TargetType]="STATE")* (tblTargetStatus[PlayerCompleted]=FALSE)* (tblTargetStatus[PendingQuestAcceptances]<>""), "No pending quest acceptance actions" )} -> No pending quest acceptance actions
I4: Bonsai Lv 1 | J4: BUILDING | K4: Character Level@21 | L4: 3 ruby,500 coin,500 plank,120 beans
I5: Bridge Lv 1 | J5: BUILDING | K5: Character Level@30 | L5: 4 ruby,1000 coin,400 beam,1000 plank,400 stone,100 steel
I6: Chicken Lv 1 | J6: BUILDING | K6: Character Level@15 | L6: 2 ruby,400 coin,400 beam,200 stone,20 wheat,10 thread,1 egg
I7: Dungeon Lv 1 | J7: BUILDING | K7: Character Level@10 | L7: 1 ruby,300 coin,200 wood,50 stone,100 steel,30 fan
I8: Field Lv 1 | J8: BUILDING | K8: Character Level@7 | L8: 1 ruby,200 coin,100 wood,20 chemicals
I9: Food Stall Lv 1 | J9: BUILDING | K9: Character Level@8 | L9: 1 ruby,300 coin,150 wood,150 stone,20 rice
I10: Furnace Lv 1 | J10: BUILDING | K10: Character Level@8 | L10: 1 ruby,200 coin,100 wood,100 stone
I11: Garden Lv 1 | J11: BUILDING | K11: Character Level@12 | L11: 1 ruby,400 coin,200 wood,100 stone
I12: Gong Lv 1 | J12: BUILDING | K12: Character Level@10 | L12: 3 ruby,200 coin,100 wood,50 stone,50 steel
I13: Guild Lv 3 | J13: BUILDING | K13: Guild Lv 2 | L13: 2 ruby,150 coin,300 beam,150 stone
I14: Lumber Lv 1 | J14: BUILDING | K14: Character Level@11 | L14: 1 ruby,300 coin,150 wood,150 stone
I15: Onsen Lv 1 | J15: BUILDING | K15: Character Level@20 | L15: 3 ruby,500 coin,500 plank,400 stone
... I22: Workshop Lv 1 | J22: BUILDING | K22: Character Level@2 | L22: 1 ruby,20 coin,10 wood,10 stone

Sheet Checklist
A1: TargetID | B1: DisplayName | C1: Successors | D1: TargetType | E1: ChainAwareStatus | F1: PlayerSort | G1: PlayerCompleted | H1: TargetFunded | I1: Recommended
A2: building.airship@1 | B2: =_xlfn.XLOOKUP(tblChecklist[[#This Row],[TargetID]],tblTargets[TargetID],tblTargets[DisplayName]) -> Airship Lv 1 | C2: =_xlfn.XLOOKUP( tblChecklist[[#This Row],[TargetID]], tblTargetStatus[TargetID], tblTargetStatus[successors], "" ) -> Airship Lv 2, Astrolabe, Cinema Projector, Dagger, Helmet, Safe, Telescope, Tetrachloroaurate, Festival Returns Accepted, Quest for Knowledge Chapter 5 Accepted | D2: BUILDING | E2: =_xlfn.XLOOKUP(tblChecklist[[#This Row],[TargetID]],tblTargetStatus[TargetID],tblTargetStatus[ChainAwareStatus],"") -> BLOCKED | F2: 44 | G2: FALSE | H2: =_xlfn.XLOOKUP(tblChecklist[[#This Row],[TargetID]],tblTargetStatus[TargetID],tblTargetStatus[TargetFunded],"") -> FALSE | I2: =IF( tblChecklist[[#This Row],[TargetType]]<>"BUILDING", "", IF( Player!$H$1="Active", _xlfn.XLOOKUP( tblChecklist[[#This Row],[TargetID]], tblrecommended[ActiveTargetID], tblrecommended[Order], "" ), _xlfn.XLOOKUP( tblChecklist[[#This Row],[TargetID]], tblrecommended[PassiveTargetID], tblrecommended[Order], "" ) ) ) -> 44
A3: building.airship@2 | B3: =_xlfn.XLOOKUP(tblChecklist[[#This Row],[TargetID]],tblTargets[TargetID],tblTargets[DisplayName]) -> Airship Lv 2 | C3: =_xlfn.XLOOKUP( tblChecklist[[#This Row],[TargetID]], tblTargetStatus[TargetID], tblTargetStatus[successors], "" ) -> Airship maxed | D3: BUILDING | E3: =_xlfn.XLOOKUP(tblChecklist[[#This Row],[TargetID]],tblTargetStatus[TargetID],tblTargetStatus[ChainAwareStatus],"") -> BLOCKED | F3: 45 | G3: FALSE | H3: =_xlfn.XLOOKUP(tblChecklist[[#This Row],[TargetID]],tblTargetStatus[TargetID],tblTargetStatus[TargetFunded],"") -> FALSE | I3: =IF( tblChecklist[[#This Row],[TargetType]]<>"BUILDING", "", IF( Player!$H$1="Active", _xlfn.XLOOKUP( tblChecklist[[#This Row],[TargetID]], tblrecommended[ActiveTargetID], tblrecommended[Order], "" ), _xlfn.XLOOKUP( tblChecklist[[#This Row],[TargetID]], tblrecommended[PassiveTargetID], tblrecommended[Order], "" ) ) ) -> 45
A4: building.alchemists_hut@1 | B4: =_xlfn.XLOOKUP(tblChecklist[[#This Row],[TargetID]],tblTargets[TargetID],tblTargets[DisplayName]) -> Alchemist's Hut Lv 1 | C4: =_xlfn.XLOOKUP( tblChecklist[[#This Row],[TargetID]], tblTargetStatus[TargetID], tblTargetStatus[successors], "" ) -> Alchemist's Hut Lv 2 | D4: BUILDING | E4: =_xlfn.XLOOKUP(tblChecklist[[#This Row],[TargetID]],tblTargetStatus[TargetID],tblTargetStatus[ChainAwareStatus],"") -> ONE AWAY | F4: 4 | G4: FALSE | H4: =_xlfn.XLOOKUP(tblChecklist[[#This Row],[TargetID]],tblTargetStatus[TargetID],tblTargetStatus[TargetFunded],"") -> FALSE | I4: =IF( tblChecklist[[#This Row],[TargetType]]<>"BUILDING", "", IF( Player!$H$1="Active", _xlfn.XLOOKUP( tblChecklist[[#This Row],[TargetID]], tblrecommended[ActiveTargetID], tblrecommended[Order], "" ), _xlfn.XLOOKUP( tblChecklist[[#This Row],[TargetID]], tblrecommended[PassiveTargetID], tblrecommended[Order], "" ) ) ) -> 4
A5: building.alchemists_hut@2 | B5: =_xlfn.XLOOKUP(tblChecklist[[#This Row],[TargetID]],tblTargets[TargetID],tblTargets[DisplayName]) -> Alchemist's Hut Lv 2 | C5: =_xlfn.XLOOKUP( tblChecklist[[#This Row],[TargetID]], tblTargetStatus[TargetID], tblTargetStatus[successors], "" ) -> Alchemist's Hut Lv 3 | D5: BUILDING | E5: =_xlfn.XLOOKUP(tblChecklist[[#This Row],[TargetID]],tblTargetStatus[TargetID],tblTargetStatus[ChainAwareStatus],"") -> BLOCKED | F5: 5 | G5: FALSE | H5: =_xlfn.XLOOKUP(tblChecklist[[#This Row],[TargetID]],tblTargetStatus[TargetID],tblTargetStatus[TargetFunded],"") -> FALSE | I5: =IF( tblChecklist[[#This Row],[TargetType]]<>"BUILDING", "", IF( Player!$H$1="Active", _xlfn.XLOOKUP( tblChecklist[[#This Row],[TargetID]], tblrecommended[ActiveTargetID], tblrecommended[Order], "" ), _xlfn.XLOOKUP( tblChecklist[[#This Row],[TargetID]], tblrecommended[PassiveTargetID], tblrecommended[Order], "" ) ) ) -> 5
A6: building.alchemists_hut@3 | B6: =_xlfn.XLOOKUP(tblChecklist[[#This Row],[TargetID]],tblTargets[TargetID],tblTargets[DisplayName]) -> Alchemist's Hut Lv 3 | C6: =_xlfn.XLOOKUP( tblChecklist[[#This Row],[TargetID]], tblTargetStatus[TargetID], tblTargetStatus[successors], "" ) -> Alchemist's Hut Lv 4 | D6: BUILDING | E6: =_xlfn.XLOOKUP(tblChecklist[[#This Row],[TargetID]],tblTargetStatus[TargetID],tblTargetStatus[ChainAwareStatus],"") -> BLOCKED | F6: 51 | G6: FALSE | H6: =_xlfn.XLOOKUP(tblChecklist[[#This Row],[TargetID]],tblTargetStatus[TargetID],tblTargetStatus[TargetFunded],"") -> FALSE | I6: =IF( tblChecklist[[#This Row],[TargetType]]<>"BUILDING", "", IF( Player!$H$1="Active", _xlfn.XLOOKUP( tblChecklist[[#This Row],[TargetID]], tblrecommended[ActiveTargetID], tblrecommended[Order], "" ), _xlfn.XLOOKUP( tblChecklist[[#This Row],[TargetID]], tblrecommended[PassiveTargetID], tblrecommended[Order], "" ) ) ) -> 51
A7: building.alchemists_hut@4 | B7: =_xlfn.XLOOKUP(tblChecklist[[#This Row],[TargetID]],tblTargets[TargetID],tblTargets[DisplayName]) -> Alchemist's Hut Lv 4 | C7: =_xlfn.XLOOKUP( tblChecklist[[#This Row],[TargetID]], tblTargetStatus[TargetID], tblTargetStatus[successors], "" ) -> Alchemist's Hut Lv 5 | D7: BUILDING | E7: =_xlfn.XLOOKUP(tblChecklist[[#This Row],[TargetID]],tblTargetStatus[TargetID],tblTargetStatus[ChainAwareStatus],"") -> BLOCKED | F7: 52 | G7: FALSE | H7: =_xlfn.XLOOKUP(tblChecklist[[#This Row],[TargetID]],tblTargetStatus[TargetID],tblTargetStatus[TargetFunded],"") -> FALSE | I7: =IF( tblChecklist[[#This Row],[TargetType]]<>"BUILDING", "", IF( Player!$H$1="Active", _xlfn.XLOOKUP( tblChecklist[[#This Row],[TargetID]], tblrecommended[ActiveTargetID], tblrecommended[Order], "" ), _xlfn.XLOOKUP( tblChecklist[[#This Row],[TargetID]], tblrecommended[PassiveTargetID], tblrecommended[Order], "" ) ) ) -> 52
A8: building.alchemists_hut@5 | B8: =_xlfn.XLOOKUP(tblChecklist[[#This Row],[TargetID]],tblTargets[TargetID],tblTargets[DisplayName]) -> Alchemist's Hut Lv 5 | C8: =_xlfn.XLOOKUP( tblChecklist[[#This Row],[TargetID]], tblTargetStatus[TargetID], tblTargetStatus[successors], "" ) -> Alchemist's Hut Lv 6 | D8: BUILDING | E8: =_xlfn.XLOOKUP(tblChecklist[[#This Row],[TargetID]],tblTargetStatus[TargetID],tblTargetStatus[ChainAwareStatus],"") -> BLOCKED | F8: 53 | G8: FALSE | H8: =_xlfn.XLOOKUP(tblChecklist[[#This Row],[TargetID]],tblTargetStatus[TargetID],tblTargetStatus[TargetFunded],"") -> FALSE | I8: =IF( tblChecklist[[#This Row],[TargetType]]<>"BUILDING", "", IF( Player!$H$1="Active", _xlfn.XLOOKUP( tblChecklist[[#This Row],[TargetID]], tblrecommended[ActiveTargetID], tblrecommended[Order], "" ), _xlfn.XLOOKUP( tblChecklist[[#This Row],[TargetID]], tblrecommended[PassiveTargetID], tblrecommended[Order], "" ) ) ) -> 53
A9: building.alchemists_hut@6 | B9: =_xlfn.XLOOKUP(tblChecklist[[#This Row],[TargetID]],tblTargets[TargetID],tblTargets[DisplayName]) -> Alchemist's Hut Lv 6 | C9: =_xlfn.XLOOKUP( tblChecklist[[#This Row],[TargetID]], tblTargetStatus[TargetID], tblTargetStatus[successors], "" ) -> Alchemists Hut maxed, Flamethrower, Tetrachloroaurate | D9: BUILDING | E9: =_xlfn.XLOOKUP(tblChecklist[[#This Row],[TargetID]],tblTargetStatus[TargetID],tblTargetStatus[ChainAwareStatus],"") -> BLOCKED | F9: 54 | G9: FALSE | H9: =_xlfn.XLOOKUP(tblChecklist[[#This Row],[TargetID]],tblTargetStatus[TargetID],tblTargetStatus[TargetFunded],"") -> FALSE | I9: =IF( tblChecklist[[#This Row],[TargetType]]<>"BUILDING", "", IF( Player!$H$1="Active", _xlfn.XLOOKUP( tblChecklist[[#This Row],[TargetID]], tblrecommended[ActiveTargetID], tblrecommended[Order], "" ), _xlfn.XLOOKUP( tblChecklist[[#This Row],[TargetID]], tblrecommended[PassiveTargetID], tblrecommended[Order], "" ) ) ) -> 54
A10: building.bonsai@1 | B10: =_xlfn.XLOOKUP(tblChecklist[[#This Row],[TargetID]],tblTargets[TargetID],tblTargets[DisplayName]) -> Bonsai Lv 1 | C10: =_xlfn.XLOOKUP( tblChecklist[[#This Row],[TargetID]], tblTargetStatus[TargetID], tblTargetStatus[successors], "" ) -> Bonsai Lv 2 | D10: BUILDING | E10: =_xlfn.XLOOKUP(tblChecklist[[#This Row],[TargetID]],tblTargetStatus[TargetID],tblTargetStatus[ChainAwareStatus],"") -> ONE AWAY | F10: 89 | G10: FALSE | H10: =_xlfn.XLOOKUP(tblChecklist[[#This Row],[TargetID]],tblTargetStatus[TargetID],tblTargetStatus[TargetFunded],"") -> FALSE | I10: =IF( tblChecklist[[#This Row],[TargetType]]<>"BUILDING", "", IF( Player!$H$1="Active", _xlfn.XLOOKUP( tblChecklist[[#This Row],[TargetID]], tblrecommended[ActiveTargetID], tblrecommended[Order], "" ), _xlfn.XLOOKUP( tblChecklist[[#This Row],[TargetID]], tblrecommended[PassiveTargetID], tblrecommended[Order], "" ) ) ) -> 89
A11: building.bonsai@2 | B11: =_xlfn.XLOOKUP(tblChecklist[[#This Row],[TargetID]],tblTargets[TargetID],tblTargets[DisplayName]) -> Bonsai Lv 2 | C11: =_xlfn.XLOOKUP( tblChecklist[[#This Row],[TargetID]], tblTargetStatus[TargetID], tblTargetStatus[successors], "" ) | D11: BUILDING | E11: =_xlfn.XLOOKUP(tblChecklist[[#This Row],[TargetID]],tblTargetStatus[TargetID],tblTargetStatus[ChainAwareStatus],"") -> BLOCKED | F11: 90 | G11: FALSE | H11: =_xlfn.XLOOKUP(tblChecklist[[#This Row],[TargetID]],tblTargetStatus[TargetID],tblTargetStatus[TargetFunded],"") -> FALSE | I11: =IF( tblChecklist[[#This Row],[TargetType]]<>"BUILDING", "", IF( Player!$H$1="Active", _xlfn.XLOOKUP( tblChecklist[[#This Row],[TargetID]], tblrecommended[ActiveTargetID], tblrecommended[Order], "" ), _xlfn.XLOOKUP( tblChecklist[[#This Row],[TargetID]], tblrecommended[PassiveTargetID], tblrecommended[Order], "" ) ) ) -> 90
A12: building.bridge@1 | B12: =_xlfn.XLOOKUP(tblChecklist[[#This Row],[TargetID]],tblTargets[TargetID],tblTargets[DisplayName]) -> Bridge Lv 1 | C12: =_xlfn.XLOOKUP( tblChecklist[[#This Row],[TargetID]], tblTargetStatus[TargetID], tblTargetStatus[successors], "" ) -> Airship Lv 1, Bridge maxed, Caravan Lv 1, Outpost Lv 1, Station Lv 1, Tailor Lv 1, Guild Banner, Guild Codex, Guild Supplies, Festival Accepted, Honor, Glory, Sushi Accepted, Silk Road Accepted | D12: BUILDING | E12: =_xlfn.XLOOKUP(tblChecklist[[#This Row],[TargetID]],tblTargetStatus[TargetID],tblTargetStatus[ChainAwareStatus],"") -> ONE AWAY | F12: 27 | G12: FALSE | H12: =_xlfn.XLOOKUP(tblChecklist[[#This Row],[TargetID]],tblTargetStatus[TargetID],tblTargetStatus[TargetFunded],"") -> FALSE | I12: =IF( tblChecklist[[#This Row],[TargetType]]<>"BUILDING", "", IF( Player!$H$1="Active", _xlfn.XLOOKUP( tblChecklist[[#This Row],[TargetID]], tblrecommended[ActiveTargetID], tblrecommended[Order], "" ), _xlfn.XLOOKUP( tblChecklist[[#This Row],[TargetID]], tblrecommended[PassiveTargetID], tblrecommended[Order], "" ) ) ) -> 27
A13: building.caravan@1 | B13: =_xlfn.XLOOKUP(tblChecklist[[#This Row],[TargetID]],tblTargets[TargetID],tblTargets[DisplayName]) -> Caravan Lv 1 | C13: =_xlfn.XLOOKUP( tblChecklist[[#This Row],[TargetID]], tblTargetStatus[TargetID], tblTargetStatus[successors], "" ) -> Caravan Lv 2 | D13: BUILDING | E13: =_xlfn.XLOOKUP(tblChecklist[[#This Row],[TargetID]],tblTargetStatus[TargetID],tblTargetStatus[ChainAwareStatus],"") -> BLOCKED | F13: 36 | G13: FALSE | H13: =_xlfn.XLOOKUP(tblChecklist[[#This Row],[TargetID]],tblTargetStatus[TargetID],tblTargetStatus[TargetFunded],"") -> FALSE | I13: =IF( tblChecklist[[#This Row],[TargetType]]<>"BUILDING", "", IF( Player!$H$1="Active", _xlfn.XLOOKUP( tblChecklist[[#This Row],[TargetID]], tblrecommended[ActiveTargetID], tblrecommended[Order], "" ), _xlfn.XLOOKUP( tblChecklist[[#This Row],[TargetID]], tblrecommended[PassiveTargetID], tblrecommended[Order], "" ) ) ) -> 36
... A25: building.dungeon@5 | B25: =_xlfn.XLOOKUP(tblChecklist[[#This Row],[TargetID]],tblTargets[TargetID],tblTargets[DisplayName]) -> Dungeon Lv 5 | C25: =_xlfn.XLOOKUP( tblChecklist[[#This Row],[TargetID]], tblTargetStatus[TargetID], tblTargetStatus[successors], "" ) -> dungeon maxed, Dungeon Lv 6, Attic, Courtyard, Lair lvl. 1, Tavern, Metal Detector, Magic Beans Accepted, Tame A Critter, Complete Dungeon 5C | D25: BUILDING | E25: =_xlfn.XLOOKUP(tblChecklist[[#This Row],[TargetID]],tblTargetStatus[TargetID],tblTargetStatus[ChainAwareStatus],"") -> BLOCKED | F25: 65 | G25: FALSE | H25: =_xlfn.XLOOKUP(tblChecklist[[#This Row],[TargetID]],tblTargetStatus[TargetID],tblTargetStatus[TargetFunded],"") -> FALSE | I25: =IF( tblChecklist[[#This Row],[TargetType]]<>"BUILDING", "", IF( Player!$H$1="Active", _xlfn.XLOOKUP( tblChecklist[[#This Row],[TargetID]], tblrecommended[ActiveTargetID], tblrecommended[Order], "" ), _xlfn.XLOOKUP( tblChecklist[[#This Row],[TargetID]], tblrecommended[PassiveTargetID], tblrecommended[Order], "" ) ) ) -> 65
A26: building.dungeon@6 | B26: =_xlfn.XLOOKUP(tblChecklist[[#This Row],[TargetID]],tblTargets[TargetID],tblTargets[DisplayName]) -> Dungeon Lv 6 | C26: =_xlfn.XLOOKUP( tblChecklist[[#This Row],[TargetID]], tblTargetStatus[TargetID], tblTargetStatus[successors], "" ) -> Complete Dungeon 6C | D26: BUILDING | E26: =_xlfn.XLOOKUP(tblChecklist[[#This Row],[TargetID]],tblTargetStatus[TargetID],tblTargetStatus[ChainAwareStatus],"") -> BLOCKED | G26: FALSE | H26: =_xlfn.XLOOKUP(tblChecklist[[#This Row],[TargetID]],tblTargetStatus[TargetID],tblTargetStatus[TargetFunded],"") -> N/A | I26: =IF( tblChecklist[[#This Row],[TargetType]]<>"BUILDING", "", IF( Player!$H$1="Active", _xlfn.XLOOKUP( tblChecklist[[#This Row],[TargetID]], tblrecommended[ActiveTargetID], tblrecommended[Order], "" ), _xlfn.XLOOKUP( tblChecklist[[#This Row],[TargetID]], tblrecommended[PassiveTargetID], tblrecommended[Order], "" ) ) )
A27: building.fermentory@1 | B27: =_xlfn.XLOOKUP(tblChecklist[[#This Row],[TargetID]],tblTargets[TargetID],tblTargets[DisplayName]) -> Fermentory Lv 1 | C27: =_xlfn.XLOOKUP( tblChecklist[[#This Row],[TargetID]], tblTargetStatus[TargetID], tblTargetStatus[successors], "" ) -> Fermentory Lv 2 | D27: =_xlfn.XLOOKUP(tblChecklist[[#This Row],[TargetID]],tblTargets[TargetID],tblTargets[TargetType],"") -> BUILDING | E27: =_xlfn.XLOOKUP(tblChecklist[[#This Row],[TargetID]],tblTargetStatus[TargetID],tblTargetStatus[ChainAwareStatus],"") -> BLOCKED | F27: 72 | G27: FALSE | H27: =_xlfn.XLOOKUP(tblChecklist[[#This Row],[TargetID]],tblTargetStatus[TargetID],tblTargetStatus[TargetFunded],"") -> FALSE | I27: =IF( tblChecklist[[#This Row],[TargetType]]<>"BUILDING", "", IF( Player!$H$1="Active", _xlfn.XLOOKUP( tblChecklist[[#This Row],[TargetID]], tblrecommended[ActiveTargetID], tblrecommended[Order], "" ), _xlfn.XLOOKUP( tblChecklist[[#This Row],[TargetID]], tblrecommended[PassiveTargetID], tblrecommended[Order], "" ) ) ) -> 72
A28: building.fermentory@2 | B28: =_xlfn.XLOOKUP(tblChecklist[[#This Row],[TargetID]],tblTargets[TargetID],tblTargets[DisplayName]) -> Fermentory Lv 2 | C28: =_xlfn.XLOOKUP( tblChecklist[[#This Row],[TargetID]], tblTargetStatus[TargetID], tblTargetStatus[successors], "" ) -> Fermentory Lv 3 | D28: =_xlfn.XLOOKUP(tblChecklist[[#This Row],[TargetID]],tblTargets[TargetID],tblTargets[TargetType],"") -> BUILDING | E28: =_xlfn.XLOOKUP(tblChecklist[[#This Row],[TargetID]],tblTargetStatus[TargetID],tblTargetStatus[ChainAwareStatus],"") -> BLOCKED | F28: 73 | G28: FALSE | H28: =_xlfn.XLOOKUP(tblChecklist[[#This Row],[TargetID]],tblTargetStatus[TargetID],tblTargetStatus[TargetFunded],"") -> FALSE | I28: =IF( tblChecklist[[#This Row],[TargetType]]<>"BUILDING", "", IF( Player!$H$1="Active", _xlfn.XLOOKUP( tblChecklist[[#This Row],[TargetID]], tblrecommended[ActiveTargetID], tblrecommended[Order], "" ), _xlfn.XLOOKUP( tblChecklist[[#This Row],[TargetID]], tblrecommended[PassiveTargetID], tblrecommended[Order], "" ) ) ) -> 73
A29: building.fermentory@3 | B29: =_xlfn.XLOOKUP(tblChecklist[[#This Row],[TargetID]],tblTargets[TargetID],tblTargets[DisplayName]) -> Fermentory Lv 3 | C29: =_xlfn.XLOOKUP( tblChecklist[[#This Row],[TargetID]], tblTargetStatus[TargetID], tblTargetStatus[successors], "" ) -> Fermentory Lv 4 | D29: =_xlfn.XLOOKUP(tblChecklist[[#This Row],[TargetID]],tblTargets[TargetID],tblTargets[TargetType],"") -> BUILDING | E29: =_xlfn.XLOOKUP(tblChecklist[[#This Row],[TargetID]],tblTargetStatus[TargetID],tblTargetStatus[ChainAwareStatus],"") -> BLOCKED | F29: 74 | G29: FALSE | H29: =_xlfn.XLOOKUP(tblChecklist[[#This Row],[TargetID]],tblTargetStatus[TargetID],tblTargetStatus[TargetFunded],"") -> FALSE | I29: =IF( tblChecklist[[#This Row],[TargetType]]<>"BUILDING", "", IF( Player!$H$1="Active", _xlfn.XLOOKUP( tblChecklist[[#This Row],[TargetID]], tblrecommended[ActiveTargetID], tblrecommended[Order], "" ), _xlfn.XLOOKUP( tblChecklist[[#This Row],[TargetID]], tblrecommended[PassiveTargetID], tblrecommended[Order], "" ) ) ) -> 74
A30: building.fermentory@4 | B30: =_xlfn.XLOOKUP(tblChecklist[[#This Row],[TargetID]],tblTargets[TargetID],tblTargets[DisplayName]) -> Fermentory Lv 4 | C30: =_xlfn.XLOOKUP( tblChecklist[[#This Row],[TargetID]], tblTargetStatus[TargetID], tblTargetStatus[successors], "" ) -> Fermentory Lv 5 | D30: =_xlfn.XLOOKUP(tblChecklist[[#This Row],[TargetID]],tblTargets[TargetID],tblTargets[TargetType],"") -> BUILDING | E30: =_xlfn.XLOOKUP(tblChecklist[[#This Row],[TargetID]],tblTargetStatus[TargetID],tblTargetStatus[ChainAwareStatus],"") -> BLOCKED | F30: 79 | G30: FALSE | H30: =_xlfn.XLOOKUP(tblChecklist[[#This Row],[TargetID]],tblTargetStatus[TargetID],tblTargetStatus[TargetFunded],"") -> FALSE | I30: =IF( tblChecklist[[#This Row],[TargetType]]<>"BUILDING", "", IF( Player!$H$1="Active", _xlfn.XLOOKUP( tblChecklist[[#This Row],[TargetID]], tblrecommended[ActiveTargetID], tblrecommended[Order], "" ), _xlfn.XLOOKUP( tblChecklist[[#This Row],[TargetID]], tblrecommended[PassiveTargetID], tblrecommended[Order], "" ) ) ) -> 79
A31: building.fermentory@5 | B31: =_xlfn.XLOOKUP(tblChecklist[[#This Row],[TargetID]],tblTargets[TargetID],tblTargets[DisplayName]) -> Fermentory Lv 5 | C31: =_xlfn.XLOOKUP( tblChecklist[[#This Row],[TargetID]], tblTargetStatus[TargetID], tblTargetStatus[successors], "" ) -> Fermentory Lv 6 | D31: =_xlfn.XLOOKUP(tblChecklist[[#This Row],[TargetID]],tblTargets[TargetID],tblTargets[TargetType],"") -> BUILDING | E31: =_xlfn.XLOOKUP(tblChecklist[[#This Row],[TargetID]],tblTargetStatus[TargetID],tblTargetStatus[ChainAwareStatus],"") -> BLOCKED | F31: 80 | G31: FALSE | H31: =_xlfn.XLOOKUP(tblChecklist[[#This Row],[TargetID]],tblTargetStatus[TargetID],tblTargetStatus[TargetFunded],"") -> FALSE | I31: =IF( tblChecklist[[#This Row],[TargetType]]<>"BUILDING", "", IF( Player!$H$1="Active", _xlfn.XLOOKUP( tblChecklist[[#This Row],[TargetID]], tblrecommended[ActiveTargetID], tblrecommended[Order], "" ), _xlfn.XLOOKUP( tblChecklist[[#This Row],[TargetID]], tblrecommended[PassiveTargetID], tblrecommended[Order], "" ) ) ) -> 80
A32: building.fermentory@6 | B32: =_xlfn.XLOOKUP(tblChecklist[[#This Row],[TargetID]],tblTargets[TargetID],tblTargets[DisplayName]) -> Fermentory Lv 6 | C32: =_xlfn.XLOOKUP( tblChecklist[[#This Row],[TargetID]], tblTargetStatus[TargetID], tblTargetStatus[successors], "" ) -> Fermentory maxed, Festival of Beans Accepted | D32: =_xlfn.XLOOKUP(tblChecklist[[#This Row],[TargetID]],tblTargets[TargetID],tblTargets[TargetType],"") -> BUILDING | E32: =_xlfn.XLOOKUP(tblChecklist[[#This Row],[TargetID]],tblTargetStatus[TargetID],tblTargetStatus[ChainAwareStatus],"") -> BLOCKED | F32: 81 | G32: FALSE | H32: =_xlfn.XLOOKUP(tblChecklist[[#This Row],[TargetID]],tblTargetStatus[TargetID],tblTargetStatus[TargetFunded],"") -> FALSE | I32: =IF( tblChecklist[[#This Row],[TargetType]]<>"BUILDING", "", IF( Player!$H$1="Active", _xlfn.XLOOKUP( tblChecklist[[#This Row],[TargetID]], tblrecommended[ActiveTargetID], tblrecommended[Order], "" ), _xlfn.XLOOKUP( tblChecklist[[#This Row],[TargetID]], tblrecommended[PassiveTargetID], tblrecommended[Order], "" ) ) ) -> 81
A33: building.field@1 | B33: =_xlfn.XLOOKUP(tblChecklist[[#This Row],[TargetID]],tblTargets[TargetID],tblTargets[DisplayName]) -> Field Lv 1 | C33: =_xlfn.XLOOKUP( tblChecklist[[#This Row],[TargetID]], tblTargetStatus[TargetID], tblTargetStatus[successors], "" ) -> Field Lv 2, Quest for Knowledge Chapter 1 Finished | D33: =_xlfn.XLOOKUP(tblChecklist[[#This Row],[TargetID]],tblTargets[TargetID],tblTargets[TargetType],"") -> BUILDING | E33: =_xlfn.XLOOKUP(tblChecklist[[#This Row],[TargetID]],tblTargetStatus[TargetID],tblTargetStatus[ChainAwareStatus],"") -> ONE AWAY | F33: 6 | G33: FALSE | H33: =_xlfn.XLOOKUP(tblChecklist[[#This Row],[TargetID]],tblTargetStatus[TargetID],tblTargetStatus[TargetFunded],"") -> FALSE | I33: =IF( tblChecklist[[#This Row],[TargetType]]<>"BUILDING", "", IF( Player!$H$1="Active", _xlfn.XLOOKUP( tblChecklist[[#This Row],[TargetID]], tblrecommended[ActiveTargetID], tblrecommended[Order], "" ), _xlfn.XLOOKUP( tblChecklist[[#This Row],[TargetID]], tblrecommended[PassiveTargetID], tblrecommended[Order], "" ) ) ) -> 6
A34: building.field@2 | B34: =_xlfn.XLOOKUP(tblChecklist[[#This Row],[TargetID]],tblTargets[TargetID],tblTargets[DisplayName]) -> Field Lv 2 | C34: =_xlfn.XLOOKUP( tblChecklist[[#This Row],[TargetID]], tblTargetStatus[TargetID], tblTargetStatus[successors], "" ) -> Field maxed | D34: =_xlfn.XLOOKUP(tblChecklist[[#This Row],[TargetID]],tblTargets[TargetID],tblTargets[TargetType],"") -> BUILDING | E34: =_xlfn.XLOOKUP(tblChecklist[[#This Row],[TargetID]],tblTargetStatus[TargetID],tblTargetStatus[ChainAwareStatus],"") -> BLOCKED | F34: 8 | G34: FALSE | H34: =_xlfn.XLOOKUP(tblChecklist[[#This Row],[TargetID]],tblTargetStatus[TargetID],tblTargetStatus[TargetFunded],"") -> FALSE | I34: =IF( tblChecklist[[#This Row],[TargetType]]<>"BUILDING", "", IF( Player!$H$1="Active", _xlfn.XLOOKUP( tblChecklist[[#This Row],[TargetID]], tblrecommended[ActiveTargetID], tblrecommended[Order], "" ), _xlfn.XLOOKUP( tblChecklist[[#This Row],[TargetID]], tblrecommended[PassiveTargetID], tblrecommended[Order], "" ) ) ) -> 8
A35: building.food_stall@1 | B35: =_xlfn.XLOOKUP(tblChecklist[[#This Row],[TargetID]],tblTargets[TargetID],tblTargets[DisplayName]) -> Food Stall Lv 1 | C35: =_xlfn.XLOOKUP( tblChecklist[[#This Row],[TargetID]], tblTargetStatus[TargetID], tblTargetStatus[successors], "" ) -> Food Stall Lv 2, Quest for Knowledge Chapter 1 Finished | D35: =_xlfn.XLOOKUP(tblChecklist[[#This Row],[TargetID]],tblTargets[TargetID],tblTargets[TargetType],"") -> BUILDING | E35: =_xlfn.XLOOKUP(tblChecklist[[#This Row],[TargetID]],tblTargetStatus[TargetID],tblTargetStatus[ChainAwareStatus],"") -> ONE AWAY | F35: 7 | G35: FALSE | H35: =_xlfn.XLOOKUP(tblChecklist[[#This Row],[TargetID]],tblTargetStatus[TargetID],tblTargetStatus[TargetFunded],"") -> FALSE | I35: =IF( tblChecklist[[#This Row],[TargetType]]<>"BUILDING", "", IF( Player!$H$1="Active", _xlfn.XLOOKUP( tblChecklist[[#This Row],[TargetID]], tblrecommended[ActiveTargetID], tblrecommended[Order], "" ), _xlfn.XLOOKUP( tblChecklist[[#This Row],[TargetID]], tblrecommended[PassiveTargetID], tblrecommended[Order], "" ) ) ) -> 7
A36: building.food_stall@2 | B36: =_xlfn.XLOOKUP(tblChecklist[[#This Row],[TargetID]],tblTargets[TargetID],tblTargets[DisplayName]) -> Food Stall Lv 2 | C36: =_xlfn.XLOOKUP( tblChecklist[[#This Row],[TargetID]], tblTargetStatus[TargetID], tblTargetStatus[successors], "" ) -> Food Stall Lv 3, Shogun's Katana Chapter 3 Finished | D36: =_xlfn.XLOOKUP(tblChecklist[[#This Row],[TargetID]],tblTargets[TargetID],tblTargets[TargetType],"") -> BUILDING | E36: =_xlfn.XLOOKUP(tblChecklist[[#This Row],[TargetID]],tblTargetStatus[TargetID],tblTargetStatus[ChainAwareStatus],"") -> BLOCKED | F36: 25 | G36: FALSE | H36: =_xlfn.XLOOKUP(tblChecklist[[#This Row],[TargetID]],tblTargetStatus[TargetID],tblTargetStatus[TargetFunded],"") -> FALSE | I36: =IF( tblChecklist[[#This Row],[TargetType]]<>"BUILDING", "", IF( Player!$H$1="Active", _xlfn.XLOOKUP( tblChecklist[[#This Row],[TargetID]], tblrecommended[ActiveTargetID], tblrecommended[Order], "" ), _xlfn.XLOOKUP( tblChecklist[[#This Row],[TargetID]], tblrecommended[PassiveTargetID], tblrecommended[Order], "" ) ) ) -> 25
A37: building.food_stall@3 | B37: =_xlfn.XLOOKUP(tblChecklist[[#This Row],[TargetID]],tblTargets[TargetID],tblTargets[DisplayName]) -> Food Stall Lv 3 | C37: =_xlfn.XLOOKUP( tblChecklist[[#This Row],[TargetID]], tblTargetStatus[TargetID], tblTargetStatus[successors], "" ) -> Food stall maxed, Guild Supplies, Shogun's Katana Chapter 6 Finished | D37: =_xlfn.XLOOKUP(tblChecklist[[#This Row],[TargetID]],tblTargets[TargetID],tblTargets[TargetType],"") -> BUILDING | E37: =_xlfn.XLOOKUP(tblChecklist[[#This Row],[TargetID]],tblTargetStatus[TargetID],tblTargetStatus[ChainAwareStatus],"") -> BLOCKED | F37: 26 | G37: FALSE | H37: =_xlfn.XLOOKUP(tblChecklist[[#This Row],[TargetID]],tblTargetStatus[TargetID],tblTargetStatus[TargetFunded],"") -> FALSE | I37: =IF( tblChecklist[[#This Row],[TargetType]]<>"BUILDING", "", IF( Player!$H$1="Active", _xlfn.XLOOKUP( tblChecklist[[#This Row],[TargetID]], tblrecommended[ActiveTargetID], tblrecommended[Order], "" ), _xlfn.XLOOKUP( tblChecklist[[#This Row],[TargetID]], tblrecommended[PassiveTargetID], tblrecommended[Order], "" ) ) ) -> 26
A38: building.furnace@1 | B38: =_xlfn.XLOOKUP(tblChecklist[[#This Row],[TargetID]],tblTargets[TargetID],tblTargets[DisplayName]) -> Furnace Lv 1 | C38: =_xlfn.XLOOKUP( tblChecklist[[#This Row],[TargetID]], tblTargetStatus[TargetID], tblTargetStatus[successors], "" ) -> Furnace Lv 2, Shogun's Katana Chapter 1 Finished | D38: =_xlfn.XLOOKUP(tblChecklist[[#This Row],[TargetID]],tblTargets[TargetID],tblTargets[TargetType],"") -> BUILDING | E38: =_xlfn.XLOOKUP(tblChecklist[[#This Row],[TargetID]],tblTargetStatus[TargetID],tblTargetStatus[ChainAwareStatus],"") -> ONE AWAY | F38: 10 | G38: FALSE | H38: =_xlfn.XLOOKUP(tblChecklist[[#This Row],[TargetID]],tblTargetStatus[TargetID],tblTargetStatus[TargetFunded],"") -> FALSE | I38: =IF( tblChecklist[[#This Row],[TargetType]]<>"BUILDING", "", IF( Player!$H$1="Active", _xlfn.XLOOKUP( tblChecklist[[#This Row],[TargetID]], tblrecommended[ActiveTargetID], tblrecommended[Order], "" ), _xlfn.XLOOKUP( tblChecklist[[#This Row],[TargetID]], tblrecommended[PassiveTargetID], tblrecommended[Order], "" ) ) ) -> 10
... A44: building.gong@1 | B44: =_xlfn.XLOOKUP(tblChecklist[[#This Row],[TargetID]],tblTargets[TargetID],tblTargets[DisplayName]) -> Gong Lv 1 | C44: =_xlfn.XLOOKUP( tblChecklist[[#This Row],[TargetID]], tblTargetStatus[TargetID], tblTargetStatus[successors], "" ) | D44: =_xlfn.XLOOKUP(tblChecklist[[#This Row],[TargetID]],tblTargets[TargetID],tblTargets[TargetType],"") -> BUILDING | E44: =_xlfn.XLOOKUP(tblChecklist[[#This Row],[TargetID]],tblTargetStatus[TargetID],tblTargetStatus[ChainAwareStatus],"") -> ONE AWAY | F44: 102 | G44: FALSE | H44: =_xlfn.XLOOKUP(tblChecklist[[#This Row],[TargetID]],tblTargetStatus[TargetID],tblTargetStatus[TargetFunded],"") -> FALSE | I44: =IF( tblChecklist[[#This Row],[TargetType]]<>"BUILDING", "", IF( Player!$H$1="Active", _xlfn.XLOOKUP( tblChecklist[[#This Row],[TargetID]], tblrecommended[ActiveTargetID], tblrecommended[Order], "" ), _xlfn.XLOOKUP( tblChecklist[[#This Row],[TargetID]], tblrecommended[PassiveTargetID], tblrecommended[Order], "" ) ) ) -> 102
A45: building.guild@1 | B45: =_xlfn.XLOOKUP(tblChecklist[[#This Row],[TargetID]],tblTargets[TargetID],tblTargets[DisplayName]) -> Guild Lv 1 | C45: =_xlfn.XLOOKUP( tblChecklist[[#This Row],[TargetID]], tblTargetStatus[TargetID], tblTargetStatus[successors], "" ) -> Guild Lv 2 | D45: =_xlfn.XLOOKUP(tblChecklist[[#This Row],[TargetID]],tblTargets[TargetID],tblTargets[TargetType],"") -> BUILDING | E45: =_xlfn.XLOOKUP(tblChecklist[[#This Row],[TargetID]],tblTargetStatus[TargetID],tblTargetStatus[ChainAwareStatus],"") -> COMPLETED | G45: TRUE | H45: =_xlfn.XLOOKUP(tblChecklist[[#This Row],[TargetID]],tblTargetStatus[TargetID],tblTargetStatus[TargetFunded],"") -> N/A | I45: =IF( tblChecklist[[#This Row],[TargetType]]<>"BUILDING", "", IF( Player!$H$1="Active", _xlfn.XLOOKUP( tblChecklist[[#This Row],[TargetID]], tblrecommended[ActiveTargetID], tblrecommended[Order], "" ), _xlfn.XLOOKUP( tblChecklist[[#This Row],[TargetID]], tblrecommended[PassiveTargetID], tblrecommended[Order], "" ) ) )
A46: building.guild@2 | B46: =_xlfn.XLOOKUP(tblChecklist[[#This Row],[TargetID]],tblTargets[TargetID],tblTargets[DisplayName]) -> Guild Lv 2 | C46: =_xlfn.XLOOKUP( tblChecklist[[#This Row],[TargetID]], tblTargetStatus[TargetID], tblTargetStatus[successors], "" ) -> Alchemist's Hut Lv 2, Food Stall Lv 2, Guild Lv 3, Warehouse Lv 2 | D46: =_xlfn.XLOOKUP(tblChecklist[[#This Row],[TargetID]],tblTargets[TargetID],tblTargets[TargetType],"") -> BUILDING | E46: =_xlfn.XLOOKUP(tblChecklist[[#This Row],[TargetID]],tblTargetStatus[TargetID],tblTargetStatus[ChainAwareStatus],"") -> READY | F46: 1 | G46: FALSE | H46: =_xlfn.XLOOKUP(tblChecklist[[#This Row],[TargetID]],tblTargetStatus[TargetID],tblTargetStatus[TargetFunded],"") -> FALSE | I46: =IF( tblChecklist[[#This Row],[TargetType]]<>"BUILDING", "", IF( Player!$H$1="Active", _xlfn.XLOOKUP( tblChecklist[[#This Row],[TargetID]], tblrecommended[ActiveTargetID], tblrecommended[Order], "" ), _xlfn.XLOOKUP( tblChecklist[[#This Row],[TargetID]], tblrecommended[PassiveTargetID], tblrecommended[Order], "" ) ) ) -> 1
A47: building.guild@3 | B47: =_xlfn.XLOOKUP(tblChecklist[[#This Row],[TargetID]],tblTargets[TargetID],tblTargets[DisplayName]) -> Guild Lv 3 | C47: =_xlfn.XLOOKUP( tblChecklist[[#This Row],[TargetID]], tblTargetStatus[TargetID], tblTargetStatus[successors], "" ) -> Alchemist's Hut Lv 3, Alchemist's Hut Lv 4, Guild Lv 4, Warehouse Lv 3 | D47: =_xlfn.XLOOKUP(tblChecklist[[#This Row],[TargetID]],tblTargets[TargetID],tblTargets[TargetType],"") -> BUILDING | E47: =_xlfn.XLOOKUP(tblChecklist[[#This Row],[TargetID]],tblTargetStatus[TargetID],tblTargetStatus[ChainAwareStatus],"") -> ONE AWAY | F47: 17 | G47: FALSE | H47: =_xlfn.XLOOKUP(tblChecklist[[#This Row],[TargetID]],tblTargetStatus[TargetID],tblTargetStatus[TargetFunded],"") -> FALSE | I47: =IF( tblChecklist[[#This Row],[TargetType]]<>"BUILDING", "", IF( Player!$H$1="Active", _xlfn.XLOOKUP( tblChecklist[[#This Row],[TargetID]], tblrecommended[ActiveTargetID], tblrecommended[Order], "" ), _xlfn.XLOOKUP( tblChecklist[[#This Row],[TargetID]], tblrecommended[PassiveTargetID], tblrecommended[Order], "" ) ) ) -> 17
A48: building.guild@4 | B48: =_xlfn.XLOOKUP(tblChecklist[[#This Row],[TargetID]],tblTargets[TargetID],tblTargets[DisplayName]) -> Guild Lv 4 | C48: =_xlfn.XLOOKUP( tblChecklist[[#This Row],[TargetID]], tblTargetStatus[TargetID], tblTargetStatus[successors], "" ) -> Alchemist's Hut Lv 4, Guild Lv 5, Warehouse Lv 4 | D48: =_xlfn.XLOOKUP(tblChecklist[[#This Row],[TargetID]],tblTargets[TargetID],tblTargets[TargetType],"") -> BUILDING | E48: =_xlfn.XLOOKUP(tblChecklist[[#This Row],[TargetID]],tblTargetStatus[TargetID],tblTargetStatus[ChainAwareStatus],"") -> BLOCKED | F48: 23 | G48: FALSE | H48: =_xlfn.XLOOKUP(tblChecklist[[#This Row],[TargetID]],tblTargetStatus[TargetID],tblTargetStatus[TargetFunded],"") -> FALSE | I48: =IF( tblChecklist[[#This Row],[TargetType]]<>"BUILDING", "", IF( Player!$H$1="Active", _xlfn.XLOOKUP( tblChecklist[[#This Row],[TargetID]], tblrecommended[ActiveTargetID], tblrecommended[Order], "" ), _xlfn.XLOOKUP( tblChecklist[[#This Row],[TargetID]], tblrecommended[PassiveTargetID], tblrecommended[Order], "" ) ) ) -> 23
A49: building.guild@5 | B49: =_xlfn.XLOOKUP(tblChecklist[[#This Row],[TargetID]],tblTargets[TargetID],tblTargets[DisplayName]) -> Guild Lv 5 | C49: =_xlfn.XLOOKUP( tblChecklist[[#This Row],[TargetID]], tblTargetStatus[TargetID], tblTargetStatus[successors], "" ) -> Alchemist's Hut Lv 5, Warehouse Lv 5, Emerald Tablet, Guild Codex, Historical Library, Trigonometry, Build the Guild Finished | D49: =_xlfn.XLOOKUP(tblChecklist[[#This Row],[TargetID]],tblTargets[TargetID],tblTargets[TargetType],"") -> BUILDING | E49: =_xlfn.XLOOKUP(tblChecklist[[#This Row],[TargetID]],tblTargetStatus[TargetID],tblTargetStatus[ChainAwareStatus],"") -> BLOCKED | F49: 29 | G49: FALSE | H49: =_xlfn.XLOOKUP(tblChecklist[[#This Row],[TargetID]],tblTargetStatus[TargetID],tblTargetStatus[TargetFunded],"") -> FALSE | I49: =IF( tblChecklist[[#This Row],[TargetType]]<>"BUILDING", "", IF( Player!$H$1="Active", _xlfn.XLOOKUP( tblChecklist[[#This Row],[TargetID]], tblrecommended[ActiveTargetID], tblrecommended[Order], "" ), _xlfn.XLOOKUP( tblChecklist[[#This Row],[TargetID]], tblrecommended[PassiveTargetID], tblrecommended[Order], "" ) ) ) -> 29
A50: building.guild_video_game_arcade@1 | B50: =_xlfn.XLOOKUP(tblChecklist[[#This Row],[TargetID]],tblTargets[TargetID],tblTargets[DisplayName]) -> Guild: Video Game Arcade Lv 1 | C50: =_xlfn.XLOOKUP( tblChecklist[[#This Row],[TargetID]], tblTargetStatus[TargetID], tblTargetStatus[successors], "" ) | D50: =_xlfn.XLOOKUP(tblChecklist[[#This Row],[TargetID]],tblTargets[TargetID],tblTargets[TargetType],"") -> BUILDING | E50: =_xlfn.XLOOKUP(tblChecklist[[#This Row],[TargetID]],tblTargetStatus[TargetID],tblTargetStatus[ChainAwareStatus],"") -> BLOCKED | G50: FALSE | H50: =_xlfn.XLOOKUP(tblChecklist[[#This Row],[TargetID]],tblTargetStatus[TargetID],tblTargetStatus[TargetFunded],"") -> FALSE | I50: =IF( tblChecklist[[#This Row],[TargetType]]<>"BUILDING", "", IF( Player!$H$1="Active", _xlfn.XLOOKUP( tblChecklist[[#This Row],[TargetID]], tblrecommended[ActiveTargetID], tblrecommended[Order], "" ), _xlfn.XLOOKUP( tblChecklist[[#This Row],[TargetID]], tblrecommended[PassiveTargetID], tblrecommended[Order], "" ) ) )
A51: building.laboratory@1 | B51: =_xlfn.XLOOKUP(tblChecklist[[#This Row],[TargetID]],tblTargets[TargetID],tblTargets[DisplayName]) -> Laboratory Lv 1 | C51: =_xlfn.XLOOKUP( tblChecklist[[#This Row],[TargetID]], tblTargetStatus[TargetID], tblTargetStatus[successors], "" ) -> Laboratory Lv 2 | D51: =_xlfn.XLOOKUP(tblChecklist[[#This Row],[TargetID]],tblTargets[TargetID],tblTargets[TargetType],"") -> BUILDING | E51: =_xlfn.XLOOKUP(tblChecklist[[#This Row],[TargetID]],tblTargetStatus[TargetID],tblTargetStatus[ChainAwareStatus],"") -> BLOCKED | F51: 66 | G51: FALSE | H51: =_xlfn.XLOOKUP(tblChecklist[[#This Row],[TargetID]],tblTargetStatus[TargetID],tblTargetStatus[TargetFunded],"") -> FALSE | I51: =IF( tblChecklist[[#This Row],[TargetType]]<>"BUILDING", "", IF( Player!$H$1="Active", _xlfn.XLOOKUP( tblChecklist[[#This Row],[TargetID]], tblrecommended[ActiveTargetID], tblrecommended[Order], "" ), _xlfn.XLOOKUP( tblChecklist[[#This Row],[TargetID]], tblrecommended[PassiveTargetID], tblrecommended[Order], "" ) ) ) -> 66
A52: building.laboratory@2 | B52: =_xlfn.XLOOKUP(tblChecklist[[#This Row],[TargetID]],tblTargets[TargetID],tblTargets[DisplayName]) -> Laboratory Lv 2 | C52: =_xlfn.XLOOKUP( tblChecklist[[#This Row],[TargetID]], tblTargetStatus[TargetID], tblTargetStatus[successors], "" ) -> Laboratory Lv 3 | D52: =_xlfn.XLOOKUP(tblChecklist[[#This Row],[TargetID]],tblTargets[TargetID],tblTargets[TargetType],"") -> BUILDING | E52: =_xlfn.XLOOKUP(tblChecklist[[#This Row],[TargetID]],tblTargetStatus[TargetID],tblTargetStatus[ChainAwareStatus],"") -> BLOCKED | F52: 67 | G52: FALSE | H52: =_xlfn.XLOOKUP(tblChecklist[[#This Row],[TargetID]],tblTargetStatus[TargetID],tblTargetStatus[TargetFunded],"") -> FALSE | I52: =IF( tblChecklist[[#This Row],[TargetType]]<>"BUILDING", "", IF( Player!$H$1="Active", _xlfn.XLOOKUP( tblChecklist[[#This Row],[TargetID]], tblrecommended[ActiveTargetID], tblrecommended[Order], "" ), _xlfn.XLOOKUP( tblChecklist[[#This Row],[TargetID]], tblrecommended[PassiveTargetID], tblrecommended[Order], "" ) ) ) -> 67
A53: building.laboratory@3 | B53: =_xlfn.XLOOKUP(tblChecklist[[#This Row],[TargetID]],tblTargets[TargetID],tblTargets[DisplayName]) -> Laboratory Lv 3 | C53: =_xlfn.XLOOKUP( tblChecklist[[#This Row],[TargetID]], tblTargetStatus[TargetID], tblTargetStatus[successors], "" ) -> Laboratory Lv 4 | D53: =_xlfn.XLOOKUP(tblChecklist[[#This Row],[TargetID]],tblTargets[TargetID],tblTargets[TargetType],"") -> BUILDING | E53: =_xlfn.XLOOKUP(tblChecklist[[#This Row],[TargetID]],tblTargetStatus[TargetID],tblTargetStatus[ChainAwareStatus],"") -> BLOCKED | F53: 68 | G53: FALSE | H53: =_xlfn.XLOOKUP(tblChecklist[[#This Row],[TargetID]],tblTargetStatus[TargetID],tblTargetStatus[TargetFunded],"") -> FALSE | I53: =IF( tblChecklist[[#This Row],[TargetType]]<>"BUILDING", "", IF( Player!$H$1="Active", _xlfn.XLOOKUP( tblChecklist[[#This Row],[TargetID]], tblrecommended[ActiveTargetID], tblrecommended[Order], "" ), _xlfn.XLOOKUP( tblChecklist[[#This Row],[TargetID]], tblrecommended[PassiveTargetID], tblrecommended[Order], "" ) ) ) -> 68
A54: building.laboratory@4 | B54: =_xlfn.XLOOKUP(tblChecklist[[#This Row],[TargetID]],tblTargets[TargetID],tblTargets[DisplayName]) -> Laboratory Lv 4 | C54: =_xlfn.XLOOKUP( tblChecklist[[#This Row],[TargetID]], tblTargetStatus[TargetID], tblTargetStatus[successors], "" ) -> Laboratory Lv 5 | D54: =_xlfn.XLOOKUP(tblChecklist[[#This Row],[TargetID]],tblTargets[TargetID],tblTargets[TargetType],"") -> BUILDING | E54: =_xlfn.XLOOKUP(tblChecklist[[#This Row],[TargetID]],tblTargetStatus[TargetID],tblTargetStatus[ChainAwareStatus],"") -> BLOCKED | F54: 75 | G54: FALSE | H54: =_xlfn.XLOOKUP(tblChecklist[[#This Row],[TargetID]],tblTargetStatus[TargetID],tblTargetStatus[TargetFunded],"") -> FALSE | I54: =IF( tblChecklist[[#This Row],[TargetType]]<>"BUILDING", "", IF( Player!$H$1="Active", _xlfn.XLOOKUP( tblChecklist[[#This Row],[TargetID]], tblrecommended[ActiveTargetID], tblrecommended[Order], "" ), _xlfn.XLOOKUP( tblChecklist[[#This Row],[TargetID]], tblrecommended[PassiveTargetID], tblrecommended[Order], "" ) ) ) -> 75
A55: building.laboratory@5 | B55: =_xlfn.XLOOKUP(tblChecklist[[#This Row],[TargetID]],tblTargets[TargetID],tblTargets[DisplayName]) -> Laboratory Lv 5 | C55: =_xlfn.XLOOKUP( tblChecklist[[#This Row],[TargetID]], tblTargetStatus[TargetID], tblTargetStatus[successors], "" ) -> Laboratory maxed, Ahead of Time Chapter 1 Finished | D55: =_xlfn.XLOOKUP(tblChecklist[[#This Row],[TargetID]],tblTargets[TargetID],tblTargets[TargetType],"") -> BUILDING | E55: =_xlfn.XLOOKUP(tblChecklist[[#This Row],[TargetID]],tblTargetStatus[TargetID],tblTargetStatus[ChainAwareStatus],"") -> BLOCKED | F55: 76 | G55: FALSE | H55: =_xlfn.XLOOKUP(tblChecklist[[#This Row],[TargetID]],tblTargetStatus[TargetID],tblTargetStatus[TargetFunded],"") -> FALSE | I55: =IF( tblChecklist[[#This Row],[TargetType]]<>"BUILDING", "", IF( Player!$H$1="Active", _xlfn.XLOOKUP( tblChecklist[[#This Row],[TargetID]], tblrecommended[ActiveTargetID], tblrecommended[Order], "" ), _xlfn.XLOOKUP( tblChecklist[[#This Row],[TargetID]], tblrecommended[PassiveTargetID], tblrecommended[Order], "" ) ) ) -> 76
A56: building.laboratory_data_center@1 | B56: =_xlfn.XLOOKUP(tblChecklist[[#This Row],[TargetID]],tblTargets[TargetID],tblTargets[DisplayName]) -> Laboratory: Data Center Lv 1 | C56: =_xlfn.XLOOKUP( tblChecklist[[#This Row],[TargetID]], tblTargetStatus[TargetID], tblTargetStatus[successors], "" ) -> Laboratory: Data Center maxed, Ahead of Time Chapter 5 Finished | D56: =_xlfn.XLOOKUP(tblChecklist[[#This Row],[TargetID]],tblTargets[TargetID],tblTargets[TargetType],"") -> BUILDING | E56: =_xlfn.XLOOKUP(tblChecklist[[#This Row],[TargetID]],tblTargetStatus[TargetID],tblTargetStatus[ChainAwareStatus],"") -> BLOCKED | G56: FALSE | H56: =_xlfn.XLOOKUP(tblChecklist[[#This Row],[TargetID]],tblTargetStatus[TargetID],tblTargetStatus[TargetFunded],"") -> FALSE | I56: =IF( tblChecklist[[#This Row],[TargetType]]<>"BUILDING", "", IF( Player!$H$1="Active", _xlfn.XLOOKUP( tblChecklist[[#This Row],[TargetID]], tblrecommended[ActiveTargetID], tblrecommended[Order], "" ), _xlfn.XLOOKUP( tblChecklist[[#This Row],[TargetID]], tblrecommended[PassiveTargetID], tblrecommended[Order], "" ) ) )
A57: building.lumber@1 | B57: =_xlfn.XLOOKUP(tblChecklist[[#This Row],[TargetID]],tblTargets[TargetID],tblTargets[DisplayName]) -> Lumber Lv 1 | C57: =_xlfn.XLOOKUP( tblChecklist[[#This Row],[TargetID]], tblTargetStatus[TargetID], tblTargetStatus[successors], "" ) -> Lumber Lv 2 | D57: =_xlfn.XLOOKUP(tblChecklist[[#This Row],[TargetID]],tblTargets[TargetID],tblTargets[TargetType],"") -> BUILDING | E57: =_xlfn.XLOOKUP(tblChecklist[[#This Row],[TargetID]],tblTargetStatus[TargetID],tblTargetStatus[ChainAwareStatus],"") -> ONE AWAY | F57: 13 | G57: FALSE | H57: =_xlfn.XLOOKUP(tblChecklist[[#This Row],[TargetID]],tblTargetStatus[TargetID],tblTargetStatus[TargetFunded],"") -> FALSE | I57: =IF( tblChecklist[[#This Row],[TargetType]]<>"BUILDING", "", IF( Player!$H$1="Active", _xlfn.XLOOKUP( tblChecklist[[#This Row],[TargetID]], tblrecommended[ActiveTargetID], tblrecommended[Order], "" ), _xlfn.XLOOKUP( tblChecklist[[#This Row],[TargetID]], tblrecommended[PassiveTargetID], tblrecommended[Order], "" ) ) ) -> 13
A58: building.lumber@2 | B58: =_xlfn.XLOOKUP(tblChecklist[[#This Row],[TargetID]],tblTargets[TargetID],tblTargets[DisplayName]) -> Lumber Lv 2 | C58: =_xlfn.XLOOKUP( tblChecklist[[#This Row],[TargetID]], tblTargetStatus[TargetID], tblTargetStatus[successors], "" ) -> Lumber Lv 3 | D58: =_xlfn.XLOOKUP(tblChecklist[[#This Row],[TargetID]],tblTargets[TargetID],tblTargets[TargetType],"") -> BUILDING | E58: =_xlfn.XLOOKUP(tblChecklist[[#This Row],[TargetID]],tblTargetStatus[TargetID],tblTargetStatus[ChainAwareStatus],"") -> BLOCKED | F58: 14 | G58: FALSE | H58: =_xlfn.XLOOKUP(tblChecklist[[#This Row],[TargetID]],tblTargetStatus[TargetID],tblTargetStatus[TargetFunded],"") -> FALSE | I58: =IF( tblChecklist[[#This Row],[TargetType]]<>"BUILDING", "", IF( Player!$H$1="Active", _xlfn.XLOOKUP( tblChecklist[[#This Row],[TargetID]], tblrecommended[ActiveTargetID], tblrecommended[Order], "" ), _xlfn.XLOOKUP( tblChecklist[[#This Row],[TargetID]], tblrecommended[PassiveTargetID], tblrecommended[Order], "" ) ) ) -> 14
A59: building.lumber@3 | B59: =_xlfn.XLOOKUP(tblChecklist[[#This Row],[TargetID]],tblTargets[TargetID],tblTargets[DisplayName]) -> Lumber Lv 3 | C59: =_xlfn.XLOOKUP( tblChecklist[[#This Row],[TargetID]], tblTargetStatus[TargetID], tblTargetStatus[successors], "" ) -> Shogun's Katana Chapter 2 Finished | D59: =_xlfn.XLOOKUP(tblChecklist[[#This Row],[TargetID]],tblTargets[TargetID],tblTargets[TargetType],"") -> BUILDING | E59: =_xlfn.XLOOKUP(tblChecklist[[#This Row],[TargetID]],tblTargetStatus[TargetID],tblTargetStatus[ChainAwareStatus],"") -> BLOCKED | F59: 18 | G59: FALSE | H59: =_xlfn.XLOOKUP(tblChecklist[[#This Row],[TargetID]],tblTargetStatus[TargetID],tblTargetStatus[TargetFunded],"") -> FALSE | I59: =IF( tblChecklist[[#This Row],[TargetType]]<>"BUILDING", "", IF( Player!$H$1="Active", _xlfn.XLOOKUP( tblChecklist[[#This Row],[TargetID]], tblrecommended[ActiveTargetID], tblrecommended[Order], "" ), _xlfn.XLOOKUP( tblChecklist[[#This Row],[TargetID]], tblrecommended[PassiveTargetID], tblrecommended[Order], "" ) ) ) -> 18
A60: building.onsen@1 | B60: =_xlfn.XLOOKUP(tblChecklist[[#This Row],[TargetID]],tblTargets[TargetID],tblTargets[DisplayName]) -> Onsen Lv 1 | C60: =_xlfn.XLOOKUP( tblChecklist[[#This Row],[TargetID]], tblTargetStatus[TargetID], tblTargetStatus[successors], "" ) -> Onsen Lv 2 | D60: =_xlfn.XLOOKUP(tblChecklist[[#This Row],[TargetID]],tblTargets[TargetID],tblTargets[TargetType],"") -> BUILDING | E60: =_xlfn.XLOOKUP(tblChecklist[[#This Row],[TargetID]],tblTargetStatus[TargetID],tblTargetStatus[ChainAwareStatus],"") -> ONE AWAY | F60: 91 | G60: FALSE | H60: =_xlfn.XLOOKUP(tblChecklist[[#This Row],[TargetID]],tblTargetStatus[TargetID],tblTargetStatus[TargetFunded],"") -> FALSE | I60: =IF( tblChecklist[[#This Row],[TargetType]]<>"BUILDING", "", IF( Player!$H$1="Active", _xlfn.XLOOKUP( tblChecklist[[#This Row],[TargetID]], tblrecommended[ActiveTargetID], tblrecommended[Order], "" ), _xlfn.XLOOKUP( tblChecklist[[#This Row],[TargetID]], tblrecommended[PassiveTargetID], tblrecommended[Order], "" ) ) ) -> 91
A61: building.onsen@2 | B61: =_xlfn.XLOOKUP(tblChecklist[[#This Row],[TargetID]],tblTargets[TargetID],tblTargets[DisplayName]) -> Onsen Lv 2 | C61: =_xlfn.XLOOKUP( tblChecklist[[#This Row],[TargetID]], tblTargetStatus[TargetID], tblTargetStatus[successors], "" ) | D61: =_xlfn.XLOOKUP(tblChecklist[[#This Row],[TargetID]],tblTargets[TargetID],tblTargets[TargetType],"") -> BUILDING | E61: =_xlfn.XLOOKUP(tblChecklist[[#This Row],[TargetID]],tblTargetStatus[TargetID],tblTargetStatus[ChainAwareStatus],"") -> BLOCKED | F61: 92 | G61: FALSE | H61: =_xlfn.XLOOKUP(tblChecklist[[#This Row],[TargetID]],tblTargetStatus[TargetID],tblTargetStatus[TargetFunded],"") -> FALSE | I61: =IF( tblChecklist[[#This Row],[TargetType]]<>"BUILDING", "", IF( Player!$H$1="Active", _xlfn.XLOOKUP( tblChecklist[[#This Row],[TargetID]], tblrecommended[ActiveTargetID], tblrecommended[Order], "" ), _xlfn.XLOOKUP( tblChecklist[[#This Row],[TargetID]], tblrecommended[PassiveTargetID], tblrecommended[Order], "" ) ) ) -> 92
A62: building.outpost@1 | B62: =_xlfn.XLOOKUP(tblChecklist[[#This Row],[TargetID]],tblTargets[TargetID],tblTargets[DisplayName]) -> Outpost Lv 1 | C62: =_xlfn.XLOOKUP( tblChecklist[[#This Row],[TargetID]], tblTargetStatus[TargetID], tblTargetStatus[successors], "" ) -> Outpost Lv 2 | D62: =_xlfn.XLOOKUP(tblChecklist[[#This Row],[TargetID]],tblTargets[TargetID],tblTargets[TargetType],"") -> BUILDING | E62: =_xlfn.XLOOKUP(tblChecklist[[#This Row],[TargetID]],tblTargetStatus[TargetID],tblTargetStatus[ChainAwareStatus],"") -> BLOCKED | F62: 28 | G62: FALSE | H62: =_xlfn.XLOOKUP(tblChecklist[[#This Row],[TargetID]],tblTargetStatus[TargetID],tblTargetStatus[TargetFunded],"") -> FALSE | I62: =IF( tblChecklist[[#This Row],[TargetType]]<>"BUILDING", "", IF( Player!$H$1="Active", _xlfn.XLOOKUP( tblChecklist[[#This Row],[TargetID]], tblrecommended[ActiveTargetID], tblrecommended[Order], "" ), _xlfn.XLOOKUP( tblChecklist[[#This Row],[TargetID]], tblrecommended[PassiveTargetID], tblrecommended[Order], "" ) ) ) -> 28
A63: building.outpost@2 | B63: =_xlfn.XLOOKUP(tblChecklist[[#This Row],[TargetID]],tblTargets[TargetID],tblTargets[DisplayName]) -> Outpost Lv 2 | C63: =_xlfn.XLOOKUP( tblChecklist[[#This Row],[TargetID]], tblTargetStatus[TargetID], tblTargetStatus[successors], "" ) -> Outpost Lv 3 | D63: =_xlfn.XLOOKUP(tblChecklist[[#This Row],[TargetID]],tblTargets[TargetID],tblTargets[TargetType],"") -> BUILDING | E63: =_xlfn.XLOOKUP(tblChecklist[[#This Row],[TargetID]],tblTargetStatus[TargetID],tblTargetStatus[ChainAwareStatus],"") -> BLOCKED | F63: 35 | G63: FALSE | H63: =_xlfn.XLOOKUP(tblChecklist[[#This Row],[TargetID]],tblTargetStatus[TargetID],tblTargetStatus[TargetFunded],"") -> FALSE | I63: =IF( tblChecklist[[#This Row],[TargetType]]<>"BUILDING", "", IF( Player!$H$1="Active", _xlfn.XLOOKUP( tblChecklist[[#This Row],[TargetID]], tblrecommended[ActiveTargetID], tblrecommended[Order], "" ), _xlfn.XLOOKUP( tblChecklist[[#This Row],[TargetID]], tblrecommended[PassiveTargetID], tblrecommended[Order], "" ) ) ) -> 35
A64: building.outpost@3 | B64: =_xlfn.XLOOKUP(tblChecklist[[#This Row],[TargetID]],tblTargets[TargetID],tblTargets[DisplayName]) -> Outpost Lv 3 | C64: =_xlfn.XLOOKUP( tblChecklist[[#This Row],[TargetID]], tblTargetStatus[TargetID], tblTargetStatus[successors], "" ) -> Outpost maxed, Honor, Glory, Sushi Finished | D64: =_xlfn.XLOOKUP(tblChecklist[[#This Row],[TargetID]],tblTargets[TargetID],tblTargets[TargetType],"") -> BUILDING | E64: =_xlfn.XLOOKUP(tblChecklist[[#This Row],[TargetID]],tblTargetStatus[TargetID],tblTargetStatus[ChainAwareStatus],"") -> BLOCKED | F64: 50 | G64: FALSE | H64: =_xlfn.XLOOKUP(tblChecklist[[#This Row],[TargetID]],tblTargetStatus[TargetID],tblTargetStatus[TargetFunded],"") -> FALSE | I64: =IF( tblChecklist[[#This Row],[TargetType]]<>"BUILDING", "", IF( Player!$H$1="Active", _xlfn.XLOOKUP( tblChecklist[[#This Row],[TargetID]], tblrecommended[ActiveTargetID], tblrecommended[Order], "" ), _xlfn.XLOOKUP( tblChecklist[[#This Row],[TargetID]], tblrecommended[PassiveTargetID], tblrecommended[Order], "" ) ) ) -> 50
A65: building.pagoda@1 | B65: =_xlfn.XLOOKUP(tblChecklist[[#This Row],[TargetID]],tblTargets[TargetID],tblTargets[DisplayName]) -> Pagoda Lv 1 | C65: =_xlfn.XLOOKUP( tblChecklist[[#This Row],[TargetID]], tblTargetStatus[TargetID], tblTargetStatus[successors], "" ) -> Pagoda Lv 2 | D65: =_xlfn.XLOOKUP(tblChecklist[[#This Row],[TargetID]],tblTargets[TargetID],tblTargets[TargetType],"") -> BUILDING | E65: =_xlfn.XLOOKUP(tblChecklist[[#This Row],[TargetID]],tblTargetStatus[TargetID],tblTargetStatus[ChainAwareStatus],"") -> ONE AWAY | F65: 57 | G65: FALSE | H65: =_xlfn.XLOOKUP(tblChecklist[[#This Row],[TargetID]],tblTargetStatus[TargetID],tblTargetStatus[TargetFunded],"") -> FALSE | I65: =IF( tblChecklist[[#This Row],[TargetType]]<>"BUILDING", "", IF( Player!$H$1="Active", _xlfn.XLOOKUP( tblChecklist[[#This Row],[TargetID]], tblrecommended[ActiveTargetID], tblrecommended[Order], "" ), _xlfn.XLOOKUP( tblChecklist[[#This Row],[TargetID]], tblrecommended[PassiveTargetID], tblrecommended[Order], "" ) ) ) -> 57
A66: building.pagoda@2 | B66: =_xlfn.XLOOKUP(tblChecklist[[#This Row],[TargetID]],tblTargets[TargetID],tblTargets[DisplayName]) -> Pagoda Lv 2 | C66: =_xlfn.XLOOKUP( tblChecklist[[#This Row],[TargetID]], tblTargetStatus[TargetID], tblTargetStatus[successors], "" ) -> Pagoda Lv 3 | D66: =_xlfn.XLOOKUP(tblChecklist[[#This Row],[TargetID]],tblTargets[TargetID],tblTargets[TargetType],"") -> BUILDING | E66: =_xlfn.XLOOKUP(tblChecklist[[#This Row],[TargetID]],tblTargetStatus[TargetID],tblTargetStatus[ChainAwareStatus],"") -> BLOCKED | F66: 58 | G66: FALSE | H66: =_xlfn.XLOOKUP(tblChecklist[[#This Row],[TargetID]],tblTargetStatus[TargetID],tblTargetStatus[TargetFunded],"") -> FALSE | I66: =IF( tblChecklist[[#This Row],[TargetType]]<>"BUILDING", "", IF( Player!$H$1="Active", _xlfn.XLOOKUP( tblChecklist[[#This Row],[TargetID]], tblrecommended[ActiveTargetID], tblrecommended[Order], "" ), _xlfn.XLOOKUP( tblChecklist[[#This Row],[TargetID]], tblrecommended[PassiveTargetID], tblrecommended[Order], "" ) ) ) -> 58
A67: building.pagoda@3 | B67: =_xlfn.XLOOKUP(tblChecklist[[#This Row],[TargetID]],tblTargets[TargetID],tblTargets[DisplayName]) -> Pagoda Lv 3 | C67: =_xlfn.XLOOKUP( tblChecklist[[#This Row],[TargetID]], tblTargetStatus[TargetID], tblTargetStatus[successors], "" ) -> Pagoda Lv 4 | D67: =_xlfn.XLOOKUP(tblChecklist[[#This Row],[TargetID]],tblTargets[TargetID],tblTargets[TargetType],"") -> BUILDING | E67: =_xlfn.XLOOKUP(tblChecklist[[#This Row],[TargetID]],tblTargetStatus[TargetID],tblTargetStatus[ChainAwareStatus],"") -> BLOCKED | F67: 59 | G67: FALSE | H67: =_xlfn.XLOOKUP(tblChecklist[[#This Row],[TargetID]],tblTargetStatus[TargetID],tblTargetStatus[TargetFunded],"") -> FALSE | I67: =IF( tblChecklist[[#This Row],[TargetType]]<>"BUILDING", "", IF( Player!$H$1="Active", _xlfn.XLOOKUP( tblChecklist[[#This Row],[TargetID]], tblrecommended[ActiveTargetID], tblrecommended[Order], "" ), _xlfn.XLOOKUP( tblChecklist[[#This Row],[TargetID]], tblrecommended[PassiveTargetID], tblrecommended[Order], "" ) ) ) -> 59
A68: building.pagoda@4 | B68: =_xlfn.XLOOKUP(tblChecklist[[#This Row],[TargetID]],tblTargets[TargetID],tblTargets[DisplayName]) -> Pagoda Lv 4 | C68: =_xlfn.XLOOKUP( tblChecklist[[#This Row],[TargetID]], tblTargetStatus[TargetID], tblTargetStatus[successors], "" ) -> Pagoda Lv 5 | D68: =_xlfn.XLOOKUP(tblChecklist[[#This Row],[TargetID]],tblTargets[TargetID],tblTargets[TargetType],"") -> BUILDING | E68: =_xlfn.XLOOKUP(tblChecklist[[#This Row],[TargetID]],tblTargetStatus[TargetID],tblTargetStatus[ChainAwareStatus],"") -> BLOCKED | F68: 60 | G68: FALSE | H68: =_xlfn.XLOOKUP(tblChecklist[[#This Row],[TargetID]],tblTargetStatus[TargetID],tblTargetStatus[TargetFunded],"") -> FALSE | I68: =IF( tblChecklist[[#This Row],[TargetType]]<>"BUILDING", "", IF( Player!$H$1="Active", _xlfn.XLOOKUP( tblChecklist[[#This Row],[TargetID]], tblrecommended[ActiveTargetID], tblrecommended[Order], "" ), _xlfn.XLOOKUP( tblChecklist[[#This Row],[TargetID]], tblrecommended[PassiveTargetID], tblrecommended[Order], "" ) ) ) -> 60
... A91: building.train@2 | B91: =_xlfn.XLOOKUP(tblChecklist[[#This Row],[TargetID]],tblTargets[TargetID],tblTargets[DisplayName]) -> Train Lv 2 | C91: =_xlfn.XLOOKUP( tblChecklist[[#This Row],[TargetID]], tblTargetStatus[TargetID], tblTargetStatus[successors], "" ) -> train maxed, Visit Aomori, Visit Fukushima, Visit Tokyo, Journey Through Japan By Train Finished | D91: =_xlfn.XLOOKUP(tblChecklist[[#This Row],[TargetID]],tblTargets[TargetID],tblTargets[TargetType],"") -> BUILDING | E91: =_xlfn.XLOOKUP(tblChecklist[[#This Row],[TargetID]],tblTargetStatus[TargetID],tblTargetStatus[ChainAwareStatus],"") -> BLOCKED | F91: 71 | G91: FALSE | H91: =_xlfn.XLOOKUP(tblChecklist[[#This Row],[TargetID]],tblTargetStatus[TargetID],tblTargetStatus[TargetFunded],"") -> FALSE | I91: =IF( tblChecklist[[#This Row],[TargetType]]<>"BUILDING", "", IF( Player!$H$1="Active", _xlfn.XLOOKUP( tblChecklist[[#This Row],[TargetID]], tblrecommended[ActiveTargetID], tblrecommended[Order], "" ), _xlfn.XLOOKUP( tblChecklist[[#This Row],[TargetID]], tblrecommended[PassiveTargetID], tblrecommended[Order], "" ) ) ) -> 71
A92: building.train_freight_carriage@1 | B92: =_xlfn.XLOOKUP(tblChecklist[[#This Row],[TargetID]],tblTargets[TargetID],tblTargets[DisplayName]) -> Train: Freight Carriage Lv 1 | C92: =_xlfn.XLOOKUP( tblChecklist[[#This Row],[TargetID]], tblTargetStatus[TargetID], tblTargetStatus[successors], "" ) -> Train: Freight Carriage Lv 2 | D92: =_xlfn.XLOOKUP(tblChecklist[[#This Row],[TargetID]],tblTargets[TargetID],tblTargets[TargetType],"") -> BUILDING | E92: =_xlfn.XLOOKUP(tblChecklist[[#This Row],[TargetID]],tblTargetStatus[TargetID],tblTargetStatus[ChainAwareStatus],"") -> BLOCKED | G92: FALSE | H92: =_xlfn.XLOOKUP(tblChecklist[[#This Row],[TargetID]],tblTargetStatus[TargetID],tblTargetStatus[TargetFunded],"") -> FALSE | I92: =IF( tblChecklist[[#This Row],[TargetType]]<>"BUILDING", "", IF( Player!$H$1="Active", _xlfn.XLOOKUP( tblChecklist[[#This Row],[TargetID]], tblrecommended[ActiveTargetID], tblrecommended[Order], "" ), _xlfn.XLOOKUP( tblChecklist[[#This Row],[TargetID]], tblrecommended[PassiveTargetID], tblrecommended[Order], "" ) ) )
A93: building.train_freight_carriage@2 | B93: =_xlfn.XLOOKUP(tblChecklist[[#This Row],[TargetID]],tblTargets[TargetID],tblTargets[DisplayName]) -> Train: Freight Carriage Lv 2 | C93: =_xlfn.XLOOKUP( tblChecklist[[#This Row],[TargetID]], tblTargetStatus[TargetID], tblTargetStatus[successors], "" ) | D93: =_xlfn.XLOOKUP(tblChecklist[[#This Row],[TargetID]],tblTargets[TargetID],tblTargets[TargetType],"") -> BUILDING | E93: =_xlfn.XLOOKUP(tblChecklist[[#This Row],[TargetID]],tblTargetStatus[TargetID],tblTargetStatus[ChainAwareStatus],"") -> BLOCKED | G93: FALSE | H93: =_xlfn.XLOOKUP(tblChecklist[[#This Row],[TargetID]],tblTargetStatus[TargetID],tblTargetStatus[TargetFunded],"") -> FALSE | I93: =IF( tblChecklist[[#This Row],[TargetType]]<>"BUILDING", "", IF( Player!$H$1="Active", _xlfn.XLOOKUP( tblChecklist[[#This Row],[TargetID]], tblrecommended[ActiveTargetID], tblrecommended[Order], "" ), _xlfn.XLOOKUP( tblChecklist[[#This Row],[TargetID]], tblrecommended[PassiveTargetID], tblrecommended[Order], "" ) ) )
A94: building.train_passenger_carriage@1 | B94: =_xlfn.XLOOKUP(tblChecklist[[#This Row],[TargetID]],tblTargets[TargetID],tblTargets[DisplayName]) -> Train: Passenger Carriage Lv 1 | C94: =_xlfn.XLOOKUP( tblChecklist[[#This Row],[TargetID]], tblTargetStatus[TargetID], tblTargetStatus[successors], "" ) -> Train: Passenger Carriage Lv 2, Journey Through Japan By Train Finished | D94: =_xlfn.XLOOKUP(tblChecklist[[#This Row],[TargetID]],tblTargets[TargetID],tblTargets[TargetType],"") -> BUILDING | E94: =_xlfn.XLOOKUP(tblChecklist[[#This Row],[TargetID]],tblTargetStatus[TargetID],tblTargetStatus[ChainAwareStatus],"") -> BLOCKED | G94: FALSE | H94: =_xlfn.XLOOKUP(tblChecklist[[#This Row],[TargetID]],tblTargetStatus[TargetID],tblTargetStatus[TargetFunded],"") -> FALSE | I94: =IF( tblChecklist[[#This Row],[TargetType]]<>"BUILDING", "", IF( Player!$H$1="Active", _xlfn.XLOOKUP( tblChecklist[[#This Row],[TargetID]], tblrecommended[ActiveTargetID], tblrecommended[Order], "" ), _xlfn.XLOOKUP( tblChecklist[[#This Row],[TargetID]], tblrecommended[PassiveTargetID], tblrecommended[Order], "" ) ) )
A95: building.train_passenger_carriage@2 | B95: =_xlfn.XLOOKUP(tblChecklist[[#This Row],[TargetID]],tblTargets[TargetID],tblTargets[DisplayName]) -> Train: Passenger Carriage Lv 2 | C95: =_xlfn.XLOOKUP( tblChecklist[[#This Row],[TargetID]], tblTargetStatus[TargetID], tblTargetStatus[successors], "" ) | D95: =_xlfn.XLOOKUP(tblChecklist[[#This Row],[TargetID]],tblTargets[TargetID],tblTargets[TargetType],"") -> BUILDING | E95: =_xlfn.XLOOKUP(tblChecklist[[#This Row],[TargetID]],tblTargetStatus[TargetID],tblTargetStatus[ChainAwareStatus],"") -> BLOCKED | G95: FALSE | H95: =_xlfn.XLOOKUP(tblChecklist[[#This Row],[TargetID]],tblTargetStatus[TargetID],tblTargetStatus[TargetFunded],"") -> FALSE | I95: =IF( tblChecklist[[#This Row],[TargetType]]<>"BUILDING", "", IF( Player!$H$1="Active", _xlfn.XLOOKUP( tblChecklist[[#This Row],[TargetID]], tblrecommended[ActiveTargetID], tblrecommended[Order], "" ), _xlfn.XLOOKUP( tblChecklist[[#This Row],[TargetID]], tblrecommended[PassiveTargetID], tblrecommended[Order], "" ) ) )
A96: building.warehouse@1 | B96: =_xlfn.XLOOKUP(tblChecklist[[#This Row],[TargetID]],tblTargets[TargetID],tblTargets[DisplayName]) -> Warehouse Lv 1 | C96: =_xlfn.XLOOKUP( tblChecklist[[#This Row],[TargetID]], tblTargetStatus[TargetID], tblTargetStatus[successors], "" ) -> Pier Lv 1, Warehouse Lv 2, Shogun's Katana Chapter 2 Finished | D96: =_xlfn.XLOOKUP(tblChecklist[[#This Row],[TargetID]],tblTargets[TargetID],tblTargets[TargetType],"") -> BUILDING | E96: =_xlfn.XLOOKUP(tblChecklist[[#This Row],[TargetID]],tblTargetStatus[TargetID],tblTargetStatus[ChainAwareStatus],"") -> ONE AWAY | F96: 2 | G96: FALSE | H96: =_xlfn.XLOOKUP(tblChecklist[[#This Row],[TargetID]],tblTargetStatus[TargetID],tblTargetStatus[TargetFunded],"") -> FALSE | I96: =IF( tblChecklist[[#This Row],[TargetType]]<>"BUILDING", "", IF( Player!$H$1="Active", _xlfn.XLOOKUP( tblChecklist[[#This Row],[TargetID]], tblrecommended[ActiveTargetID], tblrecommended[Order], "" ), _xlfn.XLOOKUP( tblChecklist[[#This Row],[TargetID]], tblrecommended[PassiveTargetID], tblrecommended[Order], "" ) ) ) -> 2
A97: building.warehouse@2 | B97: =_xlfn.XLOOKUP(tblChecklist[[#This Row],[TargetID]],tblTargets[TargetID],tblTargets[DisplayName]) -> Warehouse Lv 2 | C97: =_xlfn.XLOOKUP( tblChecklist[[#This Row],[TargetID]], tblTargetStatus[TargetID], tblTargetStatus[successors], "" ) -> Warehouse Lv 3 | D97: =_xlfn.XLOOKUP(tblChecklist[[#This Row],[TargetID]],tblTargets[TargetID],tblTargets[TargetType],"") -> BUILDING | E97: =_xlfn.XLOOKUP(tblChecklist[[#This Row],[TargetID]],tblTargetStatus[TargetID],tblTargetStatus[ChainAwareStatus],"") -> BLOCKED | F97: 94 | G97: FALSE | H97: =_xlfn.XLOOKUP(tblChecklist[[#This Row],[TargetID]],tblTargetStatus[TargetID],tblTargetStatus[TargetFunded],"") -> FALSE | I97: =IF( tblChecklist[[#This Row],[TargetType]]<>"BUILDING", "", IF( Player!$H$1="Active", _xlfn.XLOOKUP( tblChecklist[[#This Row],[TargetID]], tblrecommended[ActiveTargetID], tblrecommended[Order], "" ), _xlfn.XLOOKUP( tblChecklist[[#This Row],[TargetID]], tblrecommended[PassiveTargetID], tblrecommended[Order], "" ) ) ) -> 94
A98: building.warehouse@3 | B98: =_xlfn.XLOOKUP(tblChecklist[[#This Row],[TargetID]],tblTargets[TargetID],tblTargets[DisplayName]) -> Warehouse Lv 3 | C98: =_xlfn.XLOOKUP( tblChecklist[[#This Row],[TargetID]], tblTargetStatus[TargetID], tblTargetStatus[successors], "" ) -> Warehouse Lv 4 | D98: =_xlfn.XLOOKUP(tblChecklist[[#This Row],[TargetID]],tblTargets[TargetID],tblTargets[TargetType],"") -> BUILDING | E98: =_xlfn.XLOOKUP(tblChecklist[[#This Row],[TargetID]],tblTargetStatus[TargetID],tblTargetStatus[ChainAwareStatus],"") -> BLOCKED | F98: 95 | G98: FALSE | H98: =_xlfn.XLOOKUP(tblChecklist[[#This Row],[TargetID]],tblTargetStatus[TargetID],tblTargetStatus[TargetFunded],"") -> FALSE | I98: =IF( tblChecklist[[#This Row],[TargetType]]<>"BUILDING", "", IF( Player!$H$1="Active", _xlfn.XLOOKUP( tblChecklist[[#This Row],[TargetID]], tblrecommended[ActiveTargetID], tblrecommended[Order], "" ), _xlfn.XLOOKUP( tblChecklist[[#This Row],[TargetID]], tblrecommended[PassiveTargetID], tblrecommended[Order], "" ) ) ) -> 95
A99: building.warehouse@4 | B99: =_xlfn.XLOOKUP(tblChecklist[[#This Row],[TargetID]],tblTargets[TargetID],tblTargets[DisplayName]) -> Warehouse Lv 4 | C99: =_xlfn.XLOOKUP( tblChecklist[[#This Row],[TargetID]], tblTargetStatus[TargetID], tblTargetStatus[successors], "" ) -> Warehouse Lv 5 | D99: =_xlfn.XLOOKUP(tblChecklist[[#This Row],[TargetID]],tblTargets[TargetID],tblTargets[TargetType],"") -> BUILDING | E99: =_xlfn.XLOOKUP(tblChecklist[[#This Row],[TargetID]],tblTargetStatus[TargetID],tblTargetStatus[ChainAwareStatus],"") -> BLOCKED | F99: 96 | G99: FALSE | H99: =_xlfn.XLOOKUP(tblChecklist[[#This Row],[TargetID]],tblTargetStatus[TargetID],tblTargetStatus[TargetFunded],"") -> FALSE | I99: =IF( tblChecklist[[#This Row],[TargetType]]<>"BUILDING", "", IF( Player!$H$1="Active", _xlfn.XLOOKUP( tblChecklist[[#This Row],[TargetID]], tblrecommended[ActiveTargetID], tblrecommended[Order], "" ), _xlfn.XLOOKUP( tblChecklist[[#This Row],[TargetID]], tblrecommended[PassiveTargetID], tblrecommended[Order], "" ) ) ) -> 96
A100: building.warehouse@5 | B100: =_xlfn.XLOOKUP(tblChecklist[[#This Row],[TargetID]],tblTargets[TargetID],tblTargets[DisplayName]) -> Warehouse Lv 5 | C100: =_xlfn.XLOOKUP( tblChecklist[[#This Row],[TargetID]], tblTargetStatus[TargetID], tblTargetStatus[successors], "" ) -> Warehouse Lv 6 | D100: =_xlfn.XLOOKUP(tblChecklist[[#This Row],[TargetID]],tblTargets[TargetID],tblTargets[TargetType],"") -> BUILDING | E100: =_xlfn.XLOOKUP(tblChecklist[[#This Row],[TargetID]],tblTargetStatus[TargetID],tblTargetStatus[ChainAwareStatus],"") -> BLOCKED | F100: 97 | G100: FALSE | H100: =_xlfn.XLOOKUP(tblChecklist[[#This Row],[TargetID]],tblTargetStatus[TargetID],tblTargetStatus[TargetFunded],"") -> FALSE | I100: =IF( tblChecklist[[#This Row],[TargetType]]<>"BUILDING", "", IF( Player!$H$1="Active", _xlfn.XLOOKUP( tblChecklist[[#This Row],[TargetID]], tblrecommended[ActiveTargetID], tblrecommended[Order], "" ), _xlfn.XLOOKUP( tblChecklist[[#This Row],[TargetID]], tblrecommended[PassiveTargetID], tblrecommended[Order], "" ) ) ) -> 97
A101: building.warehouse@6 | B101: =_xlfn.XLOOKUP(tblChecklist[[#This Row],[TargetID]],tblTargets[TargetID],tblTargets[DisplayName]) -> Warehouse Lv 6 | C101: =_xlfn.XLOOKUP( tblChecklist[[#This Row],[TargetID]], tblTargetStatus[TargetID], tblTargetStatus[successors], "" ) -> Warehouse Lv 7 | D101: =_xlfn.XLOOKUP(tblChecklist[[#This Row],[TargetID]],tblTargets[TargetID],tblTargets[TargetType],"") -> BUILDING | E101: =_xlfn.XLOOKUP(tblChecklist[[#This Row],[TargetID]],tblTargetStatus[TargetID],tblTargetStatus[ChainAwareStatus],"") -> BLOCKED | F101: 98 | G101: FALSE | H101: =_xlfn.XLOOKUP(tblChecklist[[#This Row],[TargetID]],tblTargetStatus[TargetID],tblTargetStatus[TargetFunded],"") -> FALSE | I101: =IF( tblChecklist[[#This Row],[TargetType]]<>"BUILDING", "", IF( Player!$H$1="Active", _xlfn.XLOOKUP( tblChecklist[[#This Row],[TargetID]], tblrecommended[ActiveTargetID], tblrecommended[Order], "" ), _xlfn.XLOOKUP( tblChecklist[[#This Row],[TargetID]], tblrecommended[PassiveTargetID], tblrecommended[Order], "" ) ) ) -> 98
A102: building.warehouse@7 | B102: =_xlfn.XLOOKUP(tblChecklist[[#This Row],[TargetID]],tblTargets[TargetID],tblTargets[DisplayName]) -> Warehouse Lv 7 | C102: =_xlfn.XLOOKUP( tblChecklist[[#This Row],[TargetID]], tblTargetStatus[TargetID], tblTargetStatus[successors], "" ) -> warehouse maxed | D102: =_xlfn.XLOOKUP(tblChecklist[[#This Row],[TargetID]],tblTargets[TargetID],tblTargets[TargetType],"") -> BUILDING | E102: =_xlfn.XLOOKUP(tblChecklist[[#This Row],[TargetID]],tblTargetStatus[TargetID],tblTargetStatus[ChainAwareStatus],"") -> BLOCKED | F102: 99 | G102: FALSE | H102: =_xlfn.XLOOKUP(tblChecklist[[#This Row],[TargetID]],tblTargetStatus[TargetID],tblTargetStatus[TargetFunded],"") -> FALSE | I102: =IF( tblChecklist[[#This Row],[TargetType]]<>"BUILDING", "", IF( Player!$H$1="Active", _xlfn.XLOOKUP( tblChecklist[[#This Row],[TargetID]], tblrecommended[ActiveTargetID], tblrecommended[Order], "" ), _xlfn.XLOOKUP( tblChecklist[[#This Row],[TargetID]], tblrecommended[PassiveTargetID], tblrecommended[Order], "" ) ) ) -> 99
A103: building.windmill@1 | B103: =_xlfn.XLOOKUP(tblChecklist[[#This Row],[TargetID]],tblTargets[TargetID],tblTargets[DisplayName]) -> Windmill Lv 1 | C103: =_xlfn.XLOOKUP( tblChecklist[[#This Row],[TargetID]], tblTargetStatus[TargetID], tblTargetStatus[successors], "" ) -> Windmill Lv 2 | D103: =_xlfn.XLOOKUP(tblChecklist[[#This Row],[TargetID]],tblTargets[TargetID],tblTargets[TargetType],"") -> BUILDING | E103: =_xlfn.XLOOKUP(tblChecklist[[#This Row],[TargetID]],tblTargetStatus[TargetID],tblTargetStatus[ChainAwareStatus],"") -> ONE AWAY | F103: 9 | G103: FALSE | H103: =_xlfn.XLOOKUP(tblChecklist[[#This Row],[TargetID]],tblTargetStatus[TargetID],tblTargetStatus[TargetFunded],"") -> FALSE | I103: =IF( tblChecklist[[#This Row],[TargetType]]<>"BUILDING", "", IF( Player!$H$1="Active", _xlfn.XLOOKUP( tblChecklist[[#This Row],[TargetID]], tblrecommended[ActiveTargetID], tblrecommended[Order], "" ), _xlfn.XLOOKUP( tblChecklist[[#This Row],[TargetID]], tblrecommended[PassiveTargetID], tblrecommended[Order], "" ) ) ) -> 9
A104: building.windmill@2 | B104: =_xlfn.XLOOKUP(tblChecklist[[#This Row],[TargetID]],tblTargets[TargetID],tblTargets[DisplayName]) -> Windmill Lv 2 | C104: =_xlfn.XLOOKUP( tblChecklist[[#This Row],[TargetID]], tblTargetStatus[TargetID], tblTargetStatus[successors], "" ) -> windmill maxed | D104: =_xlfn.XLOOKUP(tblChecklist[[#This Row],[TargetID]],tblTargets[TargetID],tblTargets[TargetType],"") -> BUILDING | E104: =_xlfn.XLOOKUP(tblChecklist[[#This Row],[TargetID]],tblTargetStatus[TargetID],tblTargetStatus[ChainAwareStatus],"") -> BLOCKED | F104: 15 | G104: FALSE | H104: =_xlfn.XLOOKUP(tblChecklist[[#This Row],[TargetID]],tblTargetStatus[TargetID],tblTargetStatus[TargetFunded],"") -> FALSE | I104: =IF( tblChecklist[[#This Row],[TargetType]]<>"BUILDING", "", IF( Player!$H$1="Active", _xlfn.XLOOKUP( tblChecklist[[#This Row],[TargetID]], tblrecommended[ActiveTargetID], tblrecommended[Order], "" ), _xlfn.XLOOKUP( tblChecklist[[#This Row],[TargetID]], tblrecommended[PassiveTargetID], tblrecommended[Order], "" ) ) ) -> 15
A105: building.workshop@1 | B105: =_xlfn.XLOOKUP(tblChecklist[[#This Row],[TargetID]],tblTargets[TargetID],tblTargets[DisplayName]) -> Workshop Lv 1 | C105: =_xlfn.XLOOKUP( tblChecklist[[#This Row],[TargetID]], tblTargetStatus[TargetID], tblTargetStatus[successors], "" ) -> Workshop Lv 2 | D105: =_xlfn.XLOOKUP(tblChecklist[[#This Row],[TargetID]],tblTargets[TargetID],tblTargets[TargetType],"") -> BUILDING | E105: =_xlfn.XLOOKUP(tblChecklist[[#This Row],[TargetID]],tblTargetStatus[TargetID],tblTargetStatus[ChainAwareStatus],"") -> ONE AWAY | F105: 30 | G105: FALSE | H105: =_xlfn.XLOOKUP(tblChecklist[[#This Row],[TargetID]],tblTargetStatus[TargetID],tblTargetStatus[TargetFunded],"") -> FALSE | I105: =IF( tblChecklist[[#This Row],[TargetType]]<>"BUILDING", "", IF( Player!$H$1="Active", _xlfn.XLOOKUP( tblChecklist[[#This Row],[TargetID]], tblrecommended[ActiveTargetID], tblrecommended[Order], "" ), _xlfn.XLOOKUP( tblChecklist[[#This Row],[TargetID]], tblrecommended[PassiveTargetID], tblrecommended[Order], "" ) ) ) -> 30
A106: building.workshop@2 | B106: =_xlfn.XLOOKUP(tblChecklist[[#This Row],[TargetID]],tblTargets[TargetID],tblTargets[DisplayName]) -> Workshop Lv 2 | C106: =_xlfn.XLOOKUP( tblChecklist[[#This Row],[TargetID]], tblTargetStatus[TargetID], tblTargetStatus[successors], "" ) -> Workshop Lv 3 | D106: =_xlfn.XLOOKUP(tblChecklist[[#This Row],[TargetID]],tblTargets[TargetID],tblTargets[TargetType],"") -> BUILDING | E106: =_xlfn.XLOOKUP(tblChecklist[[#This Row],[TargetID]],tblTargetStatus[TargetID],tblTargetStatus[ChainAwareStatus],"") -> BLOCKED | F106: 31 | G106: FALSE | H106: =_xlfn.XLOOKUP(tblChecklist[[#This Row],[TargetID]],tblTargetStatus[TargetID],tblTargetStatus[TargetFunded],"") -> FALSE | I106: =IF( tblChecklist[[#This Row],[TargetType]]<>"BUILDING", "", IF( Player!$H$1="Active", _xlfn.XLOOKUP( tblChecklist[[#This Row],[TargetID]], tblrecommended[ActiveTargetID], tblrecommended[Order], "" ), _xlfn.XLOOKUP( tblChecklist[[#This Row],[TargetID]], tblrecommended[PassiveTargetID], tblrecommended[Order], "" ) ) ) -> 31
A107: building.workshop@3 | B107: =_xlfn.XLOOKUP(tblChecklist[[#This Row],[TargetID]],tblTargets[TargetID],tblTargets[DisplayName]) -> Workshop Lv 3 | C107: =_xlfn.XLOOKUP( tblChecklist[[#This Row],[TargetID]], tblTargetStatus[TargetID], tblTargetStatus[successors], "" ) -> Workshop Lv 4 | D107: =_xlfn.XLOOKUP(tblChecklist[[#This Row],[TargetID]],tblTargets[TargetID],tblTargets[TargetType],"") -> BUILDING | E107: =_xlfn.XLOOKUP(tblChecklist[[#This Row],[TargetID]],tblTargetStatus[TargetID],tblTargetStatus[ChainAwareStatus],"") -> BLOCKED | F107: 32 | G107: FALSE | H107: =_xlfn.XLOOKUP(tblChecklist[[#This Row],[TargetID]],tblTargetStatus[TargetID],tblTargetStatus[TargetFunded],"") -> FALSE | I107: =IF( tblChecklist[[#This Row],[TargetType]]<>"BUILDING", "", IF( Player!$H$1="Active", _xlfn.XLOOKUP( tblChecklist[[#This Row],[TargetID]], tblrecommended[ActiveTargetID], tblrecommended[Order], "" ), _xlfn.XLOOKUP( tblChecklist[[#This Row],[TargetID]], tblrecommended[PassiveTargetID], tblrecommended[Order], "" ) ) ) -> 32
... A109: building.workshop@5 | B109: =_xlfn.XLOOKUP(tblChecklist[[#This Row],[TargetID]],tblTargets[TargetID],tblTargets[DisplayName]) -> Workshop Lv 5 | C109: =_xlfn.XLOOKUP( tblChecklist[[#This Row],[TargetID]], tblTargetStatus[TargetID], tblTargetStatus[successors], "" ) -> workshop maxed, Barometer, Cinema Projector, Necklace For Haruka, Safe, Solver 1 Prototype, Telescope | D109: =_xlfn.XLOOKUP(tblChecklist[[#This Row],[TargetID]],tblTargets[TargetID],tblTargets[TargetType],"") -> BUILDING | E109: =_xlfn.XLOOKUP(tblChecklist[[#This Row],[TargetID]],tblTargetStatus[TargetID],tblTargetStatus[ChainAwareStatus],"") -> BLOCKED | F109: 34 | G109: FALSE | H109: =_xlfn.XLOOKUP(tblChecklist[[#This Row],[TargetID]],tblTargetStatus[TargetID],tblTargetStatus[TargetFunded],"") -> FALSE | I109: =IF( tblChecklist[[#This Row],[TargetType]]<>"BUILDING", "", IF( Player!$H$1="Active", _xlfn.XLOOKUP( tblChecklist[[#This Row],[TargetID]], tblrecommended[ActiveTargetID], tblrecommended[Order], "" ), _xlfn.XLOOKUP( tblChecklist[[#This Row],[TargetID]], tblrecommended[PassiveTargetID], tblrecommended[Order], "" ) ) ) -> 34
A110: citadel.armory | B110: =_xlfn.XLOOKUP(tblChecklist[[#This Row],[TargetID]],tblTargets[TargetID],tblTargets[DisplayName]) -> Armory | C110: =_xlfn.XLOOKUP( tblChecklist[[#This Row],[TargetID]], tblTargetStatus[TargetID], tblTargetStatus[successors], "" ) -> Armory 1 Lv 1 | D110: =_xlfn.XLOOKUP(tblChecklist[[#This Row],[TargetID]],tblTargets[TargetID],tblTargets[TargetType],"") -> CITADEL | E110: =_xlfn.XLOOKUP(tblChecklist[[#This Row],[TargetID]],tblTargetStatus[TargetID],tblTargetStatus[ChainAwareStatus],"") -> BLOCKED | G110: FALSE | H110: =_xlfn.XLOOKUP(tblChecklist[[#This Row],[TargetID]],tblTargetStatus[TargetID],tblTargetStatus[TargetFunded],"") -> FALSE | I110: =IF( tblChecklist[[#This Row],[TargetType]]<>"BUILDING", "", IF( Player!$H$1="Active", _xlfn.XLOOKUP( tblChecklist[[#This Row],[TargetID]], tblrecommended[ActiveTargetID], tblrecommended[Order], "" ), _xlfn.XLOOKUP( tblChecklist[[#This Row],[TargetID]], tblrecommended[PassiveTargetID], tblrecommended[Order], "" ) ) )
A111: citadel.attic | B111: =_xlfn.XLOOKUP(tblChecklist[[#This Row],[TargetID]],tblTargets[TargetID],tblTargets[DisplayName]) -> Attic | C111: =_xlfn.XLOOKUP( tblChecklist[[#This Row],[TargetID]], tblTargetStatus[TargetID], tblTargetStatus[successors], "" ) -> Attic Lv 1 | D111: =_xlfn.XLOOKUP(tblChecklist[[#This Row],[TargetID]],tblTargets[TargetID],tblTargets[TargetType],"") -> CITADEL | E111: =_xlfn.XLOOKUP(tblChecklist[[#This Row],[TargetID]],tblTargetStatus[TargetID],tblTargetStatus[ChainAwareStatus],"") -> BLOCKED | G111: FALSE | H111: =_xlfn.XLOOKUP(tblChecklist[[#This Row],[TargetID]],tblTargetStatus[TargetID],tblTargetStatus[TargetFunded],"") -> FALSE | I111: =IF( tblChecklist[[#This Row],[TargetType]]<>"BUILDING", "", IF( Player!$H$1="Active", _xlfn.XLOOKUP( tblChecklist[[#This Row],[TargetID]], tblrecommended[ActiveTargetID], tblrecommended[Order], "" ), _xlfn.XLOOKUP( tblChecklist[[#This Row],[TargetID]], tblrecommended[PassiveTargetID], tblrecommended[Order], "" ) ) )
A112: citadel.cheese_cave | B112: =_xlfn.XLOOKUP(tblChecklist[[#This Row],[TargetID]],tblTargets[TargetID],tblTargets[DisplayName]) -> Cheese Cave | C112: =_xlfn.XLOOKUP( tblChecklist[[#This Row],[TargetID]], tblTargetStatus[TargetID], tblTargetStatus[successors], "" ) | D112: =_xlfn.XLOOKUP(tblChecklist[[#This Row],[TargetID]],tblTargets[TargetID],tblTargets[TargetType],"") -> CITADEL | E112: =_xlfn.XLOOKUP(tblChecklist[[#This Row],[TargetID]],tblTargetStatus[TargetID],tblTargetStatus[ChainAwareStatus],"") -> BLOCKED | G112: FALSE | H112: =_xlfn.XLOOKUP(tblChecklist[[#This Row],[TargetID]],tblTargetStatus[TargetID],tblTargetStatus[TargetFunded],"") -> FALSE | I112: =IF( tblChecklist[[#This Row],[TargetType]]<>"BUILDING", "", IF( Player!$H$1="Active", _xlfn.XLOOKUP( tblChecklist[[#This Row],[TargetID]], tblrecommended[ActiveTargetID], tblrecommended[Order], "" ), _xlfn.XLOOKUP( tblChecklist[[#This Row],[TargetID]], tblrecommended[PassiveTargetID], tblrecommended[Order], "" ) ) )
A113: citadel.courtyard | B113: =_xlfn.XLOOKUP(tblChecklist[[#This Row],[TargetID]],tblTargets[TargetID],tblTargets[DisplayName]) -> Courtyard | C113: =_xlfn.XLOOKUP( tblChecklist[[#This Row],[TargetID]], tblTargetStatus[TargetID], tblTargetStatus[successors], "" ) -> Courtyard 1 Lv 1, Courtyard 2 Lv 1 | D113: =_xlfn.XLOOKUP(tblChecklist[[#This Row],[TargetID]],tblTargets[TargetID],tblTargets[TargetType],"") -> CITADEL | E113: =_xlfn.XLOOKUP(tblChecklist[[#This Row],[TargetID]],tblTargetStatus[TargetID],tblTargetStatus[ChainAwareStatus],"") -> BLOCKED | G113: FALSE | H113: =_xlfn.XLOOKUP(tblChecklist[[#This Row],[TargetID]],tblTargetStatus[TargetID],tblTargetStatus[TargetFunded],"") -> FALSE | I113: =IF( tblChecklist[[#This Row],[TargetType]]<>"BUILDING", "", IF( Player!$H$1="Active", _xlfn.XLOOKUP( tblChecklist[[#This Row],[TargetID]], tblrecommended[ActiveTargetID], tblrecommended[Order], "" ), _xlfn.XLOOKUP( tblChecklist[[#This Row],[TargetID]], tblrecommended[PassiveTargetID], tblrecommended[Order], "" ) ) )
A114: citadel.gallery | B114: =_xlfn.XLOOKUP(tblChecklist[[#This Row],[TargetID]],tblTargets[TargetID],tblTargets[DisplayName]) -> Gallery | C114: =_xlfn.XLOOKUP( tblChecklist[[#This Row],[TargetID]], tblTargetStatus[TargetID], tblTargetStatus[successors], "" ) -> Gallery 1 Lv 1, Gallery 2 Lv 1, Gallery 3 Lv 1 | D114: =_xlfn.XLOOKUP(tblChecklist[[#This Row],[TargetID]],tblTargets[TargetID],tblTargets[TargetType],"") -> CITADEL | E114: =_xlfn.XLOOKUP(tblChecklist[[#This Row],[TargetID]],tblTargetStatus[TargetID],tblTargetStatus[ChainAwareStatus],"") -> BLOCKED | G114: FALSE | H114: =_xlfn.XLOOKUP(tblChecklist[[#This Row],[TargetID]],tblTargetStatus[TargetID],tblTargetStatus[TargetFunded],"") -> FALSE | I114: =IF( tblChecklist[[#This Row],[TargetType]]<>"BUILDING", "", IF( Player!$H$1="Active", _xlfn.XLOOKUP( tblChecklist[[#This Row],[TargetID]], tblrecommended[ActiveTargetID], tblrecommended[Order], "" ), _xlfn.XLOOKUP( tblChecklist[[#This Row],[TargetID]], tblrecommended[PassiveTargetID], tblrecommended[Order], "" ) ) )
A115: citadel.great_hall | B115: =_xlfn.XLOOKUP(tblChecklist[[#This Row],[TargetID]],tblTargets[TargetID],tblTargets[DisplayName]) -> Great Hall | C115: =_xlfn.XLOOKUP( tblChecklist[[#This Row],[TargetID]], tblTargetStatus[TargetID], tblTargetStatus[successors], "" ) -> Cheese Cave, Courtyard, Historical Library 1 Lv 1, Historical Library 2 Lv 1, Horse Lv 1, Statue Lv 1, Tame A Critter | D115: =_xlfn.XLOOKUP(tblChecklist[[#This Row],[TargetID]],tblTargets[TargetID],tblTargets[TargetType],"") -> CITADEL | E115: =_xlfn.XLOOKUP(tblChecklist[[#This Row],[TargetID]],tblTargetStatus[TargetID],tblTargetStatus[ChainAwareStatus],"") -> BLOCKED | G115: FALSE | H115: =_xlfn.XLOOKUP(tblChecklist[[#This Row],[TargetID]],tblTargetStatus[TargetID],tblTargetStatus[TargetFunded],"") -> FALSE | I115: =IF( tblChecklist[[#This Row],[TargetType]]<>"BUILDING", "", IF( Player!$H$1="Active", _xlfn.XLOOKUP( tblChecklist[[#This Row],[TargetID]], tblrecommended[ActiveTargetID], tblrecommended[Order], "" ), _xlfn.XLOOKUP( tblChecklist[[#This Row],[TargetID]], tblrecommended[PassiveTargetID], tblrecommended[Order], "" ) ) )
A116: citadel.kitchen_and_buttery | B116: =_xlfn.XLOOKUP(tblChecklist[[#This Row],[TargetID]],tblTargets[TargetID],tblTargets[DisplayName]) -> Kitchen and Buttery | C116: =_xlfn.XLOOKUP( tblChecklist[[#This Row],[TargetID]], tblTargetStatus[TargetID], tblTargetStatus[successors], "" ) -> Kitchen And Buttery 1 Lv 1, Kitchen And Buttery 2 Lv 1 | D116: =_xlfn.XLOOKUP(tblChecklist[[#This Row],[TargetID]],tblTargets[TargetID],tblTargets[TargetType],"") -> CITADEL | E116: =_xlfn.XLOOKUP(tblChecklist[[#This Row],[TargetID]],tblTargetStatus[TargetID],tblTargetStatus[ChainAwareStatus],"") -> BLOCKED | G116: FALSE | H116: =_xlfn.XLOOKUP(tblChecklist[[#This Row],[TargetID]],tblTargetStatus[TargetID],tblTargetStatus[TargetFunded],"") -> FALSE | I116: =IF( tblChecklist[[#This Row],[TargetType]]<>"BUILDING", "", IF( Player!$H$1="Active", _xlfn.XLOOKUP( tblChecklist[[#This Row],[TargetID]], tblrecommended[ActiveTargetID], tblrecommended[Order], "" ), _xlfn.XLOOKUP( tblChecklist[[#This Row],[TargetID]], tblrecommended[PassiveTargetID], tblrecommended[Order], "" ) ) )
A117: citadel.lair_lvl_1 | B117: =_xlfn.XLOOKUP(tblChecklist[[#This Row],[TargetID]],tblTargets[TargetID],tblTargets[DisplayName]) -> Lair lvl. 1 | C117: =_xlfn.XLOOKUP( tblChecklist[[#This Row],[TargetID]], tblTargetStatus[TargetID], tblTargetStatus[successors], "" ) -> Lair lvl. 2 | D117: =_xlfn.XLOOKUP(tblChecklist[[#This Row],[TargetID]],tblTargets[TargetID],tblTargets[TargetType],"") -> CITADEL | E117: =_xlfn.XLOOKUP(tblChecklist[[#This Row],[TargetID]],tblTargetStatus[TargetID],tblTargetStatus[ChainAwareStatus],"") -> BLOCKED | F117: 50 | G117: FALSE | H117: =_xlfn.XLOOKUP(tblChecklist[[#This Row],[TargetID]],tblTargetStatus[TargetID],tblTargetStatus[TargetFunded],"") -> FALSE | I117: =IF( tblChecklist[[#This Row],[TargetType]]<>"BUILDING", "", IF( Player!$H$1="Active", _xlfn.XLOOKUP( tblChecklist[[#This Row],[TargetID]], tblrecommended[ActiveTargetID], tblrecommended[Order], "" ), _xlfn.XLOOKUP( tblChecklist[[#This Row],[TargetID]], tblrecommended[PassiveTargetID], tblrecommended[Order], "" ) ) )
A118: citadel.lair_lvl_2 | B118: =_xlfn.XLOOKUP(tblChecklist[[#This Row],[TargetID]],tblTargets[TargetID],tblTargets[DisplayName]) -> Lair lvl. 2 | C118: =_xlfn.XLOOKUP( tblChecklist[[#This Row],[TargetID]], tblTargetStatus[TargetID], tblTargetStatus[successors], "" ) | D118: =_xlfn.XLOOKUP(tblChecklist[[#This Row],[TargetID]],tblTargets[TargetID],tblTargets[TargetType],"") -> CITADEL | E118: =_xlfn.XLOOKUP(tblChecklist[[#This Row],[TargetID]],tblTargetStatus[TargetID],tblTargetStatus[ChainAwareStatus],"") -> BLOCKED | G118: FALSE | H118: =_xlfn.XLOOKUP(tblChecklist[[#This Row],[TargetID]],tblTargetStatus[TargetID],tblTargetStatus[TargetFunded],"") -> FALSE | I118: =IF( tblChecklist[[#This Row],[TargetType]]<>"BUILDING", "", IF( Player!$H$1="Active", _xlfn.XLOOKUP( tblChecklist[[#This Row],[TargetID]], tblrecommended[ActiveTargetID], tblrecommended[Order], "" ), _xlfn.XLOOKUP( tblChecklist[[#This Row],[TargetID]], tblrecommended[PassiveTargetID], tblrecommended[Order], "" ) ) )
A119: citadel.mushroom_farm | B119: =_xlfn.XLOOKUP(tblChecklist[[#This Row],[TargetID]],tblTargets[TargetID],tblTargets[DisplayName]) -> Mushroom Farm | C119: =_xlfn.XLOOKUP( tblChecklist[[#This Row],[TargetID]], tblTargetStatus[TargetID], tblTargetStatus[successors], "" ) -> Mushroom Farm Lv 1 | D119: =_xlfn.XLOOKUP(tblChecklist[[#This Row],[TargetID]],tblTargets[TargetID],tblTargets[TargetType],"") -> CITADEL | E119: =_xlfn.XLOOKUP(tblChecklist[[#This Row],[TargetID]],tblTargetStatus[TargetID],tblTargetStatus[ChainAwareStatus],"") -> BLOCKED | G119: FALSE | H119: =_xlfn.XLOOKUP(tblChecklist[[#This Row],[TargetID]],tblTargetStatus[TargetID],tblTargetStatus[TargetFunded],"") -> FALSE | I119: =IF( tblChecklist[[#This Row],[TargetType]]<>"BUILDING", "", IF( Player!$H$1="Active", _xlfn.XLOOKUP( tblChecklist[[#This Row],[TargetID]], tblrecommended[ActiveTargetID], tblrecommended[Order], "" ), _xlfn.XLOOKUP( tblChecklist[[#This Row],[TargetID]], tblrecommended[PassiveTargetID], tblrecommended[Order], "" ) ) )
A120: citadel.orangery | B120: =_xlfn.XLOOKUP(tblChecklist[[#This Row],[TargetID]],tblTargets[TargetID],tblTargets[DisplayName]) -> Orangery | C120: =_xlfn.XLOOKUP( tblChecklist[[#This Row],[TargetID]], tblTargetStatus[TargetID], tblTargetStatus[successors], "" ) -> Orangery Lv 1 | D120: =_xlfn.XLOOKUP(tblChecklist[[#This Row],[TargetID]],tblTargets[TargetID],tblTargets[TargetType],"") -> CITADEL | E120: =_xlfn.XLOOKUP(tblChecklist[[#This Row],[TargetID]],tblTargetStatus[TargetID],tblTargetStatus[ChainAwareStatus],"") -> BLOCKED | G120: FALSE | H120: =_xlfn.XLOOKUP(tblChecklist[[#This Row],[TargetID]],tblTargetStatus[TargetID],tblTargetStatus[TargetFunded],"") -> FALSE | I120: =IF( tblChecklist[[#This Row],[TargetType]]<>"BUILDING", "", IF( Player!$H$1="Active", _xlfn.XLOOKUP( tblChecklist[[#This Row],[TargetID]], tblrecommended[ActiveTargetID], tblrecommended[Order], "" ), _xlfn.XLOOKUP( tblChecklist[[#This Row],[TargetID]], tblrecommended[PassiveTargetID], tblrecommended[Order], "" ) ) )
A121: citadel.pantry | B121: =_xlfn.XLOOKUP(tblChecklist[[#This Row],[TargetID]],tblTargets[TargetID],tblTargets[DisplayName]) -> Pantry | C121: =_xlfn.XLOOKUP( tblChecklist[[#This Row],[TargetID]], tblTargetStatus[TargetID], tblTargetStatus[successors], "" ) -> Pantry 1 Lv 1, Pantry 2 Lv 1, Pantry 3 Lv 1, Pantry 4 Lv 1 | D121: =_xlfn.XLOOKUP(tblChecklist[[#This Row],[TargetID]],tblTargets[TargetID],tblTargets[TargetType],"") -> CITADEL | E121: =_xlfn.XLOOKUP(tblChecklist[[#This Row],[TargetID]],tblTargetStatus[TargetID],tblTargetStatus[ChainAwareStatus],"") -> BLOCKED | G121: FALSE | H121: =_xlfn.XLOOKUP(tblChecklist[[#This Row],[TargetID]],tblTargetStatus[TargetID],tblTargetStatus[TargetFunded],"") -> FALSE | I121: =IF( tblChecklist[[#This Row],[TargetType]]<>"BUILDING", "", IF( Player!$H$1="Active", _xlfn.XLOOKUP( tblChecklist[[#This Row],[TargetID]], tblrecommended[ActiveTargetID], tblrecommended[Order], "" ), _xlfn.XLOOKUP( tblChecklist[[#This Row],[TargetID]], tblrecommended[PassiveTargetID], tblrecommended[Order], "" ) ) )
A122: citadel.tavern | B122: =_xlfn.XLOOKUP(tblChecklist[[#This Row],[TargetID]],tblTargets[TargetID],tblTargets[DisplayName]) -> Tavern | C122: =_xlfn.XLOOKUP( tblChecklist[[#This Row],[TargetID]], tblTargetStatus[TargetID], tblTargetStatus[successors], "" ) -> Tavern Lv 1 | D122: =_xlfn.XLOOKUP(tblChecklist[[#This Row],[TargetID]],tblTargets[TargetID],tblTargets[TargetType],"") -> CITADEL | E122: =_xlfn.XLOOKUP(tblChecklist[[#This Row],[TargetID]],tblTargetStatus[TargetID],tblTargetStatus[ChainAwareStatus],"") -> BLOCKED | G122: FALSE | H122: =_xlfn.XLOOKUP(tblChecklist[[#This Row],[TargetID]],tblTargetStatus[TargetID],tblTargetStatus[TargetFunded],"") -> FALSE | I122: =IF( tblChecklist[[#This Row],[TargetType]]<>"BUILDING", "", IF( Player!$H$1="Active", _xlfn.XLOOKUP( tblChecklist[[#This Row],[TargetID]], tblrecommended[ActiveTargetID], tblrecommended[Order], "" ), _xlfn.XLOOKUP( tblChecklist[[#This Row],[TargetID]], tblrecommended[PassiveTargetID], tblrecommended[Order], "" ) ) )
A123: citadel.treasury | B123: =_xlfn.XLOOKUP(tblChecklist[[#This Row],[TargetID]],tblTargets[TargetID],tblTargets[DisplayName]) -> Treasury | C123: =_xlfn.XLOOKUP( tblChecklist[[#This Row],[TargetID]], tblTargetStatus[TargetID], tblTargetStatus[successors], "" ) -> Treasury 1 Lv 1, Treasury 2 Lv 1, Treasury 3 Lv 1 | D123: =_xlfn.XLOOKUP(tblChecklist[[#This Row],[TargetID]],tblTargets[TargetID],tblTargets[TargetType],"") -> CITADEL | E123: =_xlfn.XLOOKUP(tblChecklist[[#This Row],[TargetID]],tblTargetStatus[TargetID],tblTargetStatus[ChainAwareStatus],"") -> BLOCKED | G123: FALSE | H123: =_xlfn.XLOOKUP(tblChecklist[[#This Row],[TargetID]],tblTargetStatus[TargetID],tblTargetStatus[TargetFunded],"") -> FALSE | I123: =IF( tblChecklist[[#This Row],[TargetType]]<>"BUILDING", "", IF( Player!$H$1="Active", _xlfn.XLOOKUP( tblChecklist[[#This Row],[TargetID]], tblrecommended[ActiveTargetID], tblrecommended[Order], "" ), _xlfn.XLOOKUP( tblChecklist[[#This Row],[TargetID]], tblrecommended[PassiveTargetID], tblrecommended[Order], "" ) ) )
A124: citadel.tunnel | B124: =_xlfn.XLOOKUP(tblChecklist[[#This Row],[TargetID]],tblTargets[TargetID],tblTargets[DisplayName]) -> Tunnel | C124: =_xlfn.XLOOKUP( tblChecklist[[#This Row],[TargetID]], tblTargetStatus[TargetID], tblTargetStatus[successors], "" ) -> Send Train to Sapporo, Ahead of Time Chapter 2 Finished | D124: =_xlfn.XLOOKUP(tblChecklist[[#This Row],[TargetID]],tblTargets[TargetID],tblTargets[TargetType],"") -> CITADEL | E124: =_xlfn.XLOOKUP(tblChecklist[[#This Row],[TargetID]],tblTargetStatus[TargetID],tblTargetStatus[ChainAwareStatus],"") -> BLOCKED | G124: FALSE | H124: =_xlfn.XLOOKUP(tblChecklist[[#This Row],[TargetID]],tblTargetStatus[TargetID],tblTargetStatus[TargetFunded],"") -> FALSE | I124: =IF( tblChecklist[[#This Row],[TargetType]]<>"BUILDING", "", IF( Player!$H$1="Active", _xlfn.XLOOKUP( tblChecklist[[#This Row],[TargetID]], tblrecommended[ActiveTargetID], tblrecommended[Order], "" ), _xlfn.XLOOKUP( tblChecklist[[#This Row],[TargetID]], tblrecommended[PassiveTargetID], tblrecommended[Order], "" ) ) )
A125: collection.alchemist_hall_1@1 | B125: =_xlfn.XLOOKUP(tblChecklist[[#This Row],[TargetID]],tblTargets[TargetID],tblTargets[DisplayName]) -> Alchemist Hall Lv 1 | C125: =_xlfn.XLOOKUP( tblChecklist[[#This Row],[TargetID]], tblTargetStatus[TargetID], tblTargetStatus[successors], "" ) -> Alchemist Hall Lv 2, Letter from the Dark Lady Finished | D125: =_xlfn.XLOOKUP(tblChecklist[[#This Row],[TargetID]],tblTargets[TargetID],tblTargets[TargetType],"") -> COLLECTION | E125: =_xlfn.XLOOKUP(tblChecklist[[#This Row],[TargetID]],tblTargetStatus[TargetID],tblTargetStatus[ChainAwareStatus],"") -> BLOCKED | G125: FALSE | H125: =_xlfn.XLOOKUP(tblChecklist[[#This Row],[TargetID]],tblTargetStatus[TargetID],tblTargetStatus[TargetFunded],"") -> FALSE | I125: =IF( tblChecklist[[#This Row],[TargetType]]<>"BUILDING", "", IF( Player!$H$1="Active", _xlfn.XLOOKUP( tblChecklist[[#This Row],[TargetID]], tblrecommended[ActiveTargetID], tblrecommended[Order], "" ), _xlfn.XLOOKUP( tblChecklist[[#This Row],[TargetID]], tblrecommended[PassiveTargetID], tblrecommended[Order], "" ) ) )
A126: collection.alchemist_hall_1@2 | B126: =_xlfn.XLOOKUP(tblChecklist[[#This Row],[TargetID]],tblTargets[TargetID],tblTargets[DisplayName]) -> Alchemist Hall Lv 2 | C126: =_xlfn.XLOOKUP( tblChecklist[[#This Row],[TargetID]], tblTargetStatus[TargetID], tblTargetStatus[successors], "" ) | D126: =_xlfn.XLOOKUP(tblChecklist[[#This Row],[TargetID]],tblTargets[TargetID],tblTargets[TargetType],"") -> COLLECTION | E126: =_xlfn.XLOOKUP(tblChecklist[[#This Row],[TargetID]],tblTargetStatus[TargetID],tblTargetStatus[ChainAwareStatus],"") -> BLOCKED | G126: FALSE | H126: =_xlfn.XLOOKUP(tblChecklist[[#This Row],[TargetID]],tblTargetStatus[TargetID],tblTargetStatus[TargetFunded],"") -> FALSE | I126: =IF( tblChecklist[[#This Row],[TargetType]]<>"BUILDING", "", IF( Player!$H$1="Active", _xlfn.XLOOKUP( tblChecklist[[#This Row],[TargetID]], tblrecommended[ActiveTargetID], tblrecommended[Order], "" ), _xlfn.XLOOKUP( tblChecklist[[#This Row],[TargetID]], tblrecommended[PassiveTargetID], tblrecommended[Order], "" ) ) )
A127: collection.alchemist_hall_2@1 | B127: =_xlfn.XLOOKUP(tblChecklist[[#This Row],[TargetID]],tblTargets[TargetID],tblTargets[DisplayName]) -> Alchemist Hall Lv 1 | C127: =_xlfn.XLOOKUP( tblChecklist[[#This Row],[TargetID]], tblTargetStatus[TargetID], tblTargetStatus[successors], "" ) -> Alchemist Hall Lv 2, Letter from the Dark Lady Finished | D127: =_xlfn.XLOOKUP(tblChecklist[[#This Row],[TargetID]],tblTargets[TargetID],tblTargets[TargetType],"") -> COLLECTION | E127: =_xlfn.XLOOKUP(tblChecklist[[#This Row],[TargetID]],tblTargetStatus[TargetID],tblTargetStatus[ChainAwareStatus],"") -> BLOCKED | G127: FALSE | H127: =_xlfn.XLOOKUP(tblChecklist[[#This Row],[TargetID]],tblTargetStatus[TargetID],tblTargetStatus[TargetFunded],"") -> FALSE | I127: =IF( tblChecklist[[#This Row],[TargetType]]<>"BUILDING", "", IF( Player!$H$1="Active", _xlfn.XLOOKUP( tblChecklist[[#This Row],[TargetID]], tblrecommended[ActiveTargetID], tblrecommended[Order], "" ), _xlfn.XLOOKUP( tblChecklist[[#This Row],[TargetID]], tblrecommended[PassiveTargetID], tblrecommended[Order], "" ) ) )
A128: collection.alchemist_hall_2@2 | B128: =_xlfn.XLOOKUP(tblChecklist[[#This Row],[TargetID]],tblTargets[TargetID],tblTargets[DisplayName]) -> Alchemist Hall Lv 2 | C128: =_xlfn.XLOOKUP( tblChecklist[[#This Row],[TargetID]], tblTargetStatus[TargetID], tblTargetStatus[successors], "" ) | D128: =_xlfn.XLOOKUP(tblChecklist[[#This Row],[TargetID]],tblTargets[TargetID],tblTargets[TargetType],"") -> COLLECTION | E128: =_xlfn.XLOOKUP(tblChecklist[[#This Row],[TargetID]],tblTargetStatus[TargetID],tblTargetStatus[ChainAwareStatus],"") -> BLOCKED | G128: FALSE | H128: =_xlfn.XLOOKUP(tblChecklist[[#This Row],[TargetID]],tblTargetStatus[TargetID],tblTargetStatus[TargetFunded],"") -> FALSE | I128: =IF( tblChecklist[[#This Row],[TargetType]]<>"BUILDING", "", IF( Player!$H$1="Active", _xlfn.XLOOKUP( tblChecklist[[#This Row],[TargetID]], tblrecommended[ActiveTargetID], tblrecommended[Order], "" ), _xlfn.XLOOKUP( tblChecklist[[#This Row],[TargetID]], tblrecommended[PassiveTargetID], tblrecommended[Order], "" ) ) )
A129: collection.alchemist_hall_3@1 | B129: =_xlfn.XLOOKUP(tblChecklist[[#This Row],[TargetID]],tblTargets[TargetID],tblTargets[DisplayName]) -> Alchemist Hall Lv 1 | C129: =_xlfn.XLOOKUP( tblChecklist[[#This Row],[TargetID]], tblTargetStatus[TargetID], tblTargetStatus[successors], "" ) -> Alchemist Hall Lv 2, Letter from the Dark Lady Finished | D129: =_xlfn.XLOOKUP(tblChecklist[[#This Row],[TargetID]],tblTargets[TargetID],tblTargets[TargetType],"") -> COLLECTION | E129: =_xlfn.XLOOKUP(tblChecklist[[#This Row],[TargetID]],tblTargetStatus[TargetID],tblTargetStatus[ChainAwareStatus],"") -> BLOCKED | G129: FALSE | H129: =_xlfn.XLOOKUP(tblChecklist[[#This Row],[TargetID]],tblTargetStatus[TargetID],tblTargetStatus[TargetFunded],"") -> FALSE | I129: =IF( tblChecklist[[#This Row],[TargetType]]<>"BUILDING", "", IF( Player!$H$1="Active", _xlfn.XLOOKUP( tblChecklist[[#This Row],[TargetID]], tblrecommended[ActiveTargetID], tblrecommended[Order], "" ), _xlfn.XLOOKUP( tblChecklist[[#This Row],[TargetID]], tblrecommended[PassiveTargetID], tblrecommended[Order], "" ) ) )
... A166: collection.historical_library_1@1 | B166: =_xlfn.XLOOKUP(tblChecklist[[#This Row],[TargetID]],tblTargets[TargetID],tblTargets[DisplayName]) -> Historical Library 1 Lv 1 | C166: =_xlfn.XLOOKUP( tblChecklist[[#This Row],[TargetID]], tblTargetStatus[TargetID], tblTargetStatus[successors], "" ) -> Historical Library 1 Lv 2 | D166: =_xlfn.XLOOKUP(tblChecklist[[#This Row],[TargetID]],tblTargets[TargetID],tblTargets[TargetType],"") -> COLLECTION | E166: =_xlfn.XLOOKUP(tblChecklist[[#This Row],[TargetID]],tblTargetStatus[TargetID],tblTargetStatus[ChainAwareStatus],"") -> BLOCKED | G166: FALSE | H166: =_xlfn.XLOOKUP(tblChecklist[[#This Row],[TargetID]],tblTargetStatus[TargetID],tblTargetStatus[TargetFunded],"") -> FALSE | I166: =IF( tblChecklist[[#This Row],[TargetType]]<>"BUILDING", "", IF( Player!$H$1="Active", _xlfn.XLOOKUP( tblChecklist[[#This Row],[TargetID]], tblrecommended[ActiveTargetID], tblrecommended[Order], "" ), _xlfn.XLOOKUP( tblChecklist[[#This Row],[TargetID]], tblrecommended[PassiveTargetID], tblrecommended[Order], "" ) ) )
A167: collection.historical_library_1@2 | B167: =_xlfn.XLOOKUP(tblChecklist[[#This Row],[TargetID]],tblTargets[TargetID],tblTargets[DisplayName]) -> Historical Library 1 Lv 2 | C167: =_xlfn.XLOOKUP( tblChecklist[[#This Row],[TargetID]], tblTargetStatus[TargetID], tblTargetStatus[successors], "" ) -> Historical Library 1 Lv 3 | D167: =_xlfn.XLOOKUP(tblChecklist[[#This Row],[TargetID]],tblTargets[TargetID],tblTargets[TargetType],"") -> COLLECTION | E167: =_xlfn.XLOOKUP(tblChecklist[[#This Row],[TargetID]],tblTargetStatus[TargetID],tblTargetStatus[ChainAwareStatus],"") -> BLOCKED | F167: 20 | G167: FALSE | H167: =_xlfn.XLOOKUP(tblChecklist[[#This Row],[TargetID]],tblTargetStatus[TargetID],tblTargetStatus[TargetFunded],"") -> FALSE | I167: =IF( tblChecklist[[#This Row],[TargetType]]<>"BUILDING", "", IF( Player!$H$1="Active", _xlfn.XLOOKUP( tblChecklist[[#This Row],[TargetID]], tblrecommended[ActiveTargetID], tblrecommended[Order], "" ), _xlfn.XLOOKUP( tblChecklist[[#This Row],[TargetID]], tblrecommended[PassiveTargetID], tblrecommended[Order], "" ) ) )
A168: collection.historical_library_1@3 | B168: =_xlfn.XLOOKUP(tblChecklist[[#This Row],[TargetID]],tblTargets[TargetID],tblTargets[DisplayName]) -> Historical Library 1 Lv 3 | C168: =_xlfn.XLOOKUP( tblChecklist[[#This Row],[TargetID]], tblTargetStatus[TargetID], tblTargetStatus[successors], "" ) | D168: =_xlfn.XLOOKUP(tblChecklist[[#This Row],[TargetID]],tblTargets[TargetID],tblTargets[TargetType],"") -> COLLECTION | E168: =_xlfn.XLOOKUP(tblChecklist[[#This Row],[TargetID]],tblTargetStatus[TargetID],tblTargetStatus[ChainAwareStatus],"") -> BLOCKED | G168: FALSE | H168: =_xlfn.XLOOKUP(tblChecklist[[#This Row],[TargetID]],tblTargetStatus[TargetID],tblTargetStatus[TargetFunded],"") -> FALSE | I168: =IF( tblChecklist[[#This Row],[TargetType]]<>"BUILDING", "", IF( Player!$H$1="Active", _xlfn.XLOOKUP( tblChecklist[[#This Row],[TargetID]], tblrecommended[ActiveTargetID], tblrecommended[Order], "" ), _xlfn.XLOOKUP( tblChecklist[[#This Row],[TargetID]], tblrecommended[PassiveTargetID], tblrecommended[Order], "" ) ) )
A169: collection.historical_library_2@1 | B169: =_xlfn.XLOOKUP(tblChecklist[[#This Row],[TargetID]],tblTargets[TargetID],tblTargets[DisplayName]) -> Historical Library 2 Lv 1 | C169: =_xlfn.XLOOKUP( tblChecklist[[#This Row],[TargetID]], tblTargetStatus[TargetID], tblTargetStatus[successors], "" ) -> Historical Library 2 Lv 2 | D169: =_xlfn.XLOOKUP(tblChecklist[[#This Row],[TargetID]],tblTargets[TargetID],tblTargets[TargetType],"") -> COLLECTION | E169: =_xlfn.XLOOKUP(tblChecklist[[#This Row],[TargetID]],tblTargetStatus[TargetID],tblTargetStatus[ChainAwareStatus],"") -> BLOCKED | G169: FALSE | H169: =_xlfn.XLOOKUP(tblChecklist[[#This Row],[TargetID]],tblTargetStatus[TargetID],tblTargetStatus[TargetFunded],"") -> FALSE | I169: =IF( tblChecklist[[#This Row],[TargetType]]<>"BUILDING", "", IF( Player!$H$1="Active", _xlfn.XLOOKUP( tblChecklist[[#This Row],[TargetID]], tblrecommended[ActiveTargetID], tblrecommended[Order], "" ), _xlfn.XLOOKUP( tblChecklist[[#This Row],[TargetID]], tblrecommended[PassiveTargetID], tblrecommended[Order], "" ) ) )
A170: collection.historical_library_2@2 | B170: =_xlfn.XLOOKUP(tblChecklist[[#This Row],[TargetID]],tblTargets[TargetID],tblTargets[DisplayName]) -> Historical Library 2 Lv 2 | C170: =_xlfn.XLOOKUP( tblChecklist[[#This Row],[TargetID]], tblTargetStatus[TargetID], tblTargetStatus[successors], "" ) -> Historical Library 2 Lv 3 | D170: =_xlfn.XLOOKUP(tblChecklist[[#This Row],[TargetID]],tblTargets[TargetID],tblTargets[TargetType],"") -> COLLECTION | E170: =_xlfn.XLOOKUP(tblChecklist[[#This Row],[TargetID]],tblTargetStatus[TargetID],tblTargetStatus[ChainAwareStatus],"") -> BLOCKED | G170: FALSE | H170: =_xlfn.XLOOKUP(tblChecklist[[#This Row],[TargetID]],tblTargetStatus[TargetID],tblTargetStatus[TargetFunded],"") -> FALSE | I170: =IF( tblChecklist[[#This Row],[TargetType]]<>"BUILDING", "", IF( Player!$H$1="Active", _xlfn.XLOOKUP( tblChecklist[[#This Row],[TargetID]], tblrecommended[ActiveTargetID], tblrecommended[Order], "" ), _xlfn.XLOOKUP( tblChecklist[[#This Row],[TargetID]], tblrecommended[PassiveTargetID], tblrecommended[Order], "" ) ) )
A171: collection.historical_library_2@3 | B171: =_xlfn.XLOOKUP(tblChecklist[[#This Row],[TargetID]],tblTargets[TargetID],tblTargets[DisplayName]) -> Historical Library 2 Lv 3 | C171: =_xlfn.XLOOKUP( tblChecklist[[#This Row],[TargetID]], tblTargetStatus[TargetID], tblTargetStatus[successors], "" ) | D171: =_xlfn.XLOOKUP(tblChecklist[[#This Row],[TargetID]],tblTargets[TargetID],tblTargets[TargetType],"") -> COLLECTION | E171: =_xlfn.XLOOKUP(tblChecklist[[#This Row],[TargetID]],tblTargetStatus[TargetID],tblTargetStatus[ChainAwareStatus],"") -> BLOCKED | F171: 21 | G171: FALSE | H171: =_xlfn.XLOOKUP(tblChecklist[[#This Row],[TargetID]],tblTargetStatus[TargetID],tblTargetStatus[TargetFunded],"") -> FALSE | I171: =IF( tblChecklist[[#This Row],[TargetType]]<>"BUILDING", "", IF( Player!$H$1="Active", _xlfn.XLOOKUP( tblChecklist[[#This Row],[TargetID]], tblrecommended[ActiveTargetID], tblrecommended[Order], "" ), _xlfn.XLOOKUP( tblChecklist[[#This Row],[TargetID]], tblrecommended[PassiveTargetID], tblrecommended[Order], "" ) ) )
A172: collection.horse@1 | B172: =_xlfn.XLOOKUP(tblChecklist[[#This Row],[TargetID]],tblTargets[TargetID],tblTargets[DisplayName]) -> Horse Lv 1 | C172: =_xlfn.XLOOKUP( tblChecklist[[#This Row],[TargetID]], tblTargetStatus[TargetID], tblTargetStatus[successors], "" ) | D172: =_xlfn.XLOOKUP(tblChecklist[[#This Row],[TargetID]],tblTargets[TargetID],tblTargets[TargetType],"") -> COLLECTION | E172: =_xlfn.XLOOKUP(tblChecklist[[#This Row],[TargetID]],tblTargetStatus[TargetID],tblTargetStatus[ChainAwareStatus],"") -> BLOCKED | F172: 800 | G172: FALSE | H172: =_xlfn.XLOOKUP(tblChecklist[[#This Row],[TargetID]],tblTargetStatus[TargetID],tblTargetStatus[TargetFunded],"") -> FALSE | I172: =IF( tblChecklist[[#This Row],[TargetType]]<>"BUILDING", "", IF( Player!$H$1="Active", _xlfn.XLOOKUP( tblChecklist[[#This Row],[TargetID]], tblrecommended[ActiveTargetID], tblrecommended[Order], "" ), _xlfn.XLOOKUP( tblChecklist[[#This Row],[TargetID]], tblrecommended[PassiveTargetID], tblrecommended[Order], "" ) ) )
A173: collection.kitchen_and_buttery_1@1 | B173: =_xlfn.XLOOKUP(tblChecklist[[#This Row],[TargetID]],tblTargets[TargetID],tblTargets[DisplayName]) -> Kitchen And Buttery 1 Lv 1 | C173: =_xlfn.XLOOKUP( tblChecklist[[#This Row],[TargetID]], tblTargetStatus[TargetID], tblTargetStatus[successors], "" ) -> Kitchen And Buttery 1 Lv 2 | D173: =_xlfn.XLOOKUP(tblChecklist[[#This Row],[TargetID]],tblTargets[TargetID],tblTargets[TargetType],"") -> COLLECTION | E173: =_xlfn.XLOOKUP(tblChecklist[[#This Row],[TargetID]],tblTargetStatus[TargetID],tblTargetStatus[ChainAwareStatus],"") -> BLOCKED | G173: FALSE | H173: =_xlfn.XLOOKUP(tblChecklist[[#This Row],[TargetID]],tblTargetStatus[TargetID],tblTargetStatus[TargetFunded],"") -> FALSE | I173: =IF( tblChecklist[[#This Row],[TargetType]]<>"BUILDING", "", IF( Player!$H$1="Active", _xlfn.XLOOKUP( tblChecklist[[#This Row],[TargetID]], tblrecommended[ActiveTargetID], tblrecommended[Order], "" ), _xlfn.XLOOKUP( tblChecklist[[#This Row],[TargetID]], tblrecommended[PassiveTargetID], tblrecommended[Order], "" ) ) )
A174: collection.kitchen_and_buttery_1@2 | B174: =_xlfn.XLOOKUP(tblChecklist[[#This Row],[TargetID]],tblTargets[TargetID],tblTargets[DisplayName]) -> Kitchen And Buttery 1 Lv 2 | C174: =_xlfn.XLOOKUP( tblChecklist[[#This Row],[TargetID]], tblTargetStatus[TargetID], tblTargetStatus[successors], "" ) -> Kitchen And Buttery 1 Lv 3 | D174: =_xlfn.XLOOKUP(tblChecklist[[#This Row],[TargetID]],tblTargets[TargetID],tblTargets[TargetType],"") -> COLLECTION | E174: =_xlfn.XLOOKUP(tblChecklist[[#This Row],[TargetID]],tblTargetStatus[TargetID],tblTargetStatus[ChainAwareStatus],"") -> BLOCKED | G174: FALSE | H174: =_xlfn.XLOOKUP(tblChecklist[[#This Row],[TargetID]],tblTargetStatus[TargetID],tblTargetStatus[TargetFunded],"") -> FALSE | I174: =IF( tblChecklist[[#This Row],[TargetType]]<>"BUILDING", "", IF( Player!$H$1="Active", _xlfn.XLOOKUP( tblChecklist[[#This Row],[TargetID]], tblrecommended[ActiveTargetID], tblrecommended[Order], "" ), _xlfn.XLOOKUP( tblChecklist[[#This Row],[TargetID]], tblrecommended[PassiveTargetID], tblrecommended[Order], "" ) ) )
A175: collection.kitchen_and_buttery_1@3 | B175: =_xlfn.XLOOKUP(tblChecklist[[#This Row],[TargetID]],tblTargets[TargetID],tblTargets[DisplayName]) -> Kitchen And Buttery 1 Lv 3 | C175: =_xlfn.XLOOKUP( tblChecklist[[#This Row],[TargetID]], tblTargetStatus[TargetID], tblTargetStatus[successors], "" ) -> Kitchen And Buttery 1 Lv 4 | D175: =_xlfn.XLOOKUP(tblChecklist[[#This Row],[TargetID]],tblTargets[TargetID],tblTargets[TargetType],"") -> COLLECTION | E175: =_xlfn.XLOOKUP(tblChecklist[[#This Row],[TargetID]],tblTargetStatus[TargetID],tblTargetStatus[ChainAwareStatus],"") -> BLOCKED | G175: FALSE | H175: =_xlfn.XLOOKUP(tblChecklist[[#This Row],[TargetID]],tblTargetStatus[TargetID],tblTargetStatus[TargetFunded],"") -> FALSE | I175: =IF( tblChecklist[[#This Row],[TargetType]]<>"BUILDING", "", IF( Player!$H$1="Active", _xlfn.XLOOKUP( tblChecklist[[#This Row],[TargetID]], tblrecommended[ActiveTargetID], tblrecommended[Order], "" ), _xlfn.XLOOKUP( tblChecklist[[#This Row],[TargetID]], tblrecommended[PassiveTargetID], tblrecommended[Order], "" ) ) )
...

Sheet cost checklist
A1: RequirementID | B1: TargetID | C1: DisplayName | D1: TargetType | E1: ResourceID | F1: PaymentSlot | G1: QuantityRequired | H1: Sort | I1: TargetCompleted | J1: PlayerPaid | R1: {=_xlfn._xlws.SORT( _xlfn.UNIQUE( _xlfn._xlws.FILTER( tblCostChecklist[ResourceID], (tblCostChecklist[PlayerPaid]=FALSE)* (tblCostChecklist[TargetCompleted]="READY") ) ) )} -> coin
A2: cost.building.airship@1.ruby.1 | B2: =_xlfn.TEXTAFTER( _xlfn.TEXTBEFORE(tblCostChecklist[[#This Row],[RequirementID]],".",-2), "cost." ) -> building.airship@1 | C2: =_xlfn.XLOOKUP(tblCostChecklist[[#This Row],[TargetID]],tblTargets[TargetID],tblTargets[DisplayName],"") -> Airship Lv 1 | D2: =_xlfn.XLOOKUP(tblCostChecklist[[#This Row],[TargetID]],tblTargets[TargetID],tblTargets[TargetType],"") -> BUILDING | E2: ruby | F2: 1 | G2: =_xlfn.XLOOKUP( tblCostChecklist[[#This Row],[RequirementID]], tblCost[RequirementID], tblCost[QuantityRequired], "" ) -> 10 | H2: =IF(OR(LEFT(tblCostChecklist[[#This Row],[TargetID]],10)="state.CHAR",RIGHT(tblCostChecklist[[#This Row],[TargetID]],5)="maxed"),0,IF(_xlfn.XLOOKUP(tblCostChecklist[[#This Row],[TargetID]],tblChecklist[TargetID],tblChecklist[PlayerSort])=0,500,_xlfn.XLOOKUP(tblCostChecklist[[#This Row],[TargetID]],tblChecklist[TargetID],tblChecklist[PlayerSort]))) -> 44 | I2: =_xlfn.XLOOKUP(tblCostChecklist[[#This Row],[TargetID]],tblTargetStatus[TargetID],tblTargetStatus[Status]) -> BLOCKED | J2: FALSE | R2: ruby
A3: cost.building.airship@1.coin.1 | B3: =_xlfn.TEXTAFTER( _xlfn.TEXTBEFORE(tblCostChecklist[[#This Row],[RequirementID]],".",-2), "cost." ) -> building.airship@1 | C3: =_xlfn.XLOOKUP(tblCostChecklist[[#This Row],[TargetID]],tblTargets[TargetID],tblTargets[DisplayName],"") -> Airship Lv 1 | D3: =_xlfn.XLOOKUP(tblCostChecklist[[#This Row],[TargetID]],tblTargets[TargetID],tblTargets[TargetType],"") -> BUILDING | E3: coin | F3: 1 | G3: =_xlfn.XLOOKUP( tblCostChecklist[[#This Row],[RequirementID]], tblCost[RequirementID], tblCost[QuantityRequired], "" ) -> 2000 | H3: =IF(OR(LEFT(tblCostChecklist[[#This Row],[TargetID]],10)="state.CHAR",RIGHT(tblCostChecklist[[#This Row],[TargetID]],5)="maxed"),0,IF(_xlfn.XLOOKUP(tblCostChecklist[[#This Row],[TargetID]],tblChecklist[TargetID],tblChecklist[PlayerSort])=0,500,_xlfn.XLOOKUP(tblCostChecklist[[#This Row],[TargetID]],tblChecklist[TargetID],tblChecklist[PlayerSort]))) -> 44 | I3: =_xlfn.XLOOKUP(tblCostChecklist[[#This Row],[TargetID]],tblTargetStatus[TargetID],tblTargetStatus[Status]) -> BLOCKED | J3: FALSE | R3: stone
A4: cost.building.airship@1.silk.1 | B4: =_xlfn.TEXTAFTER( _xlfn.TEXTBEFORE(tblCostChecklist[[#This Row],[RequirementID]],".",-2), "cost." ) -> building.airship@1 | C4: =_xlfn.XLOOKUP(tblCostChecklist[[#This Row],[TargetID]],tblTargets[TargetID],tblTargets[DisplayName],"") -> Airship Lv 1 | D4: =_xlfn.XLOOKUP(tblCostChecklist[[#This Row],[TargetID]],tblTargets[TargetID],tblTargets[TargetType],"") -> BUILDING | E4: silk | F4: 1 | G4: =_xlfn.XLOOKUP( tblCostChecklist[[#This Row],[RequirementID]], tblCost[RequirementID], tblCost[QuantityRequired], "" ) -> 120 | H4: =IF(OR(LEFT(tblCostChecklist[[#This Row],[TargetID]],10)="state.CHAR",RIGHT(tblCostChecklist[[#This Row],[TargetID]],5)="maxed"),0,IF(_xlfn.XLOOKUP(tblCostChecklist[[#This Row],[TargetID]],tblChecklist[TargetID],tblChecklist[PlayerSort])=0,500,_xlfn.XLOOKUP(tblCostChecklist[[#This Row],[TargetID]],tblChecklist[TargetID],tblChecklist[PlayerSort]))) -> 44 | I4: =_xlfn.XLOOKUP(tblCostChecklist[[#This Row],[TargetID]],tblTargetStatus[TargetID],tblTargetStatus[Status]) -> BLOCKED | J4: FALSE | R4: wood
A5: cost.building.airship@1.thread.1 | B5: =_xlfn.TEXTAFTER( _xlfn.TEXTBEFORE(tblCostChecklist[[#This Row],[RequirementID]],".",-2), "cost." ) -> building.airship@1 | C5: =_xlfn.XLOOKUP(tblCostChecklist[[#This Row],[TargetID]],tblTargets[TargetID],tblTargets[DisplayName],"") -> Airship Lv 1 | D5: =_xlfn.XLOOKUP(tblCostChecklist[[#This Row],[TargetID]],tblTargets[TargetID],tblTargets[TargetType],"") -> BUILDING | E5: thread | F5: 1 | G5: =_xlfn.XLOOKUP( tblCostChecklist[[#This Row],[RequirementID]], tblCost[RequirementID], tblCost[QuantityRequired], "" ) -> 20 | H5: =IF(OR(LEFT(tblCostChecklist[[#This Row],[TargetID]],10)="state.CHAR",RIGHT(tblCostChecklist[[#This Row],[TargetID]],5)="maxed"),0,IF(_xlfn.XLOOKUP(tblCostChecklist[[#This Row],[TargetID]],tblChecklist[TargetID],tblChecklist[PlayerSort])=0,500,_xlfn.XLOOKUP(tblCostChecklist[[#This Row],[TargetID]],tblChecklist[TargetID],tblChecklist[PlayerSort]))) -> 44 | I5: =_xlfn.XLOOKUP(tblCostChecklist[[#This Row],[TargetID]],tblTargetStatus[TargetID],tblTargetStatus[Status]) -> BLOCKED | J5: FALSE
A6: cost.building.airship@1.chemicals.1 | B6: =_xlfn.TEXTAFTER( _xlfn.TEXTBEFORE(tblCostChecklist[[#This Row],[RequirementID]],".",-2), "cost." ) -> building.airship@1 | C6: =_xlfn.XLOOKUP(tblCostChecklist[[#This Row],[TargetID]],tblTargets[TargetID],tblTargets[DisplayName],"") -> Airship Lv 1 | D6: =_xlfn.XLOOKUP(tblCostChecklist[[#This Row],[TargetID]],tblTargets[TargetID],tblTargets[TargetType],"") -> BUILDING | E6: chemicals | F6: 1 | G6: =_xlfn.XLOOKUP( tblCostChecklist[[#This Row],[RequirementID]], tblCost[RequirementID], tblCost[QuantityRequired], "" ) -> 200 | H6: =IF(OR(LEFT(tblCostChecklist[[#This Row],[TargetID]],10)="state.CHAR",RIGHT(tblCostChecklist[[#This Row],[TargetID]],5)="maxed"),0,IF(_xlfn.XLOOKUP(tblCostChecklist[[#This Row],[TargetID]],tblChecklist[TargetID],tblChecklist[PlayerSort])=0,500,_xlfn.XLOOKUP(tblCostChecklist[[#This Row],[TargetID]],tblChecklist[TargetID],tblChecklist[PlayerSort]))) -> 44 | I6: =_xlfn.XLOOKUP(tblCostChecklist[[#This Row],[TargetID]],tblTargetStatus[TargetID],tblTargetStatus[Status]) -> BLOCKED | J6: FALSE
A7: cost.building.airship@1.reagent.1 | B7: =_xlfn.TEXTAFTER( _xlfn.TEXTBEFORE(tblCostChecklist[[#This Row],[RequirementID]],".",-2), "cost." ) -> building.airship@1 | C7: =_xlfn.XLOOKUP(tblCostChecklist[[#This Row],[TargetID]],tblTargets[TargetID],tblTargets[DisplayName],"") -> Airship Lv 1 | D7: =_xlfn.XLOOKUP(tblCostChecklist[[#This Row],[TargetID]],tblTargets[TargetID],tblTargets[TargetType],"") -> BUILDING | E7: reagent | F7: 1 | G7: =_xlfn.XLOOKUP( tblCostChecklist[[#This Row],[RequirementID]], tblCost[RequirementID], tblCost[QuantityRequired], "" ) -> 20 | H7: =IF(OR(LEFT(tblCostChecklist[[#This Row],[TargetID]],10)="state.CHAR",RIGHT(tblCostChecklist[[#This Row],[TargetID]],5)="maxed"),0,IF(_xlfn.XLOOKUP(tblCostChecklist[[#This Row],[TargetID]],tblChecklist[TargetID],tblChecklist[PlayerSort])=0,500,_xlfn.XLOOKUP(tblCostChecklist[[#This Row],[TargetID]],tblChecklist[TargetID],tblChecklist[PlayerSort]))) -> 44 | I7: =_xlfn.XLOOKUP(tblCostChecklist[[#This Row],[TargetID]],tblTargetStatus[TargetID],tblTargetStatus[Status]) -> BLOCKED | J7: FALSE
A8: cost.building.airship@1.miron.1 | B8: =_xlfn.TEXTAFTER( _xlfn.TEXTBEFORE(tblCostChecklist[[#This Row],[RequirementID]],".",-2), "cost." ) -> building.airship@1 | C8: =_xlfn.XLOOKUP(tblCostChecklist[[#This Row],[TargetID]],tblTargets[TargetID],tblTargets[DisplayName],"") -> Airship Lv 1 | D8: =_xlfn.XLOOKUP(tblCostChecklist[[#This Row],[TargetID]],tblTargets[TargetID],tblTargets[TargetType],"") -> BUILDING | E8: miron | F8: 1 | G8: =_xlfn.XLOOKUP( tblCostChecklist[[#This Row],[RequirementID]], tblCost[RequirementID], tblCost[QuantityRequired], "" ) -> 50 | H8: =IF(OR(LEFT(tblCostChecklist[[#This Row],[TargetID]],10)="state.CHAR",RIGHT(tblCostChecklist[[#This Row],[TargetID]],5)="maxed"),0,IF(_xlfn.XLOOKUP(tblCostChecklist[[#This Row],[TargetID]],tblChecklist[TargetID],tblChecklist[PlayerSort])=0,500,_xlfn.XLOOKUP(tblCostChecklist[[#This Row],[TargetID]],tblChecklist[TargetID],tblChecklist[PlayerSort]))) -> 44 | I8: =_xlfn.XLOOKUP(tblCostChecklist[[#This Row],[TargetID]],tblTargetStatus[TargetID],tblTargetStatus[Status]) -> BLOCKED | J8: FALSE
A9: cost.building.airship@1.page.1 | B9: =_xlfn.TEXTAFTER( _xlfn.TEXTBEFORE(tblCostChecklist[[#This Row],[RequirementID]],".",-2), "cost." ) -> building.airship@1 | C9: =_xlfn.XLOOKUP(tblCostChecklist[[#This Row],[TargetID]],tblTargets[TargetID],tblTargets[DisplayName],"") -> Airship Lv 1 | D9: =_xlfn.XLOOKUP(tblCostChecklist[[#This Row],[TargetID]],tblTargets[TargetID],tblTargets[TargetType],"") -> BUILDING | E9: page | F9: 1 | G9: =_xlfn.XLOOKUP( tblCostChecklist[[#This Row],[RequirementID]], tblCost[RequirementID], tblCost[QuantityRequired], "" ) -> 40 | H9: =IF(OR(LEFT(tblCostChecklist[[#This Row],[TargetID]],10)="state.CHAR",RIGHT(tblCostChecklist[[#This Row],[TargetID]],5)="maxed"),0,IF(_xlfn.XLOOKUP(tblCostChecklist[[#This Row],[TargetID]],tblChecklist[TargetID],tblChecklist[PlayerSort])=0,500,_xlfn.XLOOKUP(tblCostChecklist[[#This Row],[TargetID]],tblChecklist[TargetID],tblChecklist[PlayerSort]))) -> 44 | I9: =_xlfn.XLOOKUP(tblCostChecklist[[#This Row],[TargetID]],tblTargetStatus[TargetID],tblTargetStatus[Status]) -> BLOCKED | J9: FALSE
A10: cost.building.airship@2.ruby.1 | B10: =_xlfn.TEXTAFTER( _xlfn.TEXTBEFORE(tblCostChecklist[[#This Row],[RequirementID]],".",-2), "cost." ) -> building.airship@2 | C10: =_xlfn.XLOOKUP(tblCostChecklist[[#This Row],[TargetID]],tblTargets[TargetID],tblTargets[DisplayName],"") -> Airship Lv 2 | D10: =_xlfn.XLOOKUP(tblCostChecklist[[#This Row],[TargetID]],tblTargets[TargetID],tblTargets[TargetType],"") -> BUILDING | E10: ruby | F10: 1 | G10: =_xlfn.XLOOKUP( tblCostChecklist[[#This Row],[RequirementID]], tblCost[RequirementID], tblCost[QuantityRequired], "" ) -> 12 | H10: =IF(OR(LEFT(tblCostChecklist[[#This Row],[TargetID]],10)="state.CHAR",RIGHT(tblCostChecklist[[#This Row],[TargetID]],5)="maxed"),0,IF(_xlfn.XLOOKUP(tblCostChecklist[[#This Row],[TargetID]],tblChecklist[TargetID],tblChecklist[PlayerSort])=0,500,_xlfn.XLOOKUP(tblCostChecklist[[#This Row],[TargetID]],tblChecklist[TargetID],tblChecklist[PlayerSort]))) -> 45 | I10: =_xlfn.XLOOKUP(tblCostChecklist[[#This Row],[TargetID]],tblTargetStatus[TargetID],tblTargetStatus[Status]) -> BLOCKED | J10: FALSE
A11: cost.building.airship@2.coin.1 | B11: =_xlfn.TEXTAFTER( _xlfn.TEXTBEFORE(tblCostChecklist[[#This Row],[RequirementID]],".",-2), "cost." ) -> building.airship@2 | C11: =_xlfn.XLOOKUP(tblCostChecklist[[#This Row],[TargetID]],tblTargets[TargetID],tblTargets[DisplayName],"") -> Airship Lv 2 | D11: =_xlfn.XLOOKUP(tblCostChecklist[[#This Row],[TargetID]],tblTargets[TargetID],tblTargets[TargetType],"") -> BUILDING | E11: coin | F11: 1 | G11: =_xlfn.XLOOKUP( tblCostChecklist[[#This Row],[RequirementID]], tblCost[RequirementID], tblCost[QuantityRequired], "" ) -> 3000 | H11: =IF(OR(LEFT(tblCostChecklist[[#This Row],[TargetID]],10)="state.CHAR",RIGHT(tblCostChecklist[[#This Row],[TargetID]],5)="maxed"),0,IF(_xlfn.XLOOKUP(tblCostChecklist[[#This Row],[TargetID]],tblChecklist[TargetID],tblChecklist[PlayerSort])=0,500,_xlfn.XLOOKUP(tblCostChecklist[[#This Row],[TargetID]],tblChecklist[TargetID],tblChecklist[PlayerSort]))) -> 45 | I11: =_xlfn.XLOOKUP(tblCostChecklist[[#This Row],[TargetID]],tblTargetStatus[TargetID],tblTargetStatus[Status]) -> BLOCKED | J11: FALSE
A12: cost.building.airship@2.plank.1 | B12: =_xlfn.TEXTAFTER( _xlfn.TEXTBEFORE(tblCostChecklist[[#This Row],[RequirementID]],".",-2), "cost." ) -> building.airship@2 | C12: =_xlfn.XLOOKUP(tblCostChecklist[[#This Row],[TargetID]],tblTargets[TargetID],tblTargets[DisplayName],"") -> Airship Lv 2 | D12: =_xlfn.XLOOKUP(tblCostChecklist[[#This Row],[TargetID]],tblTargets[TargetID],tblTargets[TargetType],"") -> BUILDING | E12: plank | F12: 1 | G12: =_xlfn.XLOOKUP( tblCostChecklist[[#This Row],[RequirementID]], tblCost[RequirementID], tblCost[QuantityRequired], "" ) -> 60 | H12: =IF(OR(LEFT(tblCostChecklist[[#This Row],[TargetID]],10)="state.CHAR",RIGHT(tblCostChecklist[[#This Row],[TargetID]],5)="maxed"),0,IF(_xlfn.XLOOKUP(tblCostChecklist[[#This Row],[TargetID]],tblChecklist[TargetID],tblChecklist[PlayerSort])=0,500,_xlfn.XLOOKUP(tblCostChecklist[[#This Row],[TargetID]],tblChecklist[TargetID],tblChecklist[PlayerSort]))) -> 45 | I12: =_xlfn.XLOOKUP(tblCostChecklist[[#This Row],[TargetID]],tblTargetStatus[TargetID],tblTargetStatus[Status]) -> BLOCKED | J12: FALSE
A13: cost.building.airship@2.silk.1 | B13: =_xlfn.TEXTAFTER( _xlfn.TEXTBEFORE(tblCostChecklist[[#This Row],[RequirementID]],".",-2), "cost." ) -> building.airship@2 | C13: =_xlfn.XLOOKUP(tblCostChecklist[[#This Row],[TargetID]],tblTargets[TargetID],tblTargets[DisplayName],"") -> Airship Lv 2 | D13: =_xlfn.XLOOKUP(tblCostChecklist[[#This Row],[TargetID]],tblTargets[TargetID],tblTargets[TargetType],"") -> BUILDING | E13: silk | F13: 1 | G13: =_xlfn.XLOOKUP( tblCostChecklist[[#This Row],[RequirementID]], tblCost[RequirementID], tblCost[QuantityRequired], "" ) -> 100 | H13: =IF(OR(LEFT(tblCostChecklist[[#This Row],[TargetID]],10)="state.CHAR",RIGHT(tblCostChecklist[[#This Row],[TargetID]],5)="maxed"),0,IF(_xlfn.XLOOKUP(tblCostChecklist[[#This Row],[TargetID]],tblChecklist[TargetID],tblChecklist[PlayerSort])=0,500,_xlfn.XLOOKUP(tblCostChecklist[[#This Row],[TargetID]],tblChecklist[TargetID],tblChecklist[PlayerSort]))) -> 45 | I13: =_xlfn.XLOOKUP(tblCostChecklist[[#This Row],[TargetID]],tblTargetStatus[TargetID],tblTargetStatus[Status]) -> BLOCKED | J13: FALSE
A14: cost.building.airship@2.gears.1 | B14: =_xlfn.TEXTAFTER( _xlfn.TEXTBEFORE(tblCostChecklist[[#This Row],[RequirementID]],".",-2), "cost." ) -> building.airship@2 | C14: =_xlfn.XLOOKUP(tblCostChecklist[[#This Row],[TargetID]],tblTargets[TargetID],tblTargets[DisplayName],"") -> Airship Lv 2 | D14: =_xlfn.XLOOKUP(tblCostChecklist[[#This Row],[TargetID]],tblTargets[TargetID],tblTargets[TargetType],"") -> BUILDING | E14: gears | F14: 1 | G14: =_xlfn.XLOOKUP( tblCostChecklist[[#This Row],[RequirementID]], tblCost[RequirementID], tblCost[QuantityRequired], "" ) -> 20 | H14: =IF(OR(LEFT(tblCostChecklist[[#This Row],[TargetID]],10)="state.CHAR",RIGHT(tblCostChecklist[[#This Row],[TargetID]],5)="maxed"),0,IF(_xlfn.XLOOKUP(tblCostChecklist[[#This Row],[TargetID]],tblChecklist[TargetID],tblChecklist[PlayerSort])=0,500,_xlfn.XLOOKUP(tblCostChecklist[[#This Row],[TargetID]],tblChecklist[TargetID],tblChecklist[PlayerSort]))) -> 45 | I14: =_xlfn.XLOOKUP(tblCostChecklist[[#This Row],[TargetID]],tblTargetStatus[TargetID],tblTargetStatus[Status]) -> BLOCKED | J14: FALSE
A15: cost.building.airship@2.fan.1 | B15: =_xlfn.TEXTAFTER( _xlfn.TEXTBEFORE(tblCostChecklist[[#This Row],[RequirementID]],".",-2), "cost." ) -> building.airship@2 | C15: =_xlfn.XLOOKUP(tblCostChecklist[[#This Row],[TargetID]],tblTargets[TargetID],tblTargets[DisplayName],"") -> Airship Lv 2 | D15: =_xlfn.XLOOKUP(tblCostChecklist[[#This Row],[TargetID]],tblTargets[TargetID],tblTargets[TargetType],"") -> BUILDING | E15: fan | F15: 1 | G15: =_xlfn.XLOOKUP( tblCostChecklist[[#This Row],[RequirementID]], tblCost[RequirementID], tblCost[QuantityRequired], "" ) -> 50 | H15: =IF(OR(LEFT(tblCostChecklist[[#This Row],[TargetID]],10)="state.CHAR",RIGHT(tblCostChecklist[[#This Row],[TargetID]],5)="maxed"),0,IF(_xlfn.XLOOKUP(tblCostChecklist[[#This Row],[TargetID]],tblChecklist[TargetID],tblChecklist[PlayerSort])=0,500,_xlfn.XLOOKUP(tblCostChecklist[[#This Row],[TargetID]],tblChecklist[TargetID],tblChecklist[PlayerSort]))) -> 45 | I15: =_xlfn.XLOOKUP(tblCostChecklist[[#This Row],[TargetID]],tblTargetStatus[TargetID],tblTargetStatus[Status]) -> BLOCKED | J15: FALSE
A16: cost.building.airship@2.thread.1 | B16: =_xlfn.TEXTAFTER( _xlfn.TEXTBEFORE(tblCostChecklist[[#This Row],[RequirementID]],".",-2), "cost." ) -> building.airship@2 | C16: =_xlfn.XLOOKUP(tblCostChecklist[[#This Row],[TargetID]],tblTargets[TargetID],tblTargets[DisplayName],"") -> Airship Lv 2 | D16: =_xlfn.XLOOKUP(tblCostChecklist[[#This Row],[TargetID]],tblTargets[TargetID],tblTargets[TargetType],"") -> BUILDING | E16: thread | F16: 1 | G16: =_xlfn.XLOOKUP( tblCostChecklist[[#This Row],[RequirementID]], tblCost[RequirementID], tblCost[QuantityRequired], "" ) -> 10 | H16: =IF(OR(LEFT(tblCostChecklist[[#This Row],[TargetID]],10)="state.CHAR",RIGHT(tblCostChecklist[[#This Row],[TargetID]],5)="maxed"),0,IF(_xlfn.XLOOKUP(tblCostChecklist[[#This Row],[TargetID]],tblChecklist[TargetID],tblChecklist[PlayerSort])=0,500,_xlfn.XLOOKUP(tblCostChecklist[[#This Row],[TargetID]],tblChecklist[TargetID],tblChecklist[PlayerSort]))) -> 45 | I16: =_xlfn.XLOOKUP(tblCostChecklist[[#This Row],[TargetID]],tblTargetStatus[TargetID],tblTargetStatus[Status]) -> BLOCKED | J16: FALSE
... A1847: cost.craftifact.trigonometry.page.1 | B1847: =_xlfn.TEXTAFTER( _xlfn.TEXTBEFORE(tblCostChecklist[[#This Row],[RequirementID]],".",-2), "cost." ) -> craftifact.trigonometry | C1847: =_xlfn.XLOOKUP(tblCostChecklist[[#This Row],[TargetID]],tblTargets[TargetID],tblTargets[DisplayName],"") -> Trigonometry | D1847: =_xlfn.XLOOKUP(tblCostChecklist[[#This Row],[TargetID]],tblTargets[TargetID],tblTargets[TargetType],"") -> CRAFTIFACT | E1847: page | F1847: 1 | G1847: =_xlfn.XLOOKUP( tblCostChecklist[[#This Row],[RequirementID]], tblCost[RequirementID], tblCost[QuantityRequired], "" ) -> 60 | H1847: =IF(OR(LEFT(tblCostChecklist[[#This Row],[TargetID]],10)="state.CHAR",RIGHT(tblCostChecklist[[#This Row],[TargetID]],5)="maxed"),0,IF(_xlfn.XLOOKUP(tblCostChecklist[[#This Row],[TargetID]],tblChecklist[TargetID],tblChecklist[PlayerSort])=0,500,_xlfn.XLOOKUP(tblCostChecklist[[#This Row],[TargetID]],tblChecklist[TargetID],tblChecklist[PlayerSort]))) -> 500 | I1847: =_xlfn.XLOOKUP(tblCostChecklist[[#This Row],[TargetID]],tblTargetStatus[TargetID],tblTargetStatus[Status]) -> BLOCKED | J1847: FALSE
A1848: cost.craftifact.trigonometry.scroll.1 | B1848: =_xlfn.TEXTAFTER( _xlfn.TEXTBEFORE(tblCostChecklist[[#This Row],[RequirementID]],".",-2), "cost." ) -> craftifact.trigonometry | C1848: =_xlfn.XLOOKUP(tblCostChecklist[[#This Row],[TargetID]],tblTargets[TargetID],tblTargets[DisplayName],"") -> Trigonometry | D1848: =_xlfn.XLOOKUP(tblCostChecklist[[#This Row],[TargetID]],tblTargets[TargetID],tblTargets[TargetType],"") -> CRAFTIFACT | E1848: scroll | F1848: 1 | G1848: =_xlfn.XLOOKUP( tblCostChecklist[[#This Row],[RequirementID]], tblCost[RequirementID], tblCost[QuantityRequired], "" ) -> 1 | H1848: =IF(OR(LEFT(tblCostChecklist[[#This Row],[TargetID]],10)="state.CHAR",RIGHT(tblCostChecklist[[#This Row],[TargetID]],5)="maxed"),0,IF(_xlfn.XLOOKUP(tblCostChecklist[[#This Row],[TargetID]],tblChecklist[TargetID],tblChecklist[PlayerSort])=0,500,_xlfn.XLOOKUP(tblCostChecklist[[#This Row],[TargetID]],tblChecklist[TargetID],tblChecklist[PlayerSort]))) -> 500 | I1848: =_xlfn.XLOOKUP(tblCostChecklist[[#This Row],[TargetID]],tblTargetStatus[TargetID],tblTargetStatus[Status]) -> BLOCKED | J1848: FALSE | L1848: =_xlfn.REGEXREPLACE(tblCostChecklist[[#This Row],[RequirementID]],"finished","accepted") -> cost.craftifact.trigonometry.scroll.1
A1849: cost.quest.ahead_of_time_chapter_1.finished.pbr.1 | B1849: =_xlfn.TEXTAFTER( _xlfn.TEXTBEFORE(tblCostChecklist[[#This Row],[RequirementID]],".",-2), "cost." ) -> quest.ahead_of_time_chapter_1.finished | C1849: =_xlfn.XLOOKUP(tblCostChecklist[[#This Row],[TargetID]],tblTargets[TargetID],tblTargets[DisplayName],"") -> Ahead of Time Chapter 1 Finished | D1849: =_xlfn.XLOOKUP(tblCostChecklist[[#This Row],[TargetID]],tblTargets[TargetID],tblTargets[TargetType],"") -> QUEST | E1849: pbr | F1849: 1 | G1849: =_xlfn.XLOOKUP( tblCostChecklist[[#This Row],[RequirementID]], tblCost[RequirementID], tblCost[QuantityRequired], "" ) -> 1 | H1849: =IF(OR(LEFT(tblCostChecklist[[#This Row],[TargetID]],10)="state.CHAR",RIGHT(tblCostChecklist[[#This Row],[TargetID]],5)="maxed"),0,IF(_xlfn.XLOOKUP(tblCostChecklist[[#This Row],[TargetID]],tblChecklist[TargetID],tblChecklist[PlayerSort])=0,500,_xlfn.XLOOKUP(tblCostChecklist[[#This Row],[TargetID]],tblChecklist[TargetID],tblChecklist[PlayerSort]))) -> 500 | I1849: =_xlfn.XLOOKUP(tblCostChecklist[[#This Row],[TargetID]],tblTargetStatus[TargetID],tblTargetStatus[Status]) -> BLOCKED | J1849: FALSE | L1849: =_xlfn.REGEXREPLACE(tblCostChecklist[[#This Row],[RequirementID]],"finished","accepted") -> cost.quest.ahead_of_time_chapter_1.accepted.pbr.1
A1850: cost.quest.ahead_of_time_chapter_1.finished.horn.1 | B1850: =_xlfn.TEXTAFTER( _xlfn.TEXTBEFORE(tblCostChecklist[[#This Row],[RequirementID]],".",-2), "cost." ) -> quest.ahead_of_time_chapter_1.finished | C1850: =_xlfn.XLOOKUP(tblCostChecklist[[#This Row],[TargetID]],tblTargets[TargetID],tblTargets[DisplayName],"") -> Ahead of Time Chapter 1 Finished | D1850: =_xlfn.XLOOKUP(tblCostChecklist[[#This Row],[TargetID]],tblTargets[TargetID],tblTargets[TargetType],"") -> QUEST | E1850: horn | F1850: 1 | G1850: =_xlfn.XLOOKUP( tblCostChecklist[[#This Row],[RequirementID]], tblCost[RequirementID], tblCost[QuantityRequired], "" ) -> 1 | H1850: =IF(OR(LEFT(tblCostChecklist[[#This Row],[TargetID]],10)="state.CHAR",RIGHT(tblCostChecklist[[#This Row],[TargetID]],5)="maxed"),0,IF(_xlfn.XLOOKUP(tblCostChecklist[[#This Row],[TargetID]],tblChecklist[TargetID],tblChecklist[PlayerSort])=0,500,_xlfn.XLOOKUP(tblCostChecklist[[#This Row],[TargetID]],tblChecklist[TargetID],tblChecklist[PlayerSort]))) -> 500 | I1850: =_xlfn.XLOOKUP(tblCostChecklist[[#This Row],[TargetID]],tblTargetStatus[TargetID],tblTargetStatus[Status]) -> BLOCKED | J1850: FALSE
A1851: cost.quest.ahead_of_time_chapter_1.finished.pa.1 | B1851: =_xlfn.TEXTAFTER( _xlfn.TEXTBEFORE(tblCostChecklist[[#This Row],[RequirementID]],".",-2), "cost." ) -> quest.ahead_of_time_chapter_1.finished | C1851: =_xlfn.XLOOKUP(tblCostChecklist[[#This Row],[TargetID]],tblTargets[TargetID],tblTargets[DisplayName],"") -> Ahead of Time Chapter 1 Finished | D1851: =_xlfn.XLOOKUP(tblCostChecklist[[#This Row],[TargetID]],tblTargets[TargetID],tblTargets[TargetType],"") -> QUEST | E1851: pa | F1851: 1 | G1851: =_xlfn.XLOOKUP( tblCostChecklist[[#This Row],[RequirementID]], tblCost[RequirementID], tblCost[QuantityRequired], "" ) -> 1 | H1851: =IF(OR(LEFT(tblCostChecklist[[#This Row],[TargetID]],10)="state.CHAR",RIGHT(tblCostChecklist[[#This Row],[TargetID]],5)="maxed"),0,IF(_xlfn.XLOOKUP(tblCostChecklist[[#This Row],[TargetID]],tblChecklist[TargetID],tblChecklist[PlayerSort])=0,500,_xlfn.XLOOKUP(tblCostChecklist[[#This Row],[TargetID]],tblChecklist[TargetID],tblChecklist[PlayerSort]))) -> 500 | I1851: =_xlfn.XLOOKUP(tblCostChecklist[[#This Row],[TargetID]],tblTargetStatus[TargetID],tblTargetStatus[Status]) -> BLOCKED | J1851: FALSE
A1852: cost.quest.ahead_of_time_chapter_1.finished.pasta.1 | B1852: =_xlfn.TEXTAFTER( _xlfn.TEXTBEFORE(tblCostChecklist[[#This Row],[RequirementID]],".",-2), "cost." ) -> quest.ahead_of_time_chapter_1.finished | C1852: =_xlfn.XLOOKUP(tblCostChecklist[[#This Row],[TargetID]],tblTargets[TargetID],tblTargets[DisplayName],"") -> Ahead of Time Chapter 1 Finished | D1852: =_xlfn.XLOOKUP(tblCostChecklist[[#This Row],[TargetID]],tblTargets[TargetID],tblTargets[TargetType],"") -> QUEST | E1852: pasta | F1852: 1 | G1852: =_xlfn.XLOOKUP( tblCostChecklist[[#This Row],[RequirementID]], tblCost[RequirementID], tblCost[QuantityRequired], "" ) -> 1 | H1852: =IF(OR(LEFT(tblCostChecklist[[#This Row],[TargetID]],10)="state.CHAR",RIGHT(tblCostChecklist[[#This Row],[TargetID]],5)="maxed"),0,IF(_xlfn.XLOOKUP(tblCostChecklist[[#This Row],[TargetID]],tblChecklist[TargetID],tblChecklist[PlayerSort])=0,500,_xlfn.XLOOKUP(tblCostChecklist[[#This Row],[TargetID]],tblChecklist[TargetID],tblChecklist[PlayerSort]))) -> 500 | I1852: =_xlfn.XLOOKUP(tblCostChecklist[[#This Row],[TargetID]],tblTargetStatus[TargetID],tblTargetStatus[Status]) -> BLOCKED | J1852: FALSE
A1853: cost.quest.ahead_of_time_chapter_1.finished.bedroll.1 | B1853: =_xlfn.TEXTAFTER( _xlfn.TEXTBEFORE(tblCostChecklist[[#This Row],[RequirementID]],".",-2), "cost." ) -> quest.ahead_of_time_chapter_1.finished | C1853: =_xlfn.XLOOKUP(tblCostChecklist[[#This Row],[TargetID]],tblTargets[TargetID],tblTargets[DisplayName],"") -> Ahead of Time Chapter 1 Finished | D1853: =_xlfn.XLOOKUP(tblCostChecklist[[#This Row],[TargetID]],tblTargets[TargetID],tblTargets[TargetType],"") -> QUEST | E1853: bedroll | F1853: 1 | G1853: =_xlfn.XLOOKUP( tblCostChecklist[[#This Row],[RequirementID]], tblCost[RequirementID], tblCost[QuantityRequired], "" ) -> 1 | H1853: =IF(OR(LEFT(tblCostChecklist[[#This Row],[TargetID]],10)="state.CHAR",RIGHT(tblCostChecklist[[#This Row],[TargetID]],5)="maxed"),0,IF(_xlfn.XLOOKUP(tblCostChecklist[[#This Row],[TargetID]],tblChecklist[TargetID],tblChecklist[PlayerSort])=0,500,_xlfn.XLOOKUP(tblCostChecklist[[#This Row],[TargetID]],tblChecklist[TargetID],tblChecklist[PlayerSort]))) -> 500 | I1853: =_xlfn.XLOOKUP(tblCostChecklist[[#This Row],[TargetID]],tblTargetStatus[TargetID],tblTargetStatus[Status]) -> BLOCKED | J1853: FALSE
A1854: cost.quest.ahead_of_time_chapter_1.finished.yuba.1 | B1854: =_xlfn.TEXTAFTER( _xlfn.TEXTBEFORE(tblCostChecklist[[#This Row],[RequirementID]],".",-2), "cost." ) -> quest.ahead_of_time_chapter_1.finished | C1854: =_xlfn.XLOOKUP(tblCostChecklist[[#This Row],[TargetID]],tblTargets[TargetID],tblTargets[DisplayName],"") -> Ahead of Time Chapter 1 Finished | D1854: =_xlfn.XLOOKUP(tblCostChecklist[[#This Row],[TargetID]],tblTargets[TargetID],tblTargets[TargetType],"") -> QUEST | E1854: yuba | F1854: 1 | G1854: =_xlfn.XLOOKUP( tblCostChecklist[[#This Row],[RequirementID]], tblCost[RequirementID], tblCost[QuantityRequired], "" ) -> 1 | H1854: =IF(OR(LEFT(tblCostChecklist[[#This Row],[TargetID]],10)="state.CHAR",RIGHT(tblCostChecklist[[#This Row],[TargetID]],5)="maxed"),0,IF(_xlfn.XLOOKUP(tblCostChecklist[[#This Row],[TargetID]],tblChecklist[TargetID],tblChecklist[PlayerSort])=0,500,_xlfn.XLOOKUP(tblCostChecklist[[#This Row],[TargetID]],tblChecklist[TargetID],tblChecklist[PlayerSort]))) -> 500 | I1854: =_xlfn.XLOOKUP(tblCostChecklist[[#This Row],[TargetID]],tblTargetStatus[TargetID],tblTargetStatus[Status]) -> BLOCKED | J1854: FALSE
A1855: cost.quest.ahead_of_time_chapter_1.finished.pizza.1 | B1855: =_xlfn.TEXTAFTER( _xlfn.TEXTBEFORE(tblCostChecklist[[#This Row],[RequirementID]],".",-2), "cost." ) -> quest.ahead_of_time_chapter_1.finished | C1855: =_xlfn.XLOOKUP(tblCostChecklist[[#This Row],[TargetID]],tblTargets[TargetID],tblTargets[DisplayName],"") -> Ahead of Time Chapter 1 Finished | D1855: =_xlfn.XLOOKUP(tblCostChecklist[[#This Row],[TargetID]],tblTargets[TargetID],tblTargets[TargetType],"") -> QUEST | E1855: pizza | F1855: 1 | G1855: =_xlfn.XLOOKUP( tblCostChecklist[[#This Row],[RequirementID]], tblCost[RequirementID], tblCost[QuantityRequired], "" ) -> 2 | H1855: =IF(OR(LEFT(tblCostChecklist[[#This Row],[TargetID]],10)="state.CHAR",RIGHT(tblCostChecklist[[#This Row],[TargetID]],5)="maxed"),0,IF(_xlfn.XLOOKUP(tblCostChecklist[[#This Row],[TargetID]],tblChecklist[TargetID],tblChecklist[PlayerSort])=0,500,_xlfn.XLOOKUP(tblCostChecklist[[#This Row],[TargetID]],tblChecklist[TargetID],tblChecklist[PlayerSort]))) -> 500 | I1855: =_xlfn.XLOOKUP(tblCostChecklist[[#This Row],[TargetID]],tblTargetStatus[TargetID],tblTargetStatus[Status]) -> BLOCKED | J1855: FALSE
A1856: cost.quest.culinary_battle.finished.onigiri.1 | B1856: =_xlfn.TEXTAFTER( _xlfn.TEXTBEFORE(tblCostChecklist[[#This Row],[RequirementID]],".",-2), "cost." ) -> quest.culinary_battle.finished | C1856: =_xlfn.XLOOKUP(tblCostChecklist[[#This Row],[TargetID]],tblTargets[TargetID],tblTargets[DisplayName],"") -> Culinary Battle Finished | D1856: =_xlfn.XLOOKUP(tblCostChecklist[[#This Row],[TargetID]],tblTargets[TargetID],tblTargets[TargetType],"") -> QUEST | E1856: onigiri | F1856: 1 | G1856: =_xlfn.XLOOKUP( tblCostChecklist[[#This Row],[RequirementID]], tblCost[RequirementID], tblCost[QuantityRequired], "" ) -> 2 | H1856: =IF(OR(LEFT(tblCostChecklist[[#This Row],[TargetID]],10)="state.CHAR",RIGHT(tblCostChecklist[[#This Row],[TargetID]],5)="maxed"),0,IF(_xlfn.XLOOKUP(tblCostChecklist[[#This Row],[TargetID]],tblChecklist[TargetID],tblChecklist[PlayerSort])=0,500,_xlfn.XLOOKUP(tblCostChecklist[[#This Row],[TargetID]],tblChecklist[TargetID],tblChecklist[PlayerSort]))) -> 500 | I1856: =_xlfn.XLOOKUP(tblCostChecklist[[#This Row],[TargetID]],tblTargetStatus[TargetID],tblTargetStatus[Status]) -> BLOCKED | J1856: FALSE
A1857: cost.quest.culinary_battle.finished.flatbread.1 | B1857: =_xlfn.TEXTAFTER( _xlfn.TEXTBEFORE(tblCostChecklist[[#This Row],[RequirementID]],".",-2), "cost." ) -> quest.culinary_battle.finished | C1857: =_xlfn.XLOOKUP(tblCostChecklist[[#This Row],[TargetID]],tblTargets[TargetID],tblTargets[DisplayName],"") -> Culinary Battle Finished | D1857: =_xlfn.XLOOKUP(tblCostChecklist[[#This Row],[TargetID]],tblTargets[TargetID],tblTargets[TargetType],"") -> QUEST | E1857: flatbread | F1857: 1 | G1857: =_xlfn.XLOOKUP( tblCostChecklist[[#This Row],[RequirementID]], tblCost[RequirementID], tblCost[QuantityRequired], "" ) -> 2 | H1857: =IF(OR(LEFT(tblCostChecklist[[#This Row],[TargetID]],10)="state.CHAR",RIGHT(tblCostChecklist[[#This Row],[TargetID]],5)="maxed"),0,IF(_xlfn.XLOOKUP(tblCostChecklist[[#This Row],[TargetID]],tblChecklist[TargetID],tblChecklist[PlayerSort])=0,500,_xlfn.XLOOKUP(tblCostChecklist[[#This Row],[TargetID]],tblChecklist[TargetID],tblChecklist[PlayerSort]))) -> 500 | I1857: =_xlfn.XLOOKUP(tblCostChecklist[[#This Row],[TargetID]],tblTargetStatus[TargetID],tblTargetStatus[Status]) -> BLOCKED | J1857: FALSE
A1858: cost.quest.culinary_battle.finished.cherrybun.1 | B1858: =_xlfn.TEXTAFTER( _xlfn.TEXTBEFORE(tblCostChecklist[[#This Row],[RequirementID]],".",-2), "cost." ) -> quest.culinary_battle.finished | C1858: =_xlfn.XLOOKUP(tblCostChecklist[[#This Row],[TargetID]],tblTargets[TargetID],tblTargets[DisplayName],"") -> Culinary Battle Finished | D1858: =_xlfn.XLOOKUP(tblCostChecklist[[#This Row],[TargetID]],tblTargets[TargetID],tblTargets[TargetType],"") -> QUEST | E1858: cherrybun | F1858: 1 | G1858: =_xlfn.XLOOKUP( tblCostChecklist[[#This Row],[RequirementID]], tblCost[RequirementID], tblCost[QuantityRequired], "" ) -> 2 | H1858: =IF(OR(LEFT(tblCostChecklist[[#This Row],[TargetID]],10)="state.CHAR",RIGHT(tblCostChecklist[[#This Row],[TargetID]],5)="maxed"),0,IF(_xlfn.XLOOKUP(tblCostChecklist[[#This Row],[TargetID]],tblChecklist[TargetID],tblChecklist[PlayerSort])=0,500,_xlfn.XLOOKUP(tblCostChecklist[[#This Row],[TargetID]],tblChecklist[TargetID],tblChecklist[PlayerSort]))) -> 500 | I1858: =_xlfn.XLOOKUP(tblCostChecklist[[#This Row],[TargetID]],tblTargetStatus[TargetID],tblTargetStatus[Status]) -> BLOCKED | J1858: FALSE
A1859: cost.quest.culinary_battle.finished.bento.1 | B1859: =_xlfn.TEXTAFTER( _xlfn.TEXTBEFORE(tblCostChecklist[[#This Row],[RequirementID]],".",-2), "cost." ) -> quest.culinary_battle.finished | C1859: =_xlfn.XLOOKUP(tblCostChecklist[[#This Row],[TargetID]],tblTargets[TargetID],tblTargets[DisplayName],"") -> Culinary Battle Finished | D1859: =_xlfn.XLOOKUP(tblCostChecklist[[#This Row],[TargetID]],tblTargets[TargetID],tblTargets[TargetType],"") -> QUEST | E1859: bento | F1859: 1 | G1859: =_xlfn.XLOOKUP( tblCostChecklist[[#This Row],[RequirementID]], tblCost[RequirementID], tblCost[QuantityRequired], "" ) -> 2 | H1859: =IF(OR(LEFT(tblCostChecklist[[#This Row],[TargetID]],10)="state.CHAR",RIGHT(tblCostChecklist[[#This Row],[TargetID]],5)="maxed"),0,IF(_xlfn.XLOOKUP(tblCostChecklist[[#This Row],[TargetID]],tblChecklist[TargetID],tblChecklist[PlayerSort])=0,500,_xlfn.XLOOKUP(tblCostChecklist[[#This Row],[TargetID]],tblChecklist[TargetID],tblChecklist[PlayerSort]))) -> 500 | I1859: =_xlfn.XLOOKUP(tblCostChecklist[[#This Row],[TargetID]],tblTargetStatus[TargetID],tblTargetStatus[Status]) -> BLOCKED | J1859: FALSE
A1860: cost.quest.culinary_battle.finished.fried.1 | B1860: =_xlfn.TEXTAFTER( _xlfn.TEXTBEFORE(tblCostChecklist[[#This Row],[RequirementID]],".",-2), "cost." ) -> quest.culinary_battle.finished | C1860: =_xlfn.XLOOKUP(tblCostChecklist[[#This Row],[TargetID]],tblTargets[TargetID],tblTargets[DisplayName],"") -> Culinary Battle Finished | D1860: =_xlfn.XLOOKUP(tblCostChecklist[[#This Row],[TargetID]],tblTargets[TargetID],tblTargets[TargetType],"") -> QUEST | E1860: fried | F1860: 1 | G1860: =_xlfn.XLOOKUP( tblCostChecklist[[#This Row],[RequirementID]], tblCost[RequirementID], tblCost[QuantityRequired], "" ) -> 2 | H1860: =IF(OR(LEFT(tblCostChecklist[[#This Row],[TargetID]],10)="state.CHAR",RIGHT(tblCostChecklist[[#This Row],[TargetID]],5)="maxed"),0,IF(_xlfn.XLOOKUP(tblCostChecklist[[#This Row],[TargetID]],tblChecklist[TargetID],tblChecklist[PlayerSort])=0,500,_xlfn.XLOOKUP(tblCostChecklist[[#This Row],[TargetID]],tblChecklist[TargetID],tblChecklist[PlayerSort]))) -> 500 | I1860: =_xlfn.XLOOKUP(tblCostChecklist[[#This Row],[TargetID]],tblTargetStatus[TargetID],tblTargetStatus[Status]) -> BLOCKED | J1860: FALSE
A1861: cost.quest.culinary_battle.finished.sushi.1 | B1861: =_xlfn.TEXTAFTER( _xlfn.TEXTBEFORE(tblCostChecklist[[#This Row],[RequirementID]],".",-2), "cost." ) -> quest.culinary_battle.finished | C1861: =_xlfn.XLOOKUP(tblCostChecklist[[#This Row],[TargetID]],tblTargets[TargetID],tblTargets[DisplayName],"") -> Culinary Battle Finished | D1861: =_xlfn.XLOOKUP(tblCostChecklist[[#This Row],[TargetID]],tblTargets[TargetID],tblTargets[TargetType],"") -> QUEST | E1861: sushi | F1861: 1 | G1861: =_xlfn.XLOOKUP( tblCostChecklist[[#This Row],[RequirementID]], tblCost[RequirementID], tblCost[QuantityRequired], "" ) -> 2 | H1861: =IF(OR(LEFT(tblCostChecklist[[#This Row],[TargetID]],10)="state.CHAR",RIGHT(tblCostChecklist[[#This Row],[TargetID]],5)="maxed"),0,IF(_xlfn.XLOOKUP(tblCostChecklist[[#This Row],[TargetID]],tblChecklist[TargetID],tblChecklist[PlayerSort])=0,500,_xlfn.XLOOKUP(tblCostChecklist[[#This Row],[TargetID]],tblChecklist[TargetID],tblChecklist[PlayerSort]))) -> 500 | I1861: =_xlfn.XLOOKUP(tblCostChecklist[[#This Row],[TargetID]],tblTargetStatus[TargetID],tblTargetStatus[Status]) -> BLOCKED | J1861: FALSE
... A2010: cost.collection.staircase@1.blueprint.1 | B2010: =_xlfn.TEXTAFTER( _xlfn.TEXTBEFORE(tblCostChecklist[[#This Row],[RequirementID]],".",-2), "cost." ) -> collection.staircase@1 | C2010: =_xlfn.XLOOKUP(tblCostChecklist[[#This Row],[TargetID]],tblTargets[TargetID],tblTargets[DisplayName],"") -> Collection Staircase | D2010: =_xlfn.XLOOKUP(tblCostChecklist[[#This Row],[TargetID]],tblTargets[TargetID],tblTargets[TargetType],"") -> COLLECTION | E2010: blueprint | F2010: 1 | G2010: =_xlfn.XLOOKUP( tblCostChecklist[[#This Row],[RequirementID]], tblCost[RequirementID], tblCost[QuantityRequired], "" ) -> 5 | H2010: =IF(OR(LEFT(tblCostChecklist[[#This Row],[TargetID]],10)="state.CHAR",RIGHT(tblCostChecklist[[#This Row],[TargetID]],5)="maxed"),0,IF(_xlfn.XLOOKUP(tblCostChecklist[[#This Row],[TargetID]],tblChecklist[TargetID],tblChecklist[PlayerSort])=0,500,_xlfn.XLOOKUP(tblCostChecklist[[#This Row],[TargetID]],tblChecklist[TargetID],tblChecklist[PlayerSort]))) -> 500 | I2010: =_xlfn.XLOOKUP(tblCostChecklist[[#This Row],[TargetID]],tblTargetStatus[TargetID],tblTargetStatus[Status]) -> BLOCKED | J2010: FALSE

Sheet Recommended
B1: Building order list
A2: Order | B2: PassiveTargetID | C2: ActiveTargetID | F2: Order | G2: Passive Buildings | H2: Passive ID | I2: Active ID | J2: Active Buildings | K2: Notes
A3: 1 | B3: =_xlfn.XLOOKUP( tblrecommended[[#This Row],[Order]], tblwikirecommended[Order], tblwikirecommended[Passive ID], "" ) -> building.guild@2 | C3: =_xlfn.XLOOKUP( tblrecommended[[#This Row],[Order]], tblwikirecommended[Order], tblwikirecommended[Active ID], "" ) -> building.guild@2 | F3: 1 | G3: Guild lvl. 2 | H3: {=_xlfn.LET( _xlpm.src,tblwikirecommended[[#This Row],[Passive Buildings]], _xlpm.clean, TRIM( SUBSTITUTE( SUBSTITUTE( SUBSTITUTE(_xlpm.src,CHAR(160)," "), "lvl.","Lv" ), "lvl","Lv" ) ), _xlpm.direct, _xlfn.XLOOKUP( _xlpm.clean, tblTargets[DisplayName], tblTargets[TargetID], "" ), _xlpm.lvl, IFERROR(--_xlfn.TEXTAFTER(_xlpm.clean,"Lv "),""), _xlpm.base, IFERROR(TRIM(_xlfn.TEXTBEFORE(_xlpm.clean,"Lv")),""), _xlpm.aliasPattern, _xlfn.XLOOKUP( 1, (tblBuildingAliases[SourceType]="Building")* (tblBuildingAliases[Source ID]=_xlpm.base), tblBuildingAliases[Tracker Target Pattern], "" ), _xlpm.aliasID, IF( _xlpm.aliasPattern="", "", SUBSTITUTE(_xlpm.aliasPattern,"{level}",_xlpm.lvl) ), IF( _xlpm.src="", "", IF(_xlpm.direct<>"",_xlpm.direct,IF(_xlpm.aliasID<>"",_xlpm.aliasID,"CHECK")) ) )} -> building.guild@2 | I3: {=_xlfn.LET( _xlpm.src,tblwikirecommended[[#This Row],[Active Buildings]], _xlpm.clean, TRIM( SUBSTITUTE( SUBSTITUTE( SUBSTITUTE(_xlpm.src,CHAR(160)," "), "lvl.","Lv" ), "lvl","Lv" ) ), _xlpm.direct, _xlfn.XLOOKUP( _xlpm.clean, tblTargets[DisplayName], tblTargets[TargetID], "" ), _xlpm.lvl, IFERROR(--_xlfn.TEXTAFTER(_xlpm.clean,"Lv "),""), _xlpm.base, IFERROR(TRIM(_xlfn.TEXTBEFORE(_xlpm.clean,"Lv")),""), _xlpm.aliasPattern, _xlfn.XLOOKUP( 1, (tblBuildingAliases[SourceType]="Building")* (tblBuildingAliases[Source ID]=_xlpm.base), tblBuildingAliases[Tracker Target Pattern], "" ), _xlpm.aliasID, IF( _xlpm.aliasPattern="", "", SUBSTITUTE(_xlpm.aliasPattern,"{level}",_xlpm.lvl) ), IF( _xlpm.src="", "", IF(_xlpm.direct<>"",_xlpm.direct,IF(_xlpm.aliasID<>"",_xlpm.aliasID,"CHECK")) ) )} -> building.guild@2 | J3: Guild lvl. 2 | K3: Increases daily rewards and enables building lvl. 2 buildings.
A4: 2 | B4: =_xlfn.XLOOKUP( tblrecommended[[#This Row],[Order]], tblwikirecommended[Order], tblwikirecommended[Passive ID], "" ) -> building.warehouse@1 | C4: =_xlfn.XLOOKUP( tblrecommended[[#This Row],[Order]], tblwikirecommended[Order], tblwikirecommended[Active ID], "" ) -> building.warehouse@1 | F4: =1+F3 -> 2 | G4: Warehouse lvl. 1 | H4: {=_xlfn.LET( _xlpm.src,tblwikirecommended[[#This Row],[Passive Buildings]], _xlpm.clean, TRIM( SUBSTITUTE( SUBSTITUTE( SUBSTITUTE(_xlpm.src,CHAR(160)," "), "lvl.","Lv" ), "lvl","Lv" ) ), _xlpm.direct, _xlfn.XLOOKUP( _xlpm.clean, tblTargets[DisplayName], tblTargets[TargetID], "" ), _xlpm.lvl, IFERROR(--_xlfn.TEXTAFTER(_xlpm.clean,"Lv "),""), _xlpm.base, IFERROR(TRIM(_xlfn.TEXTBEFORE(_xlpm.clean,"Lv")),""), _xlpm.aliasPattern, _xlfn.XLOOKUP( 1, (tblBuildingAliases[SourceType]="Building")* (tblBuildingAliases[Source ID]=_xlpm.base), tblBuildingAliases[Tracker Target Pattern], "" ), _xlpm.aliasID, IF( _xlpm.aliasPattern="", "", SUBSTITUTE(_xlpm.aliasPattern,"{level}",_xlpm.lvl) ), IF( _xlpm.src="", "", IF(_xlpm.direct<>"",_xlpm.direct,IF(_xlpm.aliasID<>"",_xlpm.aliasID,"CHECK")) ) )} -> building.warehouse@1 | I4: {=_xlfn.LET( _xlpm.src,tblwikirecommended[[#This Row],[Active Buildings]], _xlpm.clean, TRIM( SUBSTITUTE( SUBSTITUTE( SUBSTITUTE(_xlpm.src,CHAR(160)," "), "lvl.","Lv" ), "lvl","Lv" ) ), _xlpm.direct, _xlfn.XLOOKUP( _xlpm.clean, tblTargets[DisplayName], tblTargets[TargetID], "" ), _xlpm.lvl, IFERROR(--_xlfn.TEXTAFTER(_xlpm.clean,"Lv "),""), _xlpm.base, IFERROR(TRIM(_xlfn.TEXTBEFORE(_xlpm.clean,"Lv")),""), _xlpm.aliasPattern, _xlfn.XLOOKUP( 1, (tblBuildingAliases[SourceType]="Building")* (tblBuildingAliases[Source ID]=_xlpm.base), tblBuildingAliases[Tracker Target Pattern], "" ), _xlpm.aliasID, IF( _xlpm.aliasPattern="", "", SUBSTITUTE(_xlpm.aliasPattern,"{level}",_xlpm.lvl) ), IF( _xlpm.src="", "", IF(_xlpm.direct<>"",_xlpm.direct,IF(_xlpm.aliasID<>"",_xlpm.aliasID,"CHECK")) ) )} -> building.warehouse@1 | J4: Warehouse lvl. 1 | K4: Unlocks Bourse - watching ads for Treasure map fragments, Katanas and Coffee beans.
A5: 3 | B5: =_xlfn.XLOOKUP( tblrecommended[[#This Row],[Order]], tblwikirecommended[Order], tblwikirecommended[Passive ID], "" ) -> building.shop@1 | C5: =_xlfn.XLOOKUP( tblrecommended[[#This Row],[Order]], tblwikirecommended[Order], tblwikirecommended[Active ID], "" ) -> building.shop@1 | F5: =1+F4 -> 3 | G5: Shop lvl. 1 | H5: {=_xlfn.LET( _xlpm.src,tblwikirecommended[[#This Row],[Passive Buildings]], _xlpm.clean, TRIM( SUBSTITUTE( SUBSTITUTE( SUBSTITUTE(_xlpm.src,CHAR(160)," "), "lvl.","Lv" ), "lvl","Lv" ) ), _xlpm.direct, _xlfn.XLOOKUP( _xlpm.clean, tblTargets[DisplayName], tblTargets[TargetID], "" ), _xlpm.lvl, IFERROR(--_xlfn.TEXTAFTER(_xlpm.clean,"Lv "),""), _xlpm.base, IFERROR(TRIM(_xlfn.TEXTBEFORE(_xlpm.clean,"Lv")),""), _xlpm.aliasPattern, _xlfn.XLOOKUP( 1, (tblBuildingAliases[SourceType]="Building")* (tblBuildingAliases[Source ID]=_xlpm.base), tblBuildingAliases[Tracker Target Pattern], "" ), _xlpm.aliasID, IF( _xlpm.aliasPattern="", "", SUBSTITUTE(_xlpm.aliasPattern,"{level}",_xlpm.lvl) ), IF( _xlpm.src="", "", IF(_xlpm.direct<>"",_xlpm.direct,IF(_xlpm.aliasID<>"",_xlpm.aliasID,"CHECK")) ) )} -> building.shop@1 | I5: {=_xlfn.LET( _xlpm.src,tblwikirecommended[[#This Row],[Active Buildings]], _xlpm.clean, TRIM( SUBSTITUTE( SUBSTITUTE( SUBSTITUTE(_xlpm.src,CHAR(160)," "), "lvl.","Lv" ), "lvl","Lv" ) ), _xlpm.direct, _xlfn.XLOOKUP( _xlpm.clean, tblTargets[DisplayName], tblTargets[TargetID], "" ), _xlpm.lvl, IFERROR(--_xlfn.TEXTAFTER(_xlpm.clean,"Lv "),""), _xlpm.base, IFERROR(TRIM(_xlfn.TEXTBEFORE(_xlpm.clean,"Lv")),""), _xlpm.aliasPattern, _xlfn.XLOOKUP( 1, (tblBuildingAliases[SourceType]="Building")* (tblBuildingAliases[Source ID]=_xlpm.base), tblBuildingAliases[Tracker Target Pattern], "" ), _xlpm.aliasID, IF( _xlpm.aliasPattern="", "", SUBSTITUTE(_xlpm.aliasPattern,"{level}",_xlpm.lvl) ), IF( _xlpm.src="", "", IF(_xlpm.direct<>"",_xlpm.direct,IF(_xlpm.aliasID<>"",_xlpm.aliasID,"CHECK")) ) )} -> building.shop@1 | J5: Shop lvl. 1 | K5: Enables buying Chemicals, which are required for Alchemist's Hut lvl. 2.
A6: 4 | B6: =_xlfn.XLOOKUP( tblrecommended[[#This Row],[Order]], tblwikirecommended[Order], tblwikirecommended[Passive ID], "" ) -> building.alchemists_hut@1 | C6: =_xlfn.XLOOKUP( tblrecommended[[#This Row],[Order]], tblwikirecommended[Order], tblwikirecommended[Active ID], "" ) -> building.alchemists_hut@1 | F6: =1+F5 -> 4 | G6: Alchemist's Hut lvl. 1 | H6: {=_xlfn.LET( _xlpm.src,tblwikirecommended[[#This Row],[Passive Buildings]], _xlpm.clean, TRIM( SUBSTITUTE( SUBSTITUTE( SUBSTITUTE(_xlpm.src,CHAR(160)," "), "lvl.","Lv" ), "lvl","Lv" ) ), _xlpm.direct, _xlfn.XLOOKUP( _xlpm.clean, tblTargets[DisplayName], tblTargets[TargetID], "" ), _xlpm.lvl, IFERROR(--_xlfn.TEXTAFTER(_xlpm.clean,"Lv "),""), _xlpm.base, IFERROR(TRIM(_xlfn.TEXTBEFORE(_xlpm.clean,"Lv")),""), _xlpm.aliasPattern, _xlfn.XLOOKUP( 1, (tblBuildingAliases[SourceType]="Building")* (tblBuildingAliases[Source ID]=_xlpm.base), tblBuildingAliases[Tracker Target Pattern], "" ), _xlpm.aliasID, IF( _xlpm.aliasPattern="", "", SUBSTITUTE(_xlpm.aliasPattern,"{level}",_xlpm.lvl) ), IF( _xlpm.src="", "", IF(_xlpm.direct<>"",_xlpm.direct,IF(_xlpm.aliasID<>"",_xlpm.aliasID,"CHECK")) ) )} -> building.alchemists_hut@1 | I6: {=_xlfn.LET( _xlpm.src,tblwikirecommended[[#This Row],[Active Buildings]], _xlpm.clean, TRIM( SUBSTITUTE( SUBSTITUTE( SUBSTITUTE(_xlpm.src,CHAR(160)," "), "lvl.","Lv" ), "lvl","Lv" ) ), _xlpm.direct, _xlfn.XLOOKUP( _xlpm.clean, tblTargets[DisplayName], tblTargets[TargetID], "" ), _xlpm.lvl, IFERROR(--_xlfn.TEXTAFTER(_xlpm.clean,"Lv "),""), _xlpm.base, IFERROR(TRIM(_xlfn.TEXTBEFORE(_xlpm.clean,"Lv")),""), _xlpm.aliasPattern, _xlfn.XLOOKUP( 1, (tblBuildingAliases[SourceType]="Building")* (tblBuildingAliases[Source ID]=_xlpm.base), tblBuildingAliases[Tracker Target Pattern], "" ), _xlpm.aliasID, IF( _xlpm.aliasPattern="", "", SUBSTITUTE(_xlpm.aliasPattern,"{level}",_xlpm.lvl) ), IF( _xlpm.src="", "", IF(_xlpm.direct<>"",_xlpm.direct,IF(_xlpm.aliasID<>"",_xlpm.aliasID,"CHECK")) ) )} -> building.alchemists_hut@1 | J6: Alchemist's Hut lvl. 1 | K6: Enables building Alchemist's Hut lvl. 2.
A7: 5 | B7: =_xlfn.XLOOKUP( tblrecommended[[#This Row],[Order]], tblwikirecommended[Order], tblwikirecommended[Passive ID], "" ) -> building.alchemists_hut@2 | C7: =_xlfn.XLOOKUP( tblrecommended[[#This Row],[Order]], tblwikirecommended[Order], tblwikirecommended[Active ID], "" ) -> building.alchemists_hut@2 | F7: =1+F6 -> 5 | G7: Alchemist's Hut lvl. 2 | H7: {=_xlfn.LET( _xlpm.src,tblwikirecommended[[#This Row],[Passive Buildings]], _xlpm.clean, TRIM( SUBSTITUTE( SUBSTITUTE( SUBSTITUTE(_xlpm.src,CHAR(160)," "), "lvl.","Lv" ), "lvl","Lv" ) ), _xlpm.direct, _xlfn.XLOOKUP( _xlpm.clean, tblTargets[DisplayName], tblTargets[TargetID], "" ), _xlpm.lvl, IFERROR(--_xlfn.TEXTAFTER(_xlpm.clean,"Lv "),""), _xlpm.base, IFERROR(TRIM(_xlfn.TEXTBEFORE(_xlpm.clean,"Lv")),""), _xlpm.aliasPattern, _xlfn.XLOOKUP( 1, (tblBuildingAliases[SourceType]="Building")* (tblBuildingAliases[Source ID]=_xlpm.base), tblBuildingAliases[Tracker Target Pattern], "" ), _xlpm.aliasID, IF( _xlpm.aliasPattern="", "", SUBSTITUTE(_xlpm.aliasPattern,"{level}",_xlpm.lvl) ), IF( _xlpm.src="", "", IF(_xlpm.direct<>"",_xlpm.direct,IF(_xlpm.aliasID<>"",_xlpm.aliasID,"CHECK")) ) )} -> building.alchemists_hut@2 | I7: {=_xlfn.LET( _xlpm.src,tblwikirecommended[[#This Row],[Active Buildings]], _xlpm.clean, TRIM( SUBSTITUTE( SUBSTITUTE( SUBSTITUTE(_xlpm.src,CHAR(160)," "), "lvl.","Lv" ), "lvl","Lv" ) ), _xlpm.direct, _xlfn.XLOOKUP( _xlpm.clean, tblTargets[DisplayName], tblTargets[TargetID], "" ), _xlpm.lvl, IFERROR(--_xlfn.TEXTAFTER(_xlpm.clean,"Lv "),""), _xlpm.base, IFERROR(TRIM(_xlfn.TEXTBEFORE(_xlpm.clean,"Lv")),""), _xlpm.aliasPattern, _xlfn.XLOOKUP( 1, (tblBuildingAliases[SourceType]="Building")* (tblBuildingAliases[Source ID]=_xlpm.base), tblBuildingAliases[Tracker Target Pattern], "" ), _xlpm.aliasID, IF( _xlpm.aliasPattern="", "", SUBSTITUTE(_xlpm.aliasPattern,"{level}",_xlpm.lvl) ), IF( _xlpm.src="", "", IF(_xlpm.direct<>"",_xlpm.direct,IF(_xlpm.aliasID<>"",_xlpm.aliasID,"CHECK")) ) )} -> building.alchemists_hut@2 | J7: Alchemist's Hut lvl. 2 | K7: Unlocks Cauldron.
A8: 6 | B8: =_xlfn.XLOOKUP( tblrecommended[[#This Row],[Order]], tblwikirecommended[Order], tblwikirecommended[Passive ID], "" ) -> building.field@1 | C8: =_xlfn.XLOOKUP( tblrecommended[[#This Row],[Order]], tblwikirecommended[Order], tblwikirecommended[Active ID], "" ) -> building.field@1 | F8: =1+F7 -> 6 | G8: Field lvl. 1 | H8: {=_xlfn.LET( _xlpm.src,tblwikirecommended[[#This Row],[Passive Buildings]], _xlpm.clean, TRIM( SUBSTITUTE( SUBSTITUTE( SUBSTITUTE(_xlpm.src,CHAR(160)," "), "lvl.","Lv" ), "lvl","Lv" ) ), _xlpm.direct, _xlfn.XLOOKUP( _xlpm.clean, tblTargets[DisplayName], tblTargets[TargetID], "" ), _xlpm.lvl, IFERROR(--_xlfn.TEXTAFTER(_xlpm.clean,"Lv "),""), _xlpm.base, IFERROR(TRIM(_xlfn.TEXTBEFORE(_xlpm.clean,"Lv")),""), _xlpm.aliasPattern, _xlfn.XLOOKUP( 1, (tblBuildingAliases[SourceType]="Building")* (tblBuildingAliases[Source ID]=_xlpm.base), tblBuildingAliases[Tracker Target Pattern], "" ), _xlpm.aliasID, IF( _xlpm.aliasPattern="", "", SUBSTITUTE(_xlpm.aliasPattern,"{level}",_xlpm.lvl) ), IF( _xlpm.src="", "", IF(_xlpm.direct<>"",_xlpm.direct,IF(_xlpm.aliasID<>"",_xlpm.aliasID,"CHECK")) ) )} -> building.field@1 | I8: {=_xlfn.LET( _xlpm.src,tblwikirecommended[[#This Row],[Active Buildings]], _xlpm.clean, TRIM( SUBSTITUTE( SUBSTITUTE( SUBSTITUTE(_xlpm.src,CHAR(160)," "), "lvl.","Lv" ), "lvl","Lv" ) ), _xlpm.direct, _xlfn.XLOOKUP( _xlpm.clean, tblTargets[DisplayName], tblTargets[TargetID], "" ), _xlpm.lvl, IFERROR(--_xlfn.TEXTAFTER(_xlpm.clean,"Lv "),""), _xlpm.base, IFERROR(TRIM(_xlfn.TEXTBEFORE(_xlpm.clean,"Lv")),""), _xlpm.aliasPattern, _xlfn.XLOOKUP( 1, (tblBuildingAliases[SourceType]="Building")* (tblBuildingAliases[Source ID]=_xlpm.base), tblBuildingAliases[Tracker Target Pattern], "" ), _xlpm.aliasID, IF( _xlpm.aliasPattern="", "", SUBSTITUTE(_xlpm.aliasPattern,"{level}",_xlpm.lvl) ), IF( _xlpm.src="", "", IF(_xlpm.direct<>"",_xlpm.direct,IF(_xlpm.aliasID<>"",_xlpm.aliasID,"CHECK")) ) )} -> building.field@1 | J8: Field lvl. 1 | K8: Passive income of Rice (used in dungeon).
A9: 7 | B9: =_xlfn.XLOOKUP( tblrecommended[[#This Row],[Order]], tblwikirecommended[Order], tblwikirecommended[Passive ID], "" ) -> building.rock_garden@1 | C9: =_xlfn.XLOOKUP( tblrecommended[[#This Row],[Order]], tblwikirecommended[Order], tblwikirecommended[Active ID], "" ) -> building.food_stall@1 | F9: =1+F8 -> 7 | G9: Rock Garden lvl. 1 | H9: {=_xlfn.LET( _xlpm.src,tblwikirecommended[[#This Row],[Passive Buildings]], _xlpm.clean, TRIM( SUBSTITUTE( SUBSTITUTE( SUBSTITUTE(_xlpm.src,CHAR(160)," "), "lvl.","Lv" ), "lvl","Lv" ) ), _xlpm.direct, _xlfn.XLOOKUP( _xlpm.clean, tblTargets[DisplayName], tblTargets[TargetID], "" ), _xlpm.lvl, IFERROR(--_xlfn.TEXTAFTER(_xlpm.clean,"Lv "),""), _xlpm.base, IFERROR(TRIM(_xlfn.TEXTBEFORE(_xlpm.clean,"Lv")),""), _xlpm.aliasPattern, _xlfn.XLOOKUP( 1, (tblBuildingAliases[SourceType]="Building")* (tblBuildingAliases[Source ID]=_xlpm.base), tblBuildingAliases[Tracker Target Pattern], "" ), _xlpm.aliasID, IF( _xlpm.aliasPattern="", "", SUBSTITUTE(_xlpm.aliasPattern,"{level}",_xlpm.lvl) ), IF( _xlpm.src="", "", IF(_xlpm.direct<>"",_xlpm.direct,IF(_xlpm.aliasID<>"",_xlpm.aliasID,"CHECK")) ) )} -> building.rock_garden@1 | I9: {=_xlfn.LET( _xlpm.src,tblwikirecommended[[#This Row],[Active Buildings]], _xlpm.clean, TRIM( SUBSTITUTE( SUBSTITUTE( SUBSTITUTE(_xlpm.src,CHAR(160)," "), "lvl.","Lv" ), "lvl","Lv" ) ), _xlpm.direct, _xlfn.XLOOKUP( _xlpm.clean, tblTargets[DisplayName], tblTargets[TargetID], "" ), _xlpm.lvl, IFERROR(--_xlfn.TEXTAFTER(_xlpm.clean,"Lv "),""), _xlpm.base, IFERROR(TRIM(_xlfn.TEXTBEFORE(_xlpm.clean,"Lv")),""), _xlpm.aliasPattern, _xlfn.XLOOKUP( 1, (tblBuildingAliases[SourceType]="Building")* (tblBuildingAliases[Source ID]=_xlpm.base), tblBuildingAliases[Tracker Target Pattern], "" ), _xlpm.aliasID, IF( _xlpm.aliasPattern="", "", SUBSTITUTE(_xlpm.aliasPattern,"{level}",_xlpm.lvl) ), IF( _xlpm.src="", "", IF(_xlpm.direct<>"",_xlpm.direct,IF(_xlpm.aliasID<>"",_xlpm.aliasID,"CHECK")) ) )} -> building.food_stall@1 | J9: Food Stall lvl. 1 | K9: Enables crafting dungeon related items.
A10: 8 | B10: =_xlfn.XLOOKUP( tblrecommended[[#This Row],[Order]], tblwikirecommended[Order], tblwikirecommended[Passive ID], "" ) -> building.rock_garden@2 | C10: =_xlfn.XLOOKUP( tblrecommended[[#This Row],[Order]], tblwikirecommended[Order], tblwikirecommended[Active ID], "" ) -> building.field@2 | F10: =1+F9 -> 8 | G10: Rock Garden lvl. 2 | H10: {=_xlfn.LET( _xlpm.src,tblwikirecommended[[#This Row],[Passive Buildings]], _xlpm.clean, TRIM( SUBSTITUTE( SUBSTITUTE( SUBSTITUTE(_xlpm.src,CHAR(160)," "), "lvl.","Lv" ), "lvl","Lv" ) ), _xlpm.direct, _xlfn.XLOOKUP( _xlpm.clean, tblTargets[DisplayName], tblTargets[TargetID], "" ), _xlpm.lvl, IFERROR(--_xlfn.TEXTAFTER(_xlpm.clean,"Lv "),""), _xlpm.base, IFERROR(TRIM(_xlfn.TEXTBEFORE(_xlpm.clean,"Lv")),""), _xlpm.aliasPattern, _xlfn.XLOOKUP( 1, (tblBuildingAliases[SourceType]="Building")* (tblBuildingAliases[Source ID]=_xlpm.base), tblBuildingAliases[Tracker Target Pattern], "" ), _xlpm.aliasID, IF( _xlpm.aliasPattern="", "", SUBSTITUTE(_xlpm.aliasPattern,"{level}",_xlpm.lvl) ), IF( _xlpm.src="", "", IF(_xlpm.direct<>"",_xlpm.direct,IF(_xlpm.aliasID<>"",_xlpm.aliasID,"CHECK")) ) )} -> building.rock_garden@2 | I10: {=_xlfn.LET( _xlpm.src,tblwikirecommended[[#This Row],[Active Buildings]], _xlpm.clean, TRIM( SUBSTITUTE( SUBSTITUTE( SUBSTITUTE(_xlpm.src,CHAR(160)," "), "lvl.","Lv" ), "lvl","Lv" ) ), _xlpm.direct, _xlfn.XLOOKUP( _xlpm.clean, tblTargets[DisplayName], tblTargets[TargetID], "" ), _xlpm.lvl, IFERROR(--_xlfn.TEXTAFTER(_xlpm.clean,"Lv "),""), _xlpm.base, IFERROR(TRIM(_xlfn.TEXTBEFORE(_xlpm.clean,"Lv")),""), _xlpm.aliasPattern, _xlfn.XLOOKUP( 1, (tblBuildingAliases[SourceType]="Building")* (tblBuildingAliases[Source ID]=_xlpm.base), tblBuildingAliases[Tracker Target Pattern], "" ), _xlpm.aliasID, IF( _xlpm.aliasPattern="", "", SUBSTITUTE(_xlpm.aliasPattern,"{level}",_xlpm.lvl) ), IF( _xlpm.src="", "", IF(_xlpm.direct<>"",_xlpm.direct,IF(_xlpm.aliasID<>"",_xlpm.aliasID,"CHECK")) ) )} -> building.field@2 | J10: Field lvl. 2 | K10: Passive income of Wheat (also used in dungeon).
A11: 9 | B11: =_xlfn.XLOOKUP( tblrecommended[[#This Row],[Order]], tblwikirecommended[Order], tblwikirecommended[Passive ID], "" ) -> building.garden@1 | C11: =_xlfn.XLOOKUP( tblrecommended[[#This Row],[Order]], tblwikirecommended[Order], tblwikirecommended[Active ID], "" ) -> building.windmill@1 | F11: =1+F10 -> 9 | G11: Garden lvl. 1 | H11: {=_xlfn.LET( _xlpm.src,tblwikirecommended[[#This Row],[Passive Buildings]], _xlpm.clean, TRIM( SUBSTITUTE( SUBSTITUTE( SUBSTITUTE(_xlpm.src,CHAR(160)," "), "lvl.","Lv" ), "lvl","Lv" ) ), _xlpm.direct, _xlfn.XLOOKUP( _xlpm.clean, tblTargets[DisplayName], tblTargets[TargetID], "" ), _xlpm.lvl, IFERROR(--_xlfn.TEXTAFTER(_xlpm.clean,"Lv "),""), _xlpm.base, IFERROR(TRIM(_xlfn.TEXTBEFORE(_xlpm.clean,"Lv")),""), _xlpm.aliasPattern, _xlfn.XLOOKUP( 1, (tblBuildingAliases[SourceType]="Building")* (tblBuildingAliases[Source ID]=_xlpm.base), tblBuildingAliases[Tracker Target Pattern], "" ), _xlpm.aliasID, IF( _xlpm.aliasPattern="", "", SUBSTITUTE(_xlpm.aliasPattern,"{level}",_xlpm.lvl) ), IF( _xlpm.src="", "", IF(_xlpm.direct<>"",_xlpm.direct,IF(_xlpm.aliasID<>"",_xlpm.aliasID,"CHECK")) ) )} -> building.garden@1 | I11: {=_xlfn.LET( _xlpm.src,tblwikirecommended[[#This Row],[Active Buildings]], _xlpm.clean, TRIM( SUBSTITUTE( SUBSTITUTE( SUBSTITUTE(_xlpm.src,CHAR(160)," "), "lvl.","Lv" ), "lvl","Lv" ) ), _xlpm.direct, _xlfn.XLOOKUP( _xlpm.clean, tblTargets[DisplayName], tblTargets[TargetID], "" ), _xlpm.lvl, IFERROR(--_xlfn.TEXTAFTER(_xlpm.clean,"Lv "),""), _xlpm.base, IFERROR(TRIM(_xlfn.TEXTBEFORE(_xlpm.clean,"Lv")),""), _xlpm.aliasPattern, _xlfn.XLOOKUP( 1, (tblBuildingAliases[SourceType]="Building")* (tblBuildingAliases[Source ID]=_xlpm.base), tblBuildingAliases[Tracker Target Pattern], "" ), _xlpm.aliasID, IF( _xlpm.aliasPattern="", "", SUBSTITUTE(_xlpm.aliasPattern,"{level}",_xlpm.lvl) ), IF( _xlpm.src="", "", IF(_xlpm.direct<>"",_xlpm.direct,IF(_xlpm.aliasID<>"",_xlpm.aliasID,"CHECK")) ) )} -> building.windmill@1 | J11: Windmill lvl. 1 | K11: Enables crafting Flour from Wheat.
A12: 10 | B12: =_xlfn.XLOOKUP( tblrecommended[[#This Row],[Order]], tblwikirecommended[Order], tblwikirecommended[Passive ID], "" ) -> building.garden@2 | C12: =_xlfn.XLOOKUP( tblrecommended[[#This Row],[Order]], tblwikirecommended[Order], tblwikirecommended[Active ID], "" ) -> building.furnace@1 | F12: =1+F11 -> 10 | G12: Garden lvl. 2 | H12: {=_xlfn.LET( _xlpm.src,tblwikirecommended[[#This Row],[Passive Buildings]], _xlpm.clean, TRIM( SUBSTITUTE( SUBSTITUTE( SUBSTITUTE(_xlpm.src,CHAR(160)," "), "lvl.","Lv" ), "lvl","Lv" ) ), _xlpm.direct, _xlfn.XLOOKUP( _xlpm.clean, tblTargets[DisplayName], tblTargets[TargetID], "" ), _xlpm.lvl, IFERROR(--_xlfn.TEXTAFTER(_xlpm.clean,"Lv "),""), _xlpm.base, IFERROR(TRIM(_xlfn.TEXTBEFORE(_xlpm.clean,"Lv")),""), _xlpm.aliasPattern, _xlfn.XLOOKUP( 1, (tblBuildingAliases[SourceType]="Building")* (tblBuildingAliases[Source ID]=_xlpm.base), tblBuildingAliases[Tracker Target Pattern], "" ), _xlpm.aliasID, IF( _xlpm.aliasPattern="", "", SUBSTITUTE(_xlpm.aliasPattern,"{level}",_xlpm.lvl) ), IF( _xlpm.src="", "", IF(_xlpm.direct<>"",_xlpm.direct,IF(_xlpm.aliasID<>"",_xlpm.aliasID,"CHECK")) ) )} -> building.garden@2 | I12: {=_xlfn.LET( _xlpm.src,tblwikirecommended[[#This Row],[Active Buildings]], _xlpm.clean, TRIM( SUBSTITUTE( SUBSTITUTE( SUBSTITUTE(_xlpm.src,CHAR(160)," "), "lvl.","Lv" ), "lvl","Lv" ) ), _xlpm.direct, _xlfn.XLOOKUP( _xlpm.clean, tblTargets[DisplayName], tblTargets[TargetID], "" ), _xlpm.lvl, IFERROR(--_xlfn.TEXTAFTER(_xlpm.clean,"Lv "),""), _xlpm.base, IFERROR(TRIM(_xlfn.TEXTBEFORE(_xlpm.clean,"Lv")),""), _xlpm.aliasPattern, _xlfn.XLOOKUP( 1, (tblBuildingAliases[SourceType]="Building")* (tblBuildingAliases[Source ID]=_xlpm.base), tblBuildingAliases[Tracker Target Pattern], "" ), _xlpm.aliasID, IF( _xlpm.aliasPattern="", "", SUBSTITUTE(_xlpm.aliasPattern,"{level}",_xlpm.lvl) ), IF( _xlpm.src="", "", IF(_xlpm.direct<>"",_xlpm.direct,IF(_xlpm.aliasID<>"",_xlpm.aliasID,"CHECK")) ) )} -> building.furnace@1 | J12: Furnace lvl. 1 | K12: Enables crafting Steel (required for Dungeon and later other buildings).
A13: 11 | B13: =_xlfn.XLOOKUP( tblrecommended[[#This Row],[Order]], tblwikirecommended[Order], tblwikirecommended[Passive ID], "" ) -> building.lumber@1 | C13: =_xlfn.XLOOKUP( tblrecommended[[#This Row],[Order]], tblwikirecommended[Order], tblwikirecommended[Active ID], "" ) -> building.furnace@2 | F13: =1+F12 -> 11 | G13: Lumber Mill lvl. 1 | H13: {=_xlfn.LET( _xlpm.src,tblwikirecommended[[#This Row],[Passive Buildings]], _xlpm.clean, TRIM( SUBSTITUTE( SUBSTITUTE( SUBSTITUTE(_xlpm.src,CHAR(160)," "), "lvl.","Lv" ), "lvl","Lv" ) ), _xlpm.direct, _xlfn.XLOOKUP( _xlpm.clean, tblTargets[DisplayName], tblTargets[TargetID], "" ), _xlpm.lvl, IFERROR(--_xlfn.TEXTAFTER(_xlpm.clean,"Lv "),""), _xlpm.base, IFERROR(TRIM(_xlfn.TEXTBEFORE(_xlpm.clean,"Lv")),""), _xlpm.aliasPattern, _xlfn.XLOOKUP( 1, (tblBuildingAliases[SourceType]="Building")* (tblBuildingAliases[Source ID]=_xlpm.base), tblBuildingAliases[Tracker Target Pattern], "" ), _xlpm.aliasID, IF( _xlpm.aliasPattern="", "", SUBSTITUTE(_xlpm.aliasPattern,"{level}",_xlpm.lvl) ), IF( _xlpm.src="", "", IF(_xlpm.direct<>"",_xlpm.direct,IF(_xlpm.aliasID<>"",_xlpm.aliasID,"CHECK")) ) )} -> building.lumber@1 | I13: {=_xlfn.LET( _xlpm.src,tblwikirecommended[[#This Row],[Active Buildings]], _xlpm.clean, TRIM( SUBSTITUTE( SUBSTITUTE( SUBSTITUTE(_xlpm.src,CHAR(160)," "), "lvl.","Lv" ), "lvl","Lv" ) ), _xlpm.direct, _xlfn.XLOOKUP( _xlpm.clean, tblTargets[DisplayName], tblTargets[TargetID], "" ), _xlpm.lvl, IFERROR(--_xlfn.TEXTAFTER(_xlpm.clean,"Lv "),""), _xlpm.base, IFERROR(TRIM(_xlfn.TEXTBEFORE(_xlpm.clean,"Lv")),""), _xlpm.aliasPattern, _xlfn.XLOOKUP( 1, (tblBuildingAliases[SourceType]="Building")* (tblBuildingAliases[Source ID]=_xlpm.base), tblBuildingAliases[Tracker Target Pattern], "" ), _xlpm.aliasID, IF( _xlpm.aliasPattern="", "", SUBSTITUTE(_xlpm.aliasPattern,"{level}",_xlpm.lvl) ), IF( _xlpm.src="", "", IF(_xlpm.direct<>"",_xlpm.direct,IF(_xlpm.aliasID<>"",_xlpm.aliasID,"CHECK")) ) )} -> building.furnace@2 | J13: Furnace lvl. 2 | K13: Increases Steel production by 25%. Preferably only craft Steel when you have Furnace lvl. 2.
A14: 12 | B14: =_xlfn.XLOOKUP( tblrecommended[[#This Row],[Order]], tblwikirecommended[Order], tblwikirecommended[Passive ID], "" ) -> building.lumber@2 | C14: =_xlfn.XLOOKUP( tblrecommended[[#This Row],[Order]], tblwikirecommended[Order], tblwikirecommended[Active ID], "" ) -> building.dungeon@1 | F14: =1+F13 -> 12 | G14: Lumber Mill lvl. 2 | H14: {=_xlfn.LET( _xlpm.src,tblwikirecommended[[#This Row],[Passive Buildings]], _xlpm.clean, TRIM( SUBSTITUTE( SUBSTITUTE( SUBSTITUTE(_xlpm.src,CHAR(160)," "), "lvl.","Lv" ), "lvl","Lv" ) ), _xlpm.direct, _xlfn.XLOOKUP( _xlpm.clean, tblTargets[DisplayName], tblTargets[TargetID], "" ), _xlpm.lvl, IFERROR(--_xlfn.TEXTAFTER(_xlpm.clean,"Lv "),""), _xlpm.base, IFERROR(TRIM(_xlfn.TEXTBEFORE(_xlpm.clean,"Lv")),""), _xlpm.aliasPattern, _xlfn.XLOOKUP( 1, (tblBuildingAliases[SourceType]="Building")* (tblBuildingAliases[Source ID]=_xlpm.base), tblBuildingAliases[Tracker Target Pattern], "" ), _xlpm.aliasID, IF( _xlpm.aliasPattern="", "", SUBSTITUTE(_xlpm.aliasPattern,"{level}",_xlpm.lvl) ), IF( _xlpm.src="", "", IF(_xlpm.direct<>"",_xlpm.direct,IF(_xlpm.aliasID<>"",_xlpm.aliasID,"CHECK")) ) )} -> building.lumber@2 | I14: {=_xlfn.LET( _xlpm.src,tblwikirecommended[[#This Row],[Active Buildings]], _xlpm.clean, TRIM( SUBSTITUTE( SUBSTITUTE( SUBSTITUTE(_xlpm.src,CHAR(160)," "), "lvl.","Lv" ), "lvl","Lv" ) ), _xlpm.direct, _xlfn.XLOOKUP( _xlpm.clean, tblTargets[DisplayName], tblTargets[TargetID], "" ), _xlpm.lvl, IFERROR(--_xlfn.TEXTAFTER(_xlpm.clean,"Lv "),""), _xlpm.base, IFERROR(TRIM(_xlfn.TEXTBEFORE(_xlpm.clean,"Lv")),""), _xlpm.aliasPattern, _xlfn.XLOOKUP( 1, (tblBuildingAliases[SourceType]="Building")* (tblBuildingAliases[Source ID]=_xlpm.base), tblBuildingAliases[Tracker Target Pattern], "" ), _xlpm.aliasID, IF( _xlpm.aliasPattern="", "", SUBSTITUTE(_xlpm.aliasPattern,"{level}",_xlpm.lvl) ), IF( _xlpm.src="", "", IF(_xlpm.direct<>"",_xlpm.direct,IF(_xlpm.aliasID<>"",_xlpm.aliasID,"CHECK")) ) )} -> building.dungeon@1 | J14: Dungeon lvl. 1 | K14: Enables acquiring dungeon related items. Allows to convert nonogram loot -> MP -> dungeon loot.
A15: 13 | B15: =_xlfn.XLOOKUP( tblrecommended[[#This Row],[Order]], tblwikirecommended[Order], tblwikirecommended[Passive ID], "" ) -> building.guild@3 | C15: =_xlfn.XLOOKUP( tblrecommended[[#This Row],[Order]], tblwikirecommended[Order], tblwikirecommended[Active ID], "" ) -> building.lumber@1 | F15: =1+F14 -> 13 | G15: Guild lvl. 3 | H15: {=_xlfn.LET( _xlpm.src,tblwikirecommended[[#This Row],[Passive Buildings]], _xlpm.clean, TRIM( SUBSTITUTE( SUBSTITUTE( SUBSTITUTE(_xlpm.src,CHAR(160)," "), "lvl.","Lv" ), "lvl","Lv" ) ), _xlpm.direct, _xlfn.XLOOKUP( _xlpm.clean, tblTargets[DisplayName], tblTargets[TargetID], "" ), _xlpm.lvl, IFERROR(--_xlfn.TEXTAFTER(_xlpm.clean,"Lv "),""), _xlpm.base, IFERROR(TRIM(_xlfn.TEXTBEFORE(_xlpm.clean,"Lv")),""), _xlpm.aliasPattern, _xlfn.XLOOKUP( 1, (tblBuildingAliases[SourceType]="Building")* (tblBuildingAliases[Source ID]=_xlpm.base), tblBuildingAliases[Tracker Target Pattern], "" ), _xlpm.aliasID, IF( _xlpm.aliasPattern="", "", SUBSTITUTE(_xlpm.aliasPattern,"{level}",_xlpm.lvl) ), IF( _xlpm.src="", "", IF(_xlpm.direct<>"",_xlpm.direct,IF(_xlpm.aliasID<>"",_xlpm.aliasID,"CHECK")) ) )} -> building.guild@3 | I15: {=_xlfn.LET( _xlpm.src,tblwikirecommended[[#This Row],[Active Buildings]], _xlpm.clean, TRIM( SUBSTITUTE( SUBSTITUTE( SUBSTITUTE(_xlpm.src,CHAR(160)," "), "lvl.","Lv" ), "lvl","Lv" ) ), _xlpm.direct, _xlfn.XLOOKUP( _xlpm.clean, tblTargets[DisplayName], tblTargets[TargetID], "" ), _xlpm.lvl, IFERROR(--_xlfn.TEXTAFTER(_xlpm.clean,"Lv "),""), _xlpm.base, IFERROR(TRIM(_xlfn.TEXTBEFORE(_xlpm.clean,"Lv")),""), _xlpm.aliasPattern, _xlfn.XLOOKUP( 1, (tblBuildingAliases[SourceType]="Building")* (tblBuildingAliases[Source ID]=_xlpm.base), tblBuildingAliases[Tracker Target Pattern], "" ), _xlpm.aliasID, IF( _xlpm.aliasPattern="", "", SUBSTITUTE(_xlpm.aliasPattern,"{level}",_xlpm.lvl) ), IF( _xlpm.src="", "", IF(_xlpm.direct<>"",_xlpm.direct,IF(_xlpm.aliasID<>"",_xlpm.aliasID,"CHECK")) ) )} -> building.lumber@1 | J15: Lumber Mill lvl. 1 | K15: Enables crafting Wooden beams, which is needed for a lot of buildings.
... A53: 51 | B53: =_xlfn.XLOOKUP( tblrecommended[[#This Row],[Order]], tblwikirecommended[Order], tblwikirecommended[Passive ID], "" ) -> building.smithy@2 | C53: =_xlfn.XLOOKUP( tblrecommended[[#This Row],[Order]], tblwikirecommended[Order], tblwikirecommended[Active ID], "" ) -> building.alchemists_hut@3 | F53: =1+F52 -> 51 | G53: Smithy lvl. 2 | H53: {=_xlfn.LET( _xlpm.src,tblwikirecommended[[#This Row],[Passive Buildings]], _xlpm.clean, TRIM( SUBSTITUTE( SUBSTITUTE( SUBSTITUTE(_xlpm.src,CHAR(160)," "), "lvl.","Lv" ), "lvl","Lv" ) ), _xlpm.direct, _xlfn.XLOOKUP( _xlpm.clean, tblTargets[DisplayName], tblTargets[TargetID], "" ), _xlpm.lvl, IFERROR(--_xlfn.TEXTAFTER(_xlpm.clean,"Lv "),""), _xlpm.base, IFERROR(TRIM(_xlfn.TEXTBEFORE(_xlpm.clean,"Lv")),""), _xlpm.aliasPattern, _xlfn.XLOOKUP( 1, (tblBuildingAliases[SourceType]="Building")* (tblBuildingAliases[Source ID]=_xlpm.base), tblBuildingAliases[Tracker Target Pattern], "" ), _xlpm.aliasID, IF( _xlpm.aliasPattern="", "", SUBSTITUTE(_xlpm.aliasPattern,"{level}",_xlpm.lvl) ), IF( _xlpm.src="", "", IF(_xlpm.direct<>"",_xlpm.direct,IF(_xlpm.aliasID<>"",_xlpm.aliasID,"CHECK")) ) )} -> building.smithy@2 | I53: {=_xlfn.LET( _xlpm.src,tblwikirecommended[[#This Row],[Active Buildings]], _xlpm.clean, TRIM( SUBSTITUTE( SUBSTITUTE( SUBSTITUTE(_xlpm.src,CHAR(160)," "), "lvl.","Lv" ), "lvl","Lv" ) ), _xlpm.direct, _xlfn.XLOOKUP( _xlpm.clean, tblTargets[DisplayName], tblTargets[TargetID], "" ), _xlpm.lvl, IFERROR(--_xlfn.TEXTAFTER(_xlpm.clean,"Lv "),""), _xlpm.base, IFERROR(TRIM(_xlfn.TEXTBEFORE(_xlpm.clean,"Lv")),""), _xlpm.aliasPattern, _xlfn.XLOOKUP( 1, (tblBuildingAliases[SourceType]="Building")* (tblBuildingAliases[Source ID]=_xlpm.base), tblBuildingAliases[Tracker Target Pattern], "" ), _xlpm.aliasID, IF( _xlpm.aliasPattern="", "", SUBSTITUTE(_xlpm.aliasPattern,"{level}",_xlpm.lvl) ), IF( _xlpm.src="", "", IF(_xlpm.direct<>"",_xlpm.direct,IF(_xlpm.aliasID<>"",_xlpm.aliasID,"CHECK")) ) )} -> building.alchemists_hut@3 | J53: Alchemist's Hut lvl. 3 | K53: Level 6 is required for completing Festival quests, mounting Catacombs maps, and unlocking technologies.
A54: 52 | B54: =_xlfn.XLOOKUP( tblrecommended[[#This Row],[Order]], tblwikirecommended[Order], tblwikirecommended[Passive ID], "" ) -> building.smithy@3 | C54: =_xlfn.XLOOKUP( tblrecommended[[#This Row],[Order]], tblwikirecommended[Order], tblwikirecommended[Active ID], "" ) -> building.alchemists_hut@4 | F54: =1+F53 -> 52 | G54: Smithy lvl. 3 | H54: {=_xlfn.LET( _xlpm.src,tblwikirecommended[[#This Row],[Passive Buildings]], _xlpm.clean, TRIM( SUBSTITUTE( SUBSTITUTE( SUBSTITUTE(_xlpm.src,CHAR(160)," "), "lvl.","Lv" ), "lvl","Lv" ) ), _xlpm.direct, _xlfn.XLOOKUP( _xlpm.clean, tblTargets[DisplayName], tblTargets[TargetID], "" ), _xlpm.lvl, IFERROR(--_xlfn.TEXTAFTER(_xlpm.clean,"Lv "),""), _xlpm.base, IFERROR(TRIM(_xlfn.TEXTBEFORE(_xlpm.clean,"Lv")),""), _xlpm.aliasPattern, _xlfn.XLOOKUP( 1, (tblBuildingAliases[SourceType]="Building")* (tblBuildingAliases[Source ID]=_xlpm.base), tblBuildingAliases[Tracker Target Pattern], "" ), _xlpm.aliasID, IF( _xlpm.aliasPattern="", "", SUBSTITUTE(_xlpm.aliasPattern,"{level}",_xlpm.lvl) ), IF( _xlpm.src="", "", IF(_xlpm.direct<>"",_xlpm.direct,IF(_xlpm.aliasID<>"",_xlpm.aliasID,"CHECK")) ) )} -> building.smithy@3 | I54: {=_xlfn.LET( _xlpm.src,tblwikirecommended[[#This Row],[Active Buildings]], _xlpm.clean, TRIM( SUBSTITUTE( SUBSTITUTE( SUBSTITUTE(_xlpm.src,CHAR(160)," "), "lvl.","Lv" ), "lvl","Lv" ) ), _xlpm.direct, _xlfn.XLOOKUP( _xlpm.clean, tblTargets[DisplayName], tblTargets[TargetID], "" ), _xlpm.lvl, IFERROR(--_xlfn.TEXTAFTER(_xlpm.clean,"Lv "),""), _xlpm.base, IFERROR(TRIM(_xlfn.TEXTBEFORE(_xlpm.clean,"Lv")),""), _xlpm.aliasPattern, _xlfn.XLOOKUP( 1, (tblBuildingAliases[SourceType]="Building")* (tblBuildingAliases[Source ID]=_xlpm.base), tblBuildingAliases[Tracker Target Pattern], "" ), _xlpm.aliasID, IF( _xlpm.aliasPattern="", "", SUBSTITUTE(_xlpm.aliasPattern,"{level}",_xlpm.lvl) ), IF( _xlpm.src="", "", IF(_xlpm.direct<>"",_xlpm.direct,IF(_xlpm.aliasID<>"",_xlpm.aliasID,"CHECK")) ) )} -> building.alchemists_hut@4 | J54: Alchemist's Hut lvl. 4
A55: 53 | B55: =_xlfn.XLOOKUP( tblrecommended[[#This Row],[Order]], tblwikirecommended[Order], tblwikirecommended[Passive ID], "" ) -> building.dungeon@3 | C55: =_xlfn.XLOOKUP( tblrecommended[[#This Row],[Order]], tblwikirecommended[Order], tblwikirecommended[Active ID], "" ) -> building.alchemists_hut@5 | F55: =1+F54 -> 53 | G55: Dungeon lvl. 3 | H55: {=_xlfn.LET( _xlpm.src,tblwikirecommended[[#This Row],[Passive Buildings]], _xlpm.clean, TRIM( SUBSTITUTE( SUBSTITUTE( SUBSTITUTE(_xlpm.src,CHAR(160)," "), "lvl.","Lv" ), "lvl","Lv" ) ), _xlpm.direct, _xlfn.XLOOKUP( _xlpm.clean, tblTargets[DisplayName], tblTargets[TargetID], "" ), _xlpm.lvl, IFERROR(--_xlfn.TEXTAFTER(_xlpm.clean,"Lv "),""), _xlpm.base, IFERROR(TRIM(_xlfn.TEXTBEFORE(_xlpm.clean,"Lv")),""), _xlpm.aliasPattern, _xlfn.XLOOKUP( 1, (tblBuildingAliases[SourceType]="Building")* (tblBuildingAliases[Source ID]=_xlpm.base), tblBuildingAliases[Tracker Target Pattern], "" ), _xlpm.aliasID, IF( _xlpm.aliasPattern="", "", SUBSTITUTE(_xlpm.aliasPattern,"{level}",_xlpm.lvl) ), IF( _xlpm.src="", "", IF(_xlpm.direct<>"",_xlpm.direct,IF(_xlpm.aliasID<>"",_xlpm.aliasID,"CHECK")) ) )} -> building.dungeon@3 | I55: {=_xlfn.LET( _xlpm.src,tblwikirecommended[[#This Row],[Active Buildings]], _xlpm.clean, TRIM( SUBSTITUTE( SUBSTITUTE( SUBSTITUTE(_xlpm.src,CHAR(160)," "), "lvl.","Lv" ), "lvl","Lv" ) ), _xlpm.direct, _xlfn.XLOOKUP( _xlpm.clean, tblTargets[DisplayName], tblTargets[TargetID], "" ), _xlpm.lvl, IFERROR(--_xlfn.TEXTAFTER(_xlpm.clean,"Lv "),""), _xlpm.base, IFERROR(TRIM(_xlfn.TEXTBEFORE(_xlpm.clean,"Lv")),""), _xlpm.aliasPattern, _xlfn.XLOOKUP( 1, (tblBuildingAliases[SourceType]="Building")* (tblBuildingAliases[Source ID]=_xlpm.base), tblBuildingAliases[Tracker Target Pattern], "" ), _xlpm.aliasID, IF( _xlpm.aliasPattern="", "", SUBSTITUTE(_xlpm.aliasPattern,"{level}",_xlpm.lvl) ), IF( _xlpm.src="", "", IF(_xlpm.direct<>"",_xlpm.direct,IF(_xlpm.aliasID<>"",_xlpm.aliasID,"CHECK")) ) )} -> building.alchemists_hut@5 | J55: Alchemist's Hut lvl. 5
A56: 54 | B56: =_xlfn.XLOOKUP( tblrecommended[[#This Row],[Order]], tblwikirecommended[Order], tblwikirecommended[Passive ID], "" ) -> building.airship@1 | C56: =_xlfn.XLOOKUP( tblrecommended[[#This Row],[Order]], tblwikirecommended[Order], tblwikirecommended[Active ID], "" ) -> building.alchemists_hut@6 | F56: =1+F55 -> 54 | G56: Airship lvl. 1 | H56: {=_xlfn.LET( _xlpm.src,tblwikirecommended[[#This Row],[Passive Buildings]], _xlpm.clean, TRIM( SUBSTITUTE( SUBSTITUTE( SUBSTITUTE(_xlpm.src,CHAR(160)," "), "lvl.","Lv" ), "lvl","Lv" ) ), _xlpm.direct, _xlfn.XLOOKUP( _xlpm.clean, tblTargets[DisplayName], tblTargets[TargetID], "" ), _xlpm.lvl, IFERROR(--_xlfn.TEXTAFTER(_xlpm.clean,"Lv "),""), _xlpm.base, IFERROR(TRIM(_xlfn.TEXTBEFORE(_xlpm.clean,"Lv")),""), _xlpm.aliasPattern, _xlfn.XLOOKUP( 1, (tblBuildingAliases[SourceType]="Building")* (tblBuildingAliases[Source ID]=_xlpm.base), tblBuildingAliases[Tracker Target Pattern], "" ), _xlpm.aliasID, IF( _xlpm.aliasPattern="", "", SUBSTITUTE(_xlpm.aliasPattern,"{level}",_xlpm.lvl) ), IF( _xlpm.src="", "", IF(_xlpm.direct<>"",_xlpm.direct,IF(_xlpm.aliasID<>"",_xlpm.aliasID,"CHECK")) ) )} -> building.airship@1 | I56: {=_xlfn.LET( _xlpm.src,tblwikirecommended[[#This Row],[Active Buildings]], _xlpm.clean, TRIM( SUBSTITUTE( SUBSTITUTE( SUBSTITUTE(_xlpm.src,CHAR(160)," "), "lvl.","Lv" ), "lvl","Lv" ) ), _xlpm.direct, _xlfn.XLOOKUP( _xlpm.clean, tblTargets[DisplayName], tblTargets[TargetID], "" ), _xlpm.lvl, IFERROR(--_xlfn.TEXTAFTER(_xlpm.clean,"Lv "),""), _xlpm.base, IFERROR(TRIM(_xlfn.TEXTBEFORE(_xlpm.clean,"Lv")),""), _xlpm.aliasPattern, _xlfn.XLOOKUP( 1, (tblBuildingAliases[SourceType]="Building")* (tblBuildingAliases[Source ID]=_xlpm.base), tblBuildingAliases[Tracker Target Pattern], "" ), _xlpm.aliasID, IF( _xlpm.aliasPattern="", "", SUBSTITUTE(_xlpm.aliasPattern,"{level}",_xlpm.lvl) ), IF( _xlpm.src="", "", IF(_xlpm.direct<>"",_xlpm.direct,IF(_xlpm.aliasID<>"",_xlpm.aliasID,"CHECK")) ) )} -> building.alchemists_hut@6 | J56: Alchemist's Hut lvl. 6
A57: 55 | B57: =_xlfn.XLOOKUP( tblrecommended[[#This Row],[Order]], tblwikirecommended[Order], tblwikirecommended[Passive ID], "" ) -> building.ship@4 | C57: =_xlfn.XLOOKUP( tblrecommended[[#This Row],[Order]], tblwikirecommended[Order], tblwikirecommended[Active ID], "" ) -> building.chicken@1 | F57: =1+F56 -> 55 | G57: Ship lvl. 4 | H57: {=_xlfn.LET( _xlpm.src,tblwikirecommended[[#This Row],[Passive Buildings]], _xlpm.clean, TRIM( SUBSTITUTE( SUBSTITUTE( SUBSTITUTE(_xlpm.src,CHAR(160)," "), "lvl.","Lv" ), "lvl","Lv" ) ), _xlpm.direct, _xlfn.XLOOKUP( _xlpm.clean, tblTargets[DisplayName], tblTargets[TargetID], "" ), _xlpm.lvl, IFERROR(--_xlfn.TEXTAFTER(_xlpm.clean,"Lv "),""), _xlpm.base, IFERROR(TRIM(_xlfn.TEXTBEFORE(_xlpm.clean,"Lv")),""), _xlpm.aliasPattern, _xlfn.XLOOKUP( 1, (tblBuildingAliases[SourceType]="Building")* (tblBuildingAliases[Source ID]=_xlpm.base), tblBuildingAliases[Tracker Target Pattern], "" ), _xlpm.aliasID, IF( _xlpm.aliasPattern="", "", SUBSTITUTE(_xlpm.aliasPattern,"{level}",_xlpm.lvl) ), IF( _xlpm.src="", "", IF(_xlpm.direct<>"",_xlpm.direct,IF(_xlpm.aliasID<>"",_xlpm.aliasID,"CHECK")) ) )} -> building.ship@4 | I57: {=_xlfn.LET( _xlpm.src,tblwikirecommended[[#This Row],[Active Buildings]], _xlpm.clean, TRIM( SUBSTITUTE( SUBSTITUTE( SUBSTITUTE(_xlpm.src,CHAR(160)," "), "lvl.","Lv" ), "lvl","Lv" ) ), _xlpm.direct, _xlfn.XLOOKUP( _xlpm.clean, tblTargets[DisplayName], tblTargets[TargetID], "" ), _xlpm.lvl, IFERROR(--_xlfn.TEXTAFTER(_xlpm.clean,"Lv "),""), _xlpm.base, IFERROR(TRIM(_xlfn.TEXTBEFORE(_xlpm.clean,"Lv")),""), _xlpm.aliasPattern, _xlfn.XLOOKUP( 1, (tblBuildingAliases[SourceType]="Building")* (tblBuildingAliases[Source ID]=_xlpm.base), tblBuildingAliases[Tracker Target Pattern], "" ), _xlpm.aliasID, IF( _xlpm.aliasPattern="", "", SUBSTITUTE(_xlpm.aliasPattern,"{level}",_xlpm.lvl) ), IF( _xlpm.src="", "", IF(_xlpm.direct<>"",_xlpm.direct,IF(_xlpm.aliasID<>"",_xlpm.aliasID,"CHECK")) ) )} -> building.chicken@1 | J57: Chicken Coop lvl. 1 | K57: Enables crafting Eggs. Eggs are used for crafting dungeon related items.
A58: 56 | B58: =_xlfn.XLOOKUP( tblrecommended[[#This Row],[Order]], tblwikirecommended[Order], tblwikirecommended[Passive ID], "" ) -> building.furnace@3 | C58: =_xlfn.XLOOKUP( tblrecommended[[#This Row],[Order]], tblwikirecommended[Order], tblwikirecommended[Active ID], "" ) -> building.chicken@2 | F58: =1+F57 -> 56 | G58: Furnace lvl. 3 | H58: {=_xlfn.LET( _xlpm.src,tblwikirecommended[[#This Row],[Passive Buildings]], _xlpm.clean, TRIM( SUBSTITUTE( SUBSTITUTE( SUBSTITUTE(_xlpm.src,CHAR(160)," "), "lvl.","Lv" ), "lvl","Lv" ) ), _xlpm.direct, _xlfn.XLOOKUP( _xlpm.clean, tblTargets[DisplayName], tblTargets[TargetID], "" ), _xlpm.lvl, IFERROR(--_xlfn.TEXTAFTER(_xlpm.clean,"Lv "),""), _xlpm.base, IFERROR(TRIM(_xlfn.TEXTBEFORE(_xlpm.clean,"Lv")),""), _xlpm.aliasPattern, _xlfn.XLOOKUP( 1, (tblBuildingAliases[SourceType]="Building")* (tblBuildingAliases[Source ID]=_xlpm.base), tblBuildingAliases[Tracker Target Pattern], "" ), _xlpm.aliasID, IF( _xlpm.aliasPattern="", "", SUBSTITUTE(_xlpm.aliasPattern,"{level}",_xlpm.lvl) ), IF( _xlpm.src="", "", IF(_xlpm.direct<>"",_xlpm.direct,IF(_xlpm.aliasID<>"",_xlpm.aliasID,"CHECK")) ) )} -> building.furnace@3 | I58: {=_xlfn.LET( _xlpm.src,tblwikirecommended[[#This Row],[Active Buildings]], _xlpm.clean, TRIM( SUBSTITUTE( SUBSTITUTE( SUBSTITUTE(_xlpm.src,CHAR(160)," "), "lvl.","Lv" ), "lvl","Lv" ) ), _xlpm.direct, _xlfn.XLOOKUP( _xlpm.clean, tblTargets[DisplayName], tblTargets[TargetID], "" ), _xlpm.lvl, IFERROR(--_xlfn.TEXTAFTER(_xlpm.clean,"Lv "),""), _xlpm.base, IFERROR(TRIM(_xlfn.TEXTBEFORE(_xlpm.clean,"Lv")),""), _xlpm.aliasPattern, _xlfn.XLOOKUP( 1, (tblBuildingAliases[SourceType]="Building")* (tblBuildingAliases[Source ID]=_xlpm.base), tblBuildingAliases[Tracker Target Pattern], "" ), _xlpm.aliasID, IF( _xlpm.aliasPattern="", "", SUBSTITUTE(_xlpm.aliasPattern,"{level}",_xlpm.lvl) ), IF( _xlpm.src="", "", IF(_xlpm.direct<>"",_xlpm.direct,IF(_xlpm.aliasID<>"",_xlpm.aliasID,"CHECK")) ) )} -> building.chicken@2 | J58: Chicken Coop lvl. 2 | K58: Doubles productivity of Eggs. Doubles the amount of Eggs produced, but also doubles expenses.
A59: 57 | B59: =_xlfn.XLOOKUP( tblrecommended[[#This Row],[Order]], tblwikirecommended[Order], tblwikirecommended[Passive ID], "" ) -> building.tailor@1 | C59: =_xlfn.XLOOKUP( tblrecommended[[#This Row],[Order]], tblwikirecommended[Order], tblwikirecommended[Active ID], "" ) -> building.pagoda@1 | F59: =1+F58 -> 57 | G59: Tailor lvl. 1 | H59: {=_xlfn.LET( _xlpm.src,tblwikirecommended[[#This Row],[Passive Buildings]], _xlpm.clean, TRIM( SUBSTITUTE( SUBSTITUTE( SUBSTITUTE(_xlpm.src,CHAR(160)," "), "lvl.","Lv" ), "lvl","Lv" ) ), _xlpm.direct, _xlfn.XLOOKUP( _xlpm.clean, tblTargets[DisplayName], tblTargets[TargetID], "" ), _xlpm.lvl, IFERROR(--_xlfn.TEXTAFTER(_xlpm.clean,"Lv "),""), _xlpm.base, IFERROR(TRIM(_xlfn.TEXTBEFORE(_xlpm.clean,"Lv")),""), _xlpm.aliasPattern, _xlfn.XLOOKUP( 1, (tblBuildingAliases[SourceType]="Building")* (tblBuildingAliases[Source ID]=_xlpm.base), tblBuildingAliases[Tracker Target Pattern], "" ), _xlpm.aliasID, IF( _xlpm.aliasPattern="", "", SUBSTITUTE(_xlpm.aliasPattern,"{level}",_xlpm.lvl) ), IF( _xlpm.src="", "", IF(_xlpm.direct<>"",_xlpm.direct,IF(_xlpm.aliasID<>"",_xlpm.aliasID,"CHECK")) ) )} -> building.tailor@1 | I59: {=_xlfn.LET( _xlpm.src,tblwikirecommended[[#This Row],[Active Buildings]], _xlpm.clean, TRIM( SUBSTITUTE( SUBSTITUTE( SUBSTITUTE(_xlpm.src,CHAR(160)," "), "lvl.","Lv" ), "lvl","Lv" ) ), _xlpm.direct, _xlfn.XLOOKUP( _xlpm.clean, tblTargets[DisplayName], tblTargets[TargetID], "" ), _xlpm.lvl, IFERROR(--_xlfn.TEXTAFTER(_xlpm.clean,"Lv "),""), _xlpm.base, IFERROR(TRIM(_xlfn.TEXTBEFORE(_xlpm.clean,"Lv")),""), _xlpm.aliasPattern, _xlfn.XLOOKUP( 1, (tblBuildingAliases[SourceType]="Building")* (tblBuildingAliases[Source ID]=_xlpm.base), tblBuildingAliases[Tracker Target Pattern], "" ), _xlpm.aliasID, IF( _xlpm.aliasPattern="", "", SUBSTITUTE(_xlpm.aliasPattern,"{level}",_xlpm.lvl) ), IF( _xlpm.src="", "", IF(_xlpm.direct<>"",_xlpm.direct,IF(_xlpm.aliasID<>"",_xlpm.aliasID,"CHECK")) ) )} -> building.pagoda@1 | J59: Pagoda lvl. 1 | K59: Level 7 unlocks projects and completes the Build the Pagoda quest. Also don't use hints on puzzles as the reduce rewards.
A60: 58 | B60: =_xlfn.XLOOKUP( tblrecommended[[#This Row],[Order]], tblwikirecommended[Order], tblwikirecommended[Passive ID], "" ) -> building.tailor@2 | C60: =_xlfn.XLOOKUP( tblrecommended[[#This Row],[Order]], tblwikirecommended[Order], tblwikirecommended[Active ID], "" ) -> building.pagoda@2 | F60: =1+F59 -> 58 | G60: Tailor lvl. 2 | H60: {=_xlfn.LET( _xlpm.src,tblwikirecommended[[#This Row],[Passive Buildings]], _xlpm.clean, TRIM( SUBSTITUTE( SUBSTITUTE( SUBSTITUTE(_xlpm.src,CHAR(160)," "), "lvl.","Lv" ), "lvl","Lv" ) ), _xlpm.direct, _xlfn.XLOOKUP( _xlpm.clean, tblTargets[DisplayName], tblTargets[TargetID], "" ), _xlpm.lvl, IFERROR(--_xlfn.TEXTAFTER(_xlpm.clean,"Lv "),""), _xlpm.base, IFERROR(TRIM(_xlfn.TEXTBEFORE(_xlpm.clean,"Lv")),""), _xlpm.aliasPattern, _xlfn.XLOOKUP( 1, (tblBuildingAliases[SourceType]="Building")* (tblBuildingAliases[Source ID]=_xlpm.base), tblBuildingAliases[Tracker Target Pattern], "" ), _xlpm.aliasID, IF( _xlpm.aliasPattern="", "", SUBSTITUTE(_xlpm.aliasPattern,"{level}",_xlpm.lvl) ), IF( _xlpm.src="", "", IF(_xlpm.direct<>"",_xlpm.direct,IF(_xlpm.aliasID<>"",_xlpm.aliasID,"CHECK")) ) )} -> building.tailor@2 | I60: {=_xlfn.LET( _xlpm.src,tblwikirecommended[[#This Row],[Active Buildings]], _xlpm.clean, TRIM( SUBSTITUTE( SUBSTITUTE( SUBSTITUTE(_xlpm.src,CHAR(160)," "), "lvl.","Lv" ), "lvl","Lv" ) ), _xlpm.direct, _xlfn.XLOOKUP( _xlpm.clean, tblTargets[DisplayName], tblTargets[TargetID], "" ), _xlpm.lvl, IFERROR(--_xlfn.TEXTAFTER(_xlpm.clean,"Lv "),""), _xlpm.base, IFERROR(TRIM(_xlfn.TEXTBEFORE(_xlpm.clean,"Lv")),""), _xlpm.aliasPattern, _xlfn.XLOOKUP( 1, (tblBuildingAliases[SourceType]="Building")* (tblBuildingAliases[Source ID]=_xlpm.base), tblBuildingAliases[Tracker Target Pattern], "" ), _xlpm.aliasID, IF( _xlpm.aliasPattern="", "", SUBSTITUTE(_xlpm.aliasPattern,"{level}",_xlpm.lvl) ), IF( _xlpm.src="", "", IF(_xlpm.direct<>"",_xlpm.direct,IF(_xlpm.aliasID<>"",_xlpm.aliasID,"CHECK")) ) )} -> building.pagoda@2 | J60: Pagoda lvl. 2
A61: 59 | B61: =_xlfn.XLOOKUP( tblrecommended[[#This Row],[Order]], tblwikirecommended[Order], tblwikirecommended[Passive ID], "" ) -> building.caravan@4 | C61: =_xlfn.XLOOKUP( tblrecommended[[#This Row],[Order]], tblwikirecommended[Order], tblwikirecommended[Active ID], "" ) -> building.pagoda@3 | F61: =1+F60 -> 59 | G61: Caravan lvl. 4 | H61: {=_xlfn.LET( _xlpm.src,tblwikirecommended[[#This Row],[Passive Buildings]], _xlpm.clean, TRIM( SUBSTITUTE( SUBSTITUTE( SUBSTITUTE(_xlpm.src,CHAR(160)," "), "lvl.","Lv" ), "lvl","Lv" ) ), _xlpm.direct, _xlfn.XLOOKUP( _xlpm.clean, tblTargets[DisplayName], tblTargets[TargetID], "" ), _xlpm.lvl, IFERROR(--_xlfn.TEXTAFTER(_xlpm.clean,"Lv "),""), _xlpm.base, IFERROR(TRIM(_xlfn.TEXTBEFORE(_xlpm.clean,"Lv")),""), _xlpm.aliasPattern, _xlfn.XLOOKUP( 1, (tblBuildingAliases[SourceType]="Building")* (tblBuildingAliases[Source ID]=_xlpm.base), tblBuildingAliases[Tracker Target Pattern], "" ), _xlpm.aliasID, IF( _xlpm.aliasPattern="", "", SUBSTITUTE(_xlpm.aliasPattern,"{level}",_xlpm.lvl) ), IF( _xlpm.src="", "", IF(_xlpm.direct<>"",_xlpm.direct,IF(_xlpm.aliasID<>"",_xlpm.aliasID,"CHECK")) ) )} -> building.caravan@4 | I61: {=_xlfn.LET( _xlpm.src,tblwikirecommended[[#This Row],[Active Buildings]], _xlpm.clean, TRIM( SUBSTITUTE( SUBSTITUTE( SUBSTITUTE(_xlpm.src,CHAR(160)," "), "lvl.","Lv" ), "lvl","Lv" ) ), _xlpm.direct, _xlfn.XLOOKUP( _xlpm.clean, tblTargets[DisplayName], tblTargets[TargetID], "" ), _xlpm.lvl, IFERROR(--_xlfn.TEXTAFTER(_xlpm.clean,"Lv "),""), _xlpm.base, IFERROR(TRIM(_xlfn.TEXTBEFORE(_xlpm.clean,"Lv")),""), _xlpm.aliasPattern, _xlfn.XLOOKUP( 1, (tblBuildingAliases[SourceType]="Building")* (tblBuildingAliases[Source ID]=_xlpm.base), tblBuildingAliases[Tracker Target Pattern], "" ), _xlpm.aliasID, IF( _xlpm.aliasPattern="", "", SUBSTITUTE(_xlpm.aliasPattern,"{level}",_xlpm.lvl) ), IF( _xlpm.src="", "", IF(_xlpm.direct<>"",_xlpm.direct,IF(_xlpm.aliasID<>"",_xlpm.aliasID,"CHECK")) ) )} -> building.pagoda@3 | J61: Pagoda lvl. 3
A62: 60 | B62: =_xlfn.XLOOKUP( tblrecommended[[#This Row],[Order]], tblwikirecommended[Order], tblwikirecommended[Passive ID], "" ) -> building.tailor@3 | C62: =_xlfn.XLOOKUP( tblrecommended[[#This Row],[Order]], tblwikirecommended[Order], tblwikirecommended[Active ID], "" ) -> building.pagoda@4 | F62: =1+F61 -> 60 | G62: Tailor lvl. 3 | H62: {=_xlfn.LET( _xlpm.src,tblwikirecommended[[#This Row],[Passive Buildings]], _xlpm.clean, TRIM( SUBSTITUTE( SUBSTITUTE( SUBSTITUTE(_xlpm.src,CHAR(160)," "), "lvl.","Lv" ), "lvl","Lv" ) ), _xlpm.direct, _xlfn.XLOOKUP( _xlpm.clean, tblTargets[DisplayName], tblTargets[TargetID], "" ), _xlpm.lvl, IFERROR(--_xlfn.TEXTAFTER(_xlpm.clean,"Lv "),""), _xlpm.base, IFERROR(TRIM(_xlfn.TEXTBEFORE(_xlpm.clean,"Lv")),""), _xlpm.aliasPattern, _xlfn.XLOOKUP( 1, (tblBuildingAliases[SourceType]="Building")* (tblBuildingAliases[Source ID]=_xlpm.base), tblBuildingAliases[Tracker Target Pattern], "" ), _xlpm.aliasID, IF( _xlpm.aliasPattern="", "", SUBSTITUTE(_xlpm.aliasPattern,"{level}",_xlpm.lvl) ), IF( _xlpm.src="", "", IF(_xlpm.direct<>"",_xlpm.direct,IF(_xlpm.aliasID<>"",_xlpm.aliasID,"CHECK")) ) )} -> building.tailor@3 | I62: {=_xlfn.LET( _xlpm.src,tblwikirecommended[[#This Row],[Active Buildings]], _xlpm.clean, TRIM( SUBSTITUTE( SUBSTITUTE( SUBSTITUTE(_xlpm.src,CHAR(160)," "), "lvl.","Lv" ), "lvl","Lv" ) ), _xlpm.direct, _xlfn.XLOOKUP( _xlpm.clean, tblTargets[DisplayName], tblTargets[TargetID], "" ), _xlpm.lvl, IFERROR(--_xlfn.TEXTAFTER(_xlpm.clean,"Lv "),""), _xlpm.base, IFERROR(TRIM(_xlfn.TEXTBEFORE(_xlpm.clean,"Lv")),""), _xlpm.aliasPattern, _xlfn.XLOOKUP( 1, (tblBuildingAliases[SourceType]="Building")* (tblBuildingAliases[Source ID]=_xlpm.base), tblBuildingAliases[Tracker Target Pattern], "" ), _xlpm.aliasID, IF( _xlpm.aliasPattern="", "", SUBSTITUTE(_xlpm.aliasPattern,"{level}",_xlpm.lvl) ), IF( _xlpm.src="", "", IF(_xlpm.direct<>"",_xlpm.direct,IF(_xlpm.aliasID<>"",_xlpm.aliasID,"CHECK")) ) )} -> building.pagoda@4 | J62: Pagoda lvl. 4
A63: 61 | B63: =_xlfn.XLOOKUP( tblrecommended[[#This Row],[Order]], tblwikirecommended[Order], tblwikirecommended[Passive ID], "" ) -> building.outpost@3 | C63: =_xlfn.XLOOKUP( tblrecommended[[#This Row],[Order]], tblwikirecommended[Order], tblwikirecommended[Active ID], "" ) -> building.pagoda@5 | F63: =1+F62 -> 61 | G63: Outpost lvl. 3 | H63: {=_xlfn.LET( _xlpm.src,tblwikirecommended[[#This Row],[Passive Buildings]], _xlpm.clean, TRIM( SUBSTITUTE( SUBSTITUTE( SUBSTITUTE(_xlpm.src,CHAR(160)," "), "lvl.","Lv" ), "lvl","Lv" ) ), _xlpm.direct, _xlfn.XLOOKUP( _xlpm.clean, tblTargets[DisplayName], tblTargets[TargetID], "" ), _xlpm.lvl, IFERROR(--_xlfn.TEXTAFTER(_xlpm.clean,"Lv "),""), _xlpm.base, IFERROR(TRIM(_xlfn.TEXTBEFORE(_xlpm.clean,"Lv")),""), _xlpm.aliasPattern, _xlfn.XLOOKUP( 1, (tblBuildingAliases[SourceType]="Building")* (tblBuildingAliases[Source ID]=_xlpm.base), tblBuildingAliases[Tracker Target Pattern], "" ), _xlpm.aliasID, IF( _xlpm.aliasPattern="", "", SUBSTITUTE(_xlpm.aliasPattern,"{level}",_xlpm.lvl) ), IF( _xlpm.src="", "", IF(_xlpm.direct<>"",_xlpm.direct,IF(_xlpm.aliasID<>"",_xlpm.aliasID,"CHECK")) ) )} -> building.outpost@3 | I63: {=_xlfn.LET( _xlpm.src,tblwikirecommended[[#This Row],[Active Buildings]], _xlpm.clean, TRIM( SUBSTITUTE( SUBSTITUTE( SUBSTITUTE(_xlpm.src,CHAR(160)," "), "lvl.","Lv" ), "lvl","Lv" ) ), _xlpm.direct, _xlfn.XLOOKUP( _xlpm.clean, tblTargets[DisplayName], tblTargets[TargetID], "" ), _xlpm.lvl, IFERROR(--_xlfn.TEXTAFTER(_xlpm.clean,"Lv "),""), _xlpm.base, IFERROR(TRIM(_xlfn.TEXTBEFORE(_xlpm.clean,"Lv")),""), _xlpm.aliasPattern, _xlfn.XLOOKUP( 1, (tblBuildingAliases[SourceType]="Building")* (tblBuildingAliases[Source ID]=_xlpm.base), tblBuildingAliases[Tracker Target Pattern], "" ), _xlpm.aliasID, IF( _xlpm.aliasPattern="", "", SUBSTITUTE(_xlpm.aliasPattern,"{level}",_xlpm.lvl) ), IF( _xlpm.src="", "", IF(_xlpm.direct<>"",_xlpm.direct,IF(_xlpm.aliasID<>"",_xlpm.aliasID,"CHECK")) ) )} -> building.pagoda@5 | J63: Pagoda lvl. 5
A64: 62 | B64: =_xlfn.XLOOKUP( tblrecommended[[#This Row],[Order]], tblwikirecommended[Order], tblwikirecommended[Passive ID], "" ) -> building.alchemists_hut@3 | C64: =_xlfn.XLOOKUP( tblrecommended[[#This Row],[Order]], tblwikirecommended[Order], tblwikirecommended[Active ID], "" ) -> building.pagoda@6 | F64: =1+F63 -> 62 | G64: Alchemist's Hut lvl. 3 | H64: {=_xlfn.LET( _xlpm.src,tblwikirecommended[[#This Row],[Passive Buildings]], _xlpm.clean, TRIM( SUBSTITUTE( SUBSTITUTE( SUBSTITUTE(_xlpm.src,CHAR(160)," "), "lvl.","Lv" ), "lvl","Lv" ) ), _xlpm.direct, _xlfn.XLOOKUP( _xlpm.clean, tblTargets[DisplayName], tblTargets[TargetID], "" ), _xlpm.lvl, IFERROR(--_xlfn.TEXTAFTER(_xlpm.clean,"Lv "),""), _xlpm.base, IFERROR(TRIM(_xlfn.TEXTBEFORE(_xlpm.clean,"Lv")),""), _xlpm.aliasPattern, _xlfn.XLOOKUP( 1, (tblBuildingAliases[SourceType]="Building")* (tblBuildingAliases[Source ID]=_xlpm.base), tblBuildingAliases[Tracker Target Pattern], "" ), _xlpm.aliasID, IF( _xlpm.aliasPattern="", "", SUBSTITUTE(_xlpm.aliasPattern,"{level}",_xlpm.lvl) ), IF( _xlpm.src="", "", IF(_xlpm.direct<>"",_xlpm.direct,IF(_xlpm.aliasID<>"",_xlpm.aliasID,"CHECK")) ) )} -> building.alchemists_hut@3 | I64: {=_xlfn.LET( _xlpm.src,tblwikirecommended[[#This Row],[Active Buildings]], _xlpm.clean, TRIM( SUBSTITUTE( SUBSTITUTE( SUBSTITUTE(_xlpm.src,CHAR(160)," "), "lvl.","Lv" ), "lvl","Lv" ) ), _xlpm.direct, _xlfn.XLOOKUP( _xlpm.clean, tblTargets[DisplayName], tblTargets[TargetID], "" ), _xlpm.lvl, IFERROR(--_xlfn.TEXTAFTER(_xlpm.clean,"Lv "),""), _xlpm.base, IFERROR(TRIM(_xlfn.TEXTBEFORE(_xlpm.clean,"Lv")),""), _xlpm.aliasPattern, _xlfn.XLOOKUP( 1, (tblBuildingAliases[SourceType]="Building")* (tblBuildingAliases[Source ID]=_xlpm.base), tblBuildingAliases[Tracker Target Pattern], "" ), _xlpm.aliasID, IF( _xlpm.aliasPattern="", "", SUBSTITUTE(_xlpm.aliasPattern,"{level}",_xlpm.lvl) ), IF( _xlpm.src="", "", IF(_xlpm.direct<>"",_xlpm.direct,IF(_xlpm.aliasID<>"",_xlpm.aliasID,"CHECK")) ) )} -> building.pagoda@6 | J64: Pagoda lvl. 6
A65: 63 | B65: =_xlfn.XLOOKUP( tblrecommended[[#This Row],[Order]], tblwikirecommended[Order], tblwikirecommended[Passive ID], "" ) -> building.alchemists_hut@4 | C65: =_xlfn.XLOOKUP( tblrecommended[[#This Row],[Order]], tblwikirecommended[Order], tblwikirecommended[Active ID], "" ) -> building.pagoda@7 | F65: =1+F64 -> 63 | G65: Alchemist's Hut lvl. 4 | H65: {=_xlfn.LET( _xlpm.src,tblwikirecommended[[#This Row],[Passive Buildings]], _xlpm.clean, TRIM( SUBSTITUTE( SUBSTITUTE( SUBSTITUTE(_xlpm.src,CHAR(160)," "), "lvl.","Lv" ), "lvl","Lv" ) ), _xlpm.direct, _xlfn.XLOOKUP( _xlpm.clean, tblTargets[DisplayName], tblTargets[TargetID], "" ), _xlpm.lvl, IFERROR(--_xlfn.TEXTAFTER(_xlpm.clean,"Lv "),""), _xlpm.base, IFERROR(TRIM(_xlfn.TEXTBEFORE(_xlpm.clean,"Lv")),""), _xlpm.aliasPattern, _xlfn.XLOOKUP( 1, (tblBuildingAliases[SourceType]="Building")* (tblBuildingAliases[Source ID]=_xlpm.base), tblBuildingAliases[Tracker Target Pattern], "" ), _xlpm.aliasID, IF( _xlpm.aliasPattern="", "", SUBSTITUTE(_xlpm.aliasPattern,"{level}",_xlpm.lvl) ), IF( _xlpm.src="", "", IF(_xlpm.direct<>"",_xlpm.direct,IF(_xlpm.aliasID<>"",_xlpm.aliasID,"CHECK")) ) )} -> building.alchemists_hut@4 | I65: {=_xlfn.LET( _xlpm.src,tblwikirecommended[[#This Row],[Active Buildings]], _xlpm.clean, TRIM( SUBSTITUTE( SUBSTITUTE( SUBSTITUTE(_xlpm.src,CHAR(160)," "), "lvl.","Lv" ), "lvl","Lv" ) ), _xlpm.direct, _xlfn.XLOOKUP( _xlpm.clean, tblTargets[DisplayName], tblTargets[TargetID], "" ), _xlpm.lvl, IFERROR(--_xlfn.TEXTAFTER(_xlpm.clean,"Lv "),""), _xlpm.base, IFERROR(TRIM(_xlfn.TEXTBEFORE(_xlpm.clean,"Lv")),""), _xlpm.aliasPattern, _xlfn.XLOOKUP( 1, (tblBuildingAliases[SourceType]="Building")* (tblBuildingAliases[Source ID]=_xlpm.base), tblBuildingAliases[Tracker Target Pattern], "" ), _xlpm.aliasID, IF( _xlpm.aliasPattern="", "", SUBSTITUTE(_xlpm.aliasPattern,"{level}",_xlpm.lvl) ), IF( _xlpm.src="", "", IF(_xlpm.direct<>"",_xlpm.direct,IF(_xlpm.aliasID<>"",_xlpm.aliasID,"CHECK")) ) )} -> building.pagoda@7 | J65: Pagoda lvl. 7
A66: 64 | B66: =_xlfn.XLOOKUP( tblrecommended[[#This Row],[Order]], tblwikirecommended[Order], tblwikirecommended[Passive ID], "" ) -> building.alchemists_hut@5 | C66: =_xlfn.XLOOKUP( tblrecommended[[#This Row],[Order]], tblwikirecommended[Order], tblwikirecommended[Active ID], "" ) -> building.dungeon@4 | F66: =1+F65 -> 64 | G66: Alchemist's Hut lvl. 5 | H66: {=_xlfn.LET( _xlpm.src,tblwikirecommended[[#This Row],[Passive Buildings]], _xlpm.clean, TRIM( SUBSTITUTE( SUBSTITUTE( SUBSTITUTE(_xlpm.src,CHAR(160)," "), "lvl.","Lv" ), "lvl","Lv" ) ), _xlpm.direct, _xlfn.XLOOKUP( _xlpm.clean, tblTargets[DisplayName], tblTargets[TargetID], "" ), _xlpm.lvl, IFERROR(--_xlfn.TEXTAFTER(_xlpm.clean,"Lv "),""), _xlpm.base, IFERROR(TRIM(_xlfn.TEXTBEFORE(_xlpm.clean,"Lv")),""), _xlpm.aliasPattern, _xlfn.XLOOKUP( 1, (tblBuildingAliases[SourceType]="Building")* (tblBuildingAliases[Source ID]=_xlpm.base), tblBuildingAliases[Tracker Target Pattern], "" ), _xlpm.aliasID, IF( _xlpm.aliasPattern="", "", SUBSTITUTE(_xlpm.aliasPattern,"{level}",_xlpm.lvl) ), IF( _xlpm.src="", "", IF(_xlpm.direct<>"",_xlpm.direct,IF(_xlpm.aliasID<>"",_xlpm.aliasID,"CHECK")) ) )} -> building.alchemists_hut@5 | I66: {=_xlfn.LET( _xlpm.src,tblwikirecommended[[#This Row],[Active Buildings]], _xlpm.clean, TRIM( SUBSTITUTE( SUBSTITUTE( SUBSTITUTE(_xlpm.src,CHAR(160)," "), "lvl.","Lv" ), "lvl","Lv" ) ), _xlpm.direct, _xlfn.XLOOKUP( _xlpm.clean, tblTargets[DisplayName], tblTargets[TargetID], "" ), _xlpm.lvl, IFERROR(--_xlfn.TEXTAFTER(_xlpm.clean,"Lv "),""), _xlpm.base, IFERROR(TRIM(_xlfn.TEXTBEFORE(_xlpm.clean,"Lv")),""), _xlpm.aliasPattern, _xlfn.XLOOKUP( 1, (tblBuildingAliases[SourceType]="Building")* (tblBuildingAliases[Source ID]=_xlpm.base), tblBuildingAliases[Tracker Target Pattern], "" ), _xlpm.aliasID, IF( _xlpm.aliasPattern="", "", SUBSTITUTE(_xlpm.aliasPattern,"{level}",_xlpm.lvl) ), IF( _xlpm.src="", "", IF(_xlpm.direct<>"",_xlpm.direct,IF(_xlpm.aliasID<>"",_xlpm.aliasID,"CHECK")) ) )} -> building.dungeon@4 | J66: Dungeon lvl. 4 | K66: Allows to gather items like Soy sauce, Mandrake root, etc.
A67: 65 | B67: =_xlfn.XLOOKUP( tblrecommended[[#This Row],[Order]], tblwikirecommended[Order], tblwikirecommended[Passive ID], "" ) -> building.alchemists_hut@6 | C67: =_xlfn.XLOOKUP( tblrecommended[[#This Row],[Order]], tblwikirecommended[Order], tblwikirecommended[Active ID], "" ) -> building.dungeon@5 | F67: =1+F66 -> 65 | G67: Alchemist's Hut lvl. 6 | H67: {=_xlfn.LET( _xlpm.src,tblwikirecommended[[#This Row],[Passive Buildings]], _xlpm.clean, TRIM( SUBSTITUTE( SUBSTITUTE( SUBSTITUTE(_xlpm.src,CHAR(160)," "), "lvl.","Lv" ), "lvl","Lv" ) ), _xlpm.direct, _xlfn.XLOOKUP( _xlpm.clean, tblTargets[DisplayName], tblTargets[TargetID], "" ), _xlpm.lvl, IFERROR(--_xlfn.TEXTAFTER(_xlpm.clean,"Lv "),""), _xlpm.base, IFERROR(TRIM(_xlfn.TEXTBEFORE(_xlpm.clean,"Lv")),""), _xlpm.aliasPattern, _xlfn.XLOOKUP( 1, (tblBuildingAliases[SourceType]="Building")* (tblBuildingAliases[Source ID]=_xlpm.base), tblBuildingAliases[Tracker Target Pattern], "" ), _xlpm.aliasID, IF( _xlpm.aliasPattern="", "", SUBSTITUTE(_xlpm.aliasPattern,"{level}",_xlpm.lvl) ), IF( _xlpm.src="", "", IF(_xlpm.direct<>"",_xlpm.direct,IF(_xlpm.aliasID<>"",_xlpm.aliasID,"CHECK")) ) )} -> building.alchemists_hut@6 | I67: {=_xlfn.LET( _xlpm.src,tblwikirecommended[[#This Row],[Active Buildings]], _xlpm.clean, TRIM( SUBSTITUTE( SUBSTITUTE( SUBSTITUTE(_xlpm.src,CHAR(160)," "), "lvl.","Lv" ), "lvl","Lv" ) ), _xlpm.direct, _xlfn.XLOOKUP( _xlpm.clean, tblTargets[DisplayName], tblTargets[TargetID], "" ), _xlpm.lvl, IFERROR(--_xlfn.TEXTAFTER(_xlpm.clean,"Lv "),""), _xlpm.base, IFERROR(TRIM(_xlfn.TEXTBEFORE(_xlpm.clean,"Lv")),""), _xlpm.aliasPattern, _xlfn.XLOOKUP( 1, (tblBuildingAliases[SourceType]="Building")* (tblBuildingAliases[Source ID]=_xlpm.base), tblBuildingAliases[Tracker Target Pattern], "" ), _xlpm.aliasID, IF( _xlpm.aliasPattern="", "", SUBSTITUTE(_xlpm.aliasPattern,"{level}",_xlpm.lvl) ), IF( _xlpm.src="", "", IF(_xlpm.direct<>"",_xlpm.direct,IF(_xlpm.aliasID<>"",_xlpm.aliasID,"CHECK")) ) )} -> building.dungeon@5 | J67: Dungeon lvl. 5 | K67: Allows to complete the Emerald tablet craftifact and unlocks some dungeon related quests.
